Workbook

Sheet 01_PRESUPUESTO_CRONOGRAMA_BASE
A1: Item | B1: Código WBS | C1: Descripción de la Partida Presupuestal | D1: Unidad | E1: Metrado Meta | F1: P.U. Directo (S/) | G1: Parcial Directo (S/) | H1: Fecha Inicio | I1: Fecha Fin | J1: Duración (Días) | K1: Día Inicio Obra | L1: Día Fin Obra | M1: Tasa PV Diario (S/Día)
A2: 01.01 | B2: WBS-100 | C2: Obras Preliminares y Trabajos Provisionales | D2: GLB | E2: 1 | F2: 8296.4 | G2: =ROUND(E2*F2, 2) | H2: 2026-08-01 | I2: 2026-08-14 | J2: =(L2-K2)+1 | K2: 1 | L2: 14 | M2: =ROUND(G2/J2, 2)
A3: 01.02.01 | B3: WBS-100 | C3: Trazo, Nivelación y Replanteo de Zanjas | D3: M | E3: 2400 | F3: 3.35 | G3: =ROUND(E3*F3, 2) | H3: 2026-08-01 | I3: 2026-08-14 | J3: =(L3-K3)+1 | K3: 1 | L3: 14 | M3: =ROUND(G3/J3, 2)
A4: 01.02.02 | B4: WBS-200 | C4: Excavación de Zanja H=1.50m - 2.20m a Máquina (Terreno Normal) | D4: M3 | E4: 3840 | F4: 11.66 | G4: =ROUND(E4*F4, 2) | H4: 2026-08-10 | I4: 2026-08-25 | J4: =(L4-K4)+1 | K4: 10 | L4: 25 | M4: =ROUND(G4/J4, 2)
A5: 01.02.03 | B5: WBS-200 | C5: Preparación y Colocación de Cama de Arena e=0.10m | D5: M | E5: 2400 | F5: 11.12 | G5: =ROUND(E5*F5, 2) | H5: 2026-08-12 | I5: 2026-08-28 | J5: =(L5-K5)+1 | K5: 12 | L5: 28 | M5: =ROUND(G5/J5, 2)
A6: 01.02.04 | B6: WBS-200 | C6: Suministro e Instalación de Tubería PVC UF DN 200mm Serie S-20 para Alcantarillado | D6: M | E6: 1400 | F6: 55.51 | G6: =ROUND(E6*F6, 2) | H6: 2026-08-15 | I6: 2026-08-31 | J6: =(L6-K6)+1 | K6: 15 | L6: 31 | M6: =ROUND(G6/J6, 2)
A7: 01.02.05 | B7: WBS-200 | C7: Relleno Compactado de Zanja en Capas de 0.20m con Maquinaria/Plancha | D7: M3 | E7: 3300 | F7: 28.54 | G7: =ROUND(E7*F7, 2) | H7: 2026-08-18 | I7: 2026-09-05 | J7: =(L7-K7)+1 | K7: 18 | L7: 36 | M7: =ROUND(G7/J7, 2)
A8: 01.02.06 | B8: WBS-200 | C8: Construcción de Buzones Prefabricados de Concreto h=1.50m - 2.50m (Inc. Marco y Tapa) | D8: UND | E8: 32 | F8: 2500.73 | G8: =ROUND(E8*F8, 2) | H8: 2026-08-22 | I8: 2026-09-10 | J8: =(L8-K8)+1 | K8: 22 | L8: 41 | M8: =ROUND(G8/J8, 2)
A9: 01.02.07 | B9: WBS-200 | C9: Conexiones Domiciliarias de Alcantarillado (Caja de Registro + Acometida) | D9: UND | E9: 120 | F9: 405.54 | G9: =ROUND(E9*F9, 2) | H9: 2026-08-28 | I9: 2026-09-12 | J9: =(L9-K9)+1 | K9: 28 | L9: 43 | M9: =ROUND(G9/J9, 2)
A10: 01.03.01 | B10: WBS-300 | C10: Suministro e Instalación de Tubería PVC C-10 DN 110mm para Agua Potable | D10: M | E10: 1000 | F10: 38.76 | G10: =ROUND(E10*F10, 2) | H10: 2026-08-22 | I10: 2026-09-12 | J10: =(L10-K10)+1 | K10: 22 | L10: 43 | M10: =ROUND(G10/J10, 2)
A11: 01.03.02 | B11: WBS-300 | C11: Conexiones Domiciliarias de Agua Potable (Caja de Agua + Abrazadera + Acometida) | D11: UND | E11: 120 | F11: 156.71 | G11: =ROUND(E11*F11, 2) | H11: 2026-09-01 | I11: 2026-09-20 | J11: =(L11-K11)+1 | K11: 32 | L11: 51 | M11: =ROUND(G11/J11, 2)
A12: 01.04.01 | B12: WBS-400 | C12: Pruebas Hidráulicas de Redes de Agua y Alcantarillado + Desinfección | D12: GLB | E12: 1 | F12: 9348.06 | G12: =ROUND(E12*F12, 2) | H12: 2026-09-17 | I12: 2026-09-29 | J12: =(L12-K12)+1 | K12: 48 | L12: 60 | M12: =ROUND(G12/J12, 2)
C13: COSTO DIRECTO TOTAL (S/) | G13: =SUM(G2:G12)
C14: GASTOS GENERALES (10.00%) | G14: =ROUND(G13*0.1, 2)
C15: UTILIDAD (8.00%) | G15: =ROUND(G13*0.08, 2)
C16: SUB TOTAL / VALOR VENTA (SIN IGV) | G16: =SUM(G13:G15)
C17: IMPUESTO GENERAL A LAS VENTAS (IGV 18%) | G17: =ROUND(G16*0.18, 2)
C18: PRECIO TOTAL COMERCIAL DE OBRA (CON IGV) | G18: =G16+G17

Sheet 02_CRONOGRAMA_PV_DIARIO
A1: N° Día Obra | B1: Fecha Obra | C1: Código WBS | D1: Nombre Frente WBS | E1: PV Diario Programado (S/) | F1: PV Acumulado WBS (S/)
A2: 1 | B2: 2026-08-01 | C2: WBS-100 | D2: Obras Preliminares, Trazo y Movilización | E2: =IF(AND(A2>='01_PRESUPUESTO_CRONOGRAMA_BASE'!K2, A2<='01_PRESUPUESTO_CRONOGRAMA_BASE'!L2), '01_PRESUPUESTO_CRONOGRAMA_BASE'!M2, 0) + IF(AND(A2>='01_PRESUPUESTO_CRONOGRAMA_BASE'!K3, A2<='01_PRESUPUESTO_CRONOGRAMA_BASE'!L3), '01_PRESUPUESTO_CRONOGRAMA_BASE'!M3, 0) | F2: =SUMIFS(E$2:E2, C$2:C2, C2)
A3: 1 | B3: 2026-08-01 | C3: WBS-200 | D3: Red de Alcantarillado, Zanjas y Buzones | E3: =IF(AND(A3>='01_PRESUPUESTO_CRONOGRAMA_BASE'!K4, A3<='01_PRESUPUESTO_CRONOGRAMA_BASE'!L4), '01_PRESUPUESTO_CRONOGRAMA_BASE'!M4, 0) + IF(AND(A3>='01_PRESUPUESTO_CRONOGRAMA_BASE'!K5, A3<='01_PRESUPUESTO_CRONOGRAMA_BASE'!L5), '01_PRESUPUESTO_CRONOGRAMA_BASE'!M5, 0) + IF(AND(A3>='01_PRESUPUESTO_CRONOGRAMA_BASE'!K6, A3<='01_PRESUPUESTO_CRONOGRAMA_BASE'!L6), '01_PRESUPUESTO_CRONOGRAMA_BASE'!M6, 0) + IF(AND(A3>='01_PRESUPUESTO_CRONOGRAMA_BASE'!K7, A3<='01_PRESUPUESTO_CRONOGRAMA_BASE'!L7), '01_PRESUPUESTO_CRONOGRAMA_BASE'!M7, 0) + IF(AND(A3>='01_PRESUPUESTO_CRONOGRAMA_BASE'!K8, A3<='01_PRESUPUESTO_CRONOGRAMA_BASE'!L8), '01_PRESUPUESTO_CRONOGRAMA_BASE'!M8, 0) + IF(AND(A3>='01_PRESUPUESTO_CRONOGRAMA_BASE'!K9, A3<='01_PRESUPUESTO_CRONOGRAMA_BASE'!L9), '01_PRESUPUESTO_CRONOGRAMA_BASE'!M9, 0) | F3: =SUMIFS(E$2:E3, C$2:C3, C3)
A4: 1 | B4: 2026-08-01 | C4: WBS-300 | D4: Red de Agua Potable y Conexiones Domiciliarias | E4: =IF(AND(A4>='01_PRESUPUESTO_CRONOGRAMA_BASE'!K10, A4<='01_PRESUPUESTO_CRONOGRAMA_BASE'!L10), '01_PRESUPUESTO_CRONOGRAMA_BASE'!M10, 0) + IF(AND(A4>='01_PRESUPUESTO_CRONOGRAMA_BASE'!K11, A4<='01_PRESUPUESTO_CRONOGRAMA_BASE'!L11), '01_PRESUPUESTO_CRONOGRAMA_BASE'!M11, 0) | F4: =SUMIFS(E$2:E4, C$2:C4, C4)
A5: 1 | B5: 2026-08-01 | C5: WBS-400 | D5: Pruebas Hidráulicas, Desinfección y Entrega | E5: =IF(AND(A5>='01_PRESUPUESTO_CRONOGRAMA_BASE'!K12, A5<='01_PRESUPUESTO_CRONOGRAMA_BASE'!L12), '01_PRESUPUESTO_CRONOGRAMA_BASE'!M12, 0) | F5: =SUMIFS(E$2:E5, C$2:C5, C5)
A6: 2 | B6: 2026-08-02 | C6: WBS-100 | D6: Obras Preliminares, Trazo y Movilización | E6: =IF(AND(A6>='01_PRESUPUESTO_CRONOGRAMA_BASE'!K2, A6<='01_PRESUPUESTO_CRONOGRAMA_BASE'!L2), '01_PRESUPUESTO_CRONOGRAMA_BASE'!M2, 0) + IF(AND(A6>='01_PRESUPUESTO_CRONOGRAMA_BASE'!K3, A6<='01_PRESUPUESTO_CRONOGRAMA_BASE'!L3), '01_PRESUPUESTO_CRONOGRAMA_BASE'!M3, 0) | F6: =SUMIFS(E$2:E6, C$2:C6, C6)
A7: 2 | B7: 2026-08-02 | C7: WBS-200 | D7: Red de Alcantarillado, Zanjas y Buzones | E7: =IF(AND(A7>='01_PRESUPUESTO_CRONOGRAMA_BASE'!K4, A7<='01_PRESUPUESTO_CRONOGRAMA_BASE'!L4), '01_PRESUPUESTO_CRONOGRAMA_BASE'!M4, 0) + IF(AND(A7>='01_PRESUPUESTO_CRONOGRAMA_BASE'!K5, A7<='01_PRESUPUESTO_CRONOGRAMA_BASE'!L5), '01_PRESUPUESTO_CRONOGRAMA_BASE'!M5, 0) + IF(AND(A7>='01_PRESUPUESTO_CRONOGRAMA_BASE'!K6, A7<='01_PRESUPUESTO_CRONOGRAMA_BASE'!L6), '01_PRESUPUESTO_CRONOGRAMA_BASE'!M6, 0) + IF(AND(A7>='01_PRESUPUESTO_CRONOGRAMA_BASE'!K7, A7<='01_PRESUPUESTO_CRONOGRAMA_BASE'!L7), '01_PRESUPUESTO_CRONOGRAMA_BASE'!M7, 0) + IF(AND(A7>='01_PRESUPUESTO_CRONOGRAMA_BASE'!K8, A7<='01_PRESUPUESTO_CRONOGRAMA_BASE'!L8), '01_PRESUPUESTO_CRONOGRAMA_BASE'!M8, 0) + IF(AND(A7>='01_PRESUPUESTO_CRONOGRAMA_BASE'!K9, A7<='01_PRESUPUESTO_CRONOGRAMA_BASE'!L9), '01_PRESUPUESTO_CRONOGRAMA_BASE'!M9, 0) | F7: =SUMIFS(E$2:E7, C$2:C7, C7)
A8: 2 | B8: 2026-08-02 | C8: WBS-300 | D8: Red de Agua Potable y Conexiones Domiciliarias | E8: =IF(AND(A8>='01_PRESUPUESTO_CRONOGRAMA_BASE'!K10, A8<='01_PRESUPUESTO_CRONOGRAMA_BASE'!L10), '01_PRESUPUESTO_CRONOGRAMA_BASE'!M10, 0) + IF(AND(A8>='01_PRESUPUESTO_CRONOGRAMA_BASE'!K11, A8<='01_PRESUPUESTO_CRONOGRAMA_BASE'!L11), '01_PRESUPUESTO_CRONOGRAMA_BASE'!M11, 0) | F8: =SUMIFS(E$2:E8, C$2:C8, C8)
A9: 2 | B9: 2026-08-02 | C9: WBS-400 | D9: Pruebas Hidráulicas, Desinfección y Entrega | E9: =IF(AND(A9>='01_PRESUPUESTO_CRONOGRAMA_BASE'!K12, A9<='01_PRESUPUESTO_CRONOGRAMA_BASE'!L12), '01_PRESUPUESTO_CRONOGRAMA_BASE'!M12, 0) | F9: =SUMIFS(E$2:E9, C$2:C9, C9)
A10: 3 | B10: 2026-08-03 | C10: WBS-100 | D10: Obras Preliminares, Trazo y Movilización | E10: =IF(AND(A10>='01_PRESUPUESTO_CRONOGRAMA_BASE'!K2, A10<='01_PRESUPUESTO_CRONOGRAMA_BASE'!L2), '01_PRESUPUESTO_CRONOGRAMA_BASE'!M2, 0) + IF(AND(A10>='01_PRESUPUESTO_CRONOGRAMA_BASE'!K3, A10<='01_PRESUPUESTO_CRONOGRAMA_BASE'!L3), '01_PRESUPUESTO_CRONOGRAMA_BASE'!M3, 0) | F10: =SUMIFS(E$2:E10, C$2:C10, C10)
A11: 3 | B11: 2026-08-03 | C11: WBS-200 | D11: Red de Alcantarillado, Zanjas y Buzones | E11: =IF(AND(A11>='01_PRESUPUESTO_CRONOGRAMA_BASE'!K4, A11<='01_PRESUPUESTO_CRONOGRAMA_BASE'!L4), '01_PRESUPUESTO_CRONOGRAMA_BASE'!M4, 0) + IF(AND(A11>='01_PRESUPUESTO_CRONOGRAMA_BASE'!K5, A11<='01_PRESUPUESTO_CRONOGRAMA_BASE'!L5), '01_PRESUPUESTO_CRONOGRAMA_BASE'!M5, 0) + IF(AND(A11>='01_PRESUPUESTO_CRONOGRAMA_BASE'!K6, A11<='01_PRESUPUESTO_CRONOGRAMA_BASE'!L6), '01_PRESUPUESTO_CRONOGRAMA_BASE'!M6, 0) + IF(AND(A11>='01_PRESUPUESTO_CRONOGRAMA_BASE'!K7, A11<='01_PRESUPUESTO_CRONOGRAMA_BASE'!L7), '01_PRESUPUESTO_CRONOGRAMA_BASE'!M7, 0) + IF(AND(A11>='01_PRESUPUESTO_CRONOGRAMA_BASE'!K8, A11<='01_PRESUPUESTO_CRONOGRAMA_BASE'!L8), '01_PRESUPUESTO_CRONOGRAMA_BASE'!M8, 0) + IF(AND(A11>='01_PRESUPUESTO_CRONOGRAMA_BASE'!K9, A11<='01_PRESUPUESTO_CRONOGRAMA_BASE'!L9), '01_PRESUPUESTO_CRONOGRAMA_BASE'!M9, 0) | F11: =SUMIFS(E$2:E11, C$2:C11, C11)
A12: 3 | B12: 2026-08-03 | C12: WBS-300 | D12: Red de Agua Potable y Conexiones Domiciliarias | E12: =IF(AND(A12>='01_PRESUPUESTO_CRONOGRAMA_BASE'!K10, A12<='01_PRESUPUESTO_CRONOGRAMA_BASE'!L10), '01_PRESUPUESTO_CRONOGRAMA_BASE'!M10, 0) + IF(AND(A12>='01_PRESUPUESTO_CRONOGRAMA_BASE'!K11, A12<='01_PRESUPUESTO_CRONOGRAMA_BASE'!L11), '01_PRESUPUESTO_CRONOGRAMA_BASE'!M11, 0) | F12: =SUMIFS(E$2:E12, C$2:C12, C12)
A13: 3 | B13: 2026-08-03 | C13: WBS-400 | D13: Pruebas Hidráulicas, Desinfección y Entrega | E13: =IF(AND(A13>='01_PRESUPUESTO_CRONOGRAMA_BASE'!K12, A13<='01_PRESUPUESTO_CRONOGRAMA_BASE'!L12), '01_PRESUPUESTO_CRONOGRAMA_BASE'!M12, 0) | F13: =SUMIFS(E$2:E13, C$2:C13, C13)
A14: 4 | B14: 2026-08-04 | C14: WBS-100 | D14: Obras Preliminares, Trazo y Movilización | E14: =IF(AND(A14>='01_PRESUPUESTO_CRONOGRAMA_BASE'!K2, A14<='01_PRESUPUESTO_CRONOGRAMA_BASE'!L2), '01_PRESUPUESTO_CRONOGRAMA_BASE'!M2, 0) + IF(AND(A14>='01_PRESUPUESTO_CRONOGRAMA_BASE'!K3, A14<='01_PRESUPUESTO_CRONOGRAMA_BASE'!L3), '01_PRESUPUESTO_CRONOGRAMA_BASE'!M3, 0) | F14: =SUMIFS(E$2:E14, C$2:C14, C14)
A15: 4 | B15: 2026-08-04 | C15: WBS-200 | D15: Red de Alcantarillado, Zanjas y Buzones | E15: =IF(AND(A15>='01_PRESUPUESTO_CRONOGRAMA_BASE'!K4, A15<='01_PRESUPUESTO_CRONOGRAMA_BASE'!L4), '01_PRESUPUESTO_CRONOGRAMA_BASE'!M4, 0) + IF(AND(A15>='01_PRESUPUESTO_CRONOGRAMA_BASE'!K5, A15<='01_PRESUPUESTO_CRONOGRAMA_BASE'!L5), '01_PRESUPUESTO_CRONOGRAMA_BASE'!M5, 0) + IF(AND(A15>='01_PRESUPUESTO_CRONOGRAMA_BASE'!K6, A15<='01_PRESUPUESTO_CRONOGRAMA_BASE'!L6), '01_PRESUPUESTO_CRONOGRAMA_BASE'!M6, 0) + IF(AND(A15>='01_PRESUPUESTO_CRONOGRAMA_BASE'!K7, A15<='01_PRESUPUESTO_CRONOGRAMA_BASE'!L7), '01_PRESUPUESTO_CRONOGRAMA_BASE'!M7, 0) + IF(AND(A15>='01_PRESUPUESTO_CRONOGRAMA_BASE'!K8, A15<='01_PRESUPUESTO_CRONOGRAMA_BASE'!L8), '01_PRESUPUESTO_CRONOGRAMA_BASE'!M8, 0) + IF(AND(A15>='01_PRESUPUESTO_CRONOGRAMA_BASE'!K9, A15<='01_PRESUPUESTO_CRONOGRAMA_BASE'!L9), '01_PRESUPUESTO_CRONOGRAMA_BASE'!M9, 0) | F15: =SUMIFS(E$2:E15, C$2:C15, C15)
A16: 4 | B16: 2026-08-04 | C16: WBS-300 | D16: Red de Agua Potable y Conexiones Domiciliarias | E16: =IF(AND(A16>='01_PRESUPUESTO_CRONOGRAMA_BASE'!K10, A16<='01_PRESUPUESTO_CRONOGRAMA_BASE'!L10), '01_PRESUPUESTO_CRONOGRAMA_BASE'!M10, 0) + IF(AND(A16>='01_PRESUPUESTO_CRONOGRAMA_BASE'!K11, A16<='01_PRESUPUESTO_CRONOGRAMA_BASE'!L11), '01_PRESUPUESTO_CRONOGRAMA_BASE'!M11, 0) | F16: =SUMIFS(E$2:E16, C$2:C16, C16)
A17: 4 | B17: 2026-08-04 | C17: WBS-400 | D17: Pruebas Hidráulicas, Desinfección y Entrega | E17: =IF(AND(A17>='01_PRESUPUESTO_CRONOGRAMA_BASE'!K12, A17<='01_PRESUPUESTO_CRONOGRAMA_BASE'!L12), '01_PRESUPUESTO_CRONOGRAMA_BASE'!M12, 0) | F17: =SUMIFS(E$2:E17, C$2:C17, C17)
A18: 5 | B18: 2026-08-05 | C18: WBS-100 | D18: Obras Preliminares, Trazo y Movilización | E18: =IF(AND(A18>='01_PRESUPUESTO_CRONOGRAMA_BASE'!K2, A18<='01_PRESUPUESTO_CRONOGRAMA_BASE'!L2), '01_PRESUPUESTO_CRONOGRAMA_BASE'!M2, 0) + IF(AND(A18>='01_PRESUPUESTO_CRONOGRAMA_BASE'!K3, A18<='01_PRESUPUESTO_CRONOGRAMA_BASE'!L3), '01_PRESUPUESTO_CRONOGRAMA_BASE'!M3, 0) | F18: =SUMIFS(E$2:E18, C$2:C18, C18)
A19: 5 | B19: 2026-08-05 | C19: WBS-200 | D19: Red de Alcantarillado, Zanjas y Buzones | E19: =IF(AND(A19>='01_PRESUPUESTO_CRONOGRAMA_BASE'!K4, A19<='01_PRESUPUESTO_CRONOGRAMA_BASE'!L4), '01_PRESUPUESTO_CRONOGRAMA_BASE'!M4, 0) + IF(AND(A19>='01_PRESUPUESTO_CRONOGRAMA_BASE'!K5, A19<='01_PRESUPUESTO_CRONOGRAMA_BASE'!L5), '01_PRESUPUESTO_CRONOGRAMA_BASE'!M5, 0) + IF(AND(A19>='01_PRESUPUESTO_CRONOGRAMA_BASE'!K6, A19<='01_PRESUPUESTO_CRONOGRAMA_BASE'!L6), '01_PRESUPUESTO_CRONOGRAMA_BASE'!M6, 0) + IF(AND(A19>='01_PRESUPUESTO_CRONOGRAMA_BASE'!K7, A19<='01_PRESUPUESTO_CRONOGRAMA_BASE'!L7), '01_PRESUPUESTO_CRONOGRAMA_BASE'!M7, 0) + IF(AND(A19>='01_PRESUPUESTO_CRONOGRAMA_BASE'!K8, A19<='01_PRESUPUESTO_CRONOGRAMA_BASE'!L8), '01_PRESUPUESTO_CRONOGRAMA_BASE'!M8, 0) + IF(AND(A19>='01_PRESUPUESTO_CRONOGRAMA_BASE'!K9, A19<='01_PRESUPUESTO_CRONOGRAMA_BASE'!L9), '01_PRESUPUESTO_CRONOGRAMA_BASE'!M9, 0) | F19: =SUMIFS(E$2:E19, C$2:C19, C19)
A20: 5 | B20: 2026-08-05 | C20: WBS-300 | D20: Red de Agua Potable y Conexiones Domiciliarias | E20: =IF(AND(A20>='01_PRESUPUESTO_CRONOGRAMA_BASE'!K10, A20<='01_PRESUPUESTO_CRONOGRAMA_BASE'!L10), '01_PRESUPUESTO_CRONOGRAMA_BASE'!M10, 0) + IF(AND(A20>='01_PRESUPUESTO_CRONOGRAMA_BASE'!K11, A20<='01_PRESUPUESTO_CRONOGRAMA_BASE'!L11), '01_PRESUPUESTO_CRONOGRAMA_BASE'!M11, 0) | F20: =SUMIFS(E$2:E20, C$2:C20, C20)
A21: 5 | B21: 2026-08-05 | C21: WBS-400 | D21: Pruebas Hidráulicas, Desinfección y Entrega | E21: =IF(AND(A21>='01_PRESUPUESTO_CRONOGRAMA_BASE'!K12, A21<='01_PRESUPUESTO_CRONOGRAMA_BASE'!L12), '01_PRESUPUESTO_CRONOGRAMA_BASE'!M12, 0) | F21: =SUMIFS(E$2:E21, C$2:C21, C21)
A22: 6 | B22: 2026-08-06 | C22: WBS-100 | D22: Obras Preliminares, Trazo y Movilización | E22: =IF(AND(A22>='01_PRESUPUESTO_CRONOGRAMA_BASE'!K2, A22<='01_PRESUPUESTO_CRONOGRAMA_BASE'!L2), '01_PRESUPUESTO_CRONOGRAMA_BASE'!M2, 0) + IF(AND(A22>='01_PRESUPUESTO_CRONOGRAMA_BASE'!K3, A22<='01_PRESUPUESTO_CRONOGRAMA_BASE'!L3), '01_PRESUPUESTO_CRONOGRAMA_BASE'!M3, 0) | F22: =SUMIFS(E$2:E22, C$2:C22, C22)
A23: 6 | B23: 2026-08-06 | C23: WBS-200 | D23: Red de Alcantarillado, Zanjas y Buzones | E23: =IF(AND(A23>='01_PRESUPUESTO_CRONOGRAMA_BASE'!K4, A23<='01_PRESUPUESTO_CRONOGRAMA_BASE'!L4), '01_PRESUPUESTO_CRONOGRAMA_BASE'!M4, 0) + IF(AND(A23>='01_PRESUPUESTO_CRONOGRAMA_BASE'!K5, A23<='01_PRESUPUESTO_CRONOGRAMA_BASE'!L5), '01_PRESUPUESTO_CRONOGRAMA_BASE'!M5, 0) + IF(AND(A23>='01_PRESUPUESTO_CRONOGRAMA_BASE'!K6, A23<='01_PRESUPUESTO_CRONOGRAMA_BASE'!L6), '01_PRESUPUESTO_CRONOGRAMA_BASE'!M6, 0) + IF(AND(A23>='01_PRESUPUESTO_CRONOGRAMA_BASE'!K7, A23<='01_PRESUPUESTO_CRONOGRAMA_BASE'!L7), '01_PRESUPUESTO_CRONOGRAMA_BASE'!M7, 0) + IF(AND(A23>='01_PRESUPUESTO_CRONOGRAMA_BASE'!K8, A23<='01_PRESUPUESTO_CRONOGRAMA_BASE'!L8), '01_PRESUPUESTO_CRONOGRAMA_BASE'!M8, 0) + IF(AND(A23>='01_PRESUPUESTO_CRONOGRAMA_BASE'!K9, A23<='01_PRESUPUESTO_CRONOGRAMA_BASE'!L9), '01_PRESUPUESTO_CRONOGRAMA_BASE'!M9, 0) | F23: =SUMIFS(E$2:E23, C$2:C23, C23)
A24: 6 | B24: 2026-08-06 | C24: WBS-300 | D24: Red de Agua Potable y Conexiones Domiciliarias | E24: =IF(AND(A24>='01_PRESUPUESTO_CRONOGRAMA_BASE'!K10, A24<='01_PRESUPUESTO_CRONOGRAMA_BASE'!L10), '01_PRESUPUESTO_CRONOGRAMA_BASE'!M10, 0) + IF(AND(A24>='01_PRESUPUESTO_CRONOGRAMA_BASE'!K11, A24<='01_PRESUPUESTO_CRONOGRAMA_BASE'!L11), '01_PRESUPUESTO_CRONOGRAMA_BASE'!M11, 0) | F24: =SUMIFS(E$2:E24, C$2:C24, C24)
A25: 6 | B25: 2026-08-06 | C25: WBS-400 | D25: Pruebas Hidráulicas, Desinfección y Entrega | E25: =IF(AND(A25>='01_PRESUPUESTO_CRONOGRAMA_BASE'!K12, A25<='01_PRESUPUESTO_CRONOGRAMA_BASE'!L12), '01_PRESUPUESTO_CRONOGRAMA_BASE'!M12, 0) | F25: =SUMIFS(E$2:E25, C$2:C25, C25)
A26: 7 | B26: 2026-08-07 | C26: WBS-100 | D26: Obras Preliminares, Trazo y Movilización | E26: =IF(AND(A26>='01_PRESUPUESTO_CRONOGRAMA_BASE'!K2, A26<='01_PRESUPUESTO_CRONOGRAMA_BASE'!L2), '01_PRESUPUESTO_CRONOGRAMA_BASE'!M2, 0) + IF(AND(A26>='01_PRESUPUESTO_CRONOGRAMA_BASE'!K3, A26<='01_PRESUPUESTO_CRONOGRAMA_BASE'!L3), '01_PRESUPUESTO_CRONOGRAMA_BASE'!M3, 0) | F26: =SUMIFS(E$2:E26, C$2:C26, C26)
A27: 7 | B27: 2026-08-07 | C27: WBS-200 | D27: Red de Alcantarillado, Zanjas y Buzones | E27: =IF(AND(A27>='01_PRESUPUESTO_CRONOGRAMA_BASE'!K4, A27<='01_PRESUPUESTO_CRONOGRAMA_BASE'!L4), '01_PRESUPUESTO_CRONOGRAMA_BASE'!M4, 0) + IF(AND(A27>='01_PRESUPUESTO_CRONOGRAMA_BASE'!K5, A27<='01_PRESUPUESTO_CRONOGRAMA_BASE'!L5), '01_PRESUPUESTO_CRONOGRAMA_BASE'!M5, 0) + IF(AND(A27>='01_PRESUPUESTO_CRONOGRAMA_BASE'!K6, A27<='01_PRESUPUESTO_CRONOGRAMA_BASE'!L6), '01_PRESUPUESTO_CRONOGRAMA_BASE'!M6, 0) + IF(AND(A27>='01_PRESUPUESTO_CRONOGRAMA_BASE'!K7, A27<='01_PRESUPUESTO_CRONOGRAMA_BASE'!L7), '01_PRESUPUESTO_CRONOGRAMA_BASE'!M7, 0) + IF(AND(A27>='01_PRESUPUESTO_CRONOGRAMA_BASE'!K8, A27<='01_PRESUPUESTO_CRONOGRAMA_BASE'!L8), '01_PRESUPUESTO_CRONOGRAMA_BASE'!M8, 0) + IF(AND(A27>='01_PRESUPUESTO_CRONOGRAMA_BASE'!K9, A27<='01_PRESUPUESTO_CRONOGRAMA_BASE'!L9), '01_PRESUPUESTO_CRONOGRAMA_BASE'!M9, 0) | F27: =SUMIFS(E$2:E27, C$2:C27, C27)
A28: 7 | B28: 2026-08-07 | C28: WBS-300 | D28: Red de Agua Potable y Conexiones Domiciliarias | E28: =IF(AND(A28>='01_PRESUPUESTO_CRONOGRAMA_BASE'!K10, A28<='01_PRESUPUESTO_CRONOGRAMA_BASE'!L10), '01_PRESUPUESTO_CRONOGRAMA_BASE'!M10, 0) + IF(AND(A28>='01_PRESUPUESTO_CRONOGRAMA_BASE'!K11, A28<='01_PRESUPUESTO_CRONOGRAMA_BASE'!L11), '01_PRESUPUESTO_CRONOGRAMA_BASE'!M11, 0) | F28: =SUMIFS(E$2:E28, C$2:C28, C28)
A29: 7 | B29: 2026-08-07 | C29: WBS-400 | D29: Pruebas Hidráulicas, Desinfección y Entrega | E29: =IF(AND(A29>='01_PRESUPUESTO_CRONOGRAMA_BASE'!K12, A29<='01_PRESUPUESTO_CRONOGRAMA_BASE'!L12), '01_PRESUPUESTO_CRONOGRAMA_BASE'!M12, 0) | F29: =SUMIFS(E$2:E29, C$2:C29, C29)
A30: 8 | B30: 2026-08-08 | C30: WBS-100 | D30: Obras Preliminares, Trazo y Movilización | E30: =IF(AND(A30>='01_PRESUPUESTO_CRONOGRAMA_BASE'!K2, A30<='01_PRESUPUESTO_CRONOGRAMA_BASE'!L2), '01_PRESUPUESTO_CRONOGRAMA_BASE'!M2, 0) + IF(AND(A30>='01_PRESUPUESTO_CRONOGRAMA_BASE'!K3, A30<='01_PRESUPUESTO_CRONOGRAMA_BASE'!L3), '01_PRESUPUESTO_CRONOGRAMA_BASE'!M3, 0) | F30: =SUMIFS(E$2:E30, C$2:C30, C30)
A31: 8 | B31: 2026-08-08 | C31: WBS-200 | D31: Red de Alcantarillado, Zanjas y Buzones | E31: =IF(AND(A31>='01_PRESUPUESTO_CRONOGRAMA_BASE'!K4, A31<='01_PRESUPUESTO_CRONOGRAMA_BASE'!L4), '01_PRESUPUESTO_CRONOGRAMA_BASE'!M4, 0) + IF(AND(A31>='01_PRESUPUESTO_CRONOGRAMA_BASE'!K5, A31<='01_PRESUPUESTO_CRONOGRAMA_BASE'!L5), '01_PRESUPUESTO_CRONOGRAMA_BASE'!M5, 0) + IF(AND(A31>='01_PRESUPUESTO_CRONOGRAMA_BASE'!K6, A31<='01_PRESUPUESTO_CRONOGRAMA_BASE'!L6), '01_PRESUPUESTO_CRONOGRAMA_BASE'!M6, 0) + IF(AND(A31>='01_PRESUPUESTO_CRONOGRAMA_BASE'!K7, A31<='01_PRESUPUESTO_CRONOGRAMA_BASE'!L7), '01_PRESUPUESTO_CRONOGRAMA_BASE'!M7, 0) + IF(AND(A31>='01_PRESUPUESTO_CRONOGRAMA_BASE'!K8, A31<='01_PRESUPUESTO_CRONOGRAMA_BASE'!L8), '01_PRESUPUESTO_CRONOGRAMA_BASE'!M8, 0) + IF(AND(A31>='01_PRESUPUESTO_CRONOGRAMA_BASE'!K9, A31<='01_PRESUPUESTO_CRONOGRAMA_BASE'!L9), '01_PRESUPUESTO_CRONOGRAMA_BASE'!M9, 0) | F31: =SUMIFS(E$2:E31, C$2:C31, C31)
A32: 8 | B32: 2026-08-08 | C32: WBS-300 | D32: Red de Agua Potable y Conexiones Domiciliarias | E32: =IF(AND(A32>='01_PRESUPUESTO_CRONOGRAMA_BASE'!K10, A32<='01_PRESUPUESTO_CRONOGRAMA_BASE'!L10), '01_PRESUPUESTO_CRONOGRAMA_BASE'!M10, 0) + IF(AND(A32>='01_PRESUPUESTO_CRONOGRAMA_BASE'!K11, A32<='01_PRESUPUESTO_CRONOGRAMA_BASE'!L11), '01_PRESUPUESTO_CRONOGRAMA_BASE'!M11, 0) | F32: =SUMIFS(E$2:E32, C$2:C32, C32)
A33: 8 | B33: 2026-08-08 | C33: WBS-400 | D33: Pruebas Hidráulicas, Desinfección y Entrega | E33: =IF(AND(A33>='01_PRESUPUESTO_CRONOGRAMA_BASE'!K12, A33<='01_PRESUPUESTO_CRONOGRAMA_BASE'!L12), '01_PRESUPUESTO_CRONOGRAMA_BASE'!M12, 0) | F33: =SUMIFS(E$2:E33, C$2:C33, C33)
A34: 9 | B34: 2026-08-09 | C34: WBS-100 | D34: Obras Preliminares, Trazo y Movilización | E34: =IF(AND(A34>='01_PRESUPUESTO_CRONOGRAMA_BASE'!K2, A34<='01_PRESUPUESTO_CRONOGRAMA_BASE'!L2), '01_PRESUPUESTO_CRONOGRAMA_BASE'!M2, 0) + IF(AND(A34>='01_PRESUPUESTO_CRONOGRAMA_BASE'!K3, A34<='01_PRESUPUESTO_CRONOGRAMA_BASE'!L3), '01_PRESUPUESTO_CRONOGRAMA_BASE'!M3, 0) | F34: =SUMIFS(E$2:E34, C$2:C34, C34)
A35: 9 | B35: 2026-08-09 | C35: WBS-200 | D35: Red de Alcantarillado, Zanjas y Buzones | E35: =IF(AND(A35>='01_PRESUPUESTO_CRONOGRAMA_BASE'!K4, A35<='01_PRESUPUESTO_CRONOGRAMA_BASE'!L4), '01_PRESUPUESTO_CRONOGRAMA_BASE'!M4, 0) + IF(AND(A35>='01_PRESUPUESTO_CRONOGRAMA_BASE'!K5, A35<='01_PRESUPUESTO_CRONOGRAMA_BASE'!L5), '01_PRESUPUESTO_CRONOGRAMA_BASE'!M5, 0) + IF(AND(A35>='01_PRESUPUESTO_CRONOGRAMA_BASE'!K6, A35<='01_PRESUPUESTO_CRONOGRAMA_BASE'!L6), '01_PRESUPUESTO_CRONOGRAMA_BASE'!M6, 0) + IF(AND(A35>='01_PRESUPUESTO_CRONOGRAMA_BASE'!K7, A35<='01_PRESUPUESTO_CRONOGRAMA_BASE'!L7), '01_PRESUPUESTO_CRONOGRAMA_BASE'!M7, 0) + IF(AND(A35>='01_PRESUPUESTO_CRONOGRAMA_BASE'!K8, A35<='01_PRESUPUESTO_CRONOGRAMA_BASE'!L8), '01_PRESUPUESTO_CRONOGRAMA_BASE'!M8, 0) + IF(AND(A35>='01_PRESUPUESTO_CRONOGRAMA_BASE'!K9, A35<='01_PRESUPUESTO_CRONOGRAMA_BASE'!L9), '01_PRESUPUESTO_CRONOGRAMA_BASE'!M9, 0) | F35: =SUMIFS(E$2:E35, C$2:C35, C35)
A36: 9 | B36: 2026-08-09 | C36: WBS-300 | D36: Red de Agua Potable y Conexiones Domiciliarias | E36: =IF(AND(A36>='01_PRESUPUESTO_CRONOGRAMA_BASE'!K10, A36<='01_PRESUPUESTO_CRONOGRAMA_BASE'!L10), '01_PRESUPUESTO_CRONOGRAMA_BASE'!M10, 0) + IF(AND(A36>='01_PRESUPUESTO_CRONOGRAMA_BASE'!K11, A36<='01_PRESUPUESTO_CRONOGRAMA_BASE'!L11), '01_PRESUPUESTO_CRONOGRAMA_BASE'!M11, 0) | F36: =SUMIFS(E$2:E36, C$2:C36, C36)
A37: 9 | B37: 2026-08-09 | C37: WBS-400 | D37: Pruebas Hidráulicas, Desinfección y Entrega | E37: =IF(AND(A37>='01_PRESUPUESTO_CRONOGRAMA_BASE'!K12, A37<='01_PRESUPUESTO_CRONOGRAMA_BASE'!L12), '01_PRESUPUESTO_CRONOGRAMA_BASE'!M12, 0) | F37: =SUMIFS(E$2:E37, C$2:C37, C37)
A38: 10 | B38: 2026-08-10 | C38: WBS-100 | D38: Obras Preliminares, Trazo y Movilización | E38: =IF(AND(A38>='01_PRESUPUESTO_CRONOGRAMA_BASE'!K2, A38<='01_PRESUPUESTO_CRONOGRAMA_BASE'!L2), '01_PRESUPUESTO_CRONOGRAMA_BASE'!M2, 0) + IF(AND(A38>='01_PRESUPUESTO_CRONOGRAMA_BASE'!K3, A38<='01_PRESUPUESTO_CRONOGRAMA_BASE'!L3), '01_PRESUPUESTO_CRONOGRAMA_BASE'!M3, 0) | F38: =SUMIFS(E$2:E38, C$2:C38, C38)
A39: 10 | B39: 2026-08-10 | C39: WBS-200 | D39: Red de Alcantarillado, Zanjas y Buzones | E39: =IF(AND(A39>='01_PRESUPUESTO_CRONOGRAMA_BASE'!K4, A39<='01_PRESUPUESTO_CRONOGRAMA_BASE'!L4), '01_PRESUPUESTO_CRONOGRAMA_BASE'!M4, 0) + IF(AND(A39>='01_PRESUPUESTO_CRONOGRAMA_BASE'!K5, A39<='01_PRESUPUESTO_CRONOGRAMA_BASE'!L5), '01_PRESUPUESTO_CRONOGRAMA_BASE'!M5, 0) + IF(AND(A39>='01_PRESUPUESTO_CRONOGRAMA_BASE'!K6, A39<='01_PRESUPUESTO_CRONOGRAMA_BASE'!L6), '01_PRESUPUESTO_CRONOGRAMA_BASE'!M6, 0) + IF(AND(A39>='01_PRESUPUESTO_CRONOGRAMA_BASE'!K7, A39<='01_PRESUPUESTO_CRONOGRAMA_BASE'!L7), '01_PRESUPUESTO_CRONOGRAMA_BASE'!M7, 0) + IF(AND(A39>='01_PRESUPUESTO_CRONOGRAMA_BASE'!K8, A39<='01_PRESUPUESTO_CRONOGRAMA_BASE'!L8), '01_PRESUPUESTO_CRONOGRAMA_BASE'!M8, 0) + IF(AND(A39>='01_PRESUPUESTO_CRONOGRAMA_BASE'!K9, A39<='01_PRESUPUESTO_CRONOGRAMA_BASE'!L9), '01_PRESUPUESTO_CRONOGRAMA_BASE'!M9, 0) | F39: =SUMIFS(E$2:E39, C$2:C39, C39)
A40: 10 | B40: 2026-08-10 | C40: WBS-300 | D40: Red de Agua Potable y Conexiones Domiciliarias | E40: =IF(AND(A40>='01_PRESUPUESTO_CRONOGRAMA_BASE'!K10, A40<='01_PRESUPUESTO_CRONOGRAMA_BASE'!L10), '01_PRESUPUESTO_CRONOGRAMA_BASE'!M10, 0) + IF(AND(A40>='01_PRESUPUESTO_CRONOGRAMA_BASE'!K11, A40<='01_PRESUPUESTO_CRONOGRAMA_BASE'!L11), '01_PRESUPUESTO_CRONOGRAMA_BASE'!M11, 0) | F40: =SUMIFS(E$2:E40, C$2:C40, C40)
A41: 10 | B41: 2026-08-10 | C41: WBS-400 | D41: Pruebas Hidráulicas, Desinfección y Entrega | E41: =IF(AND(A41>='01_PRESUPUESTO_CRONOGRAMA_BASE'!K12, A41<='01_PRESUPUESTO_CRONOGRAMA_BASE'!L12), '01_PRESUPUESTO_CRONOGRAMA_BASE'!M12, 0) | F41: =SUMIFS(E$2:E41, C$2:C41, C41)
A42: 11 | B42: 2026-08-11 | C42: WBS-100 | D42: Obras Preliminares, Trazo y Movilización | E42: =IF(AND(A42>='01_PRESUPUESTO_CRONOGRAMA_BASE'!K2, A42<='01_PRESUPUESTO_CRONOGRAMA_BASE'!L2), '01_PRESUPUESTO_CRONOGRAMA_BASE'!M2, 0) + IF(AND(A42>='01_PRESUPUESTO_CRONOGRAMA_BASE'!K3, A42<='01_PRESUPUESTO_CRONOGRAMA_BASE'!L3), '01_PRESUPUESTO_CRONOGRAMA_BASE'!M3, 0) | F42: =SUMIFS(E$2:E42, C$2:C42, C42)
A43: 11 | B43: 2026-08-11 | C43: WBS-200 | D43: Red de Alcantarillado, Zanjas y Buzones | E43: =IF(AND(A43>='01_PRESUPUESTO_CRONOGRAMA_BASE'!K4, A43<='01_PRESUPUESTO_CRONOGRAMA_BASE'!L4), '01_PRESUPUESTO_CRONOGRAMA_BASE'!M4, 0) + IF(AND(A43>='01_PRESUPUESTO_CRONOGRAMA_BASE'!K5, A43<='01_PRESUPUESTO_CRONOGRAMA_BASE'!L5), '01_PRESUPUESTO_CRONOGRAMA_BASE'!M5, 0) + IF(AND(A43>='01_PRESUPUESTO_CRONOGRAMA_BASE'!K6, A43<='01_PRESUPUESTO_CRONOGRAMA_BASE'!L6), '01_PRESUPUESTO_CRONOGRAMA_BASE'!M6, 0) + IF(AND(A43>='01_PRESUPUESTO_CRONOGRAMA_BASE'!K7, A43<='01_PRESUPUESTO_CRONOGRAMA_BASE'!L7), '01_PRESUPUESTO_CRONOGRAMA_BASE'!M7, 0) + IF(AND(A43>='01_PRESUPUESTO_CRONOGRAMA_BASE'!K8, A43<='01_PRESUPUESTO_CRONOGRAMA_BASE'!L8), '01_PRESUPUESTO_CRONOGRAMA_BASE'!M8, 0) + IF(AND(A43>='01_PRESUPUESTO_CRONOGRAMA_BASE'!K9, A43<='01_PRESUPUESTO_CRONOGRAMA_BASE'!L9), '01_PRESUPUESTO_CRONOGRAMA_BASE'!M9, 0) | F43: =SUMIFS(E$2:E43, C$2:C43, C43)
A44: 11 | B44: 2026-08-11 | C44: WBS-300 | D44: Red de Agua Potable y Conexiones Domiciliarias | E44: =IF(AND(A44>='01_PRESUPUESTO_CRONOGRAMA_BASE'!K10, A44<='01_PRESUPUESTO_CRONOGRAMA_BASE'!L10), '01_PRESUPUESTO_CRONOGRAMA_BASE'!M10, 0) + IF(AND(A44>='01_PRESUPUESTO_CRONOGRAMA_BASE'!K11, A44<='01_PRESUPUESTO_CRONOGRAMA_BASE'!L11), '01_PRESUPUESTO_CRONOGRAMA_BASE'!M11, 0) | F44: =SUMIFS(E$2:E44, C$2:C44, C44)
A45: 11 | B45: 2026-08-11 | C45: WBS-400 | D45: Pruebas Hidráulicas, Desinfección y Entrega | E45: =IF(AND(A45>='01_PRESUPUESTO_CRONOGRAMA_BASE'!K12, A45<='01_PRESUPUESTO_CRONOGRAMA_BASE'!L12), '01_PRESUPUESTO_CRONOGRAMA_BASE'!M12, 0) | F45: =SUMIFS(E$2:E45, C$2:C45, C45)
A46: 12 | B46: 2026-08-12 | C46: WBS-100 | D46: Obras Preliminares, Trazo y Movilización | E46: =IF(AND(A46>='01_PRESUPUESTO_CRONOGRAMA_BASE'!K2, A46<='01_PRESUPUESTO_CRONOGRAMA_BASE'!L2), '01_PRESUPUESTO_CRONOGRAMA_BASE'!M2, 0) + IF(AND(A46>='01_PRESUPUESTO_CRONOGRAMA_BASE'!K3, A46<='01_PRESUPUESTO_CRONOGRAMA_BASE'!L3), '01_PRESUPUESTO_CRONOGRAMA_BASE'!M3, 0) | F46: =SUMIFS(E$2:E46, C$2:C46, C46)
A47: 12 | B47: 2026-08-12 | C47: WBS-200 | D47: Red de Alcantarillado, Zanjas y Buzones | E47: =IF(AND(A47>='01_PRESUPUESTO_CRONOGRAMA_BASE'!K4, A47<='01_PRESUPUESTO_CRONOGRAMA_BASE'!L4), '01_PRESUPUESTO_CRONOGRAMA_BASE'!M4, 0) + IF(AND(A47>='01_PRESUPUESTO_CRONOGRAMA_BASE'!K5, A47<='01_PRESUPUESTO_CRONOGRAMA_BASE'!L5), '01_PRESUPUESTO_CRONOGRAMA_BASE'!M5, 0) + IF(AND(A47>='01_PRESUPUESTO_CRONOGRAMA_BASE'!K6, A47<='01_PRESUPUESTO_CRONOGRAMA_BASE'!L6), '01_PRESUPUESTO_CRONOGRAMA_BASE'!M6, 0) + IF(AND(A47>='01_PRESUPUESTO_CRONOGRAMA_BASE'!K7, A47<='01_PRESUPUESTO_CRONOGRAMA_BASE'!L7), '01_PRESUPUESTO_CRONOGRAMA_BASE'!M7, 0) + IF(AND(A47>='01_PRESUPUESTO_CRONOGRAMA_BASE'!K8, A47<='01_PRESUPUESTO_CRONOGRAMA_BASE'!L8), '01_PRESUPUESTO_CRONOGRAMA_BASE'!M8, 0) + IF(AND(A47>='01_PRESUPUESTO_CRONOGRAMA_BASE'!K9, A47<='01_PRESUPUESTO_CRONOGRAMA_BASE'!L9), '01_PRESUPUESTO_CRONOGRAMA_BASE'!M9, 0) | F47: =SUMIFS(E$2:E47, C$2:C47, C47)
A48: 12 | B48: 2026-08-12 | C48: WBS-300 | D48: Red de Agua Potable y Conexiones Domiciliarias | E48: =IF(AND(A48>='01_PRESUPUESTO_CRONOGRAMA_BASE'!K10, A48<='01_PRESUPUESTO_CRONOGRAMA_BASE'!L10), '01_PRESUPUESTO_CRONOGRAMA_BASE'!M10, 0) + IF(AND(A48>='01_PRESUPUESTO_CRONOGRAMA_BASE'!K11, A48<='01_PRESUPUESTO_CRONOGRAMA_BASE'!L11), '01_PRESUPUESTO_CRONOGRAMA_BASE'!M11, 0) | F48: =SUMIFS(E$2:E48, C$2:C48, C48)
A49: 12 | B49: 2026-08-12 | C49: WBS-400 | D49: Pruebas Hidráulicas, Desinfección y Entrega | E49: =IF(AND(A49>='01_PRESUPUESTO_CRONOGRAMA_BASE'!K12, A49<='01_PRESUPUESTO_CRONOGRAMA_BASE'!L12), '01_PRESUPUESTO_CRONOGRAMA_BASE'!M12, 0) | F49: =SUMIFS(E$2:E49, C$2:C49, C49)
A50: 13 | B50: 2026-08-13 | C50: WBS-100 | D50: Obras Preliminares, Trazo y Movilización | E50: =IF(AND(A50>='01_PRESUPUESTO_CRONOGRAMA_BASE'!K2, A50<='01_PRESUPUESTO_CRONOGRAMA_BASE'!L2), '01_PRESUPUESTO_CRONOGRAMA_BASE'!M2, 0) + IF(AND(A50>='01_PRESUPUESTO_CRONOGRAMA_BASE'!K3, A50<='01_PRESUPUESTO_CRONOGRAMA_BASE'!L3), '01_PRESUPUESTO_CRONOGRAMA_BASE'!M3, 0) | F50: =SUMIFS(E$2:E50, C$2:C50, C50)
A51: 13 | B51: 2026-08-13 | C51: WBS-200 | D51: Red de Alcantarillado, Zanjas y Buzones | E51: =IF(AND(A51>='01_PRESUPUESTO_CRONOGRAMA_BASE'!K4, A51<='01_PRESUPUESTO_CRONOGRAMA_BASE'!L4), '01_PRESUPUESTO_CRONOGRAMA_BASE'!M4, 0) + IF(AND(A51>='01_PRESUPUESTO_CRONOGRAMA_BASE'!K5, A51<='01_PRESUPUESTO_CRONOGRAMA_BASE'!L5), '01_PRESUPUESTO_CRONOGRAMA_BASE'!M5, 0) + IF(AND(A51>='01_PRESUPUESTO_CRONOGRAMA_BASE'!K6, A51<='01_PRESUPUESTO_CRONOGRAMA_BASE'!L6), '01_PRESUPUESTO_CRONOGRAMA_BASE'!M6, 0) + IF(AND(A51>='01_PRESUPUESTO_CRONOGRAMA_BASE'!K7, A51<='01_PRESUPUESTO_CRONOGRAMA_BASE'!L7), '01_PRESUPUESTO_CRONOGRAMA_BASE'!M7, 0) + IF(AND(A51>='01_PRESUPUESTO_CRONOGRAMA_BASE'!K8, A51<='01_PRESUPUESTO_CRONOGRAMA_BASE'!L8), '01_PRESUPUESTO_CRONOGRAMA_BASE'!M8, 0) + IF(AND(A51>='01_PRESUPUESTO_CRONOGRAMA_BASE'!K9, A51<='01_PRESUPUESTO_CRONOGRAMA_BASE'!L9), '01_PRESUPUESTO_CRONOGRAMA_BASE'!M9, 0) | F51: =SUMIFS(E$2:E51, C$2:C51, C51)
A52: 13 | B52: 2026-08-13 | C52: WBS-300 | D52: Red de Agua Potable y Conexiones Domiciliarias | E52: =IF(AND(A52>='01_PRESUPUESTO_CRONOGRAMA_BASE'!K10, A52<='01_PRESUPUESTO_CRONOGRAMA_BASE'!L10), '01_PRESUPUESTO_CRONOGRAMA_BASE'!M10, 0) + IF(AND(A52>='01_PRESUPUESTO_CRONOGRAMA_BASE'!K11, A52<='01_PRESUPUESTO_CRONOGRAMA_BASE'!L11), '01_PRESUPUESTO_CRONOGRAMA_BASE'!M11, 0) | F52: =SUMIFS(E$2:E52, C$2:C52, C52)
A53: 13 | B53: 2026-08-13 | C53: WBS-400 | D53: Pruebas Hidráulicas, Desinfección y Entrega | E53: =IF(AND(A53>='01_PRESUPUESTO_CRONOGRAMA_BASE'!K12, A53<='01_PRESUPUESTO_CRONOGRAMA_BASE'!L12), '01_PRESUPUESTO_CRONOGRAMA_BASE'!M12, 0) | F53: =SUMIFS(E$2:E53, C$2:C53, C53)
A54: 14 | B54: 2026-08-14 | C54: WBS-100 | D54: Obras Preliminares, Trazo y Movilización | E54: =IF(AND(A54>='01_PRESUPUESTO_CRONOGRAMA_BASE'!K2, A54<='01_PRESUPUESTO_CRONOGRAMA_BASE'!L2), '01_PRESUPUESTO_CRONOGRAMA_BASE'!M2, 0) + IF(AND(A54>='01_PRESUPUESTO_CRONOGRAMA_BASE'!K3, A54<='01_PRESUPUESTO_CRONOGRAMA_BASE'!L3), '01_PRESUPUESTO_CRONOGRAMA_BASE'!M3, 0) | F54: =SUMIFS(E$2:E54, C$2:C54, C54)
A55: 14 | B55: 2026-08-14 | C55: WBS-200 | D55: Red de Alcantarillado, Zanjas y Buzones | E55: =IF(AND(A55>='01_PRESUPUESTO_CRONOGRAMA_BASE'!K4, A55<='01_PRESUPUESTO_CRONOGRAMA_BASE'!L4), '01_PRESUPUESTO_CRONOGRAMA_BASE'!M4, 0) + IF(AND(A55>='01_PRESUPUESTO_CRONOGRAMA_BASE'!K5, A55<='01_PRESUPUESTO_CRONOGRAMA_BASE'!L5), '01_PRESUPUESTO_CRONOGRAMA_BASE'!M5, 0) + IF(AND(A55>='01_PRESUPUESTO_CRONOGRAMA_BASE'!K6, A55<='01_PRESUPUESTO_CRONOGRAMA_BASE'!L6), '01_PRESUPUESTO_CRONOGRAMA_BASE'!M6, 0) + IF(AND(A55>='01_PRESUPUESTO_CRONOGRAMA_BASE'!K7, A55<='01_PRESUPUESTO_CRONOGRAMA_BASE'!L7), '01_PRESUPUESTO_CRONOGRAMA_BASE'!M7, 0) + IF(AND(A55>='01_PRESUPUESTO_CRONOGRAMA_BASE'!K8, A55<='01_PRESUPUESTO_CRONOGRAMA_BASE'!L8), '01_PRESUPUESTO_CRONOGRAMA_BASE'!M8, 0) + IF(AND(A55>='01_PRESUPUESTO_CRONOGRAMA_BASE'!K9, A55<='01_PRESUPUESTO_CRONOGRAMA_BASE'!L9), '01_PRESUPUESTO_CRONOGRAMA_BASE'!M9, 0) | F55: =SUMIFS(E$2:E55, C$2:C55, C55)
A56: 14 | B56: 2026-08-14 | C56: WBS-300 | D56: Red de Agua Potable y Conexiones Domiciliarias | E56: =IF(AND(A56>='01_PRESUPUESTO_CRONOGRAMA_BASE'!K10, A56<='01_PRESUPUESTO_CRONOGRAMA_BASE'!L10), '01_PRESUPUESTO_CRONOGRAMA_BASE'!M10, 0) + IF(AND(A56>='01_PRESUPUESTO_CRONOGRAMA_BASE'!K11, A56<='01_PRESUPUESTO_CRONOGRAMA_BASE'!L11), '01_PRESUPUESTO_CRONOGRAMA_BASE'!M11, 0) | F56: =SUMIFS(E$2:E56, C$2:C56, C56)
A57: 14 | B57: 2026-08-14 | C57: WBS-400 | D57: Pruebas Hidráulicas, Desinfección y Entrega | E57: =IF(AND(A57>='01_PRESUPUESTO_CRONOGRAMA_BASE'!K12, A57<='01_PRESUPUESTO_CRONOGRAMA_BASE'!L12), '01_PRESUPUESTO_CRONOGRAMA_BASE'!M12, 0) | F57: =SUMIFS(E$2:E57, C$2:C57, C57)
A58: 15 | B58: 2026-08-15 | C58: WBS-100 | D58: Obras Preliminares, Trazo y Movilización | E58: =IF(AND(A58>='01_PRESUPUESTO_CRONOGRAMA_BASE'!K2, A58<='01_PRESUPUESTO_CRONOGRAMA_BASE'!L2), '01_PRESUPUESTO_CRONOGRAMA_BASE'!M2, 0) + IF(AND(A58>='01_PRESUPUESTO_CRONOGRAMA_BASE'!K3, A58<='01_PRESUPUESTO_CRONOGRAMA_BASE'!L3), '01_PRESUPUESTO_CRONOGRAMA_BASE'!M3, 0) | F58: =SUMIFS(E$2:E58, C$2:C58, C58)
A59: 15 | B59: 2026-08-15 | C59: WBS-200 | D59: Red de Alcantarillado, Zanjas y Buzones | E59: =IF(AND(A59>='01_PRESUPUESTO_CRONOGRAMA_BASE'!K4, A59<='01_PRESUPUESTO_CRONOGRAMA_BASE'!L4), '01_PRESUPUESTO_CRONOGRAMA_BASE'!M4, 0) + IF(AND(A59>='01_PRESUPUESTO_CRONOGRAMA_BASE'!K5, A59<='01_PRESUPUESTO_CRONOGRAMA_BASE'!L5), '01_PRESUPUESTO_CRONOGRAMA_BASE'!M5, 0) + IF(AND(A59>='01_PRESUPUESTO_CRONOGRAMA_BASE'!K6, A59<='01_PRESUPUESTO_CRONOGRAMA_BASE'!L6), '01_PRESUPUESTO_CRONOGRAMA_BASE'!M6, 0) + IF(AND(A59>='01_PRESUPUESTO_CRONOGRAMA_BASE'!K7, A59<='01_PRESUPUESTO_CRONOGRAMA_BASE'!L7), '01_PRESUPUESTO_CRONOGRAMA_BASE'!M7, 0) + IF(AND(A59>='01_PRESUPUESTO_CRONOGRAMA_BASE'!K8, A59<='01_PRESUPUESTO_CRONOGRAMA_BASE'!L8), '01_PRESUPUESTO_CRONOGRAMA_BASE'!M8, 0) + IF(AND(A59>='01_PRESUPUESTO_CRONOGRAMA_BASE'!K9, A59<='01_PRESUPUESTO_CRONOGRAMA_BASE'!L9), '01_PRESUPUESTO_CRONOGRAMA_BASE'!M9, 0) | F59: =SUMIFS(E$2:E59, C$2:C59, C59)
A60: 15 | B60: 2026-08-15 | C60: WBS-300 | D60: Red de Agua Potable y Conexiones Domiciliarias | E60: =IF(AND(A60>='01_PRESUPUESTO_CRONOGRAMA_BASE'!K10, A60<='01_PRESUPUESTO_CRONOGRAMA_BASE'!L10), '01_PRESUPUESTO_CRONOGRAMA_BASE'!M10, 0) + IF(AND(A60>='01_PRESUPUESTO_CRONOGRAMA_BASE'!K11, A60<='01_PRESUPUESTO_CRONOGRAMA_BASE'!L11), '01_PRESUPUESTO_CRONOGRAMA_BASE'!M11, 0) | F60: =SUMIFS(E$2:E60, C$2:C60, C60)
A61: 15 | B61: 2026-08-15 | C61: WBS-400 | D61: Pruebas Hidráulicas, Desinfección y Entrega | E61: =IF(AND(A61>='01_PRESUPUESTO_CRONOGRAMA_BASE'!K12, A61<='01_PRESUPUESTO_CRONOGRAMA_BASE'!L12), '01_PRESUPUESTO_CRONOGRAMA_BASE'!M12, 0) | F61: =SUMIFS(E$2:E61, C$2:C61, C61)
A62: 16 | B62: 2026-08-16 | C62: WBS-100 | D62: Obras Preliminares, Trazo y Movilización | E62: =IF(AND(A62>='01_PRESUPUESTO_CRONOGRAMA_BASE'!K2, A62<='01_PRESUPUESTO_CRONOGRAMA_BASE'!L2), '01_PRESUPUESTO_CRONOGRAMA_BASE'!M2, 0) + IF(AND(A62>='01_PRESUPUESTO_CRONOGRAMA_BASE'!K3, A62<='01_PRESUPUESTO_CRONOGRAMA_BASE'!L3), '01_PRESUPUESTO_CRONOGRAMA_BASE'!M3, 0) | F62: =SUMIFS(E$2:E62, C$2:C62, C62)
A63: 16 | B63: 2026-08-16 | C63: WBS-200 | D63: Red de Alcantarillado, Zanjas y Buzones | E63: =IF(AND(A63>='01_PRESUPUESTO_CRONOGRAMA_BASE'!K4, A63<='01_PRESUPUESTO_CRONOGRAMA_BASE'!L4), '01_PRESUPUESTO_CRONOGRAMA_BASE'!M4, 0) + IF(AND(A63>='01_PRESUPUESTO_CRONOGRAMA_BASE'!K5, A63<='01_PRESUPUESTO_CRONOGRAMA_BASE'!L5), '01_PRESUPUESTO_CRONOGRAMA_BASE'!M5, 0) + IF(AND(A63>='01_PRESUPUESTO_CRONOGRAMA_BASE'!K6, A63<='01_PRESUPUESTO_CRONOGRAMA_BASE'!L6), '01_PRESUPUESTO_CRONOGRAMA_BASE'!M6, 0) + IF(AND(A63>='01_PRESUPUESTO_CRONOGRAMA_BASE'!K7, A63<='01_PRESUPUESTO_CRONOGRAMA_BASE'!L7), '01_PRESUPUESTO_CRONOGRAMA_BASE'!M7, 0) + IF(AND(A63>='01_PRESUPUESTO_CRONOGRAMA_BASE'!K8, A63<='01_PRESUPUESTO_CRONOGRAMA_BASE'!L8), '01_PRESUPUESTO_CRONOGRAMA_BASE'!M8, 0) + IF(AND(A63>='01_PRESUPUESTO_CRONOGRAMA_BASE'!K9, A63<='01_PRESUPUESTO_CRONOGRAMA_BASE'!L9), '01_PRESUPUESTO_CRONOGRAMA_BASE'!M9, 0) | F63: =SUMIFS(E$2:E63, C$2:C63, C63)
A64: 16 | B64: 2026-08-16 | C64: WBS-300 | D64: Red de Agua Potable y Conexiones Domiciliarias | E64: =IF(AND(A64>='01_PRESUPUESTO_CRONOGRAMA_BASE'!K10, A64<='01_PRESUPUESTO_CRONOGRAMA_BASE'!L10), '01_PRESUPUESTO_CRONOGRAMA_BASE'!M10, 0) + IF(AND(A64>='01_PRESUPUESTO_CRONOGRAMA_BASE'!K11, A64<='01_PRESUPUESTO_CRONOGRAMA_BASE'!L11), '01_PRESUPUESTO_CRONOGRAMA_BASE'!M11, 0) | F64: =SUMIFS(E$2:E64, C$2:C64, C64)
A65: 16 | B65: 2026-08-16 | C65: WBS-400 | D65: Pruebas Hidráulicas, Desinfección y Entrega | E65: =IF(AND(A65>='01_PRESUPUESTO_CRONOGRAMA_BASE'!K12, A65<='01_PRESUPUESTO_CRONOGRAMA_BASE'!L12), '01_PRESUPUESTO_CRONOGRAMA_BASE'!M12, 0) | F65: =SUMIFS(E$2:E65, C$2:C65, C65)
A66: 17 | B66: 2026-08-17 | C66: WBS-100 | D66: Obras Preliminares, Trazo y Movilización | E66: =IF(AND(A66>='01_PRESUPUESTO_CRONOGRAMA_BASE'!K2, A66<='01_PRESUPUESTO_CRONOGRAMA_BASE'!L2), '01_PRESUPUESTO_CRONOGRAMA_BASE'!M2, 0) + IF(AND(A66>='01_PRESUPUESTO_CRONOGRAMA_BASE'!K3, A66<='01_PRESUPUESTO_CRONOGRAMA_BASE'!L3), '01_PRESUPUESTO_CRONOGRAMA_BASE'!M3, 0) | F66: =SUMIFS(E$2:E66, C$2:C66, C66)
A67: 17 | B67: 2026-08-17 | C67: WBS-200 | D67: Red de Alcantarillado, Zanjas y Buzones | E67: =IF(AND(A67>='01_PRESUPUESTO_CRONOGRAMA_BASE'!K4, A67<='01_PRESUPUESTO_CRONOGRAMA_BASE'!L4), '01_PRESUPUESTO_CRONOGRAMA_BASE'!M4, 0) + IF(AND(A67>='01_PRESUPUESTO_CRONOGRAMA_BASE'!K5, A67<='01_PRESUPUESTO_CRONOGRAMA_BASE'!L5), '01_PRESUPUESTO_CRONOGRAMA_BASE'!M5, 0) + IF(AND(A67>='01_PRESUPUESTO_CRONOGRAMA_BASE'!K6, A67<='01_PRESUPUESTO_CRONOGRAMA_BASE'!L6), '01_PRESUPUESTO_CRONOGRAMA_BASE'!M6, 0) + IF(AND(A67>='01_PRESUPUESTO_CRONOGRAMA_BASE'!K7, A67<='01_PRESUPUESTO_CRONOGRAMA_BASE'!L7), '01_PRESUPUESTO_CRONOGRAMA_BASE'!M7, 0) + IF(AND(A67>='01_PRESUPUESTO_CRONOGRAMA_BASE'!K8, A67<='01_PRESUPUESTO_CRONOGRAMA_BASE'!L8), '01_PRESUPUESTO_CRONOGRAMA_BASE'!M8, 0) + IF(AND(A67>='01_PRESUPUESTO_CRONOGRAMA_BASE'!K9, A67<='01_PRESUPUESTO_CRONOGRAMA_BASE'!L9), '01_PRESUPUESTO_CRONOGRAMA_BASE'!M9, 0) | F67: =SUMIFS(E$2:E67, C$2:C67, C67)
A68: 17 | B68: 2026-08-17 | C68: WBS-300 | D68: Red de Agua Potable y Conexiones Domiciliarias | E68: =IF(AND(A68>='01_PRESUPUESTO_CRONOGRAMA_BASE'!K10, A68<='01_PRESUPUESTO_CRONOGRAMA_BASE'!L10), '01_PRESUPUESTO_CRONOGRAMA_BASE'!M10, 0) + IF(AND(A68>='01_PRESUPUESTO_CRONOGRAMA_BASE'!K11, A68<='01_PRESUPUESTO_CRONOGRAMA_BASE'!L11), '01_PRESUPUESTO_CRONOGRAMA_BASE'!M11, 0) | F68: =SUMIFS(E$2:E68, C$2:C68, C68)
A69: 17 | B69: 2026-08-17 | C69: WBS-400 | D69: Pruebas Hidráulicas, Desinfección y Entrega | E69: =IF(AND(A69>='01_PRESUPUESTO_CRONOGRAMA_BASE'!K12, A69<='01_PRESUPUESTO_CRONOGRAMA_BASE'!L12), '01_PRESUPUESTO_CRONOGRAMA_BASE'!M12, 0) | F69: =SUMIFS(E$2:E69, C$2:C69, C69)
A70: 18 | B70: 2026-08-18 | C70: WBS-100 | D70: Obras Preliminares, Trazo y Movilización | E70: =IF(AND(A70>='01_PRESUPUESTO_CRONOGRAMA_BASE'!K2, A70<='01_PRESUPUESTO_CRONOGRAMA_BASE'!L2), '01_PRESUPUESTO_CRONOGRAMA_BASE'!M2, 0) + IF(AND(A70>='01_PRESUPUESTO_CRONOGRAMA_BASE'!K3, A70<='01_PRESUPUESTO_CRONOGRAMA_BASE'!L3), '01_PRESUPUESTO_CRONOGRAMA_BASE'!M3, 0) | F70: =SUMIFS(E$2:E70, C$2:C70, C70)
A71: 18 | B71: 2026-08-18 | C71: WBS-200 | D71: Red de Alcantarillado, Zanjas y Buzones | E71: =IF(AND(A71>='01_PRESUPUESTO_CRONOGRAMA_BASE'!K4, A71<='01_PRESUPUESTO_CRONOGRAMA_BASE'!L4), '01_PRESUPUESTO_CRONOGRAMA_BASE'!M4, 0) + IF(AND(A71>='01_PRESUPUESTO_CRONOGRAMA_BASE'!K5, A71<='01_PRESUPUESTO_CRONOGRAMA_BASE'!L5), '01_PRESUPUESTO_CRONOGRAMA_BASE'!M5, 0) + IF(AND(A71>='01_PRESUPUESTO_CRONOGRAMA_BASE'!K6, A71<='01_PRESUPUESTO_CRONOGRAMA_BASE'!L6), '01_PRESUPUESTO_CRONOGRAMA_BASE'!M6, 0) + IF(AND(A71>='01_PRESUPUESTO_CRONOGRAMA_BASE'!K7, A71<='01_PRESUPUESTO_CRONOGRAMA_BASE'!L7), '01_PRESUPUESTO_CRONOGRAMA_BASE'!M7, 0) + IF(AND(A71>='01_PRESUPUESTO_CRONOGRAMA_BASE'!K8, A71<='01_PRESUPUESTO_CRONOGRAMA_BASE'!L8), '01_PRESUPUESTO_CRONOGRAMA_BASE'!M8, 0) + IF(AND(A71>='01_PRESUPUESTO_CRONOGRAMA_BASE'!K9, A71<='01_PRESUPUESTO_CRONOGRAMA_BASE'!L9), '01_PRESUPUESTO_CRONOGRAMA_BASE'!M9, 0) | F71: =SUMIFS(E$2:E71, C$2:C71, C71)
A72: 18 | B72: 2026-08-18 | C72: WBS-300 | D72: Red de Agua Potable y Conexiones Domiciliarias | E72: =IF(AND(A72>='01_PRESUPUESTO_CRONOGRAMA_BASE'!K10, A72<='01_PRESUPUESTO_CRONOGRAMA_BASE'!L10), '01_PRESUPUESTO_CRONOGRAMA_BASE'!M10, 0) + IF(AND(A72>='01_PRESUPUESTO_CRONOGRAMA_BASE'!K11, A72<='01_PRESUPUESTO_CRONOGRAMA_BASE'!L11), '01_PRESUPUESTO_CRONOGRAMA_BASE'!M11, 0) | F72: =SUMIFS(E$2:E72, C$2:C72, C72)
A73: 18 | B73: 2026-08-18 | C73: WBS-400 | D73: Pruebas Hidráulicas, Desinfección y Entrega | E73: =IF(AND(A73>='01_PRESUPUESTO_CRONOGRAMA_BASE'!K12, A73<='01_PRESUPUESTO_CRONOGRAMA_BASE'!L12), '01_PRESUPUESTO_CRONOGRAMA_BASE'!M12, 0) | F73: =SUMIFS(E$2:E73, C$2:C73, C73)
A74: 19 | B74: 2026-08-19 | C74: WBS-100 | D74: Obras Preliminares, Trazo y Movilización | E74: =IF(AND(A74>='01_PRESUPUESTO_CRONOGRAMA_BASE'!K2, A74<='01_PRESUPUESTO_CRONOGRAMA_BASE'!L2), '01_PRESUPUESTO_CRONOGRAMA_BASE'!M2, 0) + IF(AND(A74>='01_PRESUPUESTO_CRONOGRAMA_BASE'!K3, A74<='01_PRESUPUESTO_CRONOGRAMA_BASE'!L3), '01_PRESUPUESTO_CRONOGRAMA_BASE'!M3, 0) | F74: =SUMIFS(E$2:E74, C$2:C74, C74)
A75: 19 | B75: 2026-08-19 | C75: WBS-200 | D75: Red de Alcantarillado, Zanjas y Buzones | E75: =IF(AND(A75>='01_PRESUPUESTO_CRONOGRAMA_BASE'!K4, A75<='01_PRESUPUESTO_CRONOGRAMA_BASE'!L4), '01_PRESUPUESTO_CRONOGRAMA_BASE'!M4, 0) + IF(AND(A75>='01_PRESUPUESTO_CRONOGRAMA_BASE'!K5, A75<='01_PRESUPUESTO_CRONOGRAMA_BASE'!L5), '01_PRESUPUESTO_CRONOGRAMA_BASE'!M5, 0) + IF(AND(A75>='01_PRESUPUESTO_CRONOGRAMA_BASE'!K6, A75<='01_PRESUPUESTO_CRONOGRAMA_BASE'!L6), '01_PRESUPUESTO_CRONOGRAMA_BASE'!M6, 0) + IF(AND(A75>='01_PRESUPUESTO_CRONOGRAMA_BASE'!K7, A75<='01_PRESUPUESTO_CRONOGRAMA_BASE'!L7), '01_PRESUPUESTO_CRONOGRAMA_BASE'!M7, 0) + IF(AND(A75>='01_PRESUPUESTO_CRONOGRAMA_BASE'!K8, A75<='01_PRESUPUESTO_CRONOGRAMA_BASE'!L8), '01_PRESUPUESTO_CRONOGRAMA_BASE'!M8, 0) + IF(AND(A75>='01_PRESUPUESTO_CRONOGRAMA_BASE'!K9, A75<='01_PRESUPUESTO_CRONOGRAMA_BASE'!L9), '01_PRESUPUESTO_CRONOGRAMA_BASE'!M9, 0) | F75: =SUMIFS(E$2:E75, C$2:C75, C75)
A76: 19 | B76: 2026-08-19 | C76: WBS-300 | D76: Red de Agua Potable y Conexiones Domiciliarias | E76: =IF(AND(A76>='01_PRESUPUESTO_CRONOGRAMA_BASE'!K10, A76<='01_PRESUPUESTO_CRONOGRAMA_BASE'!L10), '01_PRESUPUESTO_CRONOGRAMA_BASE'!M10, 0) + IF(AND(A76>='01_PRESUPUESTO_CRONOGRAMA_BASE'!K11, A76<='01_PRESUPUESTO_CRONOGRAMA_BASE'!L11), '01_PRESUPUESTO_CRONOGRAMA_BASE'!M11, 0) | F76: =SUMIFS(E$2:E76, C$2:C76, C76)
A77: 19 | B77: 2026-08-19 | C77: WBS-400 | D77: Pruebas Hidráulicas, Desinfección y Entrega | E77: =IF(AND(A77>='01_PRESUPUESTO_CRONOGRAMA_BASE'!K12, A77<='01_PRESUPUESTO_CRONOGRAMA_BASE'!L12), '01_PRESUPUESTO_CRONOGRAMA_BASE'!M12, 0) | F77: =SUMIFS(E$2:E77, C$2:C77, C77)
A78: 20 | B78: 2026-08-20 | C78: WBS-100 | D78: Obras Preliminares, Trazo y Movilización | E78: =IF(AND(A78>='01_PRESUPUESTO_CRONOGRAMA_BASE'!K2, A78<='01_PRESUPUESTO_CRONOGRAMA_BASE'!L2), '01_PRESUPUESTO_CRONOGRAMA_BASE'!M2, 0) + IF(AND(A78>='01_PRESUPUESTO_CRONOGRAMA_BASE'!K3, A78<='01_PRESUPUESTO_CRONOGRAMA_BASE'!L3), '01_PRESUPUESTO_CRONOGRAMA_BASE'!M3, 0) | F78: =SUMIFS(E$2:E78, C$2:C78, C78)
A79: 20 | B79: 2026-08-20 | C79: WBS-200 | D79: Red de Alcantarillado, Zanjas y Buzones | E79: =IF(AND(A79>='01_PRESUPUESTO_CRONOGRAMA_BASE'!K4, A79<='01_PRESUPUESTO_CRONOGRAMA_BASE'!L4), '01_PRESUPUESTO_CRONOGRAMA_BASE'!M4, 0) + IF(AND(A79>='01_PRESUPUESTO_CRONOGRAMA_BASE'!K5, A79<='01_PRESUPUESTO_CRONOGRAMA_BASE'!L5), '01_PRESUPUESTO_CRONOGRAMA_BASE'!M5, 0) + IF(AND(A79>='01_PRESUPUESTO_CRONOGRAMA_BASE'!K6, A79<='01_PRESUPUESTO_CRONOGRAMA_BASE'!L6), '01_PRESUPUESTO_CRONOGRAMA_BASE'!M6, 0) + IF(AND(A79>='01_PRESUPUESTO_CRONOGRAMA_BASE'!K7, A79<='01_PRESUPUESTO_CRONOGRAMA_BASE'!L7), '01_PRESUPUESTO_CRONOGRAMA_BASE'!M7, 0) + IF(AND(A79>='01_PRESUPUESTO_CRONOGRAMA_BASE'!K8, A79<='01_PRESUPUESTO_CRONOGRAMA_BASE'!L8), '01_PRESUPUESTO_CRONOGRAMA_BASE'!M8, 0) + IF(AND(A79>='01_PRESUPUESTO_CRONOGRAMA_BASE'!K9, A79<='01_PRESUPUESTO_CRONOGRAMA_BASE'!L9), '01_PRESUPUESTO_CRONOGRAMA_BASE'!M9, 0) | F79: =SUMIFS(E$2:E79, C$2:C79, C79)
A80: 20 | B80: 2026-08-20 | C80: WBS-300 | D80: Red de Agua Potable y Conexiones Domiciliarias | E80: =IF(AND(A80>='01_PRESUPUESTO_CRONOGRAMA_BASE'!K10, A80<='01_PRESUPUESTO_CRONOGRAMA_BASE'!L10), '01_PRESUPUESTO_CRONOGRAMA_BASE'!M10, 0) + IF(AND(A80>='01_PRESUPUESTO_CRONOGRAMA_BASE'!K11, A80<='01_PRESUPUESTO_CRONOGRAMA_BASE'!L11), '01_PRESUPUESTO_CRONOGRAMA_BASE'!M11, 0) | F80: =SUMIFS(E$2:E80, C$2:C80, C80)
A81: 20 | B81: 2026-08-20 | C81: WBS-400 | D81: Pruebas Hidráulicas, Desinfección y Entrega | E81: =IF(AND(A81>='01_PRESUPUESTO_CRONOGRAMA_BASE'!K12, A81<='01_PRESUPUESTO_CRONOGRAMA_BASE'!L12), '01_PRESUPUESTO_CRONOGRAMA_BASE'!M12, 0) | F81: =SUMIFS(E$2:E81, C$2:C81, C81)
A82: 21 | B82: 2026-08-21 | C82: WBS-100 | D82: Obras Preliminares, Trazo y Movilización | E82: =IF(AND(A82>='01_PRESUPUESTO_CRONOGRAMA_BASE'!K2, A82<='01_PRESUPUESTO_CRONOGRAMA_BASE'!L2), '01_PRESUPUESTO_CRONOGRAMA_BASE'!M2, 0) + IF(AND(A82>='01_PRESUPUESTO_CRONOGRAMA_BASE'!K3, A82<='01_PRESUPUESTO_CRONOGRAMA_BASE'!L3), '01_PRESUPUESTO_CRONOGRAMA_BASE'!M3, 0) | F82: =SUMIFS(E$2:E82, C$2:C82, C82)
A83: 21 | B83: 2026-08-21 | C83: WBS-200 | D83: Red de Alcantarillado, Zanjas y Buzones | E83: =IF(AND(A83>='01_PRESUPUESTO_CRONOGRAMA_BASE'!K4, A83<='01_PRESUPUESTO_CRONOGRAMA_BASE'!L4), '01_PRESUPUESTO_CRONOGRAMA_BASE'!M4, 0) + IF(AND(A83>='01_PRESUPUESTO_CRONOGRAMA_BASE'!K5, A83<='01_PRESUPUESTO_CRONOGRAMA_BASE'!L5), '01_PRESUPUESTO_CRONOGRAMA_BASE'!M5, 0) + IF(AND(A83>='01_PRESUPUESTO_CRONOGRAMA_BASE'!K6, A83<='01_PRESUPUESTO_CRONOGRAMA_BASE'!L6), '01_PRESUPUESTO_CRONOGRAMA_BASE'!M6, 0) + IF(AND(A83>='01_PRESUPUESTO_CRONOGRAMA_BASE'!K7, A83<='01_PRESUPUESTO_CRONOGRAMA_BASE'!L7), '01_PRESUPUESTO_CRONOGRAMA_BASE'!M7, 0) + IF(AND(A83>='01_PRESUPUESTO_CRONOGRAMA_BASE'!K8, A83<='01_PRESUPUESTO_CRONOGRAMA_BASE'!L8), '01_PRESUPUESTO_CRONOGRAMA_BASE'!M8, 0) + IF(AND(A83>='01_PRESUPUESTO_CRONOGRAMA_BASE'!K9, A83<='01_PRESUPUESTO_CRONOGRAMA_BASE'!L9), '01_PRESUPUESTO_CRONOGRAMA_BASE'!M9, 0) | F83: =SUMIFS(E$2:E83, C$2:C83, C83)
A84: 21 | B84: 2026-08-21 | C84: WBS-300 | D84: Red de Agua Potable y Conexiones Domiciliarias | E84: =IF(AND(A84>='01_PRESUPUESTO_CRONOGRAMA_BASE'!K10, A84<='01_PRESUPUESTO_CRONOGRAMA_BASE'!L10), '01_PRESUPUESTO_CRONOGRAMA_BASE'!M10, 0) + IF(AND(A84>='01_PRESUPUESTO_CRONOGRAMA_BASE'!K11, A84<='01_PRESUPUESTO_CRONOGRAMA_BASE'!L11), '01_PRESUPUESTO_CRONOGRAMA_BASE'!M11, 0) | F84: =SUMIFS(E$2:E84, C$2:C84, C84)
A85: 21 | B85: 2026-08-21 | C85: WBS-400 | D85: Pruebas Hidráulicas, Desinfección y Entrega | E85: =IF(AND(A85>='01_PRESUPUESTO_CRONOGRAMA_BASE'!K12, A85<='01_PRESUPUESTO_CRONOGRAMA_BASE'!L12), '01_PRESUPUESTO_CRONOGRAMA_BASE'!M12, 0) | F85: =SUMIFS(E$2:E85, C$2:C85, C85)
A86: 22 | B86: 2026-08-22 | C86: WBS-100 | D86: Obras Preliminares, Trazo y Movilización | E86: =IF(AND(A86>='01_PRESUPUESTO_CRONOGRAMA_BASE'!K2, A86<='01_PRESUPUESTO_CRONOGRAMA_BASE'!L2), '01_PRESUPUESTO_CRONOGRAMA_BASE'!M2, 0) + IF(AND(A86>='01_PRESUPUESTO_CRONOGRAMA_BASE'!K3, A86<='01_PRESUPUESTO_CRONOGRAMA_BASE'!L3), '01_PRESUPUESTO_CRONOGRAMA_BASE'!M3, 0) | F86: =SUMIFS(E$2:E86, C$2:C86, C86)
A87: 22 | B87: 2026-08-22 | C87: WBS-200 | D87: Red de Alcantarillado, Zanjas y Buzones | E87: =IF(AND(A87>='01_PRESUPUESTO_CRONOGRAMA_BASE'!K4, A87<='01_PRESUPUESTO_CRONOGRAMA_BASE'!L4), '01_PRESUPUESTO_CRONOGRAMA_BASE'!M4, 0) + IF(AND(A87>='01_PRESUPUESTO_CRONOGRAMA_BASE'!K5, A87<='01_PRESUPUESTO_CRONOGRAMA_BASE'!L5), '01_PRESUPUESTO_CRONOGRAMA_BASE'!M5, 0) + IF(AND(A87>='01_PRESUPUESTO_CRONOGRAMA_BASE'!K6, A87<='01_PRESUPUESTO_CRONOGRAMA_BASE'!L6), '01_PRESUPUESTO_CRONOGRAMA_BASE'!M6, 0) + IF(AND(A87>='01_PRESUPUESTO_CRONOGRAMA_BASE'!K7, A87<='01_PRESUPUESTO_CRONOGRAMA_BASE'!L7), '01_PRESUPUESTO_CRONOGRAMA_BASE'!M7, 0) + IF(AND(A87>='01_PRESUPUESTO_CRONOGRAMA_BASE'!K8, A87<='01_PRESUPUESTO_CRONOGRAMA_BASE'!L8), '01_PRESUPUESTO_CRONOGRAMA_BASE'!M8, 0) + IF(AND(A87>='01_PRESUPUESTO_CRONOGRAMA_BASE'!K9, A87<='01_PRESUPUESTO_CRONOGRAMA_BASE'!L9), '01_PRESUPUESTO_CRONOGRAMA_BASE'!M9, 0) | F87: =SUMIFS(E$2:E87, C$2:C87, C87)
A88: 22 | B88: 2026-08-22 | C88: WBS-300 | D88: Red de Agua Potable y Conexiones Domiciliarias | E88: =IF(AND(A88>='01_PRESUPUESTO_CRONOGRAMA_BASE'!K10, A88<='01_PRESUPUESTO_CRONOGRAMA_BASE'!L10), '01_PRESUPUESTO_CRONOGRAMA_BASE'!M10, 0) + IF(AND(A88>='01_PRESUPUESTO_CRONOGRAMA_BASE'!K11, A88<='01_PRESUPUESTO_CRONOGRAMA_BASE'!L11), '01_PRESUPUESTO_CRONOGRAMA_BASE'!M11, 0) | F88: =SUMIFS(E$2:E88, C$2:C88, C88)
A89: 22 | B89: 2026-08-22 | C89: WBS-400 | D89: Pruebas Hidráulicas, Desinfección y Entrega | E89: =IF(AND(A89>='01_PRESUPUESTO_CRONOGRAMA_BASE'!K12, A89<='01_PRESUPUESTO_CRONOGRAMA_BASE'!L12), '01_PRESUPUESTO_CRONOGRAMA_BASE'!M12, 0) | F89: =SUMIFS(E$2:E89, C$2:C89, C89)
A90: 23 | B90: 2026-08-23 | C90: WBS-100 | D90: Obras Preliminares, Trazo y Movilización | E90: =IF(AND(A90>='01_PRESUPUESTO_CRONOGRAMA_BASE'!K2, A90<='01_PRESUPUESTO_CRONOGRAMA_BASE'!L2), '01_PRESUPUESTO_CRONOGRAMA_BASE'!M2, 0) + IF(AND(A90>='01_PRESUPUESTO_CRONOGRAMA_BASE'!K3, A90<='01_PRESUPUESTO_CRONOGRAMA_BASE'!L3), '01_PRESUPUESTO_CRONOGRAMA_BASE'!M3, 0) | F90: =SUMIFS(E$2:E90, C$2:C90, C90)
A91: 23 | B91: 2026-08-23 | C91: WBS-200 | D91: Red de Alcantarillado, Zanjas y Buzones | E91: =IF(AND(A91>='01_PRESUPUESTO_CRONOGRAMA_BASE'!K4, A91<='01_PRESUPUESTO_CRONOGRAMA_BASE'!L4), '01_PRESUPUESTO_CRONOGRAMA_BASE'!M4, 0) + IF(AND(A91>='01_PRESUPUESTO_CRONOGRAMA_BASE'!K5, A91<='01_PRESUPUESTO_CRONOGRAMA_BASE'!L5), '01_PRESUPUESTO_CRONOGRAMA_BASE'!M5, 0) + IF(AND(A91>='01_PRESUPUESTO_CRONOGRAMA_BASE'!K6, A91<='01_PRESUPUESTO_CRONOGRAMA_BASE'!L6), '01_PRESUPUESTO_CRONOGRAMA_BASE'!M6, 0) + IF(AND(A91>='01_PRESUPUESTO_CRONOGRAMA_BASE'!K7, A91<='01_PRESUPUESTO_CRONOGRAMA_BASE'!L7), '01_PRESUPUESTO_CRONOGRAMA_BASE'!M7, 0) + IF(AND(A91>='01_PRESUPUESTO_CRONOGRAMA_BASE'!K8, A91<='01_PRESUPUESTO_CRONOGRAMA_BASE'!L8), '01_PRESUPUESTO_CRONOGRAMA_BASE'!M8, 0) + IF(AND(A91>='01_PRESUPUESTO_CRONOGRAMA_BASE'!K9, A91<='01_PRESUPUESTO_CRONOGRAMA_BASE'!L9), '01_PRESUPUESTO_CRONOGRAMA_BASE'!M9, 0) | F91: =SUMIFS(E$2:E91, C$2:C91, C91)
A92: 23 | B92: 2026-08-23 | C92: WBS-300 | D92: Red de Agua Potable y Conexiones Domiciliarias | E92: =IF(AND(A92>='01_PRESUPUESTO_CRONOGRAMA_BASE'!K10, A92<='01_PRESUPUESTO_CRONOGRAMA_BASE'!L10), '01_PRESUPUESTO_CRONOGRAMA_BASE'!M10, 0) + IF(AND(A92>='01_PRESUPUESTO_CRONOGRAMA_BASE'!K11, A92<='01_PRESUPUESTO_CRONOGRAMA_BASE'!L11), '01_PRESUPUESTO_CRONOGRAMA_BASE'!M11, 0) | F92: =SUMIFS(E$2:E92, C$2:C92, C92)
A93: 23 | B93: 2026-08-23 | C93: WBS-400 | D93: Pruebas Hidráulicas, Desinfección y Entrega | E93: =IF(AND(A93>='01_PRESUPUESTO_CRONOGRAMA_BASE'!K12, A93<='01_PRESUPUESTO_CRONOGRAMA_BASE'!L12), '01_PRESUPUESTO_CRONOGRAMA_BASE'!M12, 0) | F93: =SUMIFS(E$2:E93, C$2:C93, C93)
A94: 24 | B94: 2026-08-24 | C94: WBS-100 | D94: Obras Preliminares, Trazo y Movilización | E94: =IF(AND(A94>='01_PRESUPUESTO_CRONOGRAMA_BASE'!K2, A94<='01_PRESUPUESTO_CRONOGRAMA_BASE'!L2), '01_PRESUPUESTO_CRONOGRAMA_BASE'!M2, 0) + IF(AND(A94>='01_PRESUPUESTO_CRONOGRAMA_BASE'!K3, A94<='01_PRESUPUESTO_CRONOGRAMA_BASE'!L3), '01_PRESUPUESTO_CRONOGRAMA_BASE'!M3, 0) | F94: =SUMIFS(E$2:E94, C$2:C94, C94)
A95: 24 | B95: 2026-08-24 | C95: WBS-200 | D95: Red de Alcantarillado, Zanjas y Buzones | E95: =IF(AND(A95>='01_PRESUPUESTO_CRONOGRAMA_BASE'!K4, A95<='01_PRESUPUESTO_CRONOGRAMA_BASE'!L4), '01_PRESUPUESTO_CRONOGRAMA_BASE'!M4, 0) + IF(AND(A95>='01_PRESUPUESTO_CRONOGRAMA_BASE'!K5, A95<='01_PRESUPUESTO_CRONOGRAMA_BASE'!L5), '01_PRESUPUESTO_CRONOGRAMA_BASE'!M5, 0) + IF(AND(A95>='01_PRESUPUESTO_CRONOGRAMA_BASE'!K6, A95<='01_PRESUPUESTO_CRONOGRAMA_BASE'!L6), '01_PRESUPUESTO_CRONOGRAMA_BASE'!M6, 0) + IF(AND(A95>='01_PRESUPUESTO_CRONOGRAMA_BASE'!K7, A95<='01_PRESUPUESTO_CRONOGRAMA_BASE'!L7), '01_PRESUPUESTO_CRONOGRAMA_BASE'!M7, 0) + IF(AND(A95>='01_PRESUPUESTO_CRONOGRAMA_BASE'!K8, A95<='01_PRESUPUESTO_CRONOGRAMA_BASE'!L8), '01_PRESUPUESTO_CRONOGRAMA_BASE'!M8, 0) + IF(AND(A95>='01_PRESUPUESTO_CRONOGRAMA_BASE'!K9, A95<='01_PRESUPUESTO_CRONOGRAMA_BASE'!L9), '01_PRESUPUESTO_CRONOGRAMA_BASE'!M9, 0) | F95: =SUMIFS(E$2:E95, C$2:C95, C95)
A96: 24 | B96: 2026-08-24 | C96: WBS-300 | D96: Red de Agua Potable y Conexiones Domiciliarias | E96: =IF(AND(A96>='01_PRESUPUESTO_CRONOGRAMA_BASE'!K10, A96<='01_PRESUPUESTO_CRONOGRAMA_BASE'!L10), '01_PRESUPUESTO_CRONOGRAMA_BASE'!M10, 0) + IF(AND(A96>='01_PRESUPUESTO_CRONOGRAMA_BASE'!K11, A96<='01_PRESUPUESTO_CRONOGRAMA_BASE'!L11), '01_PRESUPUESTO_CRONOGRAMA_BASE'!M11, 0) | F96: =SUMIFS(E$2:E96, C$2:C96, C96)
A97: 24 | B97: 2026-08-24 | C97: WBS-400 | D97: Pruebas Hidráulicas, Desinfección y Entrega | E97: =IF(AND(A97>='01_PRESUPUESTO_CRONOGRAMA_BASE'!K12, A97<='01_PRESUPUESTO_CRONOGRAMA_BASE'!L12), '01_PRESUPUESTO_CRONOGRAMA_BASE'!M12, 0) | F97: =SUMIFS(E$2:E97, C$2:C97, C97)
A98: 25 | B98: 2026-08-25 | C98: WBS-100 | D98: Obras Preliminares, Trazo y Movilización | E98: =IF(AND(A98>='01_PRESUPUESTO_CRONOGRAMA_BASE'!K2, A98<='01_PRESUPUESTO_CRONOGRAMA_BASE'!L2), '01_PRESUPUESTO_CRONOGRAMA_BASE'!M2, 0) + IF(AND(A98>='01_PRESUPUESTO_CRONOGRAMA_BASE'!K3, A98<='01_PRESUPUESTO_CRONOGRAMA_BASE'!L3), '01_PRESUPUESTO_CRONOGRAMA_BASE'!M3, 0) | F98: =SUMIFS(E$2:E98, C$2:C98, C98)
A99: 25 | B99: 2026-08-25 | C99: WBS-200 | D99: Red de Alcantarillado, Zanjas y Buzones | E99: =IF(AND(A99>='01_PRESUPUESTO_CRONOGRAMA_BASE'!K4, A99<='01_PRESUPUESTO_CRONOGRAMA_BASE'!L4), '01_PRESUPUESTO_CRONOGRAMA_BASE'!M4, 0) + IF(AND(A99>='01_PRESUPUESTO_CRONOGRAMA_BASE'!K5, A99<='01_PRESUPUESTO_CRONOGRAMA_BASE'!L5), '01_PRESUPUESTO_CRONOGRAMA_BASE'!M5, 0) + IF(AND(A99>='01_PRESUPUESTO_CRONOGRAMA_BASE'!K6, A99<='01_PRESUPUESTO_CRONOGRAMA_BASE'!L6), '01_PRESUPUESTO_CRONOGRAMA_BASE'!M6, 0) + IF(AND(A99>='01_PRESUPUESTO_CRONOGRAMA_BASE'!K7, A99<='01_PRESUPUESTO_CRONOGRAMA_BASE'!L7), '01_PRESUPUESTO_CRONOGRAMA_BASE'!M7, 0) + IF(AND(A99>='01_PRESUPUESTO_CRONOGRAMA_BASE'!K8, A99<='01_PRESUPUESTO_CRONOGRAMA_BASE'!L8), '01_PRESUPUESTO_CRONOGRAMA_BASE'!M8, 0) + IF(AND(A99>='01_PRESUPUESTO_CRONOGRAMA_BASE'!K9, A99<='01_PRESUPUESTO_CRONOGRAMA_BASE'!L9), '01_PRESUPUESTO_CRONOGRAMA_BASE'!M9, 0) | F99: =SUMIFS(E$2:E99, C$2:C99, C99)
A100: 25 | B100: 2026-08-25 | C100: WBS-300 | D100: Red de Agua Potable y Conexiones Domiciliarias | E100: =IF(AND(A100>='01_PRESUPUESTO_CRONOGRAMA_BASE'!K10, A100<='01_PRESUPUESTO_CRONOGRAMA_BASE'!L10), '01_PRESUPUESTO_CRONOGRAMA_BASE'!M10, 0) + IF(AND(A100>='01_PRESUPUESTO_CRONOGRAMA_BASE'!K11, A100<='01_PRESUPUESTO_CRONOGRAMA_BASE'!L11), '01_PRESUPUESTO_CRONOGRAMA_BASE'!M11, 0) | F100: =SUMIFS(E$2:E100, C$2:C100, C100)
...

Sheet 03_CONSOLIDADO_DIARIO_EVM_WBS
A1: N° Día Obra | B1: Fecha Obra | C1: Código WBS | D1: Nombre Frente WBS | E1: Presupuesto BAC (S/) | F1: PV Programado Día (S/) | G1: PV Acumulado (S/) | H1: EV Ejecutado Día (S/) | I1: EV Acumulado (S/) | J1: AC Costo Real Día (S/) | K1: AC Acumulado (S/) | L1: Variación Costo CV (S/) | M1: Variación Plazo SV (S/) | N1: SPI Plazo (EV/PV) | O1: CPI Costo (EV/AC) | P1: Estado Alerta WBS
A2: 1 | B2: 46235 | C2: WBS-100 | D2: Obras Preliminares, Trazo y Movilización | E2: =SUM('01_PRESUPUESTO_CRONOGRAMA_BASE'!G2:G3) | F2: =SUMIFS('02_CRONOGRAMA_PV_DIARIO'!E:E, '02_CRONOGRAMA_PV_DIARIO'!A:A, A2, '02_CRONOGRAMA_PV_DIARIO'!C:C, C2) | G2: =SUMIFS(F$2:F2, C$2:C2, C2) | H2: =IF(B2 > MAX('04_LOG_FIELD_ENTRIES'!$B:$B), "", SUMIFS('04_LOG_FIELD_ENTRIES'!$J:$J, '04_LOG_FIELD_ENTRIES'!$B:$B, B2, '04_LOG_FIELD_ENTRIES'!$D:$D, C2, '04_LOG_FIELD_ENTRIES'!$K:$K, "EV_PRODUCCION")) | I2: =IF(B2 > MAX('04_LOG_FIELD_ENTRIES'!$B:$B), "", SUMIFS(H$2:H2, C$2:C2, C2)) | J2: =IF(B2 > MAX('04_LOG_FIELD_ENTRIES'!$B:$B), "", SUMIFS('04_LOG_FIELD_ENTRIES'!$J:$J, '04_LOG_FIELD_ENTRIES'!$B:$B, B2, '04_LOG_FIELD_ENTRIES'!$D:$D, C2, '04_LOG_FIELD_ENTRIES'!$K:$K, "AC_*")) | K2: =IF(B2 > MAX('04_LOG_FIELD_ENTRIES'!$B:$B), "", SUMIFS(J$2:J2, C$2:C2, C2)) | L2: =IF(K2="", "", I2-K2) | M2: =IF(I2="", "", I2-G2) | N2: =IF(I2="", "", IF(G2>0, I2/G2, 1)) | O2: =IF(I2="", "", IF(K2>0, I2/K2, 1)) | P2: =IF(I2="", "", IF(AND(N2>=0.95, O2>=0.95), "SALUDABLE", IF(N2<0.9, "ALERTA RETRASO", "ALERTA SOBRECOSTO")))
A3: 1 | B3: 46235 | C3: WBS-200 | D3: Red de Alcantarillado, Zanjas y Buzones | E3: =SUM('01_PRESUPUESTO_CRONOGRAMA_BASE'!G4:G9) | F3: =SUMIFS('02_CRONOGRAMA_PV_DIARIO'!E:E, '02_CRONOGRAMA_PV_DIARIO'!A:A, A3, '02_CRONOGRAMA_PV_DIARIO'!C:C, C3) | G3: =SUMIFS(F$2:F3, C$2:C3, C3) | H3: =IF(B3 > MAX('04_LOG_FIELD_ENTRIES'!$B:$B), "", SUMIFS('04_LOG_FIELD_ENTRIES'!$J:$J, '04_LOG_FIELD_ENTRIES'!$B:$B, B3, '04_LOG_FIELD_ENTRIES'!$D:$D, C3, '04_LOG_FIELD_ENTRIES'!$K:$K, "EV_PRODUCCION")) | I3: =IF(B3 > MAX('04_LOG_FIELD_ENTRIES'!$B:$B), "", SUMIFS(H$2:H3, C$2:C3, C3)) | J3: =IF(B3 > MAX('04_LOG_FIELD_ENTRIES'!$B:$B), "", SUMIFS('04_LOG_FIELD_ENTRIES'!$J:$J, '04_LOG_FIELD_ENTRIES'!$B:$B, B3, '04_LOG_FIELD_ENTRIES'!$D:$D, C3, '04_LOG_FIELD_ENTRIES'!$K:$K, "AC_*")) | K3: =IF(B3 > MAX('04_LOG_FIELD_ENTRIES'!$B:$B), "", SUMIFS(J$2:J3, C$2:C3, C3)) | L3: =IF(K3="", "", I3-K3) | M3: =IF(I3="", "", I3-G3) | N3: =IF(I3="", "", IF(G3>0, I3/G3, 1)) | O3: =IF(I3="", "", IF(K3>0, I3/K3, 1)) | P3: =IF(I3="", "", IF(AND(N3>=0.95, O3>=0.95), "SALUDABLE", IF(N3<0.9, "ALERTA RETRASO", "ALERTA SOBRECOSTO")))
A4: 1 | B4: 46235 | C4: WBS-300 | D4: Red de Agua Potable y Conexiones Domiciliarias | E4: =SUM('01_PRESUPUESTO_CRONOGRAMA_BASE'!G10:G11) | F4: =SUMIFS('02_CRONOGRAMA_PV_DIARIO'!E:E, '02_CRONOGRAMA_PV_DIARIO'!A:A, A4, '02_CRONOGRAMA_PV_DIARIO'!C:C, C4) | G4: =SUMIFS(F$2:F4, C$2:C4, C4) | H4: =IF(B4 > MAX('04_LOG_FIELD_ENTRIES'!$B:$B), "", SUMIFS('04_LOG_FIELD_ENTRIES'!$J:$J, '04_LOG_FIELD_ENTRIES'!$B:$B, B4, '04_LOG_FIELD_ENTRIES'!$D:$D, C4, '04_LOG_FIELD_ENTRIES'!$K:$K, "EV_PRODUCCION")) | I4: =IF(B4 > MAX('04_LOG_FIELD_ENTRIES'!$B:$B), "", SUMIFS(H$2:H4, C$2:C4, C4)) | J4: =IF(B4 > MAX('04_LOG_FIELD_ENTRIES'!$B:$B), "", SUMIFS('04_LOG_FIELD_ENTRIES'!$J:$J, '04_LOG_FIELD_ENTRIES'!$B:$B, B4, '04_LOG_FIELD_ENTRIES'!$D:$D, C4, '04_LOG_FIELD_ENTRIES'!$K:$K, "AC_*")) | K4: =IF(B4 > MAX('04_LOG_FIELD_ENTRIES'!$B:$B), "", SUMIFS(J$2:J4, C$2:C4, C4)) | L4: =IF(K4="", "", I4-K4) | M4: =IF(I4="", "", I4-G4) | N4: =IF(I4="", "", IF(G4>0, I4/G4, 1)) | O4: =IF(I4="", "", IF(K4>0, I4/K4, 1)) | P4: =IF(I4="", "", IF(AND(N4>=0.95, O4>=0.95), "SALUDABLE", IF(N4<0.9, "ALERTA RETRASO", "ALERTA SOBRECOSTO")))
A5: 1 | B5: 46235 | C5: WBS-400 | D5: Pruebas Hidráulicas, Desinfección y Entrega | E5: =SUM('01_PRESUPUESTO_CRONOGRAMA_BASE'!G12:G12) | F5: =SUMIFS('02_CRONOGRAMA_PV_DIARIO'!E:E, '02_CRONOGRAMA_PV_DIARIO'!A:A, A5, '02_CRONOGRAMA_PV_DIARIO'!C:C, C5) | G5: =SUMIFS(F$2:F5, C$2:C5, C5) | H5: =IF(B5 > MAX('04_LOG_FIELD_ENTRIES'!$B:$B), "", SUMIFS('04_LOG_FIELD_ENTRIES'!$J:$J, '04_LOG_FIELD_ENTRIES'!$B:$B, B5, '04_LOG_FIELD_ENTRIES'!$D:$D, C5, '04_LOG_FIELD_ENTRIES'!$K:$K, "EV_PRODUCCION")) | I5: =IF(B5 > MAX('04_LOG_FIELD_ENTRIES'!$B:$B), "", SUMIFS(H$2:H5, C$2:C5, C5)) | J5: =IF(B5 > MAX('04_LOG_FIELD_ENTRIES'!$B:$B), "", SUMIFS('04_LOG_FIELD_ENTRIES'!$J:$J, '04_LOG_FIELD_ENTRIES'!$B:$B, B5, '04_LOG_FIELD_ENTRIES'!$D:$D, C5, '04_LOG_FIELD_ENTRIES'!$K:$K, "AC_*")) | K5: =IF(B5 > MAX('04_LOG_FIELD_ENTRIES'!$B:$B), "", SUMIFS(J$2:J5, C$2:C5, C5)) | L5: =IF(K5="", "", I5-K5) | M5: =IF(I5="", "", I5-G5) | N5: =IF(I5="", "", IF(G5>0, I5/G5, 1)) | O5: =IF(I5="", "", IF(K5>0, I5/K5, 1)) | P5: =IF(I5="", "", IF(AND(N5>=0.95, O5>=0.95), "SALUDABLE", IF(N5<0.9, "ALERTA RETRASO", "ALERTA SOBRECOSTO")))
A6: 2 | B6: 46236 | C6: WBS-100 | D6: Obras Preliminares, Trazo y Movilización | E6: =SUM('01_PRESUPUESTO_CRONOGRAMA_BASE'!G2:G3) | F6: =SUMIFS('02_CRONOGRAMA_PV_DIARIO'!E:E, '02_CRONOGRAMA_PV_DIARIO'!A:A, A6, '02_CRONOGRAMA_PV_DIARIO'!C:C, C6) | G6: =SUMIFS(F$2:F6, C$2:C6, C6) | H6: =IF(B6 > MAX('04_LOG_FIELD_ENTRIES'!$B:$B), "", SUMIFS('04_LOG_FIELD_ENTRIES'!$J:$J, '04_LOG_FIELD_ENTRIES'!$B:$B, B6, '04_LOG_FIELD_ENTRIES'!$D:$D, C6, '04_LOG_FIELD_ENTRIES'!$K:$K, "EV_PRODUCCION")) | I6: =IF(B6 > MAX('04_LOG_FIELD_ENTRIES'!$B:$B), "", SUMIFS(H$2:H6, C$2:C6, C6)) | J6: =IF(B6 > MAX('04_LOG_FIELD_ENTRIES'!$B:$B), "", SUMIFS('04_LOG_FIELD_ENTRIES'!$J:$J, '04_LOG_FIELD_ENTRIES'!$B:$B, B6, '04_LOG_FIELD_ENTRIES'!$D:$D, C6, '04_LOG_FIELD_ENTRIES'!$K:$K, "AC_*")) | K6: =IF(B6 > MAX('04_LOG_FIELD_ENTRIES'!$B:$B), "", SUMIFS(J$2:J6, C$2:C6, C6)) | L6: =IF(K6="", "", I6-K6) | M6: =IF(I6="", "", I6-G6) | N6: =IF(I6="", "", IF(G6>0, I6/G6, 1)) | O6: =IF(I6="", "", IF(K6>0, I6/K6, 1)) | P6: =IF(I6="", "", IF(AND(N6>=0.95, O6>=0.95), "SALUDABLE", IF(N6<0.9, "ALERTA RETRASO", "ALERTA SOBRECOSTO")))
A7: 2 | B7: 46236 | C7: WBS-200 | D7: Red de Alcantarillado, Zanjas y Buzones | E7: =SUM('01_PRESUPUESTO_CRONOGRAMA_BASE'!G4:G9) | F7: =SUMIFS('02_CRONOGRAMA_PV_DIARIO'!E:E, '02_CRONOGRAMA_PV_DIARIO'!A:A, A7, '02_CRONOGRAMA_PV_DIARIO'!C:C, C7) | G7: =SUMIFS(F$2:F7, C$2:C7, C7) | H7: =IF(B7 > MAX('04_LOG_FIELD_ENTRIES'!$B:$B), "", SUMIFS('04_LOG_FIELD_ENTRIES'!$J:$J, '04_LOG_FIELD_ENTRIES'!$B:$B, B7, '04_LOG_FIELD_ENTRIES'!$D:$D, C7, '04_LOG_FIELD_ENTRIES'!$K:$K, "EV_PRODUCCION")) | I7: =IF(B7 > MAX('04_LOG_FIELD_ENTRIES'!$B:$B), "", SUMIFS(H$2:H7, C$2:C7, C7)) | J7: =IF(B7 > MAX('04_LOG_FIELD_ENTRIES'!$B:$B), "", SUMIFS('04_LOG_FIELD_ENTRIES'!$J:$J, '04_LOG_FIELD_ENTRIES'!$B:$B, B7, '04_LOG_FIELD_ENTRIES'!$D:$D, C7, '04_LOG_FIELD_ENTRIES'!$K:$K, "AC_*")) | K7: =IF(B7 > MAX('04_LOG_FIELD_ENTRIES'!$B:$B), "", SUMIFS(J$2:J7, C$2:C7, C7)) | L7: =IF(K7="", "", I7-K7) | M7: =IF(I7="", "", I7-G7) | N7: =IF(I7="", "", IF(G7>0, I7/G7, 1)) | O7: =IF(I7="", "", IF(K7>0, I7/K7, 1)) | P7: =IF(I7="", "", IF(AND(N7>=0.95, O7>=0.95), "SALUDABLE", IF(N7<0.9, "ALERTA RETRASO", "ALERTA SOBRECOSTO")))
A8: 2 | B8: 46236 | C8: WBS-300 | D8: Red de Agua Potable y Conexiones Domiciliarias | E8: =SUM('01_PRESUPUESTO_CRONOGRAMA_BASE'!G10:G11) | F8: =SUMIFS('02_CRONOGRAMA_PV_DIARIO'!E:E, '02_CRONOGRAMA_PV_DIARIO'!A:A, A8, '02_CRONOGRAMA_PV_DIARIO'!C:C, C8) | G8: =SUMIFS(F$2:F8, C$2:C8, C8) | H8: =IF(B8 > MAX('04_LOG_FIELD_ENTRIES'!$B:$B), "", SUMIFS('04_LOG_FIELD_ENTRIES'!$J:$J, '04_LOG_FIELD_ENTRIES'!$B:$B, B8, '04_LOG_FIELD_ENTRIES'!$D:$D, C8, '04_LOG_FIELD_ENTRIES'!$K:$K, "EV_PRODUCCION")) | I8: =IF(B8 > MAX('04_LOG_FIELD_ENTRIES'!$B:$B), "", SUMIFS(H$2:H8, C$2:C8, C8)) | J8: =IF(B8 > MAX('04_LOG_FIELD_ENTRIES'!$B:$B), "", SUMIFS('04_LOG_FIELD_ENTRIES'!$J:$J, '04_LOG_FIELD_ENTRIES'!$B:$B, B8, '04_LOG_FIELD_ENTRIES'!$D:$D, C8, '04_LOG_FIELD_ENTRIES'!$K:$K, "AC_*")) | K8: =IF(B8 > MAX('04_LOG_FIELD_ENTRIES'!$B:$B), "", SUMIFS(J$2:J8, C$2:C8, C8)) | L8: =IF(K8="", "", I8-K8) | M8: =IF(I8="", "", I8-G8) | N8: =IF(I8="", "", IF(G8>0, I8/G8, 1)) | O8: =IF(I8="", "", IF(K8>0, I8/K8, 1)) | P8: =IF(I8="", "", IF(AND(N8>=0.95, O8>=0.95), "SALUDABLE", IF(N8<0.9, "ALERTA RETRASO", "ALERTA SOBRECOSTO")))
A9: 2 | B9: 46236 | C9: WBS-400 | D9: Pruebas Hidráulicas, Desinfección y Entrega | E9: =SUM('01_PRESUPUESTO_CRONOGRAMA_BASE'!G12:G12) | F9: =SUMIFS('02_CRONOGRAMA_PV_DIARIO'!E:E, '02_CRONOGRAMA_PV_DIARIO'!A:A, A9, '02_CRONOGRAMA_PV_DIARIO'!C:C, C9) | G9: =SUMIFS(F$2:F9, C$2:C9, C9) | H9: =IF(B9 > MAX('04_LOG_FIELD_ENTRIES'!$B:$B), "", SUMIFS('04_LOG_FIELD_ENTRIES'!$J:$J, '04_LOG_FIELD_ENTRIES'!$B:$B, B9, '04_LOG_FIELD_ENTRIES'!$D:$D, C9, '04_LOG_FIELD_ENTRIES'!$K:$K, "EV_PRODUCCION")) | I9: =IF(B9 > MAX('04_LOG_FIELD_ENTRIES'!$B:$B), "", SUMIFS(H$2:H9, C$2:C9, C9)) | J9: =IF(B9 > MAX('04_LOG_FIELD_ENTRIES'!$B:$B), "", SUMIFS('04_LOG_FIELD_ENTRIES'!$J:$J, '04_LOG_FIELD_ENTRIES'!$B:$B, B9, '04_LOG_FIELD_ENTRIES'!$D:$D, C9, '04_LOG_FIELD_ENTRIES'!$K:$K, "AC_*")) | K9: =IF(B9 > MAX('04_LOG_FIELD_ENTRIES'!$B:$B), "", SUMIFS(J$2:J9, C$2:C9, C9)) | L9: =IF(K9="", "", I9-K9) | M9: =IF(I9="", "", I9-G9) | N9: =IF(I9="", "", IF(G9>0, I9/G9, 1)) | O9: =IF(I9="", "", IF(K9>0, I9/K9, 1)) | P9: =IF(I9="", "", IF(AND(N9>=0.95, O9>=0.95), "SALUDABLE", IF(N9<0.9, "ALERTA RETRASO", "ALERTA SOBRECOSTO")))
A10: 3 | B10: 46237 | C10: WBS-100 | D10: Obras Preliminares, Trazo y Movilización | E10: =SUM('01_PRESUPUESTO_CRONOGRAMA_BASE'!G2:G3) | F10: =SUMIFS('02_CRONOGRAMA_PV_DIARIO'!E:E, '02_CRONOGRAMA_PV_DIARIO'!A:A, A10, '02_CRONOGRAMA_PV_DIARIO'!C:C, C10) | G10: =SUMIFS(F$2:F10, C$2:C10, C10) | H10: =IF(B10 > MAX('04_LOG_FIELD_ENTRIES'!$B:$B), "", SUMIFS('04_LOG_FIELD_ENTRIES'!$J:$J, '04_LOG_FIELD_ENTRIES'!$B:$B, B10, '04_LOG_FIELD_ENTRIES'!$D:$D, C10, '04_LOG_FIELD_ENTRIES'!$K:$K, "EV_PRODUCCION")) | I10: =IF(B10 > MAX('04_LOG_FIELD_ENTRIES'!$B:$B), "", SUMIFS(H$2:H10, C$2:C10, C10)) | J10: =IF(B10 > MAX('04_LOG_FIELD_ENTRIES'!$B:$B), "", SUMIFS('04_LOG_FIELD_ENTRIES'!$J:$J, '04_LOG_FIELD_ENTRIES'!$B:$B, B10, '04_LOG_FIELD_ENTRIES'!$D:$D, C10, '04_LOG_FIELD_ENTRIES'!$K:$K, "AC_*")) | K10: =IF(B10 > MAX('04_LOG_FIELD_ENTRIES'!$B:$B), "", SUMIFS(J$2:J10, C$2:C10, C10)) | L10: =IF(K10="", "", I10-K10) | M10: =IF(I10="", "", I10-G10) | N10: =IF(I10="", "", IF(G10>0, I10/G10, 1)) | O10: =IF(I10="", "", IF(K10>0, I10/K10, 1)) | P10: =IF(I10="", "", IF(AND(N10>=0.95, O10>=0.95), "SALUDABLE", IF(N10<0.9, "ALERTA RETRASO", "ALERTA SOBRECOSTO")))
A11: 3 | B11: 46237 | C11: WBS-200 | D11: Red de Alcantarillado, Zanjas y Buzones | E11: =SUM('01_PRESUPUESTO_CRONOGRAMA_BASE'!G4:G9) | F11: =SUMIFS('02_CRONOGRAMA_PV_DIARIO'!E:E, '02_CRONOGRAMA_PV_DIARIO'!A:A, A11, '02_CRONOGRAMA_PV_DIARIO'!C:C, C11) | G11: =SUMIFS(F$2:F11, C$2:C11, C11) | H11: =IF(B11 > MAX('04_LOG_FIELD_ENTRIES'!$B:$B), "", SUMIFS('04_LOG_FIELD_ENTRIES'!$J:$J, '04_LOG_FIELD_ENTRIES'!$B:$B, B11, '04_LOG_FIELD_ENTRIES'!$D:$D, C11, '04_LOG_FIELD_ENTRIES'!$K:$K, "EV_PRODUCCION")) | I11: =IF(B11 > MAX('04_LOG_FIELD_ENTRIES'!$B:$B), "", SUMIFS(H$2:H11, C$2:C11, C11)) | J11: =IF(B11 > MAX('04_LOG_FIELD_ENTRIES'!$B:$B), "", SUMIFS('04_LOG_FIELD_ENTRIES'!$J:$J, '04_LOG_FIELD_ENTRIES'!$B:$B, B11, '04_LOG_FIELD_ENTRIES'!$D:$D, C11, '04_LOG_FIELD_ENTRIES'!$K:$K, "AC_*")) | K11: =IF(B11 > MAX('04_LOG_FIELD_ENTRIES'!$B:$B), "", SUMIFS(J$2:J11, C$2:C11, C11)) | L11: =IF(K11="", "", I11-K11) | M11: =IF(I11="", "", I11-G11) | N11: =IF(I11="", "", IF(G11>0, I11/G11, 1)) | O11: =IF(I11="", "", IF(K11>0, I11/K11, 1)) | P11: =IF(I11="", "", IF(AND(N11>=0.95, O11>=0.95), "SALUDABLE", IF(N11<0.9, "ALERTA RETRASO", "ALERTA SOBRECOSTO")))
A12: 3 | B12: 46237 | C12: WBS-300 | D12: Red de Agua Potable y Conexiones Domiciliarias | E12: =SUM('01_PRESUPUESTO_CRONOGRAMA_BASE'!G10:G11) | F12: =SUMIFS('02_CRONOGRAMA_PV_DIARIO'!E:E, '02_CRONOGRAMA_PV_DIARIO'!A:A, A12, '02_CRONOGRAMA_PV_DIARIO'!C:C, C12) | G12: =SUMIFS(F$2:F12, C$2:C12, C12) | H12: =IF(B12 > MAX('04_LOG_FIELD_ENTRIES'!$B:$B), "", SUMIFS('04_LOG_FIELD_ENTRIES'!$J:$J, '04_LOG_FIELD_ENTRIES'!$B:$B, B12, '04_LOG_FIELD_ENTRIES'!$D:$D, C12, '04_LOG_FIELD_ENTRIES'!$K:$K, "EV_PRODUCCION")) | I12: =IF(B12 > MAX('04_LOG_FIELD_ENTRIES'!$B:$B), "", SUMIFS(H$2:H12, C$2:C12, C12)) | J12: =IF(B12 > MAX('04_LOG_FIELD_ENTRIES'!$B:$B), "", SUMIFS('04_LOG_FIELD_ENTRIES'!$J:$J, '04_LOG_FIELD_ENTRIES'!$B:$B, B12, '04_LOG_FIELD_ENTRIES'!$D:$D, C12, '04_LOG_FIELD_ENTRIES'!$K:$K, "AC_*")) | K12: =IF(B12 > MAX('04_LOG_FIELD_ENTRIES'!$B:$B), "", SUMIFS(J$2:J12, C$2:C12, C12)) | L12: =IF(K12="", "", I12-K12) | M12: =IF(I12="", "", I12-G12) | N12: =IF(I12="", "", IF(G12>0, I12/G12, 1)) | O12: =IF(I12="", "", IF(K12>0, I12/K12, 1)) | P12: =IF(I12="", "", IF(AND(N12>=0.95, O12>=0.95), "SALUDABLE", IF(N12<0.9, "ALERTA RETRASO", "ALERTA SOBRECOSTO")))
A13: 3 | B13: 46237 | C13: WBS-400 | D13: Pruebas Hidráulicas, Desinfección y Entrega | E13: =SUM('01_PRESUPUESTO_CRONOGRAMA_BASE'!G12:G12) | F13: =SUMIFS('02_CRONOGRAMA_PV_DIARIO'!E:E, '02_CRONOGRAMA_PV_DIARIO'!A:A, A13, '02_CRONOGRAMA_PV_DIARIO'!C:C, C13) | G13: =SUMIFS(F$2:F13, C$2:C13, C13) | H13: =IF(B13 > MAX('04_LOG_FIELD_ENTRIES'!$B:$B), "", SUMIFS('04_LOG_FIELD_ENTRIES'!$J:$J, '04_LOG_FIELD_ENTRIES'!$B:$B, B13, '04_LOG_FIELD_ENTRIES'!$D:$D, C13, '04_LOG_FIELD_ENTRIES'!$K:$K, "EV_PRODUCCION")) | I13: =IF(B13 > MAX('04_LOG_FIELD_ENTRIES'!$B:$B), "", SUMIFS(H$2:H13, C$2:C13, C13)) | J13: =IF(B13 > MAX('04_LOG_FIELD_ENTRIES'!$B:$B), "", SUMIFS('04_LOG_FIELD_ENTRIES'!$J:$J, '04_LOG_FIELD_ENTRIES'!$B:$B, B13, '04_LOG_FIELD_ENTRIES'!$D:$D, C13, '04_LOG_FIELD_ENTRIES'!$K:$K, "AC_*")) | K13: =IF(B13 > MAX('04_LOG_FIELD_ENTRIES'!$B:$B), "", SUMIFS(J$2:J13, C$2:C13, C13)) | L13: =IF(K13="", "", I13-K13) | M13: =IF(I13="", "", I13-G13) | N13: =IF(I13="", "", IF(G13>0, I13/G13, 1)) | O13: =IF(I13="", "", IF(K13>0, I13/K13, 1)) | P13: =IF(I13="", "", IF(AND(N13>=0.95, O13>=0.95), "SALUDABLE", IF(N13<0.9, "ALERTA RETRASO", "ALERTA SOBRECOSTO")))
A14: 4 | B14: 46238 | C14: WBS-100 | D14: Obras Preliminares, Trazo y Movilización | E14: =SUM('01_PRESUPUESTO_CRONOGRAMA_BASE'!G2:G3) | F14: =SUMIFS('02_CRONOGRAMA_PV_DIARIO'!E:E, '02_CRONOGRAMA_PV_DIARIO'!A:A, A14, '02_CRONOGRAMA_PV_DIARIO'!C:C, C14) | G14: =SUMIFS(F$2:F14, C$2:C14, C14) | H14: =IF(B14 > MAX('04_LOG_FIELD_ENTRIES'!$B:$B), "", SUMIFS('04_LOG_FIELD_ENTRIES'!$J:$J, '04_LOG_FIELD_ENTRIES'!$B:$B, B14, '04_LOG_FIELD_ENTRIES'!$D:$D, C14, '04_LOG_FIELD_ENTRIES'!$K:$K, "EV_PRODUCCION")) | I14: =IF(B14 > MAX('04_LOG_FIELD_ENTRIES'!$B:$B), "", SUMIFS(H$2:H14, C$2:C14, C14)) | J14: =IF(B14 > MAX('04_LOG_FIELD_ENTRIES'!$B:$B), "", SUMIFS('04_LOG_FIELD_ENTRIES'!$J:$J, '04_LOG_FIELD_ENTRIES'!$B:$B, B14, '04_LOG_FIELD_ENTRIES'!$D:$D, C14, '04_LOG_FIELD_ENTRIES'!$K:$K, "AC_*")) | K14: =IF(B14 > MAX('04_LOG_FIELD_ENTRIES'!$B:$B), "", SUMIFS(J$2:J14, C$2:C14, C14)) | L14: =IF(K14="", "", I14-K14) | M14: =IF(I14="", "", I14-G14) | N14: =IF(I14="", "", IF(G14>0, I14/G14, 1)) | O14: =IF(I14="", "", IF(K14>0, I14/K14, 1)) | P14: =IF(I14="", "", IF(AND(N14>=0.95, O14>=0.95), "SALUDABLE", IF(N14<0.9, "ALERTA RETRASO", "ALERTA SOBRECOSTO")))
A15: 4 | B15: 46238 | C15: WBS-200 | D15: Red de Alcantarillado, Zanjas y Buzones | E15: =SUM('01_PRESUPUESTO_CRONOGRAMA_BASE'!G4:G9) | F15: =SUMIFS('02_CRONOGRAMA_PV_DIARIO'!E:E, '02_CRONOGRAMA_PV_DIARIO'!A:A, A15, '02_CRONOGRAMA_PV_DIARIO'!C:C, C15) | G15: =SUMIFS(F$2:F15, C$2:C15, C15) | H15: =IF(B15 > MAX('04_LOG_FIELD_ENTRIES'!$B:$B), "", SUMIFS('04_LOG_FIELD_ENTRIES'!$J:$J, '04_LOG_FIELD_ENTRIES'!$B:$B, B15, '04_LOG_FIELD_ENTRIES'!$D:$D, C15, '04_LOG_FIELD_ENTRIES'!$K:$K, "EV_PRODUCCION")) | I15: =IF(B15 > MAX('04_LOG_FIELD_ENTRIES'!$B:$B), "", SUMIFS(H$2:H15, C$2:C15, C15)) | J15: =IF(B15 > MAX('04_LOG_FIELD_ENTRIES'!$B:$B), "", SUMIFS('04_LOG_FIELD_ENTRIES'!$J:$J, '04_LOG_FIELD_ENTRIES'!$B:$B, B15, '04_LOG_FIELD_ENTRIES'!$D:$D, C15, '04_LOG_FIELD_ENTRIES'!$K:$K, "AC_*")) | K15: =IF(B15 > MAX('04_LOG_FIELD_ENTRIES'!$B:$B), "", SUMIFS(J$2:J15, C$2:C15, C15)) | L15: =IF(K15="", "", I15-K15) | M15: =IF(I15="", "", I15-G15) | N15: =IF(I15="", "", IF(G15>0, I15/G15, 1)) | O15: =IF(I15="", "", IF(K15>0, I15/K15, 1)) | P15: =IF(I15="", "", IF(AND(N15>=0.95, O15>=0.95), "SALUDABLE", IF(N15<0.9, "ALERTA RETRASO", "ALERTA SOBRECOSTO")))
A16: 4 | B16: 46238 | C16: WBS-300 | D16: Red de Agua Potable y Conexiones Domiciliarias | E16: =SUM('01_PRESUPUESTO_CRONOGRAMA_BASE'!G10:G11) | F16: =SUMIFS('02_CRONOGRAMA_PV_DIARIO'!E:E, '02_CRONOGRAMA_PV_DIARIO'!A:A, A16, '02_CRONOGRAMA_PV_DIARIO'!C:C, C16) | G16: =SUMIFS(F$2:F16, C$2:C16, C16) | H16: =IF(B16 > MAX('04_LOG_FIELD_ENTRIES'!$B:$B), "", SUMIFS('04_LOG_FIELD_ENTRIES'!$J:$J, '04_LOG_FIELD_ENTRIES'!$B:$B, B16, '04_LOG_FIELD_ENTRIES'!$D:$D, C16, '04_LOG_FIELD_ENTRIES'!$K:$K, "EV_PRODUCCION")) | I16: =IF(B16 > MAX('04_LOG_FIELD_ENTRIES'!$B:$B), "", SUMIFS(H$2:H16, C$2:C16, C16)) | J16: =IF(B16 > MAX('04_LOG_FIELD_ENTRIES'!$B:$B), "", SUMIFS('04_LOG_FIELD_ENTRIES'!$J:$J, '04_LOG_FIELD_ENTRIES'!$B:$B, B16, '04_LOG_FIELD_ENTRIES'!$D:$D, C16, '04_LOG_FIELD_ENTRIES'!$K:$K, "AC_*")) | K16: =IF(B16 > MAX('04_LOG_FIELD_ENTRIES'!$B:$B), "", SUMIFS(J$2:J16, C$2:C16, C16)) | L16: =IF(K16="", "", I16-K16) | M16: =IF(I16="", "", I16-G16) | N16: =IF(I16="", "", IF(G16>0, I16/G16, 1)) | O16: =IF(I16="", "", IF(K16>0, I16/K16, 1)) | P16: =IF(I16="", "", IF(AND(N16>=0.95, O16>=0.95), "SALUDABLE", IF(N16<0.9, "ALERTA RETRASO", "ALERTA SOBRECOSTO")))
A17: 4 | B17: 46238 | C17: WBS-400 | D17: Pruebas Hidráulicas, Desinfección y Entrega | E17: =SUM('01_PRESUPUESTO_CRONOGRAMA_BASE'!G12:G12) | F17: =SUMIFS('02_CRONOGRAMA_PV_DIARIO'!E:E, '02_CRONOGRAMA_PV_DIARIO'!A:A, A17, '02_CRONOGRAMA_PV_DIARIO'!C:C, C17) | G17: =SUMIFS(F$2:F17, C$2:C17, C17) | H17: =IF(B17 > MAX('04_LOG_FIELD_ENTRIES'!$B:$B), "", SUMIFS('04_LOG_FIELD_ENTRIES'!$J:$J, '04_LOG_FIELD_ENTRIES'!$B:$B, B17, '04_LOG_FIELD_ENTRIES'!$D:$D, C17, '04_LOG_FIELD_ENTRIES'!$K:$K, "EV_PRODUCCION")) | I17: =IF(B17 > MAX('04_LOG_FIELD_ENTRIES'!$B:$B), "", SUMIFS(H$2:H17, C$2:C17, C17)) | J17: =IF(B17 > MAX('04_LOG_FIELD_ENTRIES'!$B:$B), "", SUMIFS('04_LOG_FIELD_ENTRIES'!$J:$J, '04_LOG_FIELD_ENTRIES'!$B:$B, B17, '04_LOG_FIELD_ENTRIES'!$D:$D, C17, '04_LOG_FIELD_ENTRIES'!$K:$K, "AC_*")) | K17: =IF(B17 > MAX('04_LOG_FIELD_ENTRIES'!$B:$B), "", SUMIFS(J$2:J17, C$2:C17, C17)) | L17: =IF(K17="", "", I17-K17) | M17: =IF(I17="", "", I17-G17) | N17: =IF(I17="", "", IF(G17>0, I17/G17, 1)) | O17: =IF(I17="", "", IF(K17>0, I17/K17, 1)) | P17: =IF(I17="", "", IF(AND(N17>=0.95, O17>=0.95), "SALUDABLE", IF(N17<0.9, "ALERTA RETRASO", "ALERTA SOBRECOSTO")))
A18: 5 | B18: 46239 | C18: WBS-100 | D18: Obras Preliminares, Trazo y Movilización | E18: =SUM('01_PRESUPUESTO_CRONOGRAMA_BASE'!G2:G3) | F18: =SUMIFS('02_CRONOGRAMA_PV_DIARIO'!E:E, '02_CRONOGRAMA_PV_DIARIO'!A:A, A18, '02_CRONOGRAMA_PV_DIARIO'!C:C, C18) | G18: =SUMIFS(F$2:F18, C$2:C18, C18) | H18: =IF(B18 > MAX('04_LOG_FIELD_ENTRIES'!$B:$B), "", SUMIFS('04_LOG_FIELD_ENTRIES'!$J:$J, '04_LOG_FIELD_ENTRIES'!$B:$B, B18, '04_LOG_FIELD_ENTRIES'!$D:$D, C18, '04_LOG_FIELD_ENTRIES'!$K:$K, "EV_PRODUCCION")) | I18: =IF(B18 > MAX('04_LOG_FIELD_ENTRIES'!$B:$B), "", SUMIFS(H$2:H18, C$2:C18, C18)) | J18: =IF(B18 > MAX('04_LOG_FIELD_ENTRIES'!$B:$B), "", SUMIFS('04_LOG_FIELD_ENTRIES'!$J:$J, '04_LOG_FIELD_ENTRIES'!$B:$B, B18, '04_LOG_FIELD_ENTRIES'!$D:$D, C18, '04_LOG_FIELD_ENTRIES'!$K:$K, "AC_*")) | K18: =IF(B18 > MAX('04_LOG_FIELD_ENTRIES'!$B:$B), "", SUMIFS(J$2:J18, C$2:C18, C18)) | L18: =IF(K18="", "", I18-K18) | M18: =IF(I18="", "", I18-G18) | N18: =IF(I18="", "", IF(G18>0, I18/G18, 1)) | O18: =IF(I18="", "", IF(K18>0, I18/K18, 1)) | P18: =IF(I18="", "", IF(AND(N18>=0.95, O18>=0.95), "SALUDABLE", IF(N18<0.9, "ALERTA RETRASO", "ALERTA SOBRECOSTO")))
A19: 5 | B19: 46239 | C19: WBS-200 | D19: Red de Alcantarillado, Zanjas y Buzones | E19: =SUM('01_PRESUPUESTO_CRONOGRAMA_BASE'!G4:G9) | F19: =SUMIFS('02_CRONOGRAMA_PV_DIARIO'!E:E, '02_CRONOGRAMA_PV_DIARIO'!A:A, A19, '02_CRONOGRAMA_PV_DIARIO'!C:C, C19) | G19: =SUMIFS(F$2:F19, C$2:C19, C19) | H19: =IF(B19 > MAX('04_LOG_FIELD_ENTRIES'!$B:$B), "", SUMIFS('04_LOG_FIELD_ENTRIES'!$J:$J, '04_LOG_FIELD_ENTRIES'!$B:$B, B19, '04_LOG_FIELD_ENTRIES'!$D:$D, C19, '04_LOG_FIELD_ENTRIES'!$K:$K, "EV_PRODUCCION")) | I19: =IF(B19 > MAX('04_LOG_FIELD_ENTRIES'!$B:$B), "", SUMIFS(H$2:H19, C$2:C19, C19)) | J19: =IF(B19 > MAX('04_LOG_FIELD_ENTRIES'!$B:$B), "", SUMIFS('04_LOG_FIELD_ENTRIES'!$J:$J, '04_LOG_FIELD_ENTRIES'!$B:$B, B19, '04_LOG_FIELD_ENTRIES'!$D:$D, C19, '04_LOG_FIELD_ENTRIES'!$K:$K, "AC_*")) | K19: =IF(B19 > MAX('04_LOG_FIELD_ENTRIES'!$B:$B), "", SUMIFS(J$2:J19, C$2:C19, C19)) | L19: =IF(K19="", "", I19-K19) | M19: =IF(I19="", "", I19-G19) | N19: =IF(I19="", "", IF(G19>0, I19/G19, 1)) | O19: =IF(I19="", "", IF(K19>0, I19/K19, 1)) | P19: =IF(I19="", "", IF(AND(N19>=0.95, O19>=0.95), "SALUDABLE", IF(N19<0.9, "ALERTA RETRASO", "ALERTA SOBRECOSTO")))
A20: 5 | B20: 46239 | C20: WBS-300 | D20: Red de Agua Potable y Conexiones Domiciliarias | E20: =SUM('01_PRESUPUESTO_CRONOGRAMA_BASE'!G10:G11) | F20: =SUMIFS('02_CRONOGRAMA_PV_DIARIO'!E:E, '02_CRONOGRAMA_PV_DIARIO'!A:A, A20, '02_CRONOGRAMA_PV_DIARIO'!C:C, C20) | G20: =SUMIFS(F$2:F20, C$2:C20, C20) | H20: =IF(B20 > MAX('04_LOG_FIELD_ENTRIES'!$B:$B), "", SUMIFS('04_LOG_FIELD_ENTRIES'!$J:$J, '04_LOG_FIELD_ENTRIES'!$B:$B, B20, '04_LOG_FIELD_ENTRIES'!$D:$D, C20, '04_LOG_FIELD_ENTRIES'!$K:$K, "EV_PRODUCCION")) | I20: =IF(B20 > MAX('04_LOG_FIELD_ENTRIES'!$B:$B), "", SUMIFS(H$2:H20, C$2:C20, C20)) | J20: =IF(B20 > MAX('04_LOG_FIELD_ENTRIES'!$B:$B), "", SUMIFS('04_LOG_FIELD_ENTRIES'!$J:$J, '04_LOG_FIELD_ENTRIES'!$B:$B, B20, '04_LOG_FIELD_ENTRIES'!$D:$D, C20, '04_LOG_FIELD_ENTRIES'!$K:$K, "AC_*")) | K20: =IF(B20 > MAX('04_LOG_FIELD_ENTRIES'!$B:$B), "", SUMIFS(J$2:J20, C$2:C20, C20)) | L20: =IF(K20="", "", I20-K20) | M20: =IF(I20="", "", I20-G20) | N20: =IF(I20="", "", IF(G20>0, I20/G20, 1)) | O20: =IF(I20="", "", IF(K20>0, I20/K20, 1)) | P20: =IF(I20="", "", IF(AND(N20>=0.95, O20>=0.95), "SALUDABLE", IF(N20<0.9, "ALERTA RETRASO", "ALERTA SOBRECOSTO")))
A21: 5 | B21: 46239 | C21: WBS-400 | D21: Pruebas Hidráulicas, Desinfección y Entrega | E21: =SUM('01_PRESUPUESTO_CRONOGRAMA_BASE'!G12:G12) | F21: =SUMIFS('02_CRONOGRAMA_PV_DIARIO'!E:E, '02_CRONOGRAMA_PV_DIARIO'!A:A, A21, '02_CRONOGRAMA_PV_DIARIO'!C:C, C21) | G21: =SUMIFS(F$2:F21, C$2:C21, C21) | H21: =IF(B21 > MAX('04_LOG_FIELD_ENTRIES'!$B:$B), "", SUMIFS('04_LOG_FIELD_ENTRIES'!$J:$J, '04_LOG_FIELD_ENTRIES'!$B:$B, B21, '04_LOG_FIELD_ENTRIES'!$D:$D, C21, '04_LOG_FIELD_ENTRIES'!$K:$K, "EV_PRODUCCION")) | I21: =IF(B21 > MAX('04_LOG_FIELD_ENTRIES'!$B:$B), "", SUMIFS(H$2:H21, C$2:C21, C21)) | J21: =IF(B21 > MAX('04_LOG_FIELD_ENTRIES'!$B:$B), "", SUMIFS('04_LOG_FIELD_ENTRIES'!$J:$J, '04_LOG_FIELD_ENTRIES'!$B:$B, B21, '04_LOG_FIELD_ENTRIES'!$D:$D, C21, '04_LOG_FIELD_ENTRIES'!$K:$K, "AC_*")) | K21: =IF(B21 > MAX('04_LOG_FIELD_ENTRIES'!$B:$B), "", SUMIFS(J$2:J21, C$2:C21, C21)) | L21: =IF(K21="", "", I21-K21) | M21: =IF(I21="", "", I21-G21) | N21: =IF(I21="", "", IF(G21>0, I21/G21, 1)) | O21: =IF(I21="", "", IF(K21>0, I21/K21, 1)) | P21: =IF(I21="", "", IF(AND(N21>=0.95, O21>=0.95), "SALUDABLE", IF(N21<0.9, "ALERTA RETRASO", "ALERTA SOBRECOSTO")))
A22: 6 | B22: 46240 | C22: WBS-100 | D22: Obras Preliminares, Trazo y Movilización | E22: =SUM('01_PRESUPUESTO_CRONOGRAMA_BASE'!G2:G3) | F22: =SUMIFS('02_CRONOGRAMA_PV_DIARIO'!E:E, '02_CRONOGRAMA_PV_DIARIO'!A:A, A22, '02_CRONOGRAMA_PV_DIARIO'!C:C, C22) | G22: =SUMIFS(F$2:F22, C$2:C22, C22) | H22: =IF(B22 > MAX('04_LOG_FIELD_ENTRIES'!$B:$B), "", SUMIFS('04_LOG_FIELD_ENTRIES'!$J:$J, '04_LOG_FIELD_ENTRIES'!$B:$B, B22, '04_LOG_FIELD_ENTRIES'!$D:$D, C22, '04_LOG_FIELD_ENTRIES'!$K:$K, "EV_PRODUCCION")) | I22: =IF(B22 > MAX('04_LOG_FIELD_ENTRIES'!$B:$B), "", SUMIFS(H$2:H22, C$2:C22, C22)) | J22: =IF(B22 > MAX('04_LOG_FIELD_ENTRIES'!$B:$B), "", SUMIFS('04_LOG_FIELD_ENTRIES'!$J:$J, '04_LOG_FIELD_ENTRIES'!$B:$B, B22, '04_LOG_FIELD_ENTRIES'!$D:$D, C22, '04_LOG_FIELD_ENTRIES'!$K:$K, "AC_*")) | K22: =IF(B22 > MAX('04_LOG_FIELD_ENTRIES'!$B:$B), "", SUMIFS(J$2:J22, C$2:C22, C22)) | L22: =IF(K22="", "", I22-K22) | M22: =IF(I22="", "", I22-G22) | N22: =IF(I22="", "", IF(G22>0, I22/G22, 1)) | O22: =IF(I22="", "", IF(K22>0, I22/K22, 1)) | P22: =IF(I22="", "", IF(AND(N22>=0.95, O22>=0.95), "SALUDABLE", IF(N22<0.9, "ALERTA RETRASO", "ALERTA SOBRECOSTO")))
A23: 6 | B23: 46240 | C23: WBS-200 | D23: Red de Alcantarillado, Zanjas y Buzones | E23: =SUM('01_PRESUPUESTO_CRONOGRAMA_BASE'!G4:G9) | F23: =SUMIFS('02_CRONOGRAMA_PV_DIARIO'!E:E, '02_CRONOGRAMA_PV_DIARIO'!A:A, A23, '02_CRONOGRAMA_PV_DIARIO'!C:C, C23) | G23: =SUMIFS(F$2:F23, C$2:C23, C23) | H23: =IF(B23 > MAX('04_LOG_FIELD_ENTRIES'!$B:$B), "", SUMIFS('04_LOG_FIELD_ENTRIES'!$J:$J, '04_LOG_FIELD_ENTRIES'!$B:$B, B23, '04_LOG_FIELD_ENTRIES'!$D:$D, C23, '04_LOG_FIELD_ENTRIES'!$K:$K, "EV_PRODUCCION")) | I23: =IF(B23 > MAX('04_LOG_FIELD_ENTRIES'!$B:$B), "", SUMIFS(H$2:H23, C$2:C23, C23)) | J23: =IF(B23 > MAX('04_LOG_FIELD_ENTRIES'!$B:$B), "", SUMIFS('04_LOG_FIELD_ENTRIES'!$J:$J, '04_LOG_FIELD_ENTRIES'!$B:$B, B23, '04_LOG_FIELD_ENTRIES'!$D:$D, C23, '04_LOG_FIELD_ENTRIES'!$K:$K, "AC_*")) | K23: =IF(B23 > MAX('04_LOG_FIELD_ENTRIES'!$B:$B), "", SUMIFS(J$2:J23, C$2:C23, C23)) | L23: =IF(K23="", "", I23-K23) | M23: =IF(I23="", "", I23-G23) | N23: =IF(I23="", "", IF(G23>0, I23/G23, 1)) | O23: =IF(I23="", "", IF(K23>0, I23/K23, 1)) | P23: =IF(I23="", "", IF(AND(N23>=0.95, O23>=0.95), "SALUDABLE", IF(N23<0.9, "ALERTA RETRASO", "ALERTA SOBRECOSTO")))
A24: 6 | B24: 46240 | C24: WBS-300 | D24: Red de Agua Potable y Conexiones Domiciliarias | E24: =SUM('01_PRESUPUESTO_CRONOGRAMA_BASE'!G10:G11) | F24: =SUMIFS('02_CRONOGRAMA_PV_DIARIO'!E:E, '02_CRONOGRAMA_PV_DIARIO'!A:A, A24, '02_CRONOGRAMA_PV_DIARIO'!C:C, C24) | G24: =SUMIFS(F$2:F24, C$2:C24, C24) | H24: =IF(B24 > MAX('04_LOG_FIELD_ENTRIES'!$B:$B), "", SUMIFS('04_LOG_FIELD_ENTRIES'!$J:$J, '04_LOG_FIELD_ENTRIES'!$B:$B, B24, '04_LOG_FIELD_ENTRIES'!$D:$D, C24, '04_LOG_FIELD_ENTRIES'!$K:$K, "EV_PRODUCCION")) | I24: =IF(B24 > MAX('04_LOG_FIELD_ENTRIES'!$B:$B), "", SUMIFS(H$2:H24, C$2:C24, C24)) | J24: =IF(B24 > MAX('04_LOG_FIELD_ENTRIES'!$B:$B), "", SUMIFS('04_LOG_FIELD_ENTRIES'!$J:$J, '04_LOG_FIELD_ENTRIES'!$B:$B, B24, '04_LOG_FIELD_ENTRIES'!$D:$D, C24, '04_LOG_FIELD_ENTRIES'!$K:$K, "AC_*")) | K24: =IF(B24 > MAX('04_LOG_FIELD_ENTRIES'!$B:$B), "", SUMIFS(J$2:J24, C$2:C24, C24)) | L24: =IF(K24="", "", I24-K24) | M24: =IF(I24="", "", I24-G24) | N24: =IF(I24="", "", IF(G24>0, I24/G24, 1)) | O24: =IF(I24="", "", IF(K24>0, I24/K24, 1)) | P24: =IF(I24="", "", IF(AND(N24>=0.95, O24>=0.95), "SALUDABLE", IF(N24<0.9, "ALERTA RETRASO", "ALERTA SOBRECOSTO")))
A25: 6 | B25: 46240 | C25: WBS-400 | D25: Pruebas Hidráulicas, Desinfección y Entrega | E25: =SUM('01_PRESUPUESTO_CRONOGRAMA_BASE'!G12:G12) | F25: =SUMIFS('02_CRONOGRAMA_PV_DIARIO'!E:E, '02_CRONOGRAMA_PV_DIARIO'!A:A, A25, '02_CRONOGRAMA_PV_DIARIO'!C:C, C25) | G25: =SUMIFS(F$2:F25, C$2:C25, C25) | H25: =IF(B25 > MAX('04_LOG_FIELD_ENTRIES'!$B:$B), "", SUMIFS('04_LOG_FIELD_ENTRIES'!$J:$J, '04_LOG_FIELD_ENTRIES'!$B:$B, B25, '04_LOG_FIELD_ENTRIES'!$D:$D, C25, '04_LOG_FIELD_ENTRIES'!$K:$K, "EV_PRODUCCION")) | I25: =IF(B25 > MAX('04_LOG_FIELD_ENTRIES'!$B:$B), "", SUMIFS(H$2:H25, C$2:C25, C25)) | J25: =IF(B25 > MAX('04_LOG_FIELD_ENTRIES'!$B:$B), "", SUMIFS('04_LOG_FIELD_ENTRIES'!$J:$J, '04_LOG_FIELD_ENTRIES'!$B:$B, B25, '04_LOG_FIELD_ENTRIES'!$D:$D, C25, '04_LOG_FIELD_ENTRIES'!$K:$K, "AC_*")) | K25: =IF(B25 > MAX('04_LOG_FIELD_ENTRIES'!$B:$B), "", SUMIFS(J$2:J25, C$2:C25, C25)) | L25: =IF(K25="", "", I25-K25) | M25: =IF(I25="", "", I25-G25) | N25: =IF(I25="", "", IF(G25>0, I25/G25, 1)) | O25: =IF(I25="", "", IF(K25>0, I25/K25, 1)) | P25: =IF(I25="", "", IF(AND(N25>=0.95, O25>=0.95), "SALUDABLE", IF(N25<0.9, "ALERTA RETRASO", "ALERTA SOBRECOSTO")))
A26: 7 | B26: 46241 | C26: WBS-100 | D26: Obras Preliminares, Trazo y Movilización | E26: =SUM('01_PRESUPUESTO_CRONOGRAMA_BASE'!G2:G3) | F26: =SUMIFS('02_CRONOGRAMA_PV_DIARIO'!E:E, '02_CRONOGRAMA_PV_DIARIO'!A:A, A26, '02_CRONOGRAMA_PV_DIARIO'!C:C, C26) | G26: =SUMIFS(F$2:F26, C$2:C26, C26) | H26: =IF(B26 > MAX('04_LOG_FIELD_ENTRIES'!$B:$B), "", SUMIFS('04_LOG_FIELD_ENTRIES'!$J:$J, '04_LOG_FIELD_ENTRIES'!$B:$B, B26, '04_LOG_FIELD_ENTRIES'!$D:$D, C26, '04_LOG_FIELD_ENTRIES'!$K:$K, "EV_PRODUCCION")) | I26: =IF(B26 > MAX('04_LOG_FIELD_ENTRIES'!$B:$B), "", SUMIFS(H$2:H26, C$2:C26, C26)) | J26: =IF(B26 > MAX('04_LOG_FIELD_ENTRIES'!$B:$B), "", SUMIFS('04_LOG_FIELD_ENTRIES'!$J:$J, '04_LOG_FIELD_ENTRIES'!$B:$B, B26, '04_LOG_FIELD_ENTRIES'!$D:$D, C26, '04_LOG_FIELD_ENTRIES'!$K:$K, "AC_*")) | K26: =IF(B26 > MAX('04_LOG_FIELD_ENTRIES'!$B:$B), "", SUMIFS(J$2:J26, C$2:C26, C26)) | L26: =IF(K26="", "", I26-K26) | M26: =IF(I26="", "", I26-G26) | N26: =IF(I26="", "", IF(G26>0, I26/G26, 1)) | O26: =IF(I26="", "", IF(K26>0, I26/K26, 1)) | P26: =IF(I26="", "", IF(AND(N26>=0.95, O26>=0.95), "SALUDABLE", IF(N26<0.9, "ALERTA RETRASO", "ALERTA SOBRECOSTO")))
A27: 7 | B27: 46241 | C27: WBS-200 | D27: Red de Alcantarillado, Zanjas y Buzones | E27: =SUM('01_PRESUPUESTO_CRONOGRAMA_BASE'!G4:G9) | F27: =SUMIFS('02_CRONOGRAMA_PV_DIARIO'!E:E, '02_CRONOGRAMA_PV_DIARIO'!A:A, A27, '02_CRONOGRAMA_PV_DIARIO'!C:C, C27) | G27: =SUMIFS(F$2:F27, C$2:C27, C27) | H27: =IF(B27 > MAX('04_LOG_FIELD_ENTRIES'!$B:$B), "", SUMIFS('04_LOG_FIELD_ENTRIES'!$J:$J, '04_LOG_FIELD_ENTRIES'!$B:$B, B27, '04_LOG_FIELD_ENTRIES'!$D:$D, C27, '04_LOG_FIELD_ENTRIES'!$K:$K, "EV_PRODUCCION")) | I27: =IF(B27 > MAX('04_LOG_FIELD_ENTRIES'!$B:$B), "", SUMIFS(H$2:H27, C$2:C27, C27)) | J27: =IF(B27 > MAX('04_LOG_FIELD_ENTRIES'!$B:$B), "", SUMIFS('04_LOG_FIELD_ENTRIES'!$J:$J, '04_LOG_FIELD_ENTRIES'!$B:$B, B27, '04_LOG_FIELD_ENTRIES'!$D:$D, C27, '04_LOG_FIELD_ENTRIES'!$K:$K, "AC_*")) | K27: =IF(B27 > MAX('04_LOG_FIELD_ENTRIES'!$B:$B), "", SUMIFS(J$2:J27, C$2:C27, C27)) | L27: =IF(K27="", "", I27-K27) | M27: =IF(I27="", "", I27-G27) | N27: =IF(I27="", "", IF(G27>0, I27/G27, 1)) | O27: =IF(I27="", "", IF(K27>0, I27/K27, 1)) | P27: =IF(I27="", "", IF(AND(N27>=0.95, O27>=0.95), "SALUDABLE", IF(N27<0.9, "ALERTA RETRASO", "ALERTA SOBRECOSTO")))
A28: 7 | B28: 46241 | C28: WBS-300 | D28: Red de Agua Potable y Conexiones Domiciliarias | E28: =SUM('01_PRESUPUESTO_CRONOGRAMA_BASE'!G10:G11) | F28: =SUMIFS('02_CRONOGRAMA_PV_DIARIO'!E:E, '02_CRONOGRAMA_PV_DIARIO'!A:A, A28, '02_CRONOGRAMA_PV_DIARIO'!C:C, C28) | G28: =SUMIFS(F$2:F28, C$2:C28, C28) | H28: =IF(B28 > MAX('04_LOG_FIELD_ENTRIES'!$B:$B), "", SUMIFS('04_LOG_FIELD_ENTRIES'!$J:$J, '04_LOG_FIELD_ENTRIES'!$B:$B, B28, '04_LOG_FIELD_ENTRIES'!$D:$D, C28, '04_LOG_FIELD_ENTRIES'!$K:$K, "EV_PRODUCCION")) | I28: =IF(B28 > MAX('04_LOG_FIELD_ENTRIES'!$B:$B), "", SUMIFS(H$2:H28, C$2:C28, C28)) | J28: =IF(B28 > MAX('04_LOG_FIELD_ENTRIES'!$B:$B), "", SUMIFS('04_LOG_FIELD_ENTRIES'!$J:$J, '04_LOG_FIELD_ENTRIES'!$B:$B, B28, '04_LOG_FIELD_ENTRIES'!$D:$D, C28, '04_LOG_FIELD_ENTRIES'!$K:$K, "AC_*")) | K28: =IF(B28 > MAX('04_LOG_FIELD_ENTRIES'!$B:$B), "", SUMIFS(J$2:J28, C$2:C28, C28)) | L28: =IF(K28="", "", I28-K28) | M28: =IF(I28="", "", I28-G28) | N28: =IF(I28="", "", IF(G28>0, I28/G28, 1)) | O28: =IF(I28="", "", IF(K28>0, I28/K28, 1)) | P28: =IF(I28="", "", IF(AND(N28>=0.95, O28>=0.95), "SALUDABLE", IF(N28<0.9, "ALERTA RETRASO", "ALERTA SOBRECOSTO")))
A29: 7 | B29: 46241 | C29: WBS-400 | D29: Pruebas Hidráulicas, Desinfección y Entrega | E29: =SUM('01_PRESUPUESTO_CRONOGRAMA_BASE'!G12:G12) | F29: =SUMIFS('02_CRONOGRAMA_PV_DIARIO'!E:E, '02_CRONOGRAMA_PV_DIARIO'!A:A, A29, '02_CRONOGRAMA_PV_DIARIO'!C:C, C29) | G29: =SUMIFS(F$2:F29, C$2:C29, C29) | H29: =IF(B29 > MAX('04_LOG_FIELD_ENTRIES'!$B:$B), "", SUMIFS('04_LOG_FIELD_ENTRIES'!$J:$J, '04_LOG_FIELD_ENTRIES'!$B:$B, B29, '04_LOG_FIELD_ENTRIES'!$D:$D, C29, '04_LOG_FIELD_ENTRIES'!$K:$K, "EV_PRODUCCION")) | I29: =IF(B29 > MAX('04_LOG_FIELD_ENTRIES'!$B:$B), "", SUMIFS(H$2:H29, C$2:C29, C29)) | J29: =IF(B29 > MAX('04_LOG_FIELD_ENTRIES'!$B:$B), "", SUMIFS('04_LOG_FIELD_ENTRIES'!$J:$J, '04_LOG_FIELD_ENTRIES'!$B:$B, B29, '04_LOG_FIELD_ENTRIES'!$D:$D, C29, '04_LOG_FIELD_ENTRIES'!$K:$K, "AC_*")) | K29: =IF(B29 > MAX('04_LOG_FIELD_ENTRIES'!$B:$B), "", SUMIFS(J$2:J29, C$2:C29, C29)) | L29: =IF(K29="", "", I29-K29) | M29: =IF(I29="", "", I29-G29) | N29: =IF(I29="", "", IF(G29>0, I29/G29, 1)) | O29: =IF(I29="", "", IF(K29>0, I29/K29, 1)) | P29: =IF(I29="", "", IF(AND(N29>=0.95, O29>=0.95), "SALUDABLE", IF(N29<0.9, "ALERTA RETRASO", "ALERTA SOBRECOSTO")))
A30: 8 | B30: 46242 | C30: WBS-100 | D30: Obras Preliminares, Trazo y Movilización | E30: =SUM('01_PRESUPUESTO_CRONOGRAMA_BASE'!G2:G3) | F30: =SUMIFS('02_CRONOGRAMA_PV_DIARIO'!E:E, '02_CRONOGRAMA_PV_DIARIO'!A:A, A30, '02_CRONOGRAMA_PV_DIARIO'!C:C, C30) | G30: =SUMIFS(F$2:F30, C$2:C30, C30) | H30: =IF(B30 > MAX('04_LOG_FIELD_ENTRIES'!$B:$B), "", SUMIFS('04_LOG_FIELD_ENTRIES'!$J:$J, '04_LOG_FIELD_ENTRIES'!$B:$B, B30, '04_LOG_FIELD_ENTRIES'!$D:$D, C30, '04_LOG_FIELD_ENTRIES'!$K:$K, "EV_PRODUCCION")) | I30: =IF(B30 > MAX('04_LOG_FIELD_ENTRIES'!$B:$B), "", SUMIFS(H$2:H30, C$2:C30, C30)) | J30: =IF(B30 > MAX('04_LOG_FIELD_ENTRIES'!$B:$B), "", SUMIFS('04_LOG_FIELD_ENTRIES'!$J:$J, '04_LOG_FIELD_ENTRIES'!$B:$B, B30, '04_LOG_FIELD_ENTRIES'!$D:$D, C30, '04_LOG_FIELD_ENTRIES'!$K:$K, "AC_*")) | K30: =IF(B30 > MAX('04_LOG_FIELD_ENTRIES'!$B:$B), "", SUMIFS(J$2:J30, C$2:C30, C30)) | L30: =IF(K30="", "", I30-K30) | M30: =IF(I30="", "", I30-G30) | N30: =IF(I30="", "", IF(G30>0, I30/G30, 1)) | O30: =IF(I30="", "", IF(K30>0, I30/K30, 1)) | P30: =IF(I30="", "", IF(AND(N30>=0.95, O30>=0.95), "SALUDABLE", IF(N30<0.9, "ALERTA RETRASO", "ALERTA SOBRECOSTO")))
A31: 8 | B31: 46242 | C31: WBS-200 | D31: Red de Alcantarillado, Zanjas y Buzones | E31: =SUM('01_PRESUPUESTO_CRONOGRAMA_BASE'!G4:G9) | F31: =SUMIFS('02_CRONOGRAMA_PV_DIARIO'!E:E, '02_CRONOGRAMA_PV_DIARIO'!A:A, A31, '02_CRONOGRAMA_PV_DIARIO'!C:C, C31) | G31: =SUMIFS(F$2:F31, C$2:C31, C31) | H31: =IF(B31 > MAX('04_LOG_FIELD_ENTRIES'!$B:$B), "", SUMIFS('04_LOG_FIELD_ENTRIES'!$J:$J, '04_LOG_FIELD_ENTRIES'!$B:$B, B31, '04_LOG_FIELD_ENTRIES'!$D:$D, C31, '04_LOG_FIELD_ENTRIES'!$K:$K, "EV_PRODUCCION")) | I31: =IF(B31 > MAX('04_LOG_FIELD_ENTRIES'!$B:$B), "", SUMIFS(H$2:H31, C$2:C31, C31)) | J31: =IF(B31 > MAX('04_LOG_FIELD_ENTRIES'!$B:$B), "", SUMIFS('04_LOG_FIELD_ENTRIES'!$J:$J, '04_LOG_FIELD_ENTRIES'!$B:$B, B31, '04_LOG_FIELD_ENTRIES'!$D:$D, C31, '04_LOG_FIELD_ENTRIES'!$K:$K, "AC_*")) | K31: =IF(B31 > MAX('04_LOG_FIELD_ENTRIES'!$B:$B), "", SUMIFS(J$2:J31, C$2:C31, C31)) | L31: =IF(K31="", "", I31-K31) | M31: =IF(I31="", "", I31-G31) | N31: =IF(I31="", "", IF(G31>0, I31/G31, 1)) | O31: =IF(I31="", "", IF(K31>0, I31/K31, 1)) | P31: =IF(I31="", "", IF(AND(N31>=0.95, O31>=0.95), "SALUDABLE", IF(N31<0.9, "ALERTA RETRASO", "ALERTA SOBRECOSTO")))
A32: 8 | B32: 46242 | C32: WBS-300 | D32: Red de Agua Potable y Conexiones Domiciliarias | E32: =SUM('01_PRESUPUESTO_CRONOGRAMA_BASE'!G10:G11) | F32: =SUMIFS('02_CRONOGRAMA_PV_DIARIO'!E:E, '02_CRONOGRAMA_PV_DIARIO'!A:A, A32, '02_CRONOGRAMA_PV_DIARIO'!C:C, C32) | G32: =SUMIFS(F$2:F32, C$2:C32, C32) | H32: =IF(B32 > MAX('04_LOG_FIELD_ENTRIES'!$B:$B), "", SUMIFS('04_LOG_FIELD_ENTRIES'!$J:$J, '04_LOG_FIELD_ENTRIES'!$B:$B, B32, '04_LOG_FIELD_ENTRIES'!$D:$D, C32, '04_LOG_FIELD_ENTRIES'!$K:$K, "EV_PRODUCCION")) | I32: =IF(B32 > MAX('04_LOG_FIELD_ENTRIES'!$B:$B), "", SUMIFS(H$2:H32, C$2:C32, C32)) | J32: =IF(B32 > MAX('04_LOG_FIELD_ENTRIES'!$B:$B), "", SUMIFS('04_LOG_FIELD_ENTRIES'!$J:$J, '04_LOG_FIELD_ENTRIES'!$B:$B, B32, '04_LOG_FIELD_ENTRIES'!$D:$D, C32, '04_LOG_FIELD_ENTRIES'!$K:$K, "AC_*")) | K32: =IF(B32 > MAX('04_LOG_FIELD_ENTRIES'!$B:$B), "", SUMIFS(J$2:J32, C$2:C32, C32)) | L32: =IF(K32="", "", I32-K32) | M32: =IF(I32="", "", I32-G32) | N32: =IF(I32="", "", IF(G32>0, I32/G32, 1)) | O32: =IF(I32="", "", IF(K32>0, I32/K32, 1)) | P32: =IF(I32="", "", IF(AND(N32>=0.95, O32>=0.95), "SALUDABLE", IF(N32<0.9, "ALERTA RETRASO", "ALERTA SOBRECOSTO")))
A33: 8 | B33: 46242 | C33: WBS-400 | D33: Pruebas Hidráulicas, Desinfección y Entrega | E33: =SUM('01_PRESUPUESTO_CRONOGRAMA_BASE'!G12:G12) | F33: =SUMIFS('02_CRONOGRAMA_PV_DIARIO'!E:E, '02_CRONOGRAMA_PV_DIARIO'!A:A, A33, '02_CRONOGRAMA_PV_DIARIO'!C:C, C33) | G33: =SUMIFS(F$2:F33, C$2:C33, C33) | H33: =IF(B33 > MAX('04_LOG_FIELD_ENTRIES'!$B:$B), "", SUMIFS('04_LOG_FIELD_ENTRIES'!$J:$J, '04_LOG_FIELD_ENTRIES'!$B:$B, B33, '04_LOG_FIELD_ENTRIES'!$D:$D, C33, '04_LOG_FIELD_ENTRIES'!$K:$K, "EV_PRODUCCION")) | I33: =IF(B33 > MAX('04_LOG_FIELD_ENTRIES'!$B:$B), "", SUMIFS(H$2:H33, C$2:C33, C33)) | J33: =IF(B33 > MAX('04_LOG_FIELD_ENTRIES'!$B:$B), "", SUMIFS('04_LOG_FIELD_ENTRIES'!$J:$J, '04_LOG_FIELD_ENTRIES'!$B:$B, B33, '04_LOG_FIELD_ENTRIES'!$D:$D, C33, '04_LOG_FIELD_ENTRIES'!$K:$K, "AC_*")) | K33: =IF(B33 > MAX('04_LOG_FIELD_ENTRIES'!$B:$B), "", SUMIFS(J$2:J33, C$2:C33, C33)) | L33: =IF(K33="", "", I33-K33) | M33: =IF(I33="", "", I33-G33) | N33: =IF(I33="", "", IF(G33>0, I33/G33, 1)) | O33: =IF(I33="", "", IF(K33>0, I33/K33, 1)) | P33: =IF(I33="", "", IF(AND(N33>=0.95, O33>=0.95), "SALUDABLE", IF(N33<0.9, "ALERTA RETRASO", "ALERTA SOBRECOSTO")))
A34: 9 | B34: 46243 | C34: WBS-100 | D34: Obras Preliminares, Trazo y Movilización | E34: =SUM('01_PRESUPUESTO_CRONOGRAMA_BASE'!G2:G3) | F34: =SUMIFS('02_CRONOGRAMA_PV_DIARIO'!E:E, '02_CRONOGRAMA_PV_DIARIO'!A:A, A34, '02_CRONOGRAMA_PV_DIARIO'!C:C, C34) | G34: =SUMIFS(F$2:F34, C$2:C34, C34) | H34: =IF(B34 > MAX('04_LOG_FIELD_ENTRIES'!$B:$B), "", SUMIFS('04_LOG_FIELD_ENTRIES'!$J:$J, '04_LOG_FIELD_ENTRIES'!$B:$B, B34, '04_LOG_FIELD_ENTRIES'!$D:$D, C34, '04_LOG_FIELD_ENTRIES'!$K:$K, "EV_PRODUCCION")) | I34: =IF(B34 > MAX('04_LOG_FIELD_ENTRIES'!$B:$B), "", SUMIFS(H$2:H34, C$2:C34, C34)) | J34: =IF(B34 > MAX('04_LOG_FIELD_ENTRIES'!$B:$B), "", SUMIFS('04_LOG_FIELD_ENTRIES'!$J:$J, '04_LOG_FIELD_ENTRIES'!$B:$B, B34, '04_LOG_FIELD_ENTRIES'!$D:$D, C34, '04_LOG_FIELD_ENTRIES'!$K:$K, "AC_*")) | K34: =IF(B34 > MAX('04_LOG_FIELD_ENTRIES'!$B:$B), "", SUMIFS(J$2:J34, C$2:C34, C34)) | L34: =IF(K34="", "", I34-K34) | M34: =IF(I34="", "", I34-G34) | N34: =IF(I34="", "", IF(G34>0, I34/G34, 1)) | O34: =IF(I34="", "", IF(K34>0, I34/K34, 1)) | P34: =IF(I34="", "", IF(AND(N34>=0.95, O34>=0.95), "SALUDABLE", IF(N34<0.9, "ALERTA RETRASO", "ALERTA SOBRECOSTO")))
A35: 9 | B35: 46243 | C35: WBS-200 | D35: Red de Alcantarillado, Zanjas y Buzones | E35: =SUM('01_PRESUPUESTO_CRONOGRAMA_BASE'!G4:G9) | F35: =SUMIFS('02_CRONOGRAMA_PV_DIARIO'!E:E, '02_CRONOGRAMA_PV_DIARIO'!A:A, A35, '02_CRONOGRAMA_PV_DIARIO'!C:C, C35) | G35: =SUMIFS(F$2:F35, C$2:C35, C35) | H35: =IF(B35 > MAX('04_LOG_FIELD_ENTRIES'!$B:$B), "", SUMIFS('04_LOG_FIELD_ENTRIES'!$J:$J, '04_LOG_FIELD_ENTRIES'!$B:$B, B35, '04_LOG_FIELD_ENTRIES'!$D:$D, C35, '04_LOG_FIELD_ENTRIES'!$K:$K, "EV_PRODUCCION")) | I35: =IF(B35 > MAX('04_LOG_FIELD_ENTRIES'!$B:$B), "", SUMIFS(H$2:H35, C$2:C35, C35)) | J35: =IF(B35 > MAX('04_LOG_FIELD_ENTRIES'!$B:$B), "", SUMIFS('04_LOG_FIELD_ENTRIES'!$J:$J, '04_LOG_FIELD_ENTRIES'!$B:$B, B35, '04_LOG_FIELD_ENTRIES'!$D:$D, C35, '04_LOG_FIELD_ENTRIES'!$K:$K, "AC_*")) | K35: =IF(B35 > MAX('04_LOG_FIELD_ENTRIES'!$B:$B), "", SUMIFS(J$2:J35, C$2:C35, C35)) | L35: =IF(K35="", "", I35-K35) | M35: =IF(I35="", "", I35-G35) | N35: =IF(I35="", "", IF(G35>0, I35/G35, 1)) | O35: =IF(I35="", "", IF(K35>0, I35/K35, 1)) | P35: =IF(I35="", "", IF(AND(N35>=0.95, O35>=0.95), "SALUDABLE", IF(N35<0.9, "ALERTA RETRASO", "ALERTA SOBRECOSTO")))
A36: 9 | B36: 46243 | C36: WBS-300 | D36: Red de Agua Potable y Conexiones Domiciliarias | E36: =SUM('01_PRESUPUESTO_CRONOGRAMA_BASE'!G10:G11) | F36: =SUMIFS('02_CRONOGRAMA_PV_DIARIO'!E:E, '02_CRONOGRAMA_PV_DIARIO'!A:A, A36, '02_CRONOGRAMA_PV_DIARIO'!C:C, C36) | G36: =SUMIFS(F$2:F36, C$2:C36, C36) | H36: =IF(B36 > MAX('04_LOG_FIELD_ENTRIES'!$B:$B), "", SUMIFS('04_LOG_FIELD_ENTRIES'!$J:$J, '04_LOG_FIELD_ENTRIES'!$B:$B, B36, '04_LOG_FIELD_ENTRIES'!$D:$D, C36, '04_LOG_FIELD_ENTRIES'!$K:$K, "EV_PRODUCCION")) | I36: =IF(B36 > MAX('04_LOG_FIELD_ENTRIES'!$B:$B), "", SUMIFS(H$2:H36, C$2:C36, C36)) | J36: =IF(B36 > MAX('04_LOG_FIELD_ENTRIES'!$B:$B), "", SUMIFS('04_LOG_FIELD_ENTRIES'!$J:$J, '04_LOG_FIELD_ENTRIES'!$B:$B, B36, '04_LOG_FIELD_ENTRIES'!$D:$D, C36, '04_LOG_FIELD_ENTRIES'!$K:$K, "AC_*")) | K36: =IF(B36 > MAX('04_LOG_FIELD_ENTRIES'!$B:$B), "", SUMIFS(J$2:J36, C$2:C36, C36)) | L36: =IF(K36="", "", I36-K36) | M36: =IF(I36="", "", I36-G36) | N36: =IF(I36="", "", IF(G36>0, I36/G36, 1)) | O36: =IF(I36="", "", IF(K36>0, I36/K36, 1)) | P36: =IF(I36="", "", IF(AND(N36>=0.95, O36>=0.95), "SALUDABLE", IF(N36<0.9, "ALERTA RETRASO", "ALERTA SOBRECOSTO")))
A37: 9 | B37: 46243 | C37: WBS-400 | D37: Pruebas Hidráulicas, Desinfección y Entrega | E37: =SUM('01_PRESUPUESTO_CRONOGRAMA_BASE'!G12:G12) | F37: =SUMIFS('02_CRONOGRAMA_PV_DIARIO'!E:E, '02_CRONOGRAMA_PV_DIARIO'!A:A, A37, '02_CRONOGRAMA_PV_DIARIO'!C:C, C37) | G37: =SUMIFS(F$2:F37, C$2:C37, C37) | H37: =IF(B37 > MAX('04_LOG_FIELD_ENTRIES'!$B:$B), "", SUMIFS('04_LOG_FIELD_ENTRIES'!$J:$J, '04_LOG_FIELD_ENTRIES'!$B:$B, B37, '04_LOG_FIELD_ENTRIES'!$D:$D, C37, '04_LOG_FIELD_ENTRIES'!$K:$K, "EV_PRODUCCION")) | I37: =IF(B37 > MAX('04_LOG_FIELD_ENTRIES'!$B:$B), "", SUMIFS(H$2:H37, C$2:C37, C37)) | J37: =IF(B37 > MAX('04_LOG_FIELD_ENTRIES'!$B:$B), "", SUMIFS('04_LOG_FIELD_ENTRIES'!$J:$J, '04_LOG_FIELD_ENTRIES'!$B:$B, B37, '04_LOG_FIELD_ENTRIES'!$D:$D, C37, '04_LOG_FIELD_ENTRIES'!$K:$K, "AC_*")) | K37: =IF(B37 > MAX('04_LOG_FIELD_ENTRIES'!$B:$B), "", SUMIFS(J$2:J37, C$2:C37, C37)) | L37: =IF(K37="", "", I37-K37) | M37: =IF(I37="", "", I37-G37) | N37: =IF(I37="", "", IF(G37>0, I37/G37, 1)) | O37: =IF(I37="", "", IF(K37>0, I37/K37, 1)) | P37: =IF(I37="", "", IF(AND(N37>=0.95, O37>=0.95), "SALUDABLE", IF(N37<0.9, "ALERTA RETRASO", "ALERTA SOBRECOSTO")))
A38: 10 | B38: 46244 | C38: WBS-100 | D38: Obras Preliminares, Trazo y Movilización | E38: =SUM('01_PRESUPUESTO_CRONOGRAMA_BASE'!G2:G3) | F38: =SUMIFS('02_CRONOGRAMA_PV_DIARIO'!E:E, '02_CRONOGRAMA_PV_DIARIO'!A:A, A38, '02_CRONOGRAMA_PV_DIARIO'!C:C, C38) | G38: =SUMIFS(F$2:F38, C$2:C38, C38) | H38: =IF(B38 > MAX('04_LOG_FIELD_ENTRIES'!$B:$B), "", SUMIFS('04_LOG_FIELD_ENTRIES'!$J:$J, '04_LOG_FIELD_ENTRIES'!$B:$B, B38, '04_LOG_FIELD_ENTRIES'!$D:$D, C38, '04_LOG_FIELD_ENTRIES'!$K:$K, "EV_PRODUCCION")) | I38: =IF(B38 > MAX('04_LOG_FIELD_ENTRIES'!$B:$B), "", SUMIFS(H$2:H38, C$2:C38, C38)) | J38: =IF(B38 > MAX('04_LOG_FIELD_ENTRIES'!$B:$B), "", SUMIFS('04_LOG_FIELD_ENTRIES'!$J:$J, '04_LOG_FIELD_ENTRIES'!$B:$B, B38, '04_LOG_FIELD_ENTRIES'!$D:$D, C38, '04_LOG_FIELD_ENTRIES'!$K:$K, "AC_*")) | K38: =IF(B38 > MAX('04_LOG_FIELD_ENTRIES'!$B:$B), "", SUMIFS(J$2:J38, C$2:C38, C38)) | L38: =IF(K38="", "", I38-K38) | M38: =IF(I38="", "", I38-G38) | N38: =IF(I38="", "", IF(G38>0, I38/G38, 1)) | O38: =IF(I38="", "", IF(K38>0, I38/K38, 1)) | P38: =IF(I38="", "", IF(AND(N38>=0.95, O38>=0.95), "SALUDABLE", IF(N38<0.9, "ALERTA RETRASO", "ALERTA SOBRECOSTO")))
A39: 10 | B39: 46244 | C39: WBS-200 | D39: Red de Alcantarillado, Zanjas y Buzones | E39: =SUM('01_PRESUPUESTO_CRONOGRAMA_BASE'!G4:G9) | F39: =SUMIFS('02_CRONOGRAMA_PV_DIARIO'!E:E, '02_CRONOGRAMA_PV_DIARIO'!A:A, A39, '02_CRONOGRAMA_PV_DIARIO'!C:C, C39) | G39: =SUMIFS(F$2:F39, C$2:C39, C39) | H39: =IF(B39 > MAX('04_LOG_FIELD_ENTRIES'!$B:$B), "", SUMIFS('04_LOG_FIELD_ENTRIES'!$J:$J, '04_LOG_FIELD_ENTRIES'!$B:$B, B39, '04_LOG_FIELD_ENTRIES'!$D:$D, C39, '04_LOG_FIELD_ENTRIES'!$K:$K, "EV_PRODUCCION")) | I39: =IF(B39 > MAX('04_LOG_FIELD_ENTRIES'!$B:$B), "", SUMIFS(H$2:H39, C$2:C39, C39)) | J39: =IF(B39 > MAX('04_LOG_FIELD_ENTRIES'!$B:$B), "", SUMIFS('04_LOG_FIELD_ENTRIES'!$J:$J, '04_LOG_FIELD_ENTRIES'!$B:$B, B39, '04_LOG_FIELD_ENTRIES'!$D:$D, C39, '04_LOG_FIELD_ENTRIES'!$K:$K, "AC_*")) | K39: =IF(B39 > MAX('04_LOG_FIELD_ENTRIES'!$B:$B), "", SUMIFS(J$2:J39, C$2:C39, C39)) | L39: =IF(K39="", "", I39-K39) | M39: =IF(I39="", "", I39-G39) | N39: =IF(I39="", "", IF(G39>0, I39/G39, 1)) | O39: =IF(I39="", "", IF(K39>0, I39/K39, 1)) | P39: =IF(I39="", "", IF(AND(N39>=0.95, O39>=0.95), "SALUDABLE", IF(N39<0.9, "ALERTA RETRASO", "ALERTA SOBRECOSTO")))
A40: 10 | B40: 46244 | C40: WBS-300 | D40: Red de Agua Potable y Conexiones Domiciliarias | E40: =SUM('01_PRESUPUESTO_CRONOGRAMA_BASE'!G10:G11) | F40: =SUMIFS('02_CRONOGRAMA_PV_DIARIO'!E:E, '02_CRONOGRAMA_PV_DIARIO'!A:A, A40, '02_CRONOGRAMA_PV_DIARIO'!C:C, C40) | G40: =SUMIFS(F$2:F40, C$2:C40, C40) | H40: =IF(B40 > MAX('04_LOG_FIELD_ENTRIES'!$B:$B), "", SUMIFS('04_LOG_FIELD_ENTRIES'!$J:$J, '04_LOG_FIELD_ENTRIES'!$B:$B, B40, '04_LOG_FIELD_ENTRIES'!$D:$D, C40, '04_LOG_FIELD_ENTRIES'!$K:$K, "EV_PRODUCCION")) | I40: =IF(B40 > MAX('04_LOG_FIELD_ENTRIES'!$B:$B), "", SUMIFS(H$2:H40, C$2:C40, C40)) | J40: =IF(B40 > MAX('04_LOG_FIELD_ENTRIES'!$B:$B), "", SUMIFS('04_LOG_FIELD_ENTRIES'!$J:$J, '04_LOG_FIELD_ENTRIES'!$B:$B, B40, '04_LOG_FIELD_ENTRIES'!$D:$D, C40, '04_LOG_FIELD_ENTRIES'!$K:$K, "AC_*")) | K40: =IF(B40 > MAX('04_LOG_FIELD_ENTRIES'!$B:$B), "", SUMIFS(J$2:J40, C$2:C40, C40)) | L40: =IF(K40="", "", I40-K40) | M40: =IF(I40="", "", I40-G40) | N40: =IF(I40="", "", IF(G40>0, I40/G40, 1)) | O40: =IF(I40="", "", IF(K40>0, I40/K40, 1)) | P40: =IF(I40="", "", IF(AND(N40>=0.95, O40>=0.95), "SALUDABLE", IF(N40<0.9, "ALERTA RETRASO", "ALERTA SOBRECOSTO")))
A41: 10 | B41: 46244 | C41: WBS-400 | D41: Pruebas Hidráulicas, Desinfección y Entrega | E41: =SUM('01_PRESUPUESTO_CRONOGRAMA_BASE'!G12:G12) | F41: =SUMIFS('02_CRONOGRAMA_PV_DIARIO'!E:E, '02_CRONOGRAMA_PV_DIARIO'!A:A, A41, '02_CRONOGRAMA_PV_DIARIO'!C:C, C41) | G41: =SUMIFS(F$2:F41, C$2:C41, C41) | H41: =IF(B41 > MAX('04_LOG_FIELD_ENTRIES'!$B:$B), "", SUMIFS('04_LOG_FIELD_ENTRIES'!$J:$J, '04_LOG_FIELD_ENTRIES'!$B:$B, B41, '04_LOG_FIELD_ENTRIES'!$D:$D, C41, '04_LOG_FIELD_ENTRIES'!$K:$K, "EV_PRODUCCION")) | I41: =IF(B41 > MAX('04_LOG_FIELD_ENTRIES'!$B:$B), "", SUMIFS(H$2:H41, C$2:C41, C41)) | J41: =IF(B41 > MAX('04_LOG_FIELD_ENTRIES'!$B:$B), "", SUMIFS('04_LOG_FIELD_ENTRIES'!$J:$J, '04_LOG_FIELD_ENTRIES'!$B:$B, B41, '04_LOG_FIELD_ENTRIES'!$D:$D, C41, '04_LOG_FIELD_ENTRIES'!$K:$K, "AC_*")) | K41: =IF(B41 > MAX('04_LOG_FIELD_ENTRIES'!$B:$B), "", SUMIFS(J$2:J41, C$2:C41, C41)) | L41: =IF(K41="", "", I41-K41) | M41: =IF(I41="", "", I41-G41) | N41: =IF(I41="", "", IF(G41>0, I41/G41, 1)) | O41: =IF(I41="", "", IF(K41>0, I41/K41, 1)) | P41: =IF(I41="", "", IF(AND(N41>=0.95, O41>=0.95), "SALUDABLE", IF(N41<0.9, "ALERTA RETRASO", "ALERTA SOBRECOSTO")))
A42: 11 | B42: 46245 | C42: WBS-100 | D42: Obras Preliminares, Trazo y Movilización | E42: =SUM('01_PRESUPUESTO_CRONOGRAMA_BASE'!G2:G3) | F42: =SUMIFS('02_CRONOGRAMA_PV_DIARIO'!E:E, '02_CRONOGRAMA_PV_DIARIO'!A:A, A42, '02_CRONOGRAMA_PV_DIARIO'!C:C, C42) | G42: =SUMIFS(F$2:F42, C$2:C42, C42) | H42: =IF(B42 > MAX('04_LOG_FIELD_ENTRIES'!$B:$B), "", SUMIFS('04_LOG_FIELD_ENTRIES'!$J:$J, '04_LOG_FIELD_ENTRIES'!$B:$B, B42, '04_LOG_FIELD_ENTRIES'!$D:$D, C42, '04_LOG_FIELD_ENTRIES'!$K:$K, "EV_PRODUCCION")) | I42: =IF(B42 > MAX('04_LOG_FIELD_ENTRIES'!$B:$B), "", SUMIFS(H$2:H42, C$2:C42, C42)) | J42: =IF(B42 > MAX('04_LOG_FIELD_ENTRIES'!$B:$B), "", SUMIFS('04_LOG_FIELD_ENTRIES'!$J:$J, '04_LOG_FIELD_ENTRIES'!$B:$B, B42, '04_LOG_FIELD_ENTRIES'!$D:$D, C42, '04_LOG_FIELD_ENTRIES'!$K:$K, "AC_*")) | K42: =IF(B42 > MAX('04_LOG_FIELD_ENTRIES'!$B:$B), "", SUMIFS(J$2:J42, C$2:C42, C42)) | L42: =IF(K42="", "", I42-K42) | M42: =IF(I42="", "", I42-G42) | N42: =IF(I42="", "", IF(G42>0, I42/G42, 1)) | O42: =IF(I42="", "", IF(K42>0, I42/K42, 1)) | P42: =IF(I42="", "", IF(AND(N42>=0.95, O42>=0.95), "SALUDABLE", IF(N42<0.9, "ALERTA RETRASO", "ALERTA SOBRECOSTO")))
A43: 11 | B43: 46245 | C43: WBS-200 | D43: Red de Alcantarillado, Zanjas y Buzones | E43: =SUM('01_PRESUPUESTO_CRONOGRAMA_BASE'!G4:G9) | F43: =SUMIFS('02_CRONOGRAMA_PV_DIARIO'!E:E, '02_CRONOGRAMA_PV_DIARIO'!A:A, A43, '02_CRONOGRAMA_PV_DIARIO'!C:C, C43) | G43: =SUMIFS(F$2:F43, C$2:C43, C43) | H43: =IF(B43 > MAX('04_LOG_FIELD_ENTRIES'!$B:$B), "", SUMIFS('04_LOG_FIELD_ENTRIES'!$J:$J, '04_LOG_FIELD_ENTRIES'!$B:$B, B43, '04_LOG_FIELD_ENTRIES'!$D:$D, C43, '04_LOG_FIELD_ENTRIES'!$K:$K, "EV_PRODUCCION")) | I43: =IF(B43 > MAX('04_LOG_FIELD_ENTRIES'!$B:$B), "", SUMIFS(H$2:H43, C$2:C43, C43)) | J43: =IF(B43 > MAX('04_LOG_FIELD_ENTRIES'!$B:$B), "", SUMIFS('04_LOG_FIELD_ENTRIES'!$J:$J, '04_LOG_FIELD_ENTRIES'!$B:$B, B43, '04_LOG_FIELD_ENTRIES'!$D:$D, C43, '04_LOG_FIELD_ENTRIES'!$K:$K, "AC_*")) | K43: =IF(B43 > MAX('04_LOG_FIELD_ENTRIES'!$B:$B), "", SUMIFS(J$2:J43, C$2:C43, C43)) | L43: =IF(K43="", "", I43-K43) | M43: =IF(I43="", "", I43-G43) | N43: =IF(I43="", "", IF(G43>0, I43/G43, 1)) | O43: =IF(I43="", "", IF(K43>0, I43/K43, 1)) | P43: =IF(I43="", "", IF(AND(N43>=0.95, O43>=0.95), "SALUDABLE", IF(N43<0.9, "ALERTA RETRASO", "ALERTA SOBRECOSTO")))
A44: 11 | B44: 46245 | C44: WBS-300 | D44: Red de Agua Potable y Conexiones Domiciliarias | E44: =SUM('01_PRESUPUESTO_CRONOGRAMA_BASE'!G10:G11) | F44: =SUMIFS('02_CRONOGRAMA_PV_DIARIO'!E:E, '02_CRONOGRAMA_PV_DIARIO'!A:A, A44, '02_CRONOGRAMA_PV_DIARIO'!C:C, C44) | G44: =SUMIFS(F$2:F44, C$2:C44, C44) | H44: =IF(B44 > MAX('04_LOG_FIELD_ENTRIES'!$B:$B), "", SUMIFS('04_LOG_FIELD_ENTRIES'!$J:$J, '04_LOG_FIELD_ENTRIES'!$B:$B, B44, '04_LOG_FIELD_ENTRIES'!$D:$D, C44, '04_LOG_FIELD_ENTRIES'!$K:$K, "EV_PRODUCCION")) | I44: =IF(B44 > MAX('04_LOG_FIELD_ENTRIES'!$B:$B), "", SUMIFS(H$2:H44, C$2:C44, C44)) | J44: =IF(B44 > MAX('04_LOG_FIELD_ENTRIES'!$B:$B), "", SUMIFS('04_LOG_FIELD_ENTRIES'!$J:$J, '04_LOG_FIELD_ENTRIES'!$B:$B, B44, '04_LOG_FIELD_ENTRIES'!$D:$D, C44, '04_LOG_FIELD_ENTRIES'!$K:$K, "AC_*")) | K44: =IF(B44 > MAX('04_LOG_FIELD_ENTRIES'!$B:$B), "", SUMIFS(J$2:J44, C$2:C44, C44)) | L44: =IF(K44="", "", I44-K44) | M44: =IF(I44="", "", I44-G44) | N44: =IF(I44="", "", IF(G44>0, I44/G44, 1)) | O44: =IF(I44="", "", IF(K44>0, I44/K44, 1)) | P44: =IF(I44="", "", IF(AND(N44>=0.95, O44>=0.95), "SALUDABLE", IF(N44<0.9, "ALERTA RETRASO", "ALERTA SOBRECOSTO")))
A45: 11 | B45: 46245 | C45: WBS-400 | D45: Pruebas Hidráulicas, Desinfección y Entrega | E45: =SUM('01_PRESUPUESTO_CRONOGRAMA_BASE'!G12:G12) | F45: =SUMIFS('02_CRONOGRAMA_PV_DIARIO'!E:E, '02_CRONOGRAMA_PV_DIARIO'!A:A, A45, '02_CRONOGRAMA_PV_DIARIO'!C:C, C45) | G45: =SUMIFS(F$2:F45, C$2:C45, C45) | H45: =IF(B45 > MAX('04_LOG_FIELD_ENTRIES'!$B:$B), "", SUMIFS('04_LOG_FIELD_ENTRIES'!$J:$J, '04_LOG_FIELD_ENTRIES'!$B:$B, B45, '04_LOG_FIELD_ENTRIES'!$D:$D, C45, '04_LOG_FIELD_ENTRIES'!$K:$K, "EV_PRODUCCION")) | I45: =IF(B45 > MAX('04_LOG_FIELD_ENTRIES'!$B:$B), "", SUMIFS(H$2:H45, C$2:C45, C45)) | J45: =IF(B45 > MAX('04_LOG_FIELD_ENTRIES'!$B:$B), "", SUMIFS('04_LOG_FIELD_ENTRIES'!$J:$J, '04_LOG_FIELD_ENTRIES'!$B:$B, B45, '04_LOG_FIELD_ENTRIES'!$D:$D, C45, '04_LOG_FIELD_ENTRIES'!$K:$K, "AC_*")) | K45: =IF(B45 > MAX('04_LOG_FIELD_ENTRIES'!$B:$B), "", SUMIFS(J$2:J45, C$2:C45, C45)) | L45: =IF(K45="", "", I45-K45) | M45: =IF(I45="", "", I45-G45) | N45: =IF(I45="", "", IF(G45>0, I45/G45, 1)) | O45: =IF(I45="", "", IF(K45>0, I45/K45, 1)) | P45: =IF(I45="", "", IF(AND(N45>=0.95, O45>=0.95), "SALUDABLE", IF(N45<0.9, "ALERTA RETRASO", "ALERTA SOBRECOSTO")))
A46: 12 | B46: 46246 | C46: WBS-100 | D46: Obras Preliminares, Trazo y Movilización | E46: =SUM('01_PRESUPUESTO_CRONOGRAMA_BASE'!G2:G3) | F46: =SUMIFS('02_CRONOGRAMA_PV_DIARIO'!E:E, '02_CRONOGRAMA_PV_DIARIO'!A:A, A46, '02_CRONOGRAMA_PV_DIARIO'!C:C, C46) | G46: =SUMIFS(F$2:F46, C$2:C46, C46) | H46: =IF(B46 > MAX('04_LOG_FIELD_ENTRIES'!$B:$B), "", SUMIFS('04_LOG_FIELD_ENTRIES'!$J:$J, '04_LOG_FIELD_ENTRIES'!$B:$B, B46, '04_LOG_FIELD_ENTRIES'!$D:$D, C46, '04_LOG_FIELD_ENTRIES'!$K:$K, "EV_PRODUCCION")) | I46: =IF(B46 > MAX('04_LOG_FIELD_ENTRIES'!$B:$B), "", SUMIFS(H$2:H46, C$2:C46, C46)) | J46: =IF(B46 > MAX('04_LOG_FIELD_ENTRIES'!$B:$B), "", SUMIFS('04_LOG_FIELD_ENTRIES'!$J:$J, '04_LOG_FIELD_ENTRIES'!$B:$B, B46, '04_LOG_FIELD_ENTRIES'!$D:$D, C46, '04_LOG_FIELD_ENTRIES'!$K:$K, "AC_*")) | K46: =IF(B46 > MAX('04_LOG_FIELD_ENTRIES'!$B:$B), "", SUMIFS(J$2:J46, C$2:C46, C46)) | L46: =IF(K46="", "", I46-K46) | M46: =IF(I46="", "", I46-G46) | N46: =IF(I46="", "", IF(G46>0, I46/G46, 1)) | O46: =IF(I46="", "", IF(K46>0, I46/K46, 1)) | P46: =IF(I46="", "", IF(AND(N46>=0.95, O46>=0.95), "SALUDABLE", IF(N46<0.9, "ALERTA RETRASO", "ALERTA SOBRECOSTO")))
A47: 12 | B47: 46246 | C47: WBS-200 | D47: Red de Alcantarillado, Zanjas y Buzones | E47: =SUM('01_PRESUPUESTO_CRONOGRAMA_BASE'!G4:G9) | F47: =SUMIFS('02_CRONOGRAMA_PV_DIARIO'!E:E, '02_CRONOGRAMA_PV_DIARIO'!A:A, A47, '02_CRONOGRAMA_PV_DIARIO'!C:C, C47) | G47: =SUMIFS(F$2:F47, C$2:C47, C47) | H47: =IF(B47 > MAX('04_LOG_FIELD_ENTRIES'!$B:$B), "", SUMIFS('04_LOG_FIELD_ENTRIES'!$J:$J, '04_LOG_FIELD_ENTRIES'!$B:$B, B47, '04_LOG_FIELD_ENTRIES'!$D:$D, C47, '04_LOG_FIELD_ENTRIES'!$K:$K, "EV_PRODUCCION")) | I47: =IF(B47 > MAX('04_LOG_FIELD_ENTRIES'!$B:$B), "", SUMIFS(H$2:H47, C$2:C47, C47)) | J47: =IF(B47 > MAX('04_LOG_FIELD_ENTRIES'!$B:$B), "", SUMIFS('04_LOG_FIELD_ENTRIES'!$J:$J, '04_LOG_FIELD_ENTRIES'!$B:$B, B47, '04_LOG_FIELD_ENTRIES'!$D:$D, C47, '04_LOG_FIELD_ENTRIES'!$K:$K, "AC_*")) | K47: =IF(B47 > MAX('04_LOG_FIELD_ENTRIES'!$B:$B), "", SUMIFS(J$2:J47, C$2:C47, C47)) | L47: =IF(K47="", "", I47-K47) | M47: =IF(I47="", "", I47-G47) | N47: =IF(I47="", "", IF(G47>0, I47/G47, 1)) | O47: =IF(I47="", "", IF(K47>0, I47/K47, 1)) | P47: =IF(I47="", "", IF(AND(N47>=0.95, O47>=0.95), "SALUDABLE", IF(N47<0.9, "ALERTA RETRASO", "ALERTA SOBRECOSTO")))
A48: 12 | B48: 46246 | C48: WBS-300 | D48: Red de Agua Potable y Conexiones Domiciliarias | E48: =SUM('01_PRESUPUESTO_CRONOGRAMA_BASE'!G10:G11) | F48: =SUMIFS('02_CRONOGRAMA_PV_DIARIO'!E:E, '02_CRONOGRAMA_PV_DIARIO'!A:A, A48, '02_CRONOGRAMA_PV_DIARIO'!C:C, C48) | G48: =SUMIFS(F$2:F48, C$2:C48, C48) | H48: =IF(B48 > MAX('04_LOG_FIELD_ENTRIES'!$B:$B), "", SUMIFS('04_LOG_FIELD_ENTRIES'!$J:$J, '04_LOG_FIELD_ENTRIES'!$B:$B, B48, '04_LOG_FIELD_ENTRIES'!$D:$D, C48, '04_LOG_FIELD_ENTRIES'!$K:$K, "EV_PRODUCCION")) | I48: =IF(B48 > MAX('04_LOG_FIELD_ENTRIES'!$B:$B), "", SUMIFS(H$2:H48, C$2:C48, C48)) | J48: =IF(B48 > MAX('04_LOG_FIELD_ENTRIES'!$B:$B), "", SUMIFS('04_LOG_FIELD_ENTRIES'!$J:$J, '04_LOG_FIELD_ENTRIES'!$B:$B, B48, '04_LOG_FIELD_ENTRIES'!$D:$D, C48, '04_LOG_FIELD_ENTRIES'!$K:$K, "AC_*")) | K48: =IF(B48 > MAX('04_LOG_FIELD_ENTRIES'!$B:$B), "", SUMIFS(J$2:J48, C$2:C48, C48)) | L48: =IF(K48="", "", I48-K48) | M48: =IF(I48="", "", I48-G48) | N48: =IF(I48="", "", IF(G48>0, I48/G48, 1)) | O48: =IF(I48="", "", IF(K48>0, I48/K48, 1)) | P48: =IF(I48="", "", IF(AND(N48>=0.95, O48>=0.95), "SALUDABLE", IF(N48<0.9, "ALERTA RETRASO", "ALERTA SOBRECOSTO")))
A49: 12 | B49: 46246 | C49: WBS-400 | D49: Pruebas Hidráulicas, Desinfección y Entrega | E49: =SUM('01_PRESUPUESTO_CRONOGRAMA_BASE'!G12:G12) | F49: =SUMIFS('02_CRONOGRAMA_PV_DIARIO'!E:E, '02_CRONOGRAMA_PV_DIARIO'!A:A, A49, '02_CRONOGRAMA_PV_DIARIO'!C:C, C49) | G49: =SUMIFS(F$2:F49, C$2:C49, C49) | H49: =IF(B49 > MAX('04_LOG_FIELD_ENTRIES'!$B:$B), "", SUMIFS('04_LOG_FIELD_ENTRIES'!$J:$J, '04_LOG_FIELD_ENTRIES'!$B:$B, B49, '04_LOG_FIELD_ENTRIES'!$D:$D, C49, '04_LOG_FIELD_ENTRIES'!$K:$K, "EV_PRODUCCION")) | I49: =IF(B49 > MAX('04_LOG_FIELD_ENTRIES'!$B:$B), "", SUMIFS(H$2:H49, C$2:C49, C49)) | J49: =IF(B49 > MAX('04_LOG_FIELD_ENTRIES'!$B:$B), "", SUMIFS('04_LOG_FIELD_ENTRIES'!$J:$J, '04_LOG_FIELD_ENTRIES'!$B:$B, B49, '04_LOG_FIELD_ENTRIES'!$D:$D, C49, '04_LOG_FIELD_ENTRIES'!$K:$K, "AC_*")) | K49: =IF(B49 > MAX('04_LOG_FIELD_ENTRIES'!$B:$B), "", SUMIFS(J$2:J49, C$2:C49, C49)) | L49: =IF(K49="", "", I49-K49) | M49: =IF(I49="", "", I49-G49) | N49: =IF(I49="", "", IF(G49>0, I49/G49, 1)) | O49: =IF(I49="", "", IF(K49>0, I49/K49, 1)) | P49: =IF(I49="", "", IF(AND(N49>=0.95, O49>=0.95), "SALUDABLE", IF(N49<0.9, "ALERTA RETRASO", "ALERTA SOBRECOSTO")))
A50: 13 | B50: 46247 | C50: WBS-100 | D50: Obras Preliminares, Trazo y Movilización | E50: =SUM('01_PRESUPUESTO_CRONOGRAMA_BASE'!G2:G3) | F50: =SUMIFS('02_CRONOGRAMA_PV_DIARIO'!E:E, '02_CRONOGRAMA_PV_DIARIO'!A:A, A50, '02_CRONOGRAMA_PV_DIARIO'!C:C, C50) | G50: =SUMIFS(F$2:F50, C$2:C50, C50) | H50: =IF(B50 > MAX('04_LOG_FIELD_ENTRIES'!$B:$B), "", SUMIFS('04_LOG_FIELD_ENTRIES'!$J:$J, '04_LOG_FIELD_ENTRIES'!$B:$B, B50, '04_LOG_FIELD_ENTRIES'!$D:$D, C50, '04_LOG_FIELD_ENTRIES'!$K:$K, "EV_PRODUCCION")) | I50: =IF(B50 > MAX('04_LOG_FIELD_ENTRIES'!$B:$B), "", SUMIFS(H$2:H50, C$2:C50, C50)) | J50: =IF(B50 > MAX('04_LOG_FIELD_ENTRIES'!$B:$B), "", SUMIFS('04_LOG_FIELD_ENTRIES'!$J:$J, '04_LOG_FIELD_ENTRIES'!$B:$B, B50, '04_LOG_FIELD_ENTRIES'!$D:$D, C50, '04_LOG_FIELD_ENTRIES'!$K:$K, "AC_*")) | K50: =IF(B50 > MAX('04_LOG_FIELD_ENTRIES'!$B:$B), "", SUMIFS(J$2:J50, C$2:C50, C50)) | L50: =IF(K50="", "", I50-K50) | M50: =IF(I50="", "", I50-G50) | N50: =IF(I50="", "", IF(G50>0, I50/G50, 1)) | O50: =IF(I50="", "", IF(K50>0, I50/K50, 1)) | P50: =IF(I50="", "", IF(AND(N50>=0.95, O50>=0.95), "SALUDABLE", IF(N50<0.9, "ALERTA RETRASO", "ALERTA SOBRECOSTO")))
A51: 13 | B51: 46247 | C51: WBS-200 | D51: Red de Alcantarillado, Zanjas y Buzones | E51: =SUM('01_PRESUPUESTO_CRONOGRAMA_BASE'!G4:G9) | F51: =SUMIFS('02_CRONOGRAMA_PV_DIARIO'!E:E, '02_CRONOGRAMA_PV_DIARIO'!A:A, A51, '02_CRONOGRAMA_PV_DIARIO'!C:C, C51) | G51: =SUMIFS(F$2:F51, C$2:C51, C51) | H51: =IF(B51 > MAX('04_LOG_FIELD_ENTRIES'!$B:$B), "", SUMIFS('04_LOG_FIELD_ENTRIES'!$J:$J, '04_LOG_FIELD_ENTRIES'!$B:$B, B51, '04_LOG_FIELD_ENTRIES'!$D:$D, C51, '04_LOG_FIELD_ENTRIES'!$K:$K, "EV_PRODUCCION")) | I51: =IF(B51 > MAX('04_LOG_FIELD_ENTRIES'!$B:$B), "", SUMIFS(H$2:H51, C$2:C51, C51)) | J51: =IF(B51 > MAX('04_LOG_FIELD_ENTRIES'!$B:$B), "", SUMIFS('04_LOG_FIELD_ENTRIES'!$J:$J, '04_LOG_FIELD_ENTRIES'!$B:$B, B51, '04_LOG_FIELD_ENTRIES'!$D:$D, C51, '04_LOG_FIELD_ENTRIES'!$K:$K, "AC_*")) | K51: =IF(B51 > MAX('04_LOG_FIELD_ENTRIES'!$B:$B), "", SUMIFS(J$2:J51, C$2:C51, C51)) | L51: =IF(K51="", "", I51-K51) | M51: =IF(I51="", "", I51-G51) | N51: =IF(I51="", "", IF(G51>0, I51/G51, 1)) | O51: =IF(I51="", "", IF(K51>0, I51/K51, 1)) | P51: =IF(I51="", "", IF(AND(N51>=0.95, O51>=0.95), "SALUDABLE", IF(N51<0.9, "ALERTA RETRASO", "ALERTA SOBRECOSTO")))
A52: 13 | B52: 46247 | C52: WBS-300 | D52: Red de Agua Potable y Conexiones Domiciliarias | E52: =SUM('01_PRESUPUESTO_CRONOGRAMA_BASE'!G10:G11) | F52: =SUMIFS('02_CRONOGRAMA_PV_DIARIO'!E:E, '02_CRONOGRAMA_PV_DIARIO'!A:A, A52, '02_CRONOGRAMA_PV_DIARIO'!C:C, C52) | G52: =SUMIFS(F$2:F52, C$2:C52, C52) | H52: =IF(B52 > MAX('04_LOG_FIELD_ENTRIES'!$B:$B), "", SUMIFS('04_LOG_FIELD_ENTRIES'!$J:$J, '04_LOG_FIELD_ENTRIES'!$B:$B, B52, '04_LOG_FIELD_ENTRIES'!$D:$D, C52, '04_LOG_FIELD_ENTRIES'!$K:$K, "EV_PRODUCCION")) | I52: =IF(B52 > MAX('04_LOG_FIELD_ENTRIES'!$B:$B), "", SUMIFS(H$2:H52, C$2:C52, C52)) | J52: =IF(B52 > MAX('04_LOG_FIELD_ENTRIES'!$B:$B), "", SUMIFS('04_LOG_FIELD_ENTRIES'!$J:$J, '04_LOG_FIELD_ENTRIES'!$B:$B, B52, '04_LOG_FIELD_ENTRIES'!$D:$D, C52, '04_LOG_FIELD_ENTRIES'!$K:$K, "AC_*")) | K52: =IF(B52 > MAX('04_LOG_FIELD_ENTRIES'!$B:$B), "", SUMIFS(J$2:J52, C$2:C52, C52)) | L52: =IF(K52="", "", I52-K52) | M52: =IF(I52="", "", I52-G52) | N52: =IF(I52="", "", IF(G52>0, I52/G52, 1)) | O52: =IF(I52="", "", IF(K52>0, I52/K52, 1)) | P52: =IF(I52="", "", IF(AND(N52>=0.95, O52>=0.95), "SALUDABLE", IF(N52<0.9, "ALERTA RETRASO", "ALERTA SOBRECOSTO")))
A53: 13 | B53: 46247 | C53: WBS-400 | D53: Pruebas Hidráulicas, Desinfección y Entrega | E53: =SUM('01_PRESUPUESTO_CRONOGRAMA_BASE'!G12:G12) | F53: =SUMIFS('02_CRONOGRAMA_PV_DIARIO'!E:E, '02_CRONOGRAMA_PV_DIARIO'!A:A, A53, '02_CRONOGRAMA_PV_DIARIO'!C:C, C53) | G53: =SUMIFS(F$2:F53, C$2:C53, C53) | H53: =IF(B53 > MAX('04_LOG_FIELD_ENTRIES'!$B:$B), "", SUMIFS('04_LOG_FIELD_ENTRIES'!$J:$J, '04_LOG_FIELD_ENTRIES'!$B:$B, B53, '04_LOG_FIELD_ENTRIES'!$D:$D, C53, '04_LOG_FIELD_ENTRIES'!$K:$K, "EV_PRODUCCION")) | I53: =IF(B53 > MAX('04_LOG_FIELD_ENTRIES'!$B:$B), "", SUMIFS(H$2:H53, C$2:C53, C53)) | J53: =IF(B53 > MAX('04_LOG_FIELD_ENTRIES'!$B:$B), "", SUMIFS('04_LOG_FIELD_ENTRIES'!$J:$J, '04_LOG_FIELD_ENTRIES'!$B:$B, B53, '04_LOG_FIELD_ENTRIES'!$D:$D, C53, '04_LOG_FIELD_ENTRIES'!$K:$K, "AC_*")) | K53: =IF(B53 > MAX('04_LOG_FIELD_ENTRIES'!$B:$B), "", SUMIFS(J$2:J53, C$2:C53, C53)) | L53: =IF(K53="", "", I53-K53) | M53: =IF(I53="", "", I53-G53) | N53: =IF(I53="", "", IF(G53>0, I53/G53, 1)) | O53: =IF(I53="", "", IF(K53>0, I53/K53, 1)) | P53: =IF(I53="", "", IF(AND(N53>=0.95, O53>=0.95), "SALUDABLE", IF(N53<0.9, "ALERTA RETRASO", "ALERTA SOBRECOSTO")))
A54: 14 | B54: 46248 | C54: WBS-100 | D54: Obras Preliminares, Trazo y Movilización | E54: =SUM('01_PRESUPUESTO_CRONOGRAMA_BASE'!G2:G3) | F54: =SUMIFS('02_CRONOGRAMA_PV_DIARIO'!E:E, '02_CRONOGRAMA_PV_DIARIO'!A:A, A54, '02_CRONOGRAMA_PV_DIARIO'!C:C, C54) | G54: =SUMIFS(F$2:F54, C$2:C54, C54) | H54: =IF(B54 > MAX('04_LOG_FIELD_ENTRIES'!$B:$B), "", SUMIFS('04_LOG_FIELD_ENTRIES'!$J:$J, '04_LOG_FIELD_ENTRIES'!$B:$B, B54, '04_LOG_FIELD_ENTRIES'!$D:$D, C54, '04_LOG_FIELD_ENTRIES'!$K:$K, "EV_PRODUCCION")) | I54: =IF(B54 > MAX('04_LOG_FIELD_ENTRIES'!$B:$B), "", SUMIFS(H$2:H54, C$2:C54, C54)) | J54: =IF(B54 > MAX('04_LOG_FIELD_ENTRIES'!$B:$B), "", SUMIFS('04_LOG_FIELD_ENTRIES'!$J:$J, '04_LOG_FIELD_ENTRIES'!$B:$B, B54, '04_LOG_FIELD_ENTRIES'!$D:$D, C54, '04_LOG_FIELD_ENTRIES'!$K:$K, "AC_*")) | K54: =IF(B54 > MAX('04_LOG_FIELD_ENTRIES'!$B:$B), "", SUMIFS(J$2:J54, C$2:C54, C54)) | L54: =IF(K54="", "", I54-K54) | M54: =IF(I54="", "", I54-G54) | N54: =IF(I54="", "", IF(G54>0, I54/G54, 1)) | O54: =IF(I54="", "", IF(K54>0, I54/K54, 1)) | P54: =IF(I54="", "", IF(AND(N54>=0.95, O54>=0.95), "SALUDABLE", IF(N54<0.9, "ALERTA RETRASO", "ALERTA SOBRECOSTO")))
A55: 14 | B55: 46248 | C55: WBS-200 | D55: Red de Alcantarillado, Zanjas y Buzones | E55: =SUM('01_PRESUPUESTO_CRONOGRAMA_BASE'!G4:G9) | F55: =SUMIFS('02_CRONOGRAMA_PV_DIARIO'!E:E, '02_CRONOGRAMA_PV_DIARIO'!A:A, A55, '02_CRONOGRAMA_PV_DIARIO'!C:C, C55) | G55: =SUMIFS(F$2:F55, C$2:C55, C55) | H55: =IF(B55 > MAX('04_LOG_FIELD_ENTRIES'!$B:$B), "", SUMIFS('04_LOG_FIELD_ENTRIES'!$J:$J, '04_LOG_FIELD_ENTRIES'!$B:$B, B55, '04_LOG_FIELD_ENTRIES'!$D:$D, C55, '04_LOG_FIELD_ENTRIES'!$K:$K, "EV_PRODUCCION")) | I55: =IF(B55 > MAX('04_LOG_FIELD_ENTRIES'!$B:$B), "", SUMIFS(H$2:H55, C$2:C55, C55)) | J55: =IF(B55 > MAX('04_LOG_FIELD_ENTRIES'!$B:$B), "", SUMIFS('04_LOG_FIELD_ENTRIES'!$J:$J, '04_LOG_FIELD_ENTRIES'!$B:$B, B55, '04_LOG_FIELD_ENTRIES'!$D:$D, C55, '04_LOG_FIELD_ENTRIES'!$K:$K, "AC_*")) | K55: =IF(B55 > MAX('04_LOG_FIELD_ENTRIES'!$B:$B), "", SUMIFS(J$2:J55, C$2:C55, C55)) | L55: =IF(K55="", "", I55-K55) | M55: =IF(I55="", "", I55-G55) | N55: =IF(I55="", "", IF(G55>0, I55/G55, 1)) | O55: =IF(I55="", "", IF(K55>0, I55/K55, 1)) | P55: =IF(I55="", "", IF(AND(N55>=0.95, O55>=0.95), "SALUDABLE", IF(N55<0.9, "ALERTA RETRASO", "ALERTA SOBRECOSTO")))
A56: 14 | B56: 46248 | C56: WBS-300 | D56: Red de Agua Potable y Conexiones Domiciliarias | E56: =SUM('01_PRESUPUESTO_CRONOGRAMA_BASE'!G10:G11) | F56: =SUMIFS('02_CRONOGRAMA_PV_DIARIO'!E:E, '02_CRONOGRAMA_PV_DIARIO'!A:A, A56, '02_CRONOGRAMA_PV_DIARIO'!C:C, C56) | G56: =SUMIFS(F$2:F56, C$2:C56, C56) | H56: =IF(B56 > MAX('04_LOG_FIELD_ENTRIES'!$B:$B), "", SUMIFS('04_LOG_FIELD_ENTRIES'!$J:$J, '04_LOG_FIELD_ENTRIES'!$B:$B, B56, '04_LOG_FIELD_ENTRIES'!$D:$D, C56, '04_LOG_FIELD_ENTRIES'!$K:$K, "EV_PRODUCCION")) | I56: =IF(B56 > MAX('04_LOG_FIELD_ENTRIES'!$B:$B), "", SUMIFS(H$2:H56, C$2:C56, C56)) | J56: =IF(B56 > MAX('04_LOG_FIELD_ENTRIES'!$B:$B), "", SUMIFS('04_LOG_FIELD_ENTRIES'!$J:$J, '04_LOG_FIELD_ENTRIES'!$B:$B, B56, '04_LOG_FIELD_ENTRIES'!$D:$D, C56, '04_LOG_FIELD_ENTRIES'!$K:$K, "AC_*")) | K56: =IF(B56 > MAX('04_LOG_FIELD_ENTRIES'!$B:$B), "", SUMIFS(J$2:J56, C$2:C56, C56)) | L56: =IF(K56="", "", I56-K56) | M56: =IF(I56="", "", I56-G56) | N56: =IF(I56="", "", IF(G56>0, I56/G56, 1)) | O56: =IF(I56="", "", IF(K56>0, I56/K56, 1)) | P56: =IF(I56="", "", IF(AND(N56>=0.95, O56>=0.95), "SALUDABLE", IF(N56<0.9, "ALERTA RETRASO", "ALERTA SOBRECOSTO")))
A57: 14 | B57: 46248 | C57: WBS-400 | D57: Pruebas Hidráulicas, Desinfección y Entrega | E57: =SUM('01_PRESUPUESTO_CRONOGRAMA_BASE'!G12:G12) | F57: =SUMIFS('02_CRONOGRAMA_PV_DIARIO'!E:E, '02_CRONOGRAMA_PV_DIARIO'!A:A, A57, '02_CRONOGRAMA_PV_DIARIO'!C:C, C57) | G57: =SUMIFS(F$2:F57, C$2:C57, C57) | H57: =IF(B57 > MAX('04_LOG_FIELD_ENTRIES'!$B:$B), "", SUMIFS('04_LOG_FIELD_ENTRIES'!$J:$J, '04_LOG_FIELD_ENTRIES'!$B:$B, B57, '04_LOG_FIELD_ENTRIES'!$D:$D, C57, '04_LOG_FIELD_ENTRIES'!$K:$K, "EV_PRODUCCION")) | I57: =IF(B57 > MAX('04_LOG_FIELD_ENTRIES'!$B:$B), "", SUMIFS(H$2:H57, C$2:C57, C57)) | J57: =IF(B57 > MAX('04_LOG_FIELD_ENTRIES'!$B:$B), "", SUMIFS('04_LOG_FIELD_ENTRIES'!$J:$J, '04_LOG_FIELD_ENTRIES'!$B:$B, B57, '04_LOG_FIELD_ENTRIES'!$D:$D, C57, '04_LOG_FIELD_ENTRIES'!$K:$K, "AC_*")) | K57: =IF(B57 > MAX('04_LOG_FIELD_ENTRIES'!$B:$B), "", SUMIFS(J$2:J57, C$2:C57, C57)) | L57: =IF(K57="", "", I57-K57) | M57: =IF(I57="", "", I57-G57) | N57: =IF(I57="", "", IF(G57>0, I57/G57, 1)) | O57: =IF(I57="", "", IF(K57>0, I57/K57, 1)) | P57: =IF(I57="", "", IF(AND(N57>=0.95, O57>=0.95), "SALUDABLE", IF(N57<0.9, "ALERTA RETRASO", "ALERTA SOBRECOSTO")))
A58: 15 | B58: 46249 | C58: WBS-100 | D58: Obras Preliminares, Trazo y Movilización | E58: =SUM('01_PRESUPUESTO_CRONOGRAMA_BASE'!G2:G3) | F58: =SUMIFS('02_CRONOGRAMA_PV_DIARIO'!E:E, '02_CRONOGRAMA_PV_DIARIO'!A:A, A58, '02_CRONOGRAMA_PV_DIARIO'!C:C, C58) | G58: =SUMIFS(F$2:F58, C$2:C58, C58) | H58: =IF(B58 > MAX('04_LOG_FIELD_ENTRIES'!$B:$B), "", SUMIFS('04_LOG_FIELD_ENTRIES'!$J:$J, '04_LOG_FIELD_ENTRIES'!$B:$B, B58, '04_LOG_FIELD_ENTRIES'!$D:$D, C58, '04_LOG_FIELD_ENTRIES'!$K:$K, "EV_PRODUCCION")) | I58: =IF(B58 > MAX('04_LOG_FIELD_ENTRIES'!$B:$B), "", SUMIFS(H$2:H58, C$2:C58, C58)) | J58: =IF(B58 > MAX('04_LOG_FIELD_ENTRIES'!$B:$B), "", SUMIFS('04_LOG_FIELD_ENTRIES'!$J:$J, '04_LOG_FIELD_ENTRIES'!$B:$B, B58, '04_LOG_FIELD_ENTRIES'!$D:$D, C58, '04_LOG_FIELD_ENTRIES'!$K:$K, "AC_*")) | K58: =IF(B58 > MAX('04_LOG_FIELD_ENTRIES'!$B:$B), "", SUMIFS(J$2:J58, C$2:C58, C58)) | L58: =IF(K58="", "", I58-K58) | M58: =IF(I58="", "", I58-G58) | N58: =IF(I58="", "", IF(G58>0, I58/G58, 1)) | O58: =IF(I58="", "", IF(K58>0, I58/K58, 1)) | P58: =IF(I58="", "", IF(AND(N58>=0.95, O58>=0.95), "SALUDABLE", IF(N58<0.9, "ALERTA RETRASO", "ALERTA SOBRECOSTO")))
A59: 15 | B59: 46249 | C59: WBS-200 | D59: Red de Alcantarillado, Zanjas y Buzones | E59: =SUM('01_PRESUPUESTO_CRONOGRAMA_BASE'!G4:G9) | F59: =SUMIFS('02_CRONOGRAMA_PV_DIARIO'!E:E, '02_CRONOGRAMA_PV_DIARIO'!A:A, A59, '02_CRONOGRAMA_PV_DIARIO'!C:C, C59) | G59: =SUMIFS(F$2:F59, C$2:C59, C59) | H59: =IF(B59 > MAX('04_LOG_FIELD_ENTRIES'!$B:$B), "", SUMIFS('04_LOG_FIELD_ENTRIES'!$J:$J, '04_LOG_FIELD_ENTRIES'!$B:$B, B59, '04_LOG_FIELD_ENTRIES'!$D:$D, C59, '04_LOG_FIELD_ENTRIES'!$K:$K, "EV_PRODUCCION")) | I59: =IF(B59 > MAX('04_LOG_FIELD_ENTRIES'!$B:$B), "", SUMIFS(H$2:H59, C$2:C59, C59)) | J59: =IF(B59 > MAX('04_LOG_FIELD_ENTRIES'!$B:$B), "", SUMIFS('04_LOG_FIELD_ENTRIES'!$J:$J, '04_LOG_FIELD_ENTRIES'!$B:$B, B59, '04_LOG_FIELD_ENTRIES'!$D:$D, C59, '04_LOG_FIELD_ENTRIES'!$K:$K, "AC_*")) | K59: =IF(B59 > MAX('04_LOG_FIELD_ENTRIES'!$B:$B), "", SUMIFS(J$2:J59, C$2:C59, C59)) | L59: =IF(K59="", "", I59-K59) | M59: =IF(I59="", "", I59-G59) | N59: =IF(I59="", "", IF(G59>0, I59/G59, 1)) | O59: =IF(I59="", "", IF(K59>0, I59/K59, 1)) | P59: =IF(I59="", "", IF(AND(N59>=0.95, O59>=0.95), "SALUDABLE", IF(N59<0.9, "ALERTA RETRASO", "ALERTA SOBRECOSTO")))
A60: 15 | B60: 46249 | C60: WBS-300 | D60: Red de Agua Potable y Conexiones Domiciliarias | E60: =SUM('01_PRESUPUESTO_CRONOGRAMA_BASE'!G10:G11) | F60: =SUMIFS('02_CRONOGRAMA_PV_DIARIO'!E:E, '02_CRONOGRAMA_PV_DIARIO'!A:A, A60, '02_CRONOGRAMA_PV_DIARIO'!C:C, C60) | G60: =SUMIFS(F$2:F60, C$2:C60, C60) | H60: =IF(B60 > MAX('04_LOG_FIELD_ENTRIES'!$B:$B), "", SUMIFS('04_LOG_FIELD_ENTRIES'!$J:$J, '04_LOG_FIELD_ENTRIES'!$B:$B, B60, '04_LOG_FIELD_ENTRIES'!$D:$D, C60, '04_LOG_FIELD_ENTRIES'!$K:$K, "EV_PRODUCCION")) | I60: =IF(B60 > MAX('04_LOG_FIELD_ENTRIES'!$B:$B), "", SUMIFS(H$2:H60, C$2:C60, C60)) | J60: =IF(B60 > MAX('04_LOG_FIELD_ENTRIES'!$B:$B), "", SUMIFS('04_LOG_FIELD_ENTRIES'!$J:$J, '04_LOG_FIELD_ENTRIES'!$B:$B, B60, '04_LOG_FIELD_ENTRIES'!$D:$D, C60, '04_LOG_FIELD_ENTRIES'!$K:$K, "AC_*")) | K60: =IF(B60 > MAX('04_LOG_FIELD_ENTRIES'!$B:$B), "", SUMIFS(J$2:J60, C$2:C60, C60)) | L60: =IF(K60="", "", I60-K60) | M60: =IF(I60="", "", I60-G60) | N60: =IF(I60="", "", IF(G60>0, I60/G60, 1)) | O60: =IF(I60="", "", IF(K60>0, I60/K60, 1)) | P60: =IF(I60="", "", IF(AND(N60>=0.95, O60>=0.95), "SALUDABLE", IF(N60<0.9, "ALERTA RETRASO", "ALERTA SOBRECOSTO")))
A61: 15 | B61: 46249 | C61: WBS-400 | D61: Pruebas Hidráulicas, Desinfección y Entrega | E61: =SUM('01_PRESUPUESTO_CRONOGRAMA_BASE'!G12:G12) | F61: =SUMIFS('02_CRONOGRAMA_PV_DIARIO'!E:E, '02_CRONOGRAMA_PV_DIARIO'!A:A, A61, '02_CRONOGRAMA_PV_DIARIO'!C:C, C61) | G61: =SUMIFS(F$2:F61, C$2:C61, C61) | H61: =IF(B61 > MAX('04_LOG_FIELD_ENTRIES'!$B:$B), "", SUMIFS('04_LOG_FIELD_ENTRIES'!$J:$J, '04_LOG_FIELD_ENTRIES'!$B:$B, B61, '04_LOG_FIELD_ENTRIES'!$D:$D, C61, '04_LOG_FIELD_ENTRIES'!$K:$K, "EV_PRODUCCION")) | I61: =IF(B61 > MAX('04_LOG_FIELD_ENTRIES'!$B:$B), "", SUMIFS(H$2:H61, C$2:C61, C61)) | J61: =IF(B61 > MAX('04_LOG_FIELD_ENTRIES'!$B:$B), "", SUMIFS('04_LOG_FIELD_ENTRIES'!$J:$J, '04_LOG_FIELD_ENTRIES'!$B:$B, B61, '04_LOG_FIELD_ENTRIES'!$D:$D, C61, '04_LOG_FIELD_ENTRIES'!$K:$K, "AC_*")) | K61: =IF(B61 > MAX('04_LOG_FIELD_ENTRIES'!$B:$B), "", SUMIFS(J$2:J61, C$2:C61, C61)) | L61: =IF(K61="", "", I61-K61) | M61: =IF(I61="", "", I61-G61) | N61: =IF(I61="", "", IF(G61>0, I61/G61, 1)) | O61: =IF(I61="", "", IF(K61>0, I61/K61, 1)) | P61: =IF(I61="", "", IF(AND(N61>=0.95, O61>=0.95), "SALUDABLE", IF(N61<0.9, "ALERTA RETRASO", "ALERTA SOBRECOSTO")))
A62: 16 | B62: 46250 | C62: WBS-100 | D62: Obras Preliminares, Trazo y Movilización | E62: =SUM('01_PRESUPUESTO_CRONOGRAMA_BASE'!G2:G3) | F62: =SUMIFS('02_CRONOGRAMA_PV_DIARIO'!E:E, '02_CRONOGRAMA_PV_DIARIO'!A:A, A62, '02_CRONOGRAMA_PV_DIARIO'!C:C, C62) | G62: =SUMIFS(F$2:F62, C$2:C62, C62) | H62: =IF(B62 > MAX('04_LOG_FIELD_ENTRIES'!$B:$B), "", SUMIFS('04_LOG_FIELD_ENTRIES'!$J:$J, '04_LOG_FIELD_ENTRIES'!$B:$B, B62, '04_LOG_FIELD_ENTRIES'!$D:$D, C62, '04_LOG_FIELD_ENTRIES'!$K:$K, "EV_PRODUCCION")) | I62: =IF(B62 > MAX('04_LOG_FIELD_ENTRIES'!$B:$B), "", SUMIFS(H$2:H62, C$2:C62, C62)) | J62: =IF(B62 > MAX('04_LOG_FIELD_ENTRIES'!$B:$B), "", SUMIFS('04_LOG_FIELD_ENTRIES'!$J:$J, '04_LOG_FIELD_ENTRIES'!$B:$B, B62, '04_LOG_FIELD_ENTRIES'!$D:$D, C62, '04_LOG_FIELD_ENTRIES'!$K:$K, "AC_*")) | K62: =IF(B62 > MAX('04_LOG_FIELD_ENTRIES'!$B:$B), "", SUMIFS(J$2:J62, C$2:C62, C62)) | L62: =IF(K62="", "", I62-K62) | M62: =IF(I62="", "", I62-G62) | N62: =IF(I62="", "", IF(G62>0, I62/G62, 1)) | O62: =IF(I62="", "", IF(K62>0, I62/K62, 1)) | P62: =IF(I62="", "", IF(AND(N62>=0.95, O62>=0.95), "SALUDABLE", IF(N62<0.9, "ALERTA RETRASO", "ALERTA SOBRECOSTO")))
A63: 16 | B63: 46250 | C63: WBS-200 | D63: Red de Alcantarillado, Zanjas y Buzones | E63: =SUM('01_PRESUPUESTO_CRONOGRAMA_BASE'!G4:G9) | F63: =SUMIFS('02_CRONOGRAMA_PV_DIARIO'!E:E, '02_CRONOGRAMA_PV_DIARIO'!A:A, A63, '02_CRONOGRAMA_PV_DIARIO'!C:C, C63) | G63: =SUMIFS(F$2:F63, C$2:C63, C63) | H63: =IF(B63 > MAX('04_LOG_FIELD_ENTRIES'!$B:$B), "", SUMIFS('04_LOG_FIELD_ENTRIES'!$J:$J, '04_LOG_FIELD_ENTRIES'!$B:$B, B63, '04_LOG_FIELD_ENTRIES'!$D:$D, C63, '04_LOG_FIELD_ENTRIES'!$K:$K, "EV_PRODUCCION")) | I63: =IF(B63 > MAX('04_LOG_FIELD_ENTRIES'!$B:$B), "", SUMIFS(H$2:H63, C$2:C63, C63)) | J63: =IF(B63 > MAX('04_LOG_FIELD_ENTRIES'!$B:$B), "", SUMIFS('04_LOG_FIELD_ENTRIES'!$J:$J, '04_LOG_FIELD_ENTRIES'!$B:$B, B63, '04_LOG_FIELD_ENTRIES'!$D:$D, C63, '04_LOG_FIELD_ENTRIES'!$K:$K, "AC_*")) | K63: =IF(B63 > MAX('04_LOG_FIELD_ENTRIES'!$B:$B), "", SUMIFS(J$2:J63, C$2:C63, C63)) | L63: =IF(K63="", "", I63-K63) | M63: =IF(I63="", "", I63-G63) | N63: =IF(I63="", "", IF(G63>0, I63/G63, 1)) | O63: =IF(I63="", "", IF(K63>0, I63/K63, 1)) | P63: =IF(I63="", "", IF(AND(N63>=0.95, O63>=0.95), "SALUDABLE", IF(N63<0.9, "ALERTA RETRASO", "ALERTA SOBRECOSTO")))
A64: 16 | B64: 46250 | C64: WBS-300 | D64: Red de Agua Potable y Conexiones Domiciliarias | E64: =SUM('01_PRESUPUESTO_CRONOGRAMA_BASE'!G10:G11) | F64: =SUMIFS('02_CRONOGRAMA_PV_DIARIO'!E:E, '02_CRONOGRAMA_PV_DIARIO'!A:A, A64, '02_CRONOGRAMA_PV_DIARIO'!C:C, C64) | G64: =SUMIFS(F$2:F64, C$2:C64, C64) | H64: =IF(B64 > MAX('04_LOG_FIELD_ENTRIES'!$B:$B), "", SUMIFS('04_LOG_FIELD_ENTRIES'!$J:$J, '04_LOG_FIELD_ENTRIES'!$B:$B, B64, '04_LOG_FIELD_ENTRIES'!$D:$D, C64, '04_LOG_FIELD_ENTRIES'!$K:$K, "EV_PRODUCCION")) | I64: =IF(B64 > MAX('04_LOG_FIELD_ENTRIES'!$B:$B), "", SUMIFS(H$2:H64, C$2:C64, C64)) | J64: =IF(B64 > MAX('04_LOG_FIELD_ENTRIES'!$B:$B), "", SUMIFS('04_LOG_FIELD_ENTRIES'!$J:$J, '04_LOG_FIELD_ENTRIES'!$B:$B, B64, '04_LOG_FIELD_ENTRIES'!$D:$D, C64, '04_LOG_FIELD_ENTRIES'!$K:$K, "AC_*")) | K64: =IF(B64 > MAX('04_LOG_FIELD_ENTRIES'!$B:$B), "", SUMIFS(J$2:J64, C$2:C64, C64)) | L64: =IF(K64="", "", I64-K64) | M64: =IF(I64="", "", I64-G64) | N64: =IF(I64="", "", IF(G64>0, I64/G64, 1)) | O64: =IF(I64="", "", IF(K64>0, I64/K64, 1)) | P64: =IF(I64="", "", IF(AND(N64>=0.95, O64>=0.95), "SALUDABLE", IF(N64<0.9, "ALERTA RETRASO", "ALERTA SOBRECOSTO")))
A65: 16 | B65: 46250 | C65: WBS-400 | D65: Pruebas Hidráulicas, Desinfección y Entrega | E65: =SUM('01_PRESUPUESTO_CRONOGRAMA_BASE'!G12:G12) | F65: =SUMIFS('02_CRONOGRAMA_PV_DIARIO'!E:E, '02_CRONOGRAMA_PV_DIARIO'!A:A, A65, '02_CRONOGRAMA_PV_DIARIO'!C:C, C65) | G65: =SUMIFS(F$2:F65, C$2:C65, C65) | H65: =IF(B65 > MAX('04_LOG_FIELD_ENTRIES'!$B:$B), "", SUMIFS('04_LOG_FIELD_ENTRIES'!$J:$J, '04_LOG_FIELD_ENTRIES'!$B:$B, B65, '04_LOG_FIELD_ENTRIES'!$D:$D, C65, '04_LOG_FIELD_ENTRIES'!$K:$K, "EV_PRODUCCION")) | I65: =IF(B65 > MAX('04_LOG_FIELD_ENTRIES'!$B:$B), "", SUMIFS(H$2:H65, C$2:C65, C65)) | J65: =IF(B65 > MAX('04_LOG_FIELD_ENTRIES'!$B:$B), "", SUMIFS('04_LOG_FIELD_ENTRIES'!$J:$J, '04_LOG_FIELD_ENTRIES'!$B:$B, B65, '04_LOG_FIELD_ENTRIES'!$D:$D, C65, '04_LOG_FIELD_ENTRIES'!$K:$K, "AC_*")) | K65: =IF(B65 > MAX('04_LOG_FIELD_ENTRIES'!$B:$B), "", SUMIFS(J$2:J65, C$2:C65, C65)) | L65: =IF(K65="", "", I65-K65) | M65: =IF(I65="", "", I65-G65) | N65: =IF(I65="", "", IF(G65>0, I65/G65, 1)) | O65: =IF(I65="", "", IF(K65>0, I65/K65, 1)) | P65: =IF(I65="", "", IF(AND(N65>=0.95, O65>=0.95), "SALUDABLE", IF(N65<0.9, "ALERTA RETRASO", "ALERTA SOBRECOSTO")))
A66: 17 | B66: 46251 | C66: WBS-100 | D66: Obras Preliminares, Trazo y Movilización | E66: =SUM('01_PRESUPUESTO_CRONOGRAMA_BASE'!G2:G3) | F66: =SUMIFS('02_CRONOGRAMA_PV_DIARIO'!E:E, '02_CRONOGRAMA_PV_DIARIO'!A:A, A66, '02_CRONOGRAMA_PV_DIARIO'!C:C, C66) | G66: =SUMIFS(F$2:F66, C$2:C66, C66) | H66: =IF(B66 > MAX('04_LOG_FIELD_ENTRIES'!$B:$B), "", SUMIFS('04_LOG_FIELD_ENTRIES'!$J:$J, '04_LOG_FIELD_ENTRIES'!$B:$B, B66, '04_LOG_FIELD_ENTRIES'!$D:$D, C66, '04_LOG_FIELD_ENTRIES'!$K:$K, "EV_PRODUCCION")) | I66: =IF(B66 > MAX('04_LOG_FIELD_ENTRIES'!$B:$B), "", SUMIFS(H$2:H66, C$2:C66, C66)) | J66: =IF(B66 > MAX('04_LOG_FIELD_ENTRIES'!$B:$B), "", SUMIFS('04_LOG_FIELD_ENTRIES'!$J:$J, '04_LOG_FIELD_ENTRIES'!$B:$B, B66, '04_LOG_FIELD_ENTRIES'!$D:$D, C66, '04_LOG_FIELD_ENTRIES'!$K:$K, "AC_*")) | K66: =IF(B66 > MAX('04_LOG_FIELD_ENTRIES'!$B:$B), "", SUMIFS(J$2:J66, C$2:C66, C66)) | L66: =IF(K66="", "", I66-K66) | M66: =IF(I66="", "", I66-G66) | N66: =IF(I66="", "", IF(G66>0, I66/G66, 1)) | O66: =IF(I66="", "", IF(K66>0, I66/K66, 1)) | P66: =IF(I66="", "", IF(AND(N66>=0.95, O66>=0.95), "SALUDABLE", IF(N66<0.9, "ALERTA RETRASO", "ALERTA SOBRECOSTO")))
A67: 17 | B67: 46251 | C67: WBS-200 | D67: Red de Alcantarillado, Zanjas y Buzones | E67: =SUM('01_PRESUPUESTO_CRONOGRAMA_BASE'!G4:G9) | F67: =SUMIFS('02_CRONOGRAMA_PV_DIARIO'!E:E, '02_CRONOGRAMA_PV_DIARIO'!A:A, A67, '02_CRONOGRAMA_PV_DIARIO'!C:C, C67) | G67: =SUMIFS(F$2:F67, C$2:C67, C67) | H67: =IF(B67 > MAX('04_LOG_FIELD_ENTRIES'!$B:$B), "", SUMIFS('04_LOG_FIELD_ENTRIES'!$J:$J, '04_LOG_FIELD_ENTRIES'!$B:$B, B67, '04_LOG_FIELD_ENTRIES'!$D:$D, C67, '04_LOG_FIELD_ENTRIES'!$K:$K, "EV_PRODUCCION")) | I67: =IF(B67 > MAX('04_LOG_FIELD_ENTRIES'!$B:$B), "", SUMIFS(H$2:H67, C$2:C67, C67)) | J67: =IF(B67 > MAX('04_LOG_FIELD_ENTRIES'!$B:$B), "", SUMIFS('04_LOG_FIELD_ENTRIES'!$J:$J, '04_LOG_FIELD_ENTRIES'!$B:$B, B67, '04_LOG_FIELD_ENTRIES'!$D:$D, C67, '04_LOG_FIELD_ENTRIES'!$K:$K, "AC_*")) | K67: =IF(B67 > MAX('04_LOG_FIELD_ENTRIES'!$B:$B), "", SUMIFS(J$2:J67, C$2:C67, C67)) | L67: =IF(K67="", "", I67-K67) | M67: =IF(I67="", "", I67-G67) | N67: =IF(I67="", "", IF(G67>0, I67/G67, 1)) | O67: =IF(I67="", "", IF(K67>0, I67/K67, 1)) | P67: =IF(I67="", "", IF(AND(N67>=0.95, O67>=0.95), "SALUDABLE", IF(N67<0.9, "ALERTA RETRASO", "ALERTA SOBRECOSTO")))
A68: 17 | B68: 46251 | C68: WBS-300 | D68: Red de Agua Potable y Conexiones Domiciliarias | E68: =SUM('01_PRESUPUESTO_CRONOGRAMA_BASE'!G10:G11) | F68: =SUMIFS('02_CRONOGRAMA_PV_DIARIO'!E:E, '02_CRONOGRAMA_PV_DIARIO'!A:A, A68, '02_CRONOGRAMA_PV_DIARIO'!C:C, C68) | G68: =SUMIFS(F$2:F68, C$2:C68, C68) | H68: =IF(B68 > MAX('04_LOG_FIELD_ENTRIES'!$B:$B), "", SUMIFS('04_LOG_FIELD_ENTRIES'!$J:$J, '04_LOG_FIELD_ENTRIES'!$B:$B, B68, '04_LOG_FIELD_ENTRIES'!$D:$D, C68, '04_LOG_FIELD_ENTRIES'!$K:$K, "EV_PRODUCCION")) | I68: =IF(B68 > MAX('04_LOG_FIELD_ENTRIES'!$B:$B), "", SUMIFS(H$2:H68, C$2:C68, C68)) | J68: =IF(B68 > MAX('04_LOG_FIELD_ENTRIES'!$B:$B), "", SUMIFS('04_LOG_FIELD_ENTRIES'!$J:$J, '04_LOG_FIELD_ENTRIES'!$B:$B, B68, '04_LOG_FIELD_ENTRIES'!$D:$D, C68, '04_LOG_FIELD_ENTRIES'!$K:$K, "AC_*")) | K68: =IF(B68 > MAX('04_LOG_FIELD_ENTRIES'!$B:$B), "", SUMIFS(J$2:J68, C$2:C68, C68)) | L68: =IF(K68="", "", I68-K68) | M68: =IF(I68="", "", I68-G68) | N68: =IF(I68="", "", IF(G68>0, I68/G68, 1)) | O68: =IF(I68="", "", IF(K68>0, I68/K68, 1)) | P68: =IF(I68="", "", IF(AND(N68>=0.95, O68>=0.95), "SALUDABLE", IF(N68<0.9, "ALERTA RETRASO", "ALERTA SOBRECOSTO")))
A69: 17 | B69: 46251 | C69: WBS-400 | D69: Pruebas Hidráulicas, Desinfección y Entrega | E69: =SUM('01_PRESUPUESTO_CRONOGRAMA_BASE'!G12:G12) | F69: =SUMIFS('02_CRONOGRAMA_PV_DIARIO'!E:E, '02_CRONOGRAMA_PV_DIARIO'!A:A, A69, '02_CRONOGRAMA_PV_DIARIO'!C:C, C69) | G69: =SUMIFS(F$2:F69, C$2:C69, C69) | H69: =IF(B69 > MAX('04_LOG_FIELD_ENTRIES'!$B:$B), "", SUMIFS('04_LOG_FIELD_ENTRIES'!$J:$J, '04_LOG_FIELD_ENTRIES'!$B:$B, B69, '04_LOG_FIELD_ENTRIES'!$D:$D, C69, '04_LOG_FIELD_ENTRIES'!$K:$K, "EV_PRODUCCION")) | I69: =IF(B69 > MAX('04_LOG_FIELD_ENTRIES'!$B:$B), "", SUMIFS(H$2:H69, C$2:C69, C69)) | J69: =IF(B69 > MAX('04_LOG_FIELD_ENTRIES'!$B:$B), "", SUMIFS('04_LOG_FIELD_ENTRIES'!$J:$J, '04_LOG_FIELD_ENTRIES'!$B:$B, B69, '04_LOG_FIELD_ENTRIES'!$D:$D, C69, '04_LOG_FIELD_ENTRIES'!$K:$K, "AC_*")) | K69: =IF(B69 > MAX('04_LOG_FIELD_ENTRIES'!$B:$B), "", SUMIFS(J$2:J69, C$2:C69, C69)) | L69: =IF(K69="", "", I69-K69) | M69: =IF(I69="", "", I69-G69) | N69: =IF(I69="", "", IF(G69>0, I69/G69, 1)) | O69: =IF(I69="", "", IF(K69>0, I69/K69, 1)) | P69: =IF(I69="", "", IF(AND(N69>=0.95, O69>=0.95), "SALUDABLE", IF(N69<0.9, "ALERTA RETRASO", "ALERTA SOBRECOSTO")))
A70: 18 | B70: 46252 | C70: WBS-100 | D70: Obras Preliminares, Trazo y Movilización | E70: =SUM('01_PRESUPUESTO_CRONOGRAMA_BASE'!G2:G3) | F70: =SUMIFS('02_CRONOGRAMA_PV_DIARIO'!E:E, '02_CRONOGRAMA_PV_DIARIO'!A:A, A70, '02_CRONOGRAMA_PV_DIARIO'!C:C, C70) | G70: =SUMIFS(F$2:F70, C$2:C70, C70) | H70: =IF(B70 > MAX('04_LOG_FIELD_ENTRIES'!$B:$B), "", SUMIFS('04_LOG_FIELD_ENTRIES'!$J:$J, '04_LOG_FIELD_ENTRIES'!$B:$B, B70, '04_LOG_FIELD_ENTRIES'!$D:$D, C70, '04_LOG_FIELD_ENTRIES'!$K:$K, "EV_PRODUCCION")) | I70: =IF(B70 > MAX('04_LOG_FIELD_ENTRIES'!$B:$B), "", SUMIFS(H$2:H70, C$2:C70, C70)) | J70: =IF(B70 > MAX('04_LOG_FIELD_ENTRIES'!$B:$B), "", SUMIFS('04_LOG_FIELD_ENTRIES'!$J:$J, '04_LOG_FIELD_ENTRIES'!$B:$B, B70, '04_LOG_FIELD_ENTRIES'!$D:$D, C70, '04_LOG_FIELD_ENTRIES'!$K:$K, "AC_*")) | K70: =IF(B70 > MAX('04_LOG_FIELD_ENTRIES'!$B:$B), "", SUMIFS(J$2:J70, C$2:C70, C70)) | L70: =IF(K70="", "", I70-K70) | M70: =IF(I70="", "", I70-G70) | N70: =IF(I70="", "", IF(G70>0, I70/G70, 1)) | O70: =IF(I70="", "", IF(K70>0, I70/K70, 1)) | P70: =IF(I70="", "", IF(AND(N70>=0.95, O70>=0.95), "SALUDABLE", IF(N70<0.9, "ALERTA RETRASO", "ALERTA SOBRECOSTO")))
A71: 18 | B71: 46252 | C71: WBS-200 | D71: Red de Alcantarillado, Zanjas y Buzones | E71: =SUM('01_PRESUPUESTO_CRONOGRAMA_BASE'!G4:G9) | F71: =SUMIFS('02_CRONOGRAMA_PV_DIARIO'!E:E, '02_CRONOGRAMA_PV_DIARIO'!A:A, A71, '02_CRONOGRAMA_PV_DIARIO'!C:C, C71) | G71: =SUMIFS(F$2:F71, C$2:C71, C71) | H71: =IF(B71 > MAX('04_LOG_FIELD_ENTRIES'!$B:$B), "", SUMIFS('04_LOG_FIELD_ENTRIES'!$J:$J, '04_LOG_FIELD_ENTRIES'!$B:$B, B71, '04_LOG_FIELD_ENTRIES'!$D:$D, C71, '04_LOG_FIELD_ENTRIES'!$K:$K, "EV_PRODUCCION")) | I71: =IF(B71 > MAX('04_LOG_FIELD_ENTRIES'!$B:$B), "", SUMIFS(H$2:H71, C$2:C71, C71)) | J71: =IF(B71 > MAX('04_LOG_FIELD_ENTRIES'!$B:$B), "", SUMIFS('04_LOG_FIELD_ENTRIES'!$J:$J, '04_LOG_FIELD_ENTRIES'!$B:$B, B71, '04_LOG_FIELD_ENTRIES'!$D:$D, C71, '04_LOG_FIELD_ENTRIES'!$K:$K, "AC_*")) | K71: =IF(B71 > MAX('04_LOG_FIELD_ENTRIES'!$B:$B), "", SUMIFS(J$2:J71, C$2:C71, C71)) | L71: =IF(K71="", "", I71-K71) | M71: =IF(I71="", "", I71-G71) | N71: =IF(I71="", "", IF(G71>0, I71/G71, 1)) | O71: =IF(I71="", "", IF(K71>0, I71/K71, 1)) | P71: =IF(I71="", "", IF(AND(N71>=0.95, O71>=0.95), "SALUDABLE", IF(N71<0.9, "ALERTA RETRASO", "ALERTA SOBRECOSTO")))
A72: 18 | B72: 46252 | C72: WBS-300 | D72: Red de Agua Potable y Conexiones Domiciliarias | E72: =SUM('01_PRESUPUESTO_CRONOGRAMA_BASE'!G10:G11) | F72: =SUMIFS('02_CRONOGRAMA_PV_DIARIO'!E:E, '02_CRONOGRAMA_PV_DIARIO'!A:A, A72, '02_CRONOGRAMA_PV_DIARIO'!C:C, C72) | G72: =SUMIFS(F$2:F72, C$2:C72, C72) | H72: =IF(B72 > MAX('04_LOG_FIELD_ENTRIES'!$B:$B), "", SUMIFS('04_LOG_FIELD_ENTRIES'!$J:$J, '04_LOG_FIELD_ENTRIES'!$B:$B, B72, '04_LOG_FIELD_ENTRIES'!$D:$D, C72, '04_LOG_FIELD_ENTRIES'!$K:$K, "EV_PRODUCCION")) | I72: =IF(B72 > MAX('04_LOG_FIELD_ENTRIES'!$B:$B), "", SUMIFS(H$2:H72, C$2:C72, C72)) | J72: =IF(B72 > MAX('04_LOG_FIELD_ENTRIES'!$B:$B), "", SUMIFS('04_LOG_FIELD_ENTRIES'!$J:$J, '04_LOG_FIELD_ENTRIES'!$B:$B, B72, '04_LOG_FIELD_ENTRIES'!$D:$D, C72, '04_LOG_FIELD_ENTRIES'!$K:$K, "AC_*")) | K72: =IF(B72 > MAX('04_LOG_FIELD_ENTRIES'!$B:$B), "", SUMIFS(J$2:J72, C$2:C72, C72)) | L72: =IF(K72="", "", I72-K72) | M72: =IF(I72="", "", I72-G72) | N72: =IF(I72="", "", IF(G72>0, I72/G72, 1)) | O72: =IF(I72="", "", IF(K72>0, I72/K72, 1)) | P72: =IF(I72="", "", IF(AND(N72>=0.95, O72>=0.95), "SALUDABLE", IF(N72<0.9, "ALERTA RETRASO", "ALERTA SOBRECOSTO")))
A73: 18 | B73: 46252 | C73: WBS-400 | D73: Pruebas Hidráulicas, Desinfección y Entrega | E73: =SUM('01_PRESUPUESTO_CRONOGRAMA_BASE'!G12:G12) | F73: =SUMIFS('02_CRONOGRAMA_PV_DIARIO'!E:E, '02_CRONOGRAMA_PV_DIARIO'!A:A, A73, '02_CRONOGRAMA_PV_DIARIO'!C:C, C73) | G73: =SUMIFS(F$2:F73, C$2:C73, C73) | H73: =IF(B73 > MAX('04_LOG_FIELD_ENTRIES'!$B:$B), "", SUMIFS('04_LOG_FIELD_ENTRIES'!$J:$J, '04_LOG_FIELD_ENTRIES'!$B:$B, B73, '04_LOG_FIELD_ENTRIES'!$D:$D, C73, '04_LOG_FIELD_ENTRIES'!$K:$K, "EV_PRODUCCION")) | I73: =IF(B73 > MAX('04_LOG_FIELD_ENTRIES'!$B:$B), "", SUMIFS(H$2:H73, C$2:C73, C73)) | J73: =IF(B73 > MAX('04_LOG_FIELD_ENTRIES'!$B:$B), "", SUMIFS('04_LOG_FIELD_ENTRIES'!$J:$J, '04_LOG_FIELD_ENTRIES'!$B:$B, B73, '04_LOG_FIELD_ENTRIES'!$D:$D, C73, '04_LOG_FIELD_ENTRIES'!$K:$K, "AC_*")) | K73: =IF(B73 > MAX('04_LOG_FIELD_ENTRIES'!$B:$B), "", SUMIFS(J$2:J73, C$2:C73, C73)) | L73: =IF(K73="", "", I73-K73) | M73: =IF(I73="", "", I73-G73) | N73: =IF(I73="", "", IF(G73>0, I73/G73, 1)) | O73: =IF(I73="", "", IF(K73>0, I73/K73, 1)) | P73: =IF(I73="", "", IF(AND(N73>=0.95, O73>=0.95), "SALUDABLE", IF(N73<0.9, "ALERTA RETRASO", "ALERTA SOBRECOSTO")))
A74: 19 | B74: 46253 | C74: WBS-100 | D74: Obras Preliminares, Trazo y Movilización | E74: =SUM('01_PRESUPUESTO_CRONOGRAMA_BASE'!G2:G3) | F74: =SUMIFS('02_CRONOGRAMA_PV_DIARIO'!E:E, '02_CRONOGRAMA_PV_DIARIO'!A:A, A74, '02_CRONOGRAMA_PV_DIARIO'!C:C, C74) | G74: =SUMIFS(F$2:F74, C$2:C74, C74) | H74: =IF(B74 > MAX('04_LOG_FIELD_ENTRIES'!$B:$B), "", SUMIFS('04_LOG_FIELD_ENTRIES'!$J:$J, '04_LOG_FIELD_ENTRIES'!$B:$B, B74, '04_LOG_FIELD_ENTRIES'!$D:$D, C74, '04_LOG_FIELD_ENTRIES'!$K:$K, "EV_PRODUCCION")) | I74: =IF(B74 > MAX('04_LOG_FIELD_ENTRIES'!$B:$B), "", SUMIFS(H$2:H74, C$2:C74, C74)) | J74: =IF(B74 > MAX('04_LOG_FIELD_ENTRIES'!$B:$B), "", SUMIFS('04_LOG_FIELD_ENTRIES'!$J:$J, '04_LOG_FIELD_ENTRIES'!$B:$B, B74, '04_LOG_FIELD_ENTRIES'!$D:$D, C74, '04_LOG_FIELD_ENTRIES'!$K:$K, "AC_*")) | K74: =IF(B74 > MAX('04_LOG_FIELD_ENTRIES'!$B:$B), "", SUMIFS(J$2:J74, C$2:C74, C74)) | L74: =IF(K74="", "", I74-K74) | M74: =IF(I74="", "", I74-G74) | N74: =IF(I74="", "", IF(G74>0, I74/G74, 1)) | O74: =IF(I74="", "", IF(K74>0, I74/K74, 1)) | P74: =IF(I74="", "", IF(AND(N74>=0.95, O74>=0.95), "SALUDABLE", IF(N74<0.9, "ALERTA RETRASO", "ALERTA SOBRECOSTO")))
A75: 19 | B75: 46253 | C75: WBS-200 | D75: Red de Alcantarillado, Zanjas y Buzones | E75: =SUM('01_PRESUPUESTO_CRONOGRAMA_BASE'!G4:G9) | F75: =SUMIFS('02_CRONOGRAMA_PV_DIARIO'!E:E, '02_CRONOGRAMA_PV_DIARIO'!A:A, A75, '02_CRONOGRAMA_PV_DIARIO'!C:C, C75) | G75: =SUMIFS(F$2:F75, C$2:C75, C75) | H75: =IF(B75 > MAX('04_LOG_FIELD_ENTRIES'!$B:$B), "", SUMIFS('04_LOG_FIELD_ENTRIES'!$J:$J, '04_LOG_FIELD_ENTRIES'!$B:$B, B75, '04_LOG_FIELD_ENTRIES'!$D:$D, C75, '04_LOG_FIELD_ENTRIES'!$K:$K, "EV_PRODUCCION")) | I75: =IF(B75 > MAX('04_LOG_FIELD_ENTRIES'!$B:$B), "", SUMIFS(H$2:H75, C$2:C75, C75)) | J75: =IF(B75 > MAX('04_LOG_FIELD_ENTRIES'!$B:$B), "", SUMIFS('04_LOG_FIELD_ENTRIES'!$J:$J, '04_LOG_FIELD_ENTRIES'!$B:$B, B75, '04_LOG_FIELD_ENTRIES'!$D:$D, C75, '04_LOG_FIELD_ENTRIES'!$K:$K, "AC_*")) | K75: =IF(B75 > MAX('04_LOG_FIELD_ENTRIES'!$B:$B), "", SUMIFS(J$2:J75, C$2:C75, C75)) | L75: =IF(K75="", "", I75-K75) | M75: =IF(I75="", "", I75-G75) | N75: =IF(I75="", "", IF(G75>0, I75/G75, 1)) | O75: =IF(I75="", "", IF(K75>0, I75/K75, 1)) | P75: =IF(I75="", "", IF(AND(N75>=0.95, O75>=0.95), "SALUDABLE", IF(N75<0.9, "ALERTA RETRASO", "ALERTA SOBRECOSTO")))
A76: 19 | B76: 46253 | C76: WBS-300 | D76: Red de Agua Potable y Conexiones Domiciliarias | E76: =SUM('01_PRESUPUESTO_CRONOGRAMA_BASE'!G10:G11) | F76: =SUMIFS('02_CRONOGRAMA_PV_DIARIO'!E:E, '02_CRONOGRAMA_PV_DIARIO'!A:A, A76, '02_CRONOGRAMA_PV_DIARIO'!C:C, C76) | G76: =SUMIFS(F$2:F76, C$2:C76, C76) | H76: =IF(B76 > MAX('04_LOG_FIELD_ENTRIES'!$B:$B), "", SUMIFS('04_LOG_FIELD_ENTRIES'!$J:$J, '04_LOG_FIELD_ENTRIES'!$B:$B, B76, '04_LOG_FIELD_ENTRIES'!$D:$D, C76, '04_LOG_FIELD_ENTRIES'!$K:$K, "EV_PRODUCCION")) | I76: =IF(B76 > MAX('04_LOG_FIELD_ENTRIES'!$B:$B), "", SUMIFS(H$2:H76, C$2:C76, C76)) | J76: =IF(B76 > MAX('04_LOG_FIELD_ENTRIES'!$B:$B), "", SUMIFS('04_LOG_FIELD_ENTRIES'!$J:$J, '04_LOG_FIELD_ENTRIES'!$B:$B, B76, '04_LOG_FIELD_ENTRIES'!$D:$D, C76, '04_LOG_FIELD_ENTRIES'!$K:$K, "AC_*")) | K76: =IF(B76 > MAX('04_LOG_FIELD_ENTRIES'!$B:$B), "", SUMIFS(J$2:J76, C$2:C76, C76)) | L76: =IF(K76="", "", I76-K76) | M76: =IF(I76="", "", I76-G76) | N76: =IF(I76="", "", IF(G76>0, I76/G76, 1)) | O76: =IF(I76="", "", IF(K76>0, I76/K76, 1)) | P76: =IF(I76="", "", IF(AND(N76>=0.95, O76>=0.95), "SALUDABLE", IF(N76<0.9, "ALERTA RETRASO", "ALERTA SOBRECOSTO")))
A77: 19 | B77: 46253 | C77: WBS-400 | D77: Pruebas Hidráulicas, Desinfección y Entrega | E77: =SUM('01_PRESUPUESTO_CRONOGRAMA_BASE'!G12:G12) | F77: =SUMIFS('02_CRONOGRAMA_PV_DIARIO'!E:E, '02_CRONOGRAMA_PV_DIARIO'!A:A, A77, '02_CRONOGRAMA_PV_DIARIO'!C:C, C77) | G77: =SUMIFS(F$2:F77, C$2:C77, C77) | H77: =IF(B77 > MAX('04_LOG_FIELD_ENTRIES'!$B:$B), "", SUMIFS('04_LOG_FIELD_ENTRIES'!$J:$J, '04_LOG_FIELD_ENTRIES'!$B:$B, B77, '04_LOG_FIELD_ENTRIES'!$D:$D, C77, '04_LOG_FIELD_ENTRIES'!$K:$K, "EV_PRODUCCION")) | I77: =IF(B77 > MAX('04_LOG_FIELD_ENTRIES'!$B:$B), "", SUMIFS(H$2:H77, C$2:C77, C77)) | J77: =IF(B77 > MAX('04_LOG_FIELD_ENTRIES'!$B:$B), "", SUMIFS('04_LOG_FIELD_ENTRIES'!$J:$J, '04_LOG_FIELD_ENTRIES'!$B:$B, B77, '04_LOG_FIELD_ENTRIES'!$D:$D, C77, '04_LOG_FIELD_ENTRIES'!$K:$K, "AC_*")) | K77: =IF(B77 > MAX('04_LOG_FIELD_ENTRIES'!$B:$B), "", SUMIFS(J$2:J77, C$2:C77, C77)) | L77: =IF(K77="", "", I77-K77) | M77: =IF(I77="", "", I77-G77) | N77: =IF(I77="", "", IF(G77>0, I77/G77, 1)) | O77: =IF(I77="", "", IF(K77>0, I77/K77, 1)) | P77: =IF(I77="", "", IF(AND(N77>=0.95, O77>=0.95), "SALUDABLE", IF(N77<0.9, "ALERTA RETRASO", "ALERTA SOBRECOSTO")))
A78: 20 | B78: 46254 | C78: WBS-100 | D78: Obras Preliminares, Trazo y Movilización | E78: =SUM('01_PRESUPUESTO_CRONOGRAMA_BASE'!G2:G3) | F78: =SUMIFS('02_CRONOGRAMA_PV_DIARIO'!E:E, '02_CRONOGRAMA_PV_DIARIO'!A:A, A78, '02_CRONOGRAMA_PV_DIARIO'!C:C, C78) | G78: =SUMIFS(F$2:F78, C$2:C78, C78) | H78: =IF(B78 > MAX('04_LOG_FIELD_ENTRIES'!$B:$B), "", SUMIFS('04_LOG_FIELD_ENTRIES'!$J:$J, '04_LOG_FIELD_ENTRIES'!$B:$B, B78, '04_LOG_FIELD_ENTRIES'!$D:$D, C78, '04_LOG_FIELD_ENTRIES'!$K:$K, "EV_PRODUCCION")) | I78: =IF(B78 > MAX('04_LOG_FIELD_ENTRIES'!$B:$B), "", SUMIFS(H$2:H78, C$2:C78, C78)) | J78: =IF(B78 > MAX('04_LOG_FIELD_ENTRIES'!$B:$B), "", SUMIFS('04_LOG_FIELD_ENTRIES'!$J:$J, '04_LOG_FIELD_ENTRIES'!$B:$B, B78, '04_LOG_FIELD_ENTRIES'!$D:$D, C78, '04_LOG_FIELD_ENTRIES'!$K:$K, "AC_*")) | K78: =IF(B78 > MAX('04_LOG_FIELD_ENTRIES'!$B:$B), "", SUMIFS(J$2:J78, C$2:C78, C78)) | L78: =IF(K78="", "", I78-K78) | M78: =IF(I78="", "", I78-G78) | N78: =IF(I78="", "", IF(G78>0, I78/G78, 1)) | O78: =IF(I78="", "", IF(K78>0, I78/K78, 1)) | P78: =IF(I78="", "", IF(AND(N78>=0.95, O78>=0.95), "SALUDABLE", IF(N78<0.9, "ALERTA RETRASO", "ALERTA SOBRECOSTO")))
A79: 20 | B79: 46254 | C79: WBS-200 | D79: Red de Alcantarillado, Zanjas y Buzones | E79: =SUM('01_PRESUPUESTO_CRONOGRAMA_BASE'!G4:G9) | F79: =SUMIFS('02_CRONOGRAMA_PV_DIARIO'!E:E, '02_CRONOGRAMA_PV_DIARIO'!A:A, A79, '02_CRONOGRAMA_PV_DIARIO'!C:C, C79) | G79: =SUMIFS(F$2:F79, C$2:C79, C79) | H79: =IF(B79 > MAX('04_LOG_FIELD_ENTRIES'!$B:$B), "", SUMIFS('04_LOG_FIELD_ENTRIES'!$J:$J, '04_LOG_FIELD_ENTRIES'!$B:$B, B79, '04_LOG_FIELD_ENTRIES'!$D:$D, C79, '04_LOG_FIELD_ENTRIES'!$K:$K, "EV_PRODUCCION")) | I79: =IF(B79 > MAX('04_LOG_FIELD_ENTRIES'!$B:$B), "", SUMIFS(H$2:H79, C$2:C79, C79)) | J79: =IF(B79 > MAX('04_LOG_FIELD_ENTRIES'!$B:$B), "", SUMIFS('04_LOG_FIELD_ENTRIES'!$J:$J, '04_LOG_FIELD_ENTRIES'!$B:$B, B79, '04_LOG_FIELD_ENTRIES'!$D:$D, C79, '04_LOG_FIELD_ENTRIES'!$K:$K, "AC_*")) | K79: =IF(B79 > MAX('04_LOG_FIELD_ENTRIES'!$B:$B), "", SUMIFS(J$2:J79, C$2:C79, C79)) | L79: =IF(K79="", "", I79-K79) | M79: =IF(I79="", "", I79-G79) | N79: =IF(I79="", "", IF(G79>0, I79/G79, 1)) | O79: =IF(I79="", "", IF(K79>0, I79/K79, 1)) | P79: =IF(I79="", "", IF(AND(N79>=0.95, O79>=0.95), "SALUDABLE", IF(N79<0.9, "ALERTA RETRASO", "ALERTA SOBRECOSTO")))
A80: 20 | B80: 46254 | C80: WBS-300 | D80: Red de Agua Potable y Conexiones Domiciliarias | E80: =SUM('01_PRESUPUESTO_CRONOGRAMA_BASE'!G10:G11) | F80: =SUMIFS('02_CRONOGRAMA_PV_DIARIO'!E:E, '02_CRONOGRAMA_PV_DIARIO'!A:A, A80, '02_CRONOGRAMA_PV_DIARIO'!C:C, C80) | G80: =SUMIFS(F$2:F80, C$2:C80, C80) | H80: =IF(B80 > MAX('04_LOG_FIELD_ENTRIES'!$B:$B), "", SUMIFS('04_LOG_FIELD_ENTRIES'!$J:$J, '04_LOG_FIELD_ENTRIES'!$B:$B, B80, '04_LOG_FIELD_ENTRIES'!$D:$D, C80, '04_LOG_FIELD_ENTRIES'!$K:$K, "EV_PRODUCCION")) | I80: =IF(B80 > MAX('04_LOG_FIELD_ENTRIES'!$B:$B), "", SUMIFS(H$2:H80, C$2:C80, C80)) | J80: =IF(B80 > MAX('04_LOG_FIELD_ENTRIES'!$B:$B), "", SUMIFS('04_LOG_FIELD_ENTRIES'!$J:$J, '04_LOG_FIELD_ENTRIES'!$B:$B, B80, '04_LOG_FIELD_ENTRIES'!$D:$D, C80, '04_LOG_FIELD_ENTRIES'!$K:$K, "AC_*")) | K80: =IF(B80 > MAX('04_LOG_FIELD_ENTRIES'!$B:$B), "", SUMIFS(J$2:J80, C$2:C80, C80)) | L80: =IF(K80="", "", I80-K80) | M80: =IF(I80="", "", I80-G80) | N80: =IF(I80="", "", IF(G80>0, I80/G80, 1)) | O80: =IF(I80="", "", IF(K80>0, I80/K80, 1)) | P80: =IF(I80="", "", IF(AND(N80>=0.95, O80>=0.95), "SALUDABLE", IF(N80<0.9, "ALERTA RETRASO", "ALERTA SOBRECOSTO")))
A81: 20 | B81: 46254 | C81: WBS-400 | D81: Pruebas Hidráulicas, Desinfección y Entrega | E81: =SUM('01_PRESUPUESTO_CRONOGRAMA_BASE'!G12:G12) | F81: =SUMIFS('02_CRONOGRAMA_PV_DIARIO'!E:E, '02_CRONOGRAMA_PV_DIARIO'!A:A, A81, '02_CRONOGRAMA_PV_DIARIO'!C:C, C81) | G81: =SUMIFS(F$2:F81, C$2:C81, C81) | H81: =IF(B81 > MAX('04_LOG_FIELD_ENTRIES'!$B:$B), "", SUMIFS('04_LOG_FIELD_ENTRIES'!$J:$J, '04_LOG_FIELD_ENTRIES'!$B:$B, B81, '04_LOG_FIELD_ENTRIES'!$D:$D, C81, '04_LOG_FIELD_ENTRIES'!$K:$K, "EV_PRODUCCION")) | I81: =IF(B81 > MAX('04_LOG_FIELD_ENTRIES'!$B:$B), "", SUMIFS(H$2:H81, C$2:C81, C81)) | J81: =IF(B81 > MAX('04_LOG_FIELD_ENTRIES'!$B:$B), "", SUMIFS('04_LOG_FIELD_ENTRIES'!$J:$J, '04_LOG_FIELD_ENTRIES'!$B:$B, B81, '04_LOG_FIELD_ENTRIES'!$D:$D, C81, '04_LOG_FIELD_ENTRIES'!$K:$K, "AC_*")) | K81: =IF(B81 > MAX('04_LOG_FIELD_ENTRIES'!$B:$B), "", SUMIFS(J$2:J81, C$2:C81, C81)) | L81: =IF(K81="", "", I81-K81) | M81: =IF(I81="", "", I81-G81) | N81: =IF(I81="", "", IF(G81>0, I81/G81, 1)) | O81: =IF(I81="", "", IF(K81>0, I81/K81, 1)) | P81: =IF(I81="", "", IF(AND(N81>=0.95, O81>=0.95), "SALUDABLE", IF(N81<0.9, "ALERTA RETRASO", "ALERTA SOBRECOSTO")))
A82: 21 | B82: 46255 | C82: WBS-100 | D82: Obras Preliminares, Trazo y Movilización | E82: =SUM('01_PRESUPUESTO_CRONOGRAMA_BASE'!G2:G3) | F82: =SUMIFS('02_CRONOGRAMA_PV_DIARIO'!E:E, '02_CRONOGRAMA_PV_DIARIO'!A:A, A82, '02_CRONOGRAMA_PV_DIARIO'!C:C, C82) | G82: =SUMIFS(F$2:F82, C$2:C82, C82) | H82: =IF(B82 > MAX('04_LOG_FIELD_ENTRIES'!$B:$B), "", SUMIFS('04_LOG_FIELD_ENTRIES'!$J:$J, '04_LOG_FIELD_ENTRIES'!$B:$B, B82, '04_LOG_FIELD_ENTRIES'!$D:$D, C82, '04_LOG_FIELD_ENTRIES'!$K:$K, "EV_PRODUCCION")) | I82: =IF(B82 > MAX('04_LOG_FIELD_ENTRIES'!$B:$B), "", SUMIFS(H$2:H82, C$2:C82, C82)) | J82: =IF(B82 > MAX('04_LOG_FIELD_ENTRIES'!$B:$B), "", SUMIFS('04_LOG_FIELD_ENTRIES'!$J:$J, '04_LOG_FIELD_ENTRIES'!$B:$B, B82, '04_LOG_FIELD_ENTRIES'!$D:$D, C82, '04_LOG_FIELD_ENTRIES'!$K:$K, "AC_*")) | K82: =IF(B82 > MAX('04_LOG_FIELD_ENTRIES'!$B:$B), "", SUMIFS(J$2:J82, C$2:C82, C82)) | L82: =IF(K82="", "", I82-K82) | M82: =IF(I82="", "", I82-G82) | N82: =IF(I82="", "", IF(G82>0, I82/G82, 1)) | O82: =IF(I82="", "", IF(K82>0, I82/K82, 1)) | P82: =IF(I82="", "", IF(AND(N82>=0.95, O82>=0.95), "SALUDABLE", IF(N82<0.9, "ALERTA RETRASO", "ALERTA SOBRECOSTO")))
A83: 21 | B83: 46255 | C83: WBS-200 | D83: Red de Alcantarillado, Zanjas y Buzones | E83: =SUM('01_PRESUPUESTO_CRONOGRAMA_BASE'!G4:G9) | F83: =SUMIFS('02_CRONOGRAMA_PV_DIARIO'!E:E, '02_CRONOGRAMA_PV_DIARIO'!A:A, A83, '02_CRONOGRAMA_PV_DIARIO'!C:C, C83) | G83: =SUMIFS(F$2:F83, C$2:C83, C83) | H83: =IF(B83 > MAX('04_LOG_FIELD_ENTRIES'!$B:$B), "", SUMIFS('04_LOG_FIELD_ENTRIES'!$J:$J, '04_LOG_FIELD_ENTRIES'!$B:$B, B83, '04_LOG_FIELD_ENTRIES'!$D:$D, C83, '04_LOG_FIELD_ENTRIES'!$K:$K, "EV_PRODUCCION")) | I83: =IF(B83 > MAX('04_LOG_FIELD_ENTRIES'!$B:$B), "", SUMIFS(H$2:H83, C$2:C83, C83)) | J83: =IF(B83 > MAX('04_LOG_FIELD_ENTRIES'!$B:$B), "", SUMIFS('04_LOG_FIELD_ENTRIES'!$J:$J, '04_LOG_FIELD_ENTRIES'!$B:$B, B83, '04_LOG_FIELD_ENTRIES'!$D:$D, C83, '04_LOG_FIELD_ENTRIES'!$K:$K, "AC_*")) | K83: =IF(B83 > MAX('04_LOG_FIELD_ENTRIES'!$B:$B), "", SUMIFS(J$2:J83, C$2:C83, C83)) | L83: =IF(K83="", "", I83-K83) | M83: =IF(I83="", "", I83-G83) | N83: =IF(I83="", "", IF(G83>0, I83/G83, 1)) | O83: =IF(I83="", "", IF(K83>0, I83/K83, 1)) | P83: =IF(I83="", "", IF(AND(N83>=0.95, O83>=0.95), "SALUDABLE", IF(N83<0.9, "ALERTA RETRASO", "ALERTA SOBRECOSTO")))
A84: 21 | B84: 46255 | C84: WBS-300 | D84: Red de Agua Potable y Conexiones Domiciliarias | E84: =SUM('01_PRESUPUESTO_CRONOGRAMA_BASE'!G10:G11) | F84: =SUMIFS('02_CRONOGRAMA_PV_DIARIO'!E:E, '02_CRONOGRAMA_PV_DIARIO'!A:A, A84, '02_CRONOGRAMA_PV_DIARIO'!C:C, C84) | G84: =SUMIFS(F$2:F84, C$2:C84, C84) | H84: =IF(B84 > MAX('04_LOG_FIELD_ENTRIES'!$B:$B), "", SUMIFS('04_LOG_FIELD_ENTRIES'!$J:$J, '04_LOG_FIELD_ENTRIES'!$B:$B, B84, '04_LOG_FIELD_ENTRIES'!$D:$D, C84, '04_LOG_FIELD_ENTRIES'!$K:$K, "EV_PRODUCCION")) | I84: =IF(B84 > MAX('04_LOG_FIELD_ENTRIES'!$B:$B), "", SUMIFS(H$2:H84, C$2:C84, C84)) | J84: =IF(B84 > MAX('04_LOG_FIELD_ENTRIES'!$B:$B), "", SUMIFS('04_LOG_FIELD_ENTRIES'!$J:$J, '04_LOG_FIELD_ENTRIES'!$B:$B, B84, '04_LOG_FIELD_ENTRIES'!$D:$D, C84, '04_LOG_FIELD_ENTRIES'!$K:$K, "AC_*")) | K84: =IF(B84 > MAX('04_LOG_FIELD_ENTRIES'!$B:$B), "", SUMIFS(J$2:J84, C$2:C84, C84)) | L84: =IF(K84="", "", I84-K84) | M84: =IF(I84="", "", I84-G84) | N84: =IF(I84="", "", IF(G84>0, I84/G84, 1)) | O84: =IF(I84="", "", IF(K84>0, I84/K84, 1)) | P84: =IF(I84="", "", IF(AND(N84>=0.95, O84>=0.95), "SALUDABLE", IF(N84<0.9, "ALERTA RETRASO", "ALERTA SOBRECOSTO")))
A85: 21 | B85: 46255 | C85: WBS-400 | D85: Pruebas Hidráulicas, Desinfección y Entrega | E85: =SUM('01_PRESUPUESTO_CRONOGRAMA_BASE'!G12:G12) | F85: =SUMIFS('02_CRONOGRAMA_PV_DIARIO'!E:E, '02_CRONOGRAMA_PV_DIARIO'!A:A, A85, '02_CRONOGRAMA_PV_DIARIO'!C:C, C85) | G85: =SUMIFS(F$2:F85, C$2:C85, C85) | H85: =IF(B85 > MAX('04_LOG_FIELD_ENTRIES'!$B:$B), "", SUMIFS('04_LOG_FIELD_ENTRIES'!$J:$J, '04_LOG_FIELD_ENTRIES'!$B:$B, B85, '04_LOG_FIELD_ENTRIES'!$D:$D, C85, '04_LOG_FIELD_ENTRIES'!$K:$K, "EV_PRODUCCION")) | I85: =IF(B85 > MAX('04_LOG_FIELD_ENTRIES'!$B:$B), "", SUMIFS(H$2:H85, C$2:C85, C85)) | J85: =IF(B85 > MAX('04_LOG_FIELD_ENTRIES'!$B:$B), "", SUMIFS('04_LOG_FIELD_ENTRIES'!$J:$J, '04_LOG_FIELD_ENTRIES'!$B:$B, B85, '04_LOG_FIELD_ENTRIES'!$D:$D, C85, '04_LOG_FIELD_ENTRIES'!$K:$K, "AC_*")) | K85: =IF(B85 > MAX('04_LOG_FIELD_ENTRIES'!$B:$B), "", SUMIFS(J$2:J85, C$2:C85, C85)) | L85: =IF(K85="", "", I85-K85) | M85: =IF(I85="", "", I85-G85) | N85: =IF(I85="", "", IF(G85>0, I85/G85, 1)) | O85: =IF(I85="", "", IF(K85>0, I85/K85, 1)) | P85: =IF(I85="", "", IF(AND(N85>=0.95, O85>=0.95), "SALUDABLE", IF(N85<0.9, "ALERTA RETRASO", "ALERTA SOBRECOSTO")))
A86: 22 | B86: 46256 | C86: WBS-100 | D86: Obras Preliminares, Trazo y Movilización | E86: =SUM('01_PRESUPUESTO_CRONOGRAMA_BASE'!G2:G3) | F86: =SUMIFS('02_CRONOGRAMA_PV_DIARIO'!E:E, '02_CRONOGRAMA_PV_DIARIO'!A:A, A86, '02_CRONOGRAMA_PV_DIARIO'!C:C, C86) | G86: =SUMIFS(F$2:F86, C$2:C86, C86) | H86: =IF(B86 > MAX('04_LOG_FIELD_ENTRIES'!$B:$B), "", SUMIFS('04_LOG_FIELD_ENTRIES'!$J:$J, '04_LOG_FIELD_ENTRIES'!$B:$B, B86, '04_LOG_FIELD_ENTRIES'!$D:$D, C86, '04_LOG_FIELD_ENTRIES'!$K:$K, "EV_PRODUCCION")) | I86: =IF(B86 > MAX('04_LOG_FIELD_ENTRIES'!$B:$B), "", SUMIFS(H$2:H86, C$2:C86, C86)) | J86: =IF(B86 > MAX('04_LOG_FIELD_ENTRIES'!$B:$B), "", SUMIFS('04_LOG_FIELD_ENTRIES'!$J:$J, '04_LOG_FIELD_ENTRIES'!$B:$B, B86, '04_LOG_FIELD_ENTRIES'!$D:$D, C86, '04_LOG_FIELD_ENTRIES'!$K:$K, "AC_*")) | K86: =IF(B86 > MAX('04_LOG_FIELD_ENTRIES'!$B:$B), "", SUMIFS(J$2:J86, C$2:C86, C86)) | L86: =IF(K86="", "", I86-K86) | M86: =IF(I86="", "", I86-G86) | N86: =IF(I86="", "", IF(G86>0, I86/G86, 1)) | O86: =IF(I86="", "", IF(K86>0, I86/K86, 1)) | P86: =IF(I86="", "", IF(AND(N86>=0.95, O86>=0.95), "SALUDABLE", IF(N86<0.9, "ALERTA RETRASO", "ALERTA SOBRECOSTO")))
A87: 22 | B87: 46256 | C87: WBS-200 | D87: Red de Alcantarillado, Zanjas y Buzones | E87: =SUM('01_PRESUPUESTO_CRONOGRAMA_BASE'!G4:G9) | F87: =SUMIFS('02_CRONOGRAMA_PV_DIARIO'!E:E, '02_CRONOGRAMA_PV_DIARIO'!A:A, A87, '02_CRONOGRAMA_PV_DIARIO'!C:C, C87) | G87: =SUMIFS(F$2:F87, C$2:C87, C87) | H87: =IF(B87 > MAX('04_LOG_FIELD_ENTRIES'!$B:$B), "", SUMIFS('04_LOG_FIELD_ENTRIES'!$J:$J, '04_LOG_FIELD_ENTRIES'!$B:$B, B87, '04_LOG_FIELD_ENTRIES'!$D:$D, C87, '04_LOG_FIELD_ENTRIES'!$K:$K, "EV_PRODUCCION")) | I87: =IF(B87 > MAX('04_LOG_FIELD_ENTRIES'!$B:$B), "", SUMIFS(H$2:H87, C$2:C87, C87)) | J87: =IF(B87 > MAX('04_LOG_FIELD_ENTRIES'!$B:$B), "", SUMIFS('04_LOG_FIELD_ENTRIES'!$J:$J, '04_LOG_FIELD_ENTRIES'!$B:$B, B87, '04_LOG_FIELD_ENTRIES'!$D:$D, C87, '04_LOG_FIELD_ENTRIES'!$K:$K, "AC_*")) | K87: =IF(B87 > MAX('04_LOG_FIELD_ENTRIES'!$B:$B), "", SUMIFS(J$2:J87, C$2:C87, C87)) | L87: =IF(K87="", "", I87-K87) | M87: =IF(I87="", "", I87-G87) | N87: =IF(I87="", "", IF(G87>0, I87/G87, 1)) | O87: =IF(I87="", "", IF(K87>0, I87/K87, 1)) | P87: =IF(I87="", "", IF(AND(N87>=0.95, O87>=0.95), "SALUDABLE", IF(N87<0.9, "ALERTA RETRASO", "ALERTA SOBRECOSTO")))
A88: 22 | B88: 46256 | C88: WBS-300 | D88: Red de Agua Potable y Conexiones Domiciliarias | E88: =SUM('01_PRESUPUESTO_CRONOGRAMA_BASE'!G10:G11) | F88: =SUMIFS('02_CRONOGRAMA_PV_DIARIO'!E:E, '02_CRONOGRAMA_PV_DIARIO'!A:A, A88, '02_CRONOGRAMA_PV_DIARIO'!C:C, C88) | G88: =SUMIFS(F$2:F88, C$2:C88, C88) | H88: =IF(B88 > MAX('04_LOG_FIELD_ENTRIES'!$B:$B), "", SUMIFS('04_LOG_FIELD_ENTRIES'!$J:$J, '04_LOG_FIELD_ENTRIES'!$B:$B, B88, '04_LOG_FIELD_ENTRIES'!$D:$D, C88, '04_LOG_FIELD_ENTRIES'!$K:$K, "EV_PRODUCCION")) | I88: =IF(B88 > MAX('04_LOG_FIELD_ENTRIES'!$B:$B), "", SUMIFS(H$2:H88, C$2:C88, C88)) | J88: =IF(B88 > MAX('04_LOG_FIELD_ENTRIES'!$B:$B), "", SUMIFS('04_LOG_FIELD_ENTRIES'!$J:$J, '04_LOG_FIELD_ENTRIES'!$B:$B, B88, '04_LOG_FIELD_ENTRIES'!$D:$D, C88, '04_LOG_FIELD_ENTRIES'!$K:$K, "AC_*")) | K88: =IF(B88 > MAX('04_LOG_FIELD_ENTRIES'!$B:$B), "", SUMIFS(J$2:J88, C$2:C88, C88)) | L88: =IF(K88="", "", I88-K88) | M88: =IF(I88="", "", I88-G88) | N88: =IF(I88="", "", IF(G88>0, I88/G88, 1)) | O88: =IF(I88="", "", IF(K88>0, I88/K88, 1)) | P88: =IF(I88="", "", IF(AND(N88>=0.95, O88>=0.95), "SALUDABLE", IF(N88<0.9, "ALERTA RETRASO", "ALERTA SOBRECOSTO")))
A89: 22 | B89: 46256 | C89: WBS-400 | D89: Pruebas Hidráulicas, Desinfección y Entrega | E89: =SUM('01_PRESUPUESTO_CRONOGRAMA_BASE'!G12:G12) | F89: =SUMIFS('02_CRONOGRAMA_PV_DIARIO'!E:E, '02_CRONOGRAMA_PV_DIARIO'!A:A, A89, '02_CRONOGRAMA_PV_DIARIO'!C:C, C89) | G89: =SUMIFS(F$2:F89, C$2:C89, C89) | H89: =IF(B89 > MAX('04_LOG_FIELD_ENTRIES'!$B:$B), "", SUMIFS('04_LOG_FIELD_ENTRIES'!$J:$J, '04_LOG_FIELD_ENTRIES'!$B:$B, B89, '04_LOG_FIELD_ENTRIES'!$D:$D, C89, '04_LOG_FIELD_ENTRIES'!$K:$K, "EV_PRODUCCION")) | I89: =IF(B89 > MAX('04_LOG_FIELD_ENTRIES'!$B:$B), "", SUMIFS(H$2:H89, C$2:C89, C89)) | J89: =IF(B89 > MAX('04_LOG_FIELD_ENTRIES'!$B:$B), "", SUMIFS('04_LOG_FIELD_ENTRIES'!$J:$J, '04_LOG_FIELD_ENTRIES'!$B:$B, B89, '04_LOG_FIELD_ENTRIES'!$D:$D, C89, '04_LOG_FIELD_ENTRIES'!$K:$K, "AC_*")) | K89: =IF(B89 > MAX('04_LOG_FIELD_ENTRIES'!$B:$B), "", SUMIFS(J$2:J89, C$2:C89, C89)) | L89: =IF(K89="", "", I89-K89) | M89: =IF(I89="", "", I89-G89) | N89: =IF(I89="", "", IF(G89>0, I89/G89, 1)) | O89: =IF(I89="", "", IF(K89>0, I89/K89, 1)) | P89: =IF(I89="", "", IF(AND(N89>=0.95, O89>=0.95), "SALUDABLE", IF(N89<0.9, "ALERTA RETRASO", "ALERTA SOBRECOSTO")))
A90: 23 | B90: 46257 | C90: WBS-100 | D90: Obras Preliminares, Trazo y Movilización | E90: =SUM('01_PRESUPUESTO_CRONOGRAMA_BASE'!G2:G3) | F90: =SUMIFS('02_CRONOGRAMA_PV_DIARIO'!E:E, '02_CRONOGRAMA_PV_DIARIO'!A:A, A90, '02_CRONOGRAMA_PV_DIARIO'!C:C, C90) | G90: =SUMIFS(F$2:F90, C$2:C90, C90) | H90: =IF(B90 > MAX('04_LOG_FIELD_ENTRIES'!$B:$B), "", SUMIFS('04_LOG_FIELD_ENTRIES'!$J:$J, '04_LOG_FIELD_ENTRIES'!$B:$B, B90, '04_LOG_FIELD_ENTRIES'!$D:$D, C90, '04_LOG_FIELD_ENTRIES'!$K:$K, "EV_PRODUCCION")) | I90: =IF(B90 > MAX('04_LOG_FIELD_ENTRIES'!$B:$B), "", SUMIFS(H$2:H90, C$2:C90, C90)) | J90: =IF(B90 > MAX('04_LOG_FIELD_ENTRIES'!$B:$B), "", SUMIFS('04_LOG_FIELD_ENTRIES'!$J:$J, '04_LOG_FIELD_ENTRIES'!$B:$B, B90, '04_LOG_FIELD_ENTRIES'!$D:$D, C90, '04_LOG_FIELD_ENTRIES'!$K:$K, "AC_*")) | K90: =IF(B90 > MAX('04_LOG_FIELD_ENTRIES'!$B:$B), "", SUMIFS(J$2:J90, C$2:C90, C90)) | L90: =IF(K90="", "", I90-K90) | M90: =IF(I90="", "", I90-G90) | N90: =IF(I90="", "", IF(G90>0, I90/G90, 1)) | O90: =IF(I90="", "", IF(K90>0, I90/K90, 1)) | P90: =IF(I90="", "", IF(AND(N90>=0.95, O90>=0.95), "SALUDABLE", IF(N90<0.9, "ALERTA RETRASO", "ALERTA SOBRECOSTO")))
A91: 23 | B91: 46257 | C91: WBS-200 | D91: Red de Alcantarillado, Zanjas y Buzones | E91: =SUM('01_PRESUPUESTO_CRONOGRAMA_BASE'!G4:G9) | F91: =SUMIFS('02_CRONOGRAMA_PV_DIARIO'!E:E, '02_CRONOGRAMA_PV_DIARIO'!A:A, A91, '02_CRONOGRAMA_PV_DIARIO'!C:C, C91) | G91: =SUMIFS(F$2:F91, C$2:C91, C91) | H91: =IF(B91 > MAX('04_LOG_FIELD_ENTRIES'!$B:$B), "", SUMIFS('04_LOG_FIELD_ENTRIES'!$J:$J, '04_LOG_FIELD_ENTRIES'!$B:$B, B91, '04_LOG_FIELD_ENTRIES'!$D:$D, C91, '04_LOG_FIELD_ENTRIES'!$K:$K, "EV_PRODUCCION")) | I91: =IF(B91 > MAX('04_LOG_FIELD_ENTRIES'!$B:$B), "", SUMIFS(H$2:H91, C$2:C91, C91)) | J91: =IF(B91 > MAX('04_LOG_FIELD_ENTRIES'!$B:$B), "", SUMIFS('04_LOG_FIELD_ENTRIES'!$J:$J, '04_LOG_FIELD_ENTRIES'!$B:$B, B91, '04_LOG_FIELD_ENTRIES'!$D:$D, C91, '04_LOG_FIELD_ENTRIES'!$K:$K, "AC_*")) | K91: =IF(B91 > MAX('04_LOG_FIELD_ENTRIES'!$B:$B), "", SUMIFS(J$2:J91, C$2:C91, C91)) | L91: =IF(K91="", "", I91-K91) | M91: =IF(I91="", "", I91-G91) | N91: =IF(I91="", "", IF(G91>0, I91/G91, 1)) | O91: =IF(I91="", "", IF(K91>0, I91/K91, 1)) | P91: =IF(I91="", "", IF(AND(N91>=0.95, O91>=0.95), "SALUDABLE", IF(N91<0.9, "ALERTA RETRASO", "ALERTA SOBRECOSTO")))
A92: 23 | B92: 46257 | C92: WBS-300 | D92: Red de Agua Potable y Conexiones Domiciliarias | E92: =SUM('01_PRESUPUESTO_CRONOGRAMA_BASE'!G10:G11) | F92: =SUMIFS('02_CRONOGRAMA_PV_DIARIO'!E:E, '02_CRONOGRAMA_PV_DIARIO'!A:A, A92, '02_CRONOGRAMA_PV_DIARIO'!C:C, C92) | G92: =SUMIFS(F$2:F92, C$2:C92, C92) | H92: =IF(B92 > MAX('04_LOG_FIELD_ENTRIES'!$B:$B), "", SUMIFS('04_LOG_FIELD_ENTRIES'!$J:$J, '04_LOG_FIELD_ENTRIES'!$B:$B, B92, '04_LOG_FIELD_ENTRIES'!$D:$D, C92, '04_LOG_FIELD_ENTRIES'!$K:$K, "EV_PRODUCCION")) | I92: =IF(B92 > MAX('04_LOG_FIELD_ENTRIES'!$B:$B), "", SUMIFS(H$2:H92, C$2:C92, C92)) | J92: =IF(B92 > MAX('04_LOG_FIELD_ENTRIES'!$B:$B), "", SUMIFS('04_LOG_FIELD_ENTRIES'!$J:$J, '04_LOG_FIELD_ENTRIES'!$B:$B, B92, '04_LOG_FIELD_ENTRIES'!$D:$D, C92, '04_LOG_FIELD_ENTRIES'!$K:$K, "AC_*")) | K92: =IF(B92 > MAX('04_LOG_FIELD_ENTRIES'!$B:$B), "", SUMIFS(J$2:J92, C$2:C92, C92)) | L92: =IF(K92="", "", I92-K92) | M92: =IF(I92="", "", I92-G92) | N92: =IF(I92="", "", IF(G92>0, I92/G92, 1)) | O92: =IF(I92="", "", IF(K92>0, I92/K92, 1)) | P92: =IF(I92="", "", IF(AND(N92>=0.95, O92>=0.95), "SALUDABLE", IF(N92<0.9, "ALERTA RETRASO", "ALERTA SOBRECOSTO")))
A93: 23 | B93: 46257 | C93: WBS-400 | D93: Pruebas Hidráulicas, Desinfección y Entrega | E93: =SUM('01_PRESUPUESTO_CRONOGRAMA_BASE'!G12:G12) | F93: =SUMIFS('02_CRONOGRAMA_PV_DIARIO'!E:E, '02_CRONOGRAMA_PV_DIARIO'!A:A, A93, '02_CRONOGRAMA_PV_DIARIO'!C:C, C93) | G93: =SUMIFS(F$2:F93, C$2:C93, C93) | H93: =IF(B93 > MAX('04_LOG_FIELD_ENTRIES'!$B:$B), "", SUMIFS('04_LOG_FIELD_ENTRIES'!$J:$J, '04_LOG_FIELD_ENTRIES'!$B:$B, B93, '04_LOG_FIELD_ENTRIES'!$D:$D, C93, '04_LOG_FIELD_ENTRIES'!$K:$K, "EV_PRODUCCION")) | I93: =IF(B93 > MAX('04_LOG_FIELD_ENTRIES'!$B:$B), "", SUMIFS(H$2:H93, C$2:C93, C93)) | J93: =IF(B93 > MAX('04_LOG_FIELD_ENTRIES'!$B:$B), "", SUMIFS('04_LOG_FIELD_ENTRIES'!$J:$J, '04_LOG_FIELD_ENTRIES'!$B:$B, B93, '04_LOG_FIELD_ENTRIES'!$D:$D, C93, '04_LOG_FIELD_ENTRIES'!$K:$K, "AC_*")) | K93: =IF(B93 > MAX('04_LOG_FIELD_ENTRIES'!$B:$B), "", SUMIFS(J$2:J93, C$2:C93, C93)) | L93: =IF(K93="", "", I93-K93) | M93: =IF(I93="", "", I93-G93) | N93: =IF(I93="", "", IF(G93>0, I93/G93, 1)) | O93: =IF(I93="", "", IF(K93>0, I93/K93, 1)) | P93: =IF(I93="", "", IF(AND(N93>=0.95, O93>=0.95), "SALUDABLE", IF(N93<0.9, "ALERTA RETRASO", "ALERTA SOBRECOSTO")))
A94: 24 | B94: 46258 | C94: WBS-100 | D94: Obras Preliminares, Trazo y Movilización | E94: =SUM('01_PRESUPUESTO_CRONOGRAMA_BASE'!G2:G3) | F94: =SUMIFS('02_CRONOGRAMA_PV_DIARIO'!E:E, '02_CRONOGRAMA_PV_DIARIO'!A:A, A94, '02_CRONOGRAMA_PV_DIARIO'!C:C, C94) | G94: =SUMIFS(F$2:F94, C$2:C94, C94) | H94: =IF(B94 > MAX('04_LOG_FIELD_ENTRIES'!$B:$B), "", SUMIFS('04_LOG_FIELD_ENTRIES'!$J:$J, '04_LOG_FIELD_ENTRIES'!$B:$B, B94, '04_LOG_FIELD_ENTRIES'!$D:$D, C94, '04_LOG_FIELD_ENTRIES'!$K:$K, "EV_PRODUCCION")) | I94: =IF(B94 > MAX('04_LOG_FIELD_ENTRIES'!$B:$B), "", SUMIFS(H$2:H94, C$2:C94, C94)) | J94: =IF(B94 > MAX('04_LOG_FIELD_ENTRIES'!$B:$B), "", SUMIFS('04_LOG_FIELD_ENTRIES'!$J:$J, '04_LOG_FIELD_ENTRIES'!$B:$B, B94, '04_LOG_FIELD_ENTRIES'!$D:$D, C94, '04_LOG_FIELD_ENTRIES'!$K:$K, "AC_*")) | K94: =IF(B94 > MAX('04_LOG_FIELD_ENTRIES'!$B:$B), "", SUMIFS(J$2:J94, C$2:C94, C94)) | L94: =IF(K94="", "", I94-K94) | M94: =IF(I94="", "", I94-G94) | N94: =IF(I94="", "", IF(G94>0, I94/G94, 1)) | O94: =IF(I94="", "", IF(K94>0, I94/K94, 1)) | P94: =IF(I94="", "", IF(AND(N94>=0.95, O94>=0.95), "SALUDABLE", IF(N94<0.9, "ALERTA RETRASO", "ALERTA SOBRECOSTO")))
A95: 24 | B95: 46258 | C95: WBS-200 | D95: Red de Alcantarillado, Zanjas y Buzones | E95: =SUM('01_PRESUPUESTO_CRONOGRAMA_BASE'!G4:G9) | F95: =SUMIFS('02_CRONOGRAMA_PV_DIARIO'!E:E, '02_CRONOGRAMA_PV_DIARIO'!A:A, A95, '02_CRONOGRAMA_PV_DIARIO'!C:C, C95) | G95: =SUMIFS(F$2:F95, C$2:C95, C95) | H95: =IF(B95 > MAX('04_LOG_FIELD_ENTRIES'!$B:$B), "", SUMIFS('04_LOG_FIELD_ENTRIES'!$J:$J, '04_LOG_FIELD_ENTRIES'!$B:$B, B95, '04_LOG_FIELD_ENTRIES'!$D:$D, C95, '04_LOG_FIELD_ENTRIES'!$K:$K, "EV_PRODUCCION")) | I95: =IF(B95 > MAX('04_LOG_FIELD_ENTRIES'!$B:$B), "", SUMIFS(H$2:H95, C$2:C95, C95)) | J95: =IF(B95 > MAX('04_LOG_FIELD_ENTRIES'!$B:$B), "", SUMIFS('04_LOG_FIELD_ENTRIES'!$J:$J, '04_LOG_FIELD_ENTRIES'!$B:$B, B95, '04_LOG_FIELD_ENTRIES'!$D:$D, C95, '04_LOG_FIELD_ENTRIES'!$K:$K, "AC_*")) | K95: =IF(B95 > MAX('04_LOG_FIELD_ENTRIES'!$B:$B), "", SUMIFS(J$2:J95, C$2:C95, C95)) | L95: =IF(K95="", "", I95-K95) | M95: =IF(I95="", "", I95-G95) | N95: =IF(I95="", "", IF(G95>0, I95/G95, 1)) | O95: =IF(I95="", "", IF(K95>0, I95/K95, 1)) | P95: =IF(I95="", "", IF(AND(N95>=0.95, O95>=0.95), "SALUDABLE", IF(N95<0.9, "ALERTA RETRASO", "ALERTA SOBRECOSTO")))
A96: 24 | B96: 46258 | C96: WBS-300 | D96: Red de Agua Potable y Conexiones Domiciliarias | E96: =SUM('01_PRESUPUESTO_CRONOGRAMA_BASE'!G10:G11) | F96: =SUMIFS('02_CRONOGRAMA_PV_DIARIO'!E:E, '02_CRONOGRAMA_PV_DIARIO'!A:A, A96, '02_CRONOGRAMA_PV_DIARIO'!C:C, C96) | G96: =SUMIFS(F$2:F96, C$2:C96, C96) | H96: =IF(B96 > MAX('04_LOG_FIELD_ENTRIES'!$B:$B), "", SUMIFS('04_LOG_FIELD_ENTRIES'!$J:$J, '04_LOG_FIELD_ENTRIES'!$B:$B, B96, '04_LOG_FIELD_ENTRIES'!$D:$D, C96, '04_LOG_FIELD_ENTRIES'!$K:$K, "EV_PRODUCCION")) | I96: =IF(B96 > MAX('04_LOG_FIELD_ENTRIES'!$B:$B), "", SUMIFS(H$2:H96, C$2:C96, C96)) | J96: =IF(B96 > MAX('04_LOG_FIELD_ENTRIES'!$B:$B), "", SUMIFS('04_LOG_FIELD_ENTRIES'!$J:$J, '04_LOG_FIELD_ENTRIES'!$B:$B, B96, '04_LOG_FIELD_ENTRIES'!$D:$D, C96, '04_LOG_FIELD_ENTRIES'!$K:$K, "AC_*")) | K96: =IF(B96 > MAX('04_LOG_FIELD_ENTRIES'!$B:$B), "", SUMIFS(J$2:J96, C$2:C96, C96)) | L96: =IF(K96="", "", I96-K96) | M96: =IF(I96="", "", I96-G96) | N96: =IF(I96="", "", IF(G96>0, I96/G96, 1)) | O96: =IF(I96="", "", IF(K96>0, I96/K96, 1)) | P96: =IF(I96="", "", IF(AND(N96>=0.95, O96>=0.95), "SALUDABLE", IF(N96<0.9, "ALERTA RETRASO", "ALERTA SOBRECOSTO")))
A97: 24 | B97: 46258 | C97: WBS-400 | D97: Pruebas Hidráulicas, Desinfección y Entrega | E97: =SUM('01_PRESUPUESTO_CRONOGRAMA_BASE'!G12:G12) | F97: =SUMIFS('02_CRONOGRAMA_PV_DIARIO'!E:E, '02_CRONOGRAMA_PV_DIARIO'!A:A, A97, '02_CRONOGRAMA_PV_DIARIO'!C:C, C97) | G97: =SUMIFS(F$2:F97, C$2:C97, C97) | H97: =IF(B97 > MAX('04_LOG_FIELD_ENTRIES'!$B:$B), "", SUMIFS('04_LOG_FIELD_ENTRIES'!$J:$J, '04_LOG_FIELD_ENTRIES'!$B:$B, B97, '04_LOG_FIELD_ENTRIES'!$D:$D, C97, '04_LOG_FIELD_ENTRIES'!$K:$K, "EV_PRODUCCION")) | I97: =IF(B97 > MAX('04_LOG_FIELD_ENTRIES'!$B:$B), "", SUMIFS(H$2:H97, C$2:C97, C97)) | J97: =IF(B97 > MAX('04_LOG_FIELD_ENTRIES'!$B:$B), "", SUMIFS('04_LOG_FIELD_ENTRIES'!$J:$J, '04_LOG_FIELD_ENTRIES'!$B:$B, B97, '04_LOG_FIELD_ENTRIES'!$D:$D, C97, '04_LOG_FIELD_ENTRIES'!$K:$K, "AC_*")) | K97: =IF(B97 > MAX('04_LOG_FIELD_ENTRIES'!$B:$B), "", SUMIFS(J$2:J97, C$2:C97, C97)) | L97: =IF(K97="", "", I97-K97) | M97: =IF(I97="", "", I97-G97) | N97: =IF(I97="", "", IF(G97>0, I97/G97, 1)) | O97: =IF(I97="", "", IF(K97>0, I97/K97, 1)) | P97: =IF(I97="", "", IF(AND(N97>=0.95, O97>=0.95), "SALUDABLE", IF(N97<0.9, "ALERTA RETRASO", "ALERTA SOBRECOSTO")))
A98: 25 | B98: 46259 | C98: WBS-100 | D98: Obras Preliminares, Trazo y Movilización | E98: =SUM('01_PRESUPUESTO_CRONOGRAMA_BASE'!G2:G3) | F98: =SUMIFS('02_CRONOGRAMA_PV_DIARIO'!E:E, '02_CRONOGRAMA_PV_DIARIO'!A:A, A98, '02_CRONOGRAMA_PV_DIARIO'!C:C, C98) | G98: =SUMIFS(F$2:F98, C$2:C98, C98) | H98: =IF(B98 > MAX('04_LOG_FIELD_ENTRIES'!$B:$B), "", SUMIFS('04_LOG_FIELD_ENTRIES'!$J:$J, '04_LOG_FIELD_ENTRIES'!$B:$B, B98, '04_LOG_FIELD_ENTRIES'!$D:$D, C98, '04_LOG_FIELD_ENTRIES'!$K:$K, "EV_PRODUCCION")) | I98: =IF(B98 > MAX('04_LOG_FIELD_ENTRIES'!$B:$B), "", SUMIFS(H$2:H98, C$2:C98, C98)) | J98: =IF(B98 > MAX('04_LOG_FIELD_ENTRIES'!$B:$B), "", SUMIFS('04_LOG_FIELD_ENTRIES'!$J:$J, '04_LOG_FIELD_ENTRIES'!$B:$B, B98, '04_LOG_FIELD_ENTRIES'!$D:$D, C98, '04_LOG_FIELD_ENTRIES'!$K:$K, "AC_*")) | K98: =IF(B98 > MAX('04_LOG_FIELD_ENTRIES'!$B:$B), "", SUMIFS(J$2:J98, C$2:C98, C98)) | L98: =IF(K98="", "", I98-K98) | M98: =IF(I98="", "", I98-G98) | N98: =IF(I98="", "", IF(G98>0, I98/G98, 1)) | O98: =IF(I98="", "", IF(K98>0, I98/K98, 1)) | P98: =IF(I98="", "", IF(AND(N98>=0.95, O98>=0.95), "SALUDABLE", IF(N98<0.9, "ALERTA RETRASO", "ALERTA SOBRECOSTO")))
A99: 25 | B99: 46259 | C99: WBS-200 | D99: Red de Alcantarillado, Zanjas y Buzones | E99: =SUM('01_PRESUPUESTO_CRONOGRAMA_BASE'!G4:G9) | F99: =SUMIFS('02_CRONOGRAMA_PV_DIARIO'!E:E, '02_CRONOGRAMA_PV_DIARIO'!A:A, A99, '02_CRONOGRAMA_PV_DIARIO'!C:C, C99) | G99: =SUMIFS(F$2:F99, C$2:C99, C99) | H99: =IF(B99 > MAX('04_LOG_FIELD_ENTRIES'!$B:$B), "", SUMIFS('04_LOG_FIELD_ENTRIES'!$J:$J, '04_LOG_FIELD_ENTRIES'!$B:$B, B99, '04_LOG_FIELD_ENTRIES'!$D:$D, C99, '04_LOG_FIELD_ENTRIES'!$K:$K, "EV_PRODUCCION")) | I99: =IF(B99 > MAX('04_LOG_FIELD_ENTRIES'!$B:$B), "", SUMIFS(H$2:H99, C$2:C99, C99)) | J99: =IF(B99 > MAX('04_LOG_FIELD_ENTRIES'!$B:$B), "", SUMIFS('04_LOG_FIELD_ENTRIES'!$J:$J, '04_LOG_FIELD_ENTRIES'!$B:$B, B99, '04_LOG_FIELD_ENTRIES'!$D:$D, C99, '04_LOG_FIELD_ENTRIES'!$K:$K, "AC_*")) | K99: =IF(B99 > MAX('04_LOG_FIELD_ENTRIES'!$B:$B), "", SUMIFS(J$2:J99, C$2:C99, C99)) | L99: =IF(K99="", "", I99-K99) | M99: =IF(I99="", "", I99-G99) | N99: =IF(I99="", "", IF(G99>0, I99/G99, 1)) | O99: =IF(I99="", "", IF(K99>0, I99/K99, 1)) | P99: =IF(I99="", "", IF(AND(N99>=0.95, O99>=0.95), "SALUDABLE", IF(N99<0.9, "ALERTA RETRASO", "ALERTA SOBRECOSTO")))
A100: 25 | B100: 46259 | C100: WBS-300 | D100: Red de Agua Potable y Conexiones Domiciliarias | E100: =SUM('01_PRESUPUESTO_CRONOGRAMA_BASE'!G10:G11) | F100: =SUMIFS('02_CRONOGRAMA_PV_DIARIO'!E:E, '02_CRONOGRAMA_PV_DIARIO'!A:A, A100, '02_CRONOGRAMA_PV_DIARIO'!C:C, C100) | G100: =SUMIFS(F$2:F100, C$2:C100, C100) | H100: =IF(B100 > MAX('04_LOG_FIELD_ENTRIES'!$B:$B), "", SUMIFS('04_LOG_FIELD_ENTRIES'!$J:$J, '04_LOG_FIELD_ENTRIES'!$B:$B, B100, '04_LOG_FIELD_ENTRIES'!$D:$D, C100, '04_LOG_FIELD_ENTRIES'!$K:$K, "EV_PRODUCCION")) | I100: =IF(B100 > MAX('04_LOG_FIELD_ENTRIES'!$B:$B), "", SUMIFS(H$2:H100, C$2:C100, C100)) | J100: =IF(B100 > MAX('04_LOG_FIELD_ENTRIES'!$B:$B), "", SUMIFS('04_LOG_FIELD_ENTRIES'!$J:$J, '04_LOG_FIELD_ENTRIES'!$B:$B, B100, '04_LOG_FIELD_ENTRIES'!$D:$D, C100, '04_LOG_FIELD_ENTRIES'!$K:$K, "AC_*")) | K100: =IF(B100 > MAX('04_LOG_FIELD_ENTRIES'!$B:$B), "", SUMIFS(J$2:J100, C$2:C100, C100)) | L100: =IF(K100="", "", I100-K100) | M100: =IF(I100="", "", I100-G100) | N100: =IF(I100="", "", IF(G100>0, I100/G100, 1)) | O100: =IF(I100="", "", IF(K100>0, I100/K100, 1)) | P100: =IF(I100="", "", IF(AND(N100>=0.95, O100>=0.95), "SALUDABLE", IF(N100<0.9, "ALERTA RETRASO", "ALERTA SOBRECOSTO")))
...

Sheet 04_LOG_FIELD_ENTRIES
A1: ID Registro | B1: Fecha | C1: Rol Responsable | D1: Código WBS | E1: Código Recurso/Partida | F1: Descripción / Detalle | G1: Cantidad Campo | H1: Unidad | I1: P.U. (Busca en Maestro) | J1: Subtotal Monto (S/) | K1: Categoría EVM | L1: Origen HTML
A2: LOG-20260801-001 | B2: 46235 | C2: Tareador (Bildin) | D2: WBS-100 | E2: MO_CAPATAZ | F2: CAPATAZ | G2: 8 | H2: hh | I2: =IFERROR(VLOOKUP(E2, '05_MAESTRO_RECURSOS'!A:D, 4, FALSE), IFERROR(VLOOKUP(E2, '06_MAESTRO_PARTIDAS_EV'!B:F, 5, FALSE), 0)) | J2: =ROUND(G2 * I2, 2) | K2: AC_MO | L2: tareador.html
A3: LOG-20260801-002 | B3: 46235 | C3: Tareador (Bildin) | D3: WBS-100 | E3: MO_OPERARIO | F3: OPERARIO | G3: 16 | H3: hh | I3: =IFERROR(VLOOKUP(E3, '05_MAESTRO_RECURSOS'!A:D, 4, FALSE), IFERROR(VLOOKUP(E3, '06_MAESTRO_PARTIDAS_EV'!B:F, 5, FALSE), 0)) | J3: =ROUND(G3 * I3, 2) | K3: AC_MO | L3: tareador.html
A4: LOG-20260801-003 | B4: 46235 | C4: Tareador (Bildin) | D4: WBS-100 | E4: MO_PEON | F4: PEON | G4: 32 | H4: hh | I4: =IFERROR(VLOOKUP(E4, '05_MAESTRO_RECURSOS'!A:D, 4, FALSE), IFERROR(VLOOKUP(E4, '06_MAESTRO_PARTIDAS_EV'!B:F, 5, FALSE), 0)) | J4: =ROUND(G4 * I4, 2) | K4: AC_MO | L4: tareador.html
A5: LOG-20260801-004 | B5: 46235 | C5: Almacenero | D5: WBS-100 | E5: MAT_ESTACA | F5: ESTACAS Y MADERA PARA TRAZO | G5: 150 | H5: pza | I5: =IFERROR(VLOOKUP(E5, '05_MAESTRO_RECURSOS'!A:D, 4, FALSE), IFERROR(VLOOKUP(E5, '06_MAESTRO_PARTIDAS_EV'!B:F, 5, FALSE), 0)) | J5: =ROUND(G5 * I5, 2) | K5: AC_MAT | L5: almacenero.html
A6: LOG-20260801-005 | B6: 46235 | C6: Almacenero | D6: WBS-100 | E6: MAT_PINTURA | F6: PINTURA SPRAY MARCADOR ZANJA | G6: 10 | H6: gla | I6: =IFERROR(VLOOKUP(E6, '05_MAESTRO_RECURSOS'!A:D, 4, FALSE), IFERROR(VLOOKUP(E6, '06_MAESTRO_PARTIDAS_EV'!B:F, 5, FALSE), 0)) | J6: =ROUND(G6 * I6, 2) | K6: AC_MAT | L6: almacenero.html
A7: LOG-20260801-006 | B7: 46235 | C7: Almacenero | D7: WBS-100 | E7: MAT_CORDEL | F7: CORDEL / NYLON | G7: 100 | H7: m | I7: =IFERROR(VLOOKUP(E7, '05_MAESTRO_RECURSOS'!A:D, 4, FALSE), IFERROR(VLOOKUP(E7, '06_MAESTRO_PARTIDAS_EV'!B:F, 5, FALSE), 0)) | J7: =ROUND(G7 * I7, 2) | K7: AC_MAT | L7: almacenero.html
A8: LOG-20260801-007 | B8: 46235 | C8: Administradora | D8: WBS-100 | E8: SUB_MOVILIZACION | F8: MOVILIZACION MAQUINARIA | G8: 1 | H8: glb | I8: =IFERROR(VLOOKUP(E8, '05_MAESTRO_RECURSOS'!A:D, 4, FALSE), IFERROR(VLOOKUP(E8, '06_MAESTRO_PARTIDAS_EV'!B:F, 5, FALSE), 0)) | J8: =ROUND(G8 * I8, 2) | K8: AC_SUB | L8: administradora.html
A9: LOG-20260801-008 | B9: 46235 | C9: Administradora | D9: WBS-100 | E9: EQ_ESTACION_TOTAL | F9: ESTACION TOTAL TOPOGRAFICA | G9: 8 | H9: hm | I9: =IFERROR(VLOOKUP(E9, '05_MAESTRO_RECURSOS'!A:D, 4, FALSE), IFERROR(VLOOKUP(E9, '06_MAESTRO_PARTIDAS_EV'!B:F, 5, FALSE), 0)) | J9: =ROUND(G9 * I9, 2) | K9: AC_EQP | L9: administradora.html
A10: LOG-20260801-009 | B10: 46235 | C10: Ing. de Campo | D10: WBS-100 | E10: 01.01 | F10: OBRAS PRELIMINARES Y TRABAJOS PROVISIONALES | G10: 0.33 | H10: GLB | I10: =IFERROR(VLOOKUP(E10, '05_MAESTRO_RECURSOS'!A:D, 4, FALSE), IFERROR(VLOOKUP(E10, '06_MAESTRO_PARTIDAS_EV'!B:F, 5, FALSE), 0)) | J10: =ROUND(G10 * I10, 2) | K10: EV_PRODUCCION | L10: ing_campo.html
A11: LOG-20260801-010 | B11: 46235 | C11: Ing. de Campo | D11: WBS-100 | E11: 01.02.01 | F11: TRAZO, NIVELACION Y REPLANTEO DE ZANJAS | G11: 800 | H11: M | I11: =IFERROR(VLOOKUP(E11, '05_MAESTRO_RECURSOS'!A:D, 4, FALSE), IFERROR(VLOOKUP(E11, '06_MAESTRO_PARTIDAS_EV'!B:F, 5, FALSE), 0)) | J11: =ROUND(G11 * I11, 2) | K11: EV_PRODUCCION | L11: ing_campo.html
A12: LOG-20260802-011 | B12: 46236 | C12: Tareador (Bildin) | D12: WBS-100 | E12: MO_CAPATAZ | F12: CAPATAZ | G12: 8 | H12: hh | I12: =IFERROR(VLOOKUP(E12, '05_MAESTRO_RECURSOS'!A:D, 4, FALSE), IFERROR(VLOOKUP(E12, '06_MAESTRO_PARTIDAS_EV'!B:F, 5, FALSE), 0)) | J12: =ROUND(G12 * I12, 2) | K12: AC_MO | L12: tareador.html
A13: LOG-20260802-012 | B13: 46236 | C13: Tareador (Bildin) | D13: WBS-100 | E13: MO_OPERARIO | F13: OPERARIO | G13: 16 | H13: hh | I13: =IFERROR(VLOOKUP(E13, '05_MAESTRO_RECURSOS'!A:D, 4, FALSE), IFERROR(VLOOKUP(E13, '06_MAESTRO_PARTIDAS_EV'!B:F, 5, FALSE), 0)) | J13: =ROUND(G13 * I13, 2) | K13: AC_MO | L13: tareador.html
... A473: LOG-20260815-472 | B473: 46249 | C473: Ing. de Campo | D473: WBS-400 | E473: 01.04.01 | F473: PRUEBA HIDRAULICA Y DESINFECCION DE RED DE AGUA | G473: 0.16 | H473: GLB | I473: =IFERROR(VLOOKUP(E473, '05_MAESTRO_RECURSOS'!A:D, 4, FALSE), IFERROR(VLOOKUP(E473, '06_MAESTRO_PARTIDAS_EV'!B:F, 5, FALSE), 0)) | J473: =ROUND(G473 * I473, 2) | K473: EV_PRODUCCION | L473: ing_campo.html

Sheet 05_MAESTRO_RECURSOS
A1: Código Recurso | B1: Descripción del Recurso / Insumo | C1: Unidad | D1: P.U. Meta Oficial (S/) | E1: Categoría EVM
A2: MO_CAPATAZ | B2: CAPATAZ | C2: hh | D2: 32.5 | E2: AC_MO
A3: MO_OPERARIO | B3: OPERARIO | C3: hh | D3: 26.8 | E3: AC_MO
A4: MO_OFICIAL | B4: OFICIAL | C4: hh | D4: 22.4 | E4: AC_MO
A5: MO_PEON | B5: PEON | C5: hh | D5: 20.1 | E5: AC_MO
A6: MAT_ESTACA | B6: ESTACAS Y MADERA PARA TRAZO | C6: pza | D6: 4.5 | E6: AC_MAT
A7: MAT_PINTURA | B7: PINTURA SPRAY MARCADOR DE ZANJA | C7: gla | D7: 18 | E7: AC_MAT
A8: MAT_CORDEL | B8: CORDEL / NYLON | C8: m | D8: 0.8 | E8: AC_MAT
A9: MAT_ARENA_CAMAS | B9: ARENA FINA SELECCIONADA PARA CAMA E=0.10M | C9: m3 | D9: 45 | E9: AC_MAT
A10: MAT_TUB_PVC_200 | B10: TUBERIA PVC UF DN 200MM SERIE S-20 ALCANTARILLADO | C10: m | D10: 42 | E10: AC_MAT
A11: MAT_LUBRICANTE | B11: LUBRICANTE PARA TUBERIA CON ESPIGA Y CAMPANA | C11: kg | D11: 24 | E11: AC_MAT
A12: MAT_MATERIAL_PR | B12: MATERIAL DE PRÉSTAMO AFIRMADO PARA RELLENO COMPACTADO | C12: m3 | D12: 38 | E12: AC_MAT
A13: MAT_AGUA | B13: AGUA PARA COMPACTACIÓN Y PRUEBAS | C13: m3 | D13: 12 | E13: AC_MAT
... A33: SUB_MONTAJE_BUZON | B33: SUBCONTRATO SERVICIO ASENTADO Y ANCLAJE BUZONES PREFABRICADOS | C33: und | D33: 250 | E33: AC_SUB

Sheet 06_MAESTRO_PARTIDAS_EV
A1: Item Partida | B1: Código Partida | C1: Descripción de la Partida Presupuestal | D1: Unidad | E1: Metrado Presupuesto Meta | F1: P.U. Directo Meta (S/) | G1: Presupuesto Parcial Meta (S/) | H1: Metrado Ejecutado Acumulado (Formulado del Campo) | I1: % Avance Físico Partida | J1: Valor Ganado EV Acumulado (S/) | K1: Saldo Metrado por Ejecutar | L1: Saldo Valor por Ejecutar (S/)
A2: 01.01 | B2: 01.01 | C2: Obras Preliminares y Trabajos Provisionales | D2: GLB | E2: 1 | F2: 8296.4 | G2: =ROUND(E2*F2, 2) | H2: =SUMIFS('04_LOG_FIELD_ENTRIES'!G:G, '04_LOG_FIELD_ENTRIES'!E:E, B2, '04_LOG_FIELD_ENTRIES'!K:K, "EV_PRODUCCION") | I2: =IF(E2>0, H2/E2, 0) | J2: =ROUND(H2*F2, 2) | K2: =E2-H2 | L2: =G2-J2
A3: 01.02.01 | B3: 01.02.01 | C3: Trazo, Nivelación y Replanteo de Zanjas | D3: M | E3: 2400 | F3: 3.35 | G3: =ROUND(E3*F3, 2) | H3: =SUMIFS('04_LOG_FIELD_ENTRIES'!G:G, '04_LOG_FIELD_ENTRIES'!E:E, B3, '04_LOG_FIELD_ENTRIES'!K:K, "EV_PRODUCCION") | I3: =IF(E3>0, H3/E3, 0) | J3: =ROUND(H3*F3, 2) | K3: =E3-H3 | L3: =G3-J3
A4: 01.02.02 | B4: 01.02.02 | C4: Excavación de Zanja H=1.50m - 2.20m a Máquina (Terreno Normal) | D4: M3 | E4: 3840 | F4: 11.66 | G4: =ROUND(E4*F4, 2) | H4: =SUMIFS('04_LOG_FIELD_ENTRIES'!G:G, '04_LOG_FIELD_ENTRIES'!E:E, B4, '04_LOG_FIELD_ENTRIES'!K:K, "EV_PRODUCCION") | I4: =IF(E4>0, H4/E4, 0) | J4: =ROUND(H4*F4, 2) | K4: =E4-H4 | L4: =G4-J4
A5: 01.02.03 | B5: 01.02.03 | C5: Preparación y Colocación de Cama de Arena e=0.10m | D5: M | E5: 2400 | F5: 11.12 | G5: =ROUND(E5*F5, 2) | H5: =SUMIFS('04_LOG_FIELD_ENTRIES'!G:G, '04_LOG_FIELD_ENTRIES'!E:E, B5, '04_LOG_FIELD_ENTRIES'!K:K, "EV_PRODUCCION") | I5: =IF(E5>0, H5/E5, 0) | J5: =ROUND(H5*F5, 2) | K5: =E5-H5 | L5: =G5-J5
A6: 01.02.04 | B6: 01.02.04 | C6: Suministro e Instalación de Tubería PVC UF DN 200mm Serie S-20 para Alcantarillado | D6: M | E6: 1400 | F6: 55.51 | G6: =ROUND(E6*F6, 2) | H6: =SUMIFS('04_LOG_FIELD_ENTRIES'!G:G, '04_LOG_FIELD_ENTRIES'!E:E, B6, '04_LOG_FIELD_ENTRIES'!K:K, "EV_PRODUCCION") | I6: =IF(E6>0, H6/E6, 0) | J6: =ROUND(H6*F6, 2) | K6: =E6-H6 | L6: =G6-J6
A7: 01.02.05 | B7: 01.02.05 | C7: Relleno Compactado de Zanja en Capas de 0.20m con Maquinaria/Plancha | D7: M3 | E7: 3300 | F7: 28.54 | G7: =ROUND(E7*F7, 2) | H7: =SUMIFS('04_LOG_FIELD_ENTRIES'!G:G, '04_LOG_FIELD_ENTRIES'!E:E, B7, '04_LOG_FIELD_ENTRIES'!K:K, "EV_PRODUCCION") | I7: =IF(E7>0, H7/E7, 0) | J7: =ROUND(H7*F7, 2) | K7: =E7-H7 | L7: =G7-J7
A8: 01.02.06 | B8: 01.02.06 | C8: Construcción de Buzones Prefabricados de Concreto h=1.50m - 2.50m (Inc. Marco y Tapa) | D8: UND | E8: 32 | F8: 2500.73 | G8: =ROUND(E8*F8, 2) | H8: =SUMIFS('04_LOG_FIELD_ENTRIES'!G:G, '04_LOG_FIELD_ENTRIES'!E:E, B8, '04_LOG_FIELD_ENTRIES'!K:K, "EV_PRODUCCION") | I8: =IF(E8>0, H8/E8, 0) | J8: =ROUND(H8*F8, 2) | K8: =E8-H8 | L8: =G8-J8
A9: 01.02.07 | B9: 01.02.07 | C9: Conexiones Domiciliarias de Alcantarillado (Caja de Registro + Acometida) | D9: UND | E9: 120 | F9: 405.54 | G9: =ROUND(E9*F9, 2) | H9: =SUMIFS('04_LOG_FIELD_ENTRIES'!G:G, '04_LOG_FIELD_ENTRIES'!E:E, B9, '04_LOG_FIELD_ENTRIES'!K:K, "EV_PRODUCCION") | I9: =IF(E9>0, H9/E9, 0) | J9: =ROUND(H9*F9, 2) | K9: =E9-H9 | L9: =G9-J9
A10: 01.03.01 | B10: 01.03.01 | C10: Suministro e Instalación de Tubería PVC C-10 DN 110mm para Agua Potable | D10: M | E10: 1000 | F10: 38.76 | G10: =ROUND(E10*F10, 2) | H10: =SUMIFS('04_LOG_FIELD_ENTRIES'!G:G, '04_LOG_FIELD_ENTRIES'!E:E, B10, '04_LOG_FIELD_ENTRIES'!K:K, "EV_PRODUCCION") | I10: =IF(E10>0, H10/E10, 0) | J10: =ROUND(H10*F10, 2) | K10: =E10-H10 | L10: =G10-J10
A11: 01.03.02 | B11: 01.03.02 | C11: Conexiones Domiciliarias de Agua Potable (Caja de Agua + Abrazadera + Acometida) | D11: UND | E11: 120 | F11: 156.71 | G11: =ROUND(E11*F11, 2) | H11: =SUMIFS('04_LOG_FIELD_ENTRIES'!G:G, '04_LOG_FIELD_ENTRIES'!E:E, B11, '04_LOG_FIELD_ENTRIES'!K:K, "EV_PRODUCCION") | I11: =IF(E11>0, H11/E11, 0) | J11: =ROUND(H11*F11, 2) | K11: =E11-H11 | L11: =G11-J11
A12: 01.04.01 | B12: 01.04.01 | C12: Pruebas Hidráulicas de Redes de Agua y Alcantarillado + Desinfección | D12: GLB | E12: 1 | F12: 9348.06 | G12: =ROUND(E12*F12, 2) | H12: =SUMIFS('04_LOG_FIELD_ENTRIES'!G:G, '04_LOG_FIELD_ENTRIES'!E:E, B12, '04_LOG_FIELD_ENTRIES'!K:K, "EV_PRODUCCION") | I12: =IF(E12>0, H12/E12, 0) | J12: =ROUND(H12*F12, 2) | K12: =E12-H12 | L12: =G12-J12
A13: TOTAL OBRA | C13: Consolidado Partidas | G13: =SUM(G2:G12) | I13: =IF(G13>0, J13/G13, 0) | J13: =SUM(J2:J12) | L13: =SUM(L2:L12)
