Workbook

Sheet 01_PRESUPUESTO_CRONOGRAMA_BASE
A1: Item | B1: Código WBS | C1: Descripción de la Partida Presupuestal | D1: Unidad | E1: Metrado Meta | F1: P.U. Directo (S/) | G1: Parcial Directo (S/) | H1: Fecha Inicio | I1: Fecha Fin | J1: Duración (Días) | K1: Día Inicio Obra | L1: Día Fin Obra | M1: Tasa PV Diario (S/Día)
A2: 01.01 | B2: WBS-100 | C2: Obras Preliminares y Trabajos Provisionales | D2: GLB | E2: 1 | F2: 8296.4 | G2: =ROUND(E2*F2, 2) -> 8296.4 | H2: 2026-08-01 | I2: 2026-08-14 | J2: =(L2-K2)+1 -> 14 | K2: 1 | L2: 14 | M2: =ROUND(G2/J2, 2) -> 592.6
A3: 01.02.01 | B3: WBS-100 | C3: Trazo, Nivelación y Replanteo de Zanjas | D3: M | E3: 2400 | F3: 3.35 | G3: =ROUND(E3*F3, 2) -> 8040 | H3: 2026-08-01 | I3: 2026-08-14 | J3: =(L3-K3)+1 -> 14 | K3: 1 | L3: 14 | M3: =ROUND(G3/J3, 2) -> 574.29
A4: 01.02.02 | B4: WBS-200 | C4: Excavación de Zanja H=1.50m - 2.20m a Máquina (Terreno Normal) | D4: M3 | E4: 3840 | F4: 11.66 | G4: =ROUND(E4*F4, 2) -> 44774.4 | H4: 2026-08-10 | I4: 2026-08-25 | J4: =(L4-K4)+1 -> 16 | K4: 10 | L4: 25 | M4: =ROUND(G4/J4, 2) -> 2798.4
A5: 01.02.03 | B5: WBS-200 | C5: Preparación y Colocación de Cama de Arena e=0.10m | D5: M | E5: 2400 | F5: 11.12 | G5: =ROUND(E5*F5, 2) -> 26688 | H5: 2026-08-12 | I5: 2026-08-28 | J5: =(L5-K5)+1 -> 17 | K5: 12 | L5: 28 | M5: =ROUND(G5/J5, 2) -> 1569.88
A6: 01.02.04 | B6: WBS-200 | C6: Suministro e Instalación de Tubería PVC UF DN 200mm Serie S-20 para Alcantarillado | D6: M | E6: 1400 | F6: 55.51 | G6: =ROUND(E6*F6, 2) -> 77714 | H6: 2026-08-15 | I6: 2026-08-31 | J6: =(L6-K6)+1 -> 17 | K6: 15 | L6: 31 | M6: =ROUND(G6/J6, 2) -> 4571.41
A7: 01.02.05 | B7: WBS-200 | C7: Relleno Compactado de Zanja en Capas de 0.20m con Maquinaria/Plancha | D7: M3 | E7: 3300 | F7: 28.54 | G7: =ROUND(E7*F7, 2) -> 94182 | H7: 2026-08-18 | I7: 2026-09-05 | J7: =(L7-K7)+1 -> 19 | K7: 18 | L7: 36 | M7: =ROUND(G7/J7, 2) -> 4956.95
A8: 01.02.06 | B8: WBS-200 | C8: Construcción de Buzones Prefabricados de Concreto h=1.50m - 2.50m (Inc. Marco y Tapa) | D8: UND | E8: 32 | F8: 2500.73 | G8: =ROUND(E8*F8, 2) -> 80023.36 | H8: 2026-08-22 | I8: 2026-09-10 | J8: =(L8-K8)+1 -> 20 | K8: 22 | L8: 41 | M8: =ROUND(G8/J8, 2) -> 4001.17
A9: 01.02.07 | B9: WBS-200 | C9: Conexiones Domiciliarias de Alcantarillado (Caja de Registro + Acometida) | D9: UND | E9: 120 | F9: 405.54 | G9: =ROUND(E9*F9, 2) -> 48664.8 | H9: 2026-08-28 | I9: 2026-09-12 | J9: =(L9-K9)+1 -> 16 | K9: 28 | L9: 43 | M9: =ROUND(G9/J9, 2) -> 3041.55
A10: 01.03.01 | B10: WBS-300 | C10: Suministro e Instalación de Tubería PVC C-10 DN 110mm para Agua Potable | D10: M | E10: 1000 | F10: 38.76 | G10: =ROUND(E10*F10, 2) -> 38760 | H10: 2026-08-22 | I10: 2026-09-12 | J10: =(L10-K10)+1 -> 22 | K10: 22 | L10: 43 | M10: =ROUND(G10/J10, 2) -> 1761.82
A11: 01.03.02 | B11: WBS-300 | C11: Conexiones Domiciliarias de Agua Potable (Caja de Agua + Abrazadera + Acometida) | D11: UND | E11: 120 | F11: 156.71 | G11: =ROUND(E11*F11, 2) -> 18805.2 | H11: 2026-09-01 | I11: 2026-09-20 | J11: =(L11-K11)+1 -> 20 | K11: 32 | L11: 51 | M11: =ROUND(G11/J11, 2) -> 940.26
A12: 01.04.01 | B12: WBS-400 | C12: Pruebas Hidráulicas de Redes de Agua y Alcantarillado + Desinfección | D12: GLB | E12: 1 | F12: 9348.06 | G12: =ROUND(E12*F12, 2) -> 9348.06 | H12: 2026-09-17 | I12: 2026-09-29 | J12: =(L12-K12)+1 -> 13 | K12: 48 | L12: 60 | M12: =ROUND(G12/J12, 2) -> 719.08
C13: COSTO DIRECTO TOTAL (S/) | G13: =SUM(G2:G12) -> 455296.22
C14: GASTOS GENERALES (10.00%) | G14: =ROUND(G13*0.1, 2) -> 45529.62
C15: UTILIDAD (8.00%) | G15: =ROUND(G13*0.08, 2) -> 36423.7
C16: SUB TOTAL / VALOR VENTA (SIN IGV) | G16: =SUM(G13:G15) -> 537249.54
C17: IMPUESTO GENERAL A LAS VENTAS (IGV 18%) | G17: =ROUND(G16*0.18, 2) -> 96704.92
C18: PRECIO TOTAL COMERCIAL DE OBRA (CON IGV) | G18: =G16+G17 -> 633954.46

Sheet 02_CRONOGRAMA_PV_DIARIO
A1: N° Día Obra | B1: Fecha Obra | C1: Código WBS | D1: Nombre Frente WBS | E1: PV Diario Programado (S/) | F1: PV Acumulado WBS (S/)
A2: 1 | B2: 2026-08-01 | C2: WBS-100 | D2: Obras Preliminares, Trazo y Movilización | E2: =IF(AND(A2>='01_PRESUPUESTO_CRONOGRAMA_BASE'!K2, A2<='01_PRESUPUESTO_CRONOGRAMA_BASE'!L2), '01_PRESUPUESTO_CRONOGRAMA_BASE'!M2, 0) + IF(AND(A2>='01_PRESUPUESTO_CRONOGRAMA_BASE'!K3, A2<='01_PRESUPUESTO_CRONOGRAMA_BASE'!L3), '01_PRESUPUESTO_CRONOGRAMA_BASE'!M3, 0) -> 1166.89 | F2: =SUMIFS(E$2:E2, C$2:C2, C2) -> 1166.89
A3: 1 | B3: 2026-08-01 | C3: WBS-200 | D3: Red de Alcantarillado, Zanjas y Buzones | E3: =IF(AND(A3>='01_PRESUPUESTO_CRONOGRAMA_BASE'!K4, A3<='01_PRESUPUESTO_CRONOGRAMA_BASE'!L4), '01_PRESUPUESTO_CRONOGRAMA_BASE'!M4, 0) + IF(AND(A3>='01_PRESUPUESTO_CRONOGRAMA_BASE'!K5, A3<='01_PRESUPUESTO_CRONOGRAMA_BASE'!L5), '01_PRESUPUESTO_CRONOGRAMA_BASE'!M5, 0) + IF(AND(A3>='01_PRESUPUESTO_CRONOGRAMA_BASE'!K6, A3<='01_PRESUPUESTO_CRONOGRAMA_BASE'!L6), '01_PRESUPUESTO_CRONOGRAMA_BASE'!M6, 0) + IF(AND(A3>='01_PRESUPUESTO_CRONOGRAMA_BASE'!K7, A3<='01_PRESUPUESTO_CRONOGRAMA_BASE'!L7), '01_PRESUPUESTO_CRONOGRAMA_BASE'!M7, 0) + IF(AND(A3>='01_PRESUPUESTO_CRONOGRAMA_BASE'!K8, A3<='01_PRESUPUESTO_CRONOGRAMA_BASE'!L8), '01_PRESUPUESTO_CRONOGRAMA_BASE'!M8, 0) + IF(AND(A3>='01_PRESUPUESTO_CRONOGRAMA_BASE'!K9, A3<='01_PRESUPUESTO_CRONOGRAMA_BASE'!L9), '01_PRESUPUESTO_CRONOGRAMA_BASE'!M9, 0) -> 0 | F3: =SUMIFS(E$2:E3, C$2:C3, C3) -> 0
A4: 1 | B4: 2026-08-01 | C4: WBS-300 | D4: Red de Agua Potable y Conexiones Domiciliarias | E4: =IF(AND(A4>='01_PRESUPUESTO_CRONOGRAMA_BASE'!K10, A4<='01_PRESUPUESTO_CRONOGRAMA_BASE'!L10), '01_PRESUPUESTO_CRONOGRAMA_BASE'!M10, 0) + IF(AND(A4>='01_PRESUPUESTO_CRONOGRAMA_BASE'!K11, A4<='01_PRESUPUESTO_CRONOGRAMA_BASE'!L11), '01_PRESUPUESTO_CRONOGRAMA_BASE'!M11, 0) -> 0 | F4: =SUMIFS(E$2:E4, C$2:C4, C4) -> 0
A5: 1 | B5: 2026-08-01 | C5: WBS-400 | D5: Pruebas Hidráulicas, Desinfección y Entrega | E5: =IF(AND(A5>='01_PRESUPUESTO_CRONOGRAMA_BASE'!K12, A5<='01_PRESUPUESTO_CRONOGRAMA_BASE'!L12), '01_PRESUPUESTO_CRONOGRAMA_BASE'!M12, 0) -> 0 | F5: =SUMIFS(E$2:E5, C$2:C5, C5) -> 0
A6: 2 | B6: 2026-08-02 | C6: WBS-100 | D6: Obras Preliminares, Trazo y Movilización | E6: =IF(AND(A6>='01_PRESUPUESTO_CRONOGRAMA_BASE'!K2, A6<='01_PRESUPUESTO_CRONOGRAMA_BASE'!L2), '01_PRESUPUESTO_CRONOGRAMA_BASE'!M2, 0) + IF(AND(A6>='01_PRESUPUESTO_CRONOGRAMA_BASE'!K3, A6<='01_PRESUPUESTO_CRONOGRAMA_BASE'!L3), '01_PRESUPUESTO_CRONOGRAMA_BASE'!M3, 0) -> 1166.89 | F6: =SUMIFS(E$2:E6, C$2:C6, C6) -> 2333.78
A7: 2 | B7: 2026-08-02 | C7: WBS-200 | D7: Red de Alcantarillado, Zanjas y Buzones | E7: =IF(AND(A7>='01_PRESUPUESTO_CRONOGRAMA_BASE'!K4, A7<='01_PRESUPUESTO_CRONOGRAMA_BASE'!L4), '01_PRESUPUESTO_CRONOGRAMA_BASE'!M4, 0) + IF(AND(A7>='01_PRESUPUESTO_CRONOGRAMA_BASE'!K5, A7<='01_PRESUPUESTO_CRONOGRAMA_BASE'!L5), '01_PRESUPUESTO_CRONOGRAMA_BASE'!M5, 0) + IF(AND(A7>='01_PRESUPUESTO_CRONOGRAMA_BASE'!K6, A7<='01_PRESUPUESTO_CRONOGRAMA_BASE'!L6), '01_PRESUPUESTO_CRONOGRAMA_BASE'!M6, 0) + IF(AND(A7>='01_PRESUPUESTO_CRONOGRAMA_BASE'!K7, A7<='01_PRESUPUESTO_CRONOGRAMA_BASE'!L7), '01_PRESUPUESTO_CRONOGRAMA_BASE'!M7, 0) + IF(AND(A7>='01_PRESUPUESTO_CRONOGRAMA_BASE'!K8, A7<='01_PRESUPUESTO_CRONOGRAMA_BASE'!L8), '01_PRESUPUESTO_CRONOGRAMA_BASE'!M8, 0) + IF(AND(A7>='01_PRESUPUESTO_CRONOGRAMA_BASE'!K9, A7<='01_PRESUPUESTO_CRONOGRAMA_BASE'!L9), '01_PRESUPUESTO_CRONOGRAMA_BASE'!M9, 0) -> 0 | F7: =SUMIFS(E$2:E7, C$2:C7, C7) -> 0
A8: 2 | B8: 2026-08-02 | C8: WBS-300 | D8: Red de Agua Potable y Conexiones Domiciliarias | E8: =IF(AND(A8>='01_PRESUPUESTO_CRONOGRAMA_BASE'!K10, A8<='01_PRESUPUESTO_CRONOGRAMA_BASE'!L10), '01_PRESUPUESTO_CRONOGRAMA_BASE'!M10, 0) + IF(AND(A8>='01_PRESUPUESTO_CRONOGRAMA_BASE'!K11, A8<='01_PRESUPUESTO_CRONOGRAMA_BASE'!L11), '01_PRESUPUESTO_CRONOGRAMA_BASE'!M11, 0) -> 0 | F8: =SUMIFS(E$2:E8, C$2:C8, C8) -> 0
A9: 2 | B9: 2026-08-02 | C9: WBS-400 | D9: Pruebas Hidráulicas, Desinfección y Entrega | E9: =IF(AND(A9>='01_PRESUPUESTO_CRONOGRAMA_BASE'!K12, A9<='01_PRESUPUESTO_CRONOGRAMA_BASE'!L12), '01_PRESUPUESTO_CRONOGRAMA_BASE'!M12, 0) -> 0 | F9: =SUMIFS(E$2:E9, C$2:C9, C9) -> 0
A10: 3 | B10: 2026-08-03 | C10: WBS-100 | D10: Obras Preliminares, Trazo y Movilización | E10: =IF(AND(A10>='01_PRESUPUESTO_CRONOGRAMA_BASE'!K2, A10<='01_PRESUPUESTO_CRONOGRAMA_BASE'!L2), '01_PRESUPUESTO_CRONOGRAMA_BASE'!M2, 0) + IF(AND(A10>='01_PRESUPUESTO_CRONOGRAMA_BASE'!K3, A10<='01_PRESUPUESTO_CRONOGRAMA_BASE'!L3), '01_PRESUPUESTO_CRONOGRAMA_BASE'!M3, 0) -> 1166.89 | F10: =SUMIFS(E$2:E10, C$2:C10, C10) -> 3500.67
A11: 3 | B11: 2026-08-03 | C11: WBS-200 | D11: Red de Alcantarillado, Zanjas y Buzones | E11: =IF(AND(A11>='01_PRESUPUESTO_CRONOGRAMA_BASE'!K4, A11<='01_PRESUPUESTO_CRONOGRAMA_BASE'!L4), '01_PRESUPUESTO_CRONOGRAMA_BASE'!M4, 0) + IF(AND(A11>='01_PRESUPUESTO_CRONOGRAMA_BASE'!K5, A11<='01_PRESUPUESTO_CRONOGRAMA_BASE'!L5), '01_PRESUPUESTO_CRONOGRAMA_BASE'!M5, 0) + IF(AND(A11>='01_PRESUPUESTO_CRONOGRAMA_BASE'!K6, A11<='01_PRESUPUESTO_CRONOGRAMA_BASE'!L6), '01_PRESUPUESTO_CRONOGRAMA_BASE'!M6, 0) + IF(AND(A11>='01_PRESUPUESTO_CRONOGRAMA_BASE'!K7, A11<='01_PRESUPUESTO_CRONOGRAMA_BASE'!L7), '01_PRESUPUESTO_CRONOGRAMA_BASE'!M7, 0) + IF(AND(A11>='01_PRESUPUESTO_CRONOGRAMA_BASE'!K8, A11<='01_PRESUPUESTO_CRONOGRAMA_BASE'!L8), '01_PRESUPUESTO_CRONOGRAMA_BASE'!M8, 0) + IF(AND(A11>='01_PRESUPUESTO_CRONOGRAMA_BASE'!K9, A11<='01_PRESUPUESTO_CRONOGRAMA_BASE'!L9), '01_PRESUPUESTO_CRONOGRAMA_BASE'!M9, 0) -> 0 | F11: =SUMIFS(E$2:E11, C$2:C11, C11) -> 0
A12: 3 | B12: 2026-08-03 | C12: WBS-300 | D12: Red de Agua Potable y Conexiones Domiciliarias | E12: =IF(AND(A12>='01_PRESUPUESTO_CRONOGRAMA_BASE'!K10, A12<='01_PRESUPUESTO_CRONOGRAMA_BASE'!L10), '01_PRESUPUESTO_CRONOGRAMA_BASE'!M10, 0) + IF(AND(A12>='01_PRESUPUESTO_CRONOGRAMA_BASE'!K11, A12<='01_PRESUPUESTO_CRONOGRAMA_BASE'!L11), '01_PRESUPUESTO_CRONOGRAMA_BASE'!M11, 0) -> 0 | F12: =SUMIFS(E$2:E12, C$2:C12, C12) -> 0
A13: 3 | B13: 2026-08-03 | C13: WBS-400 | D13: Pruebas Hidráulicas, Desinfección y Entrega | E13: =IF(AND(A13>='01_PRESUPUESTO_CRONOGRAMA_BASE'!K12, A13<='01_PRESUPUESTO_CRONOGRAMA_BASE'!L12), '01_PRESUPUESTO_CRONOGRAMA_BASE'!M12, 0) -> 0 | F13: =SUMIFS(E$2:E13, C$2:C13, C13) -> 0
A14: 4 | B14: 2026-08-04 | C14: WBS-100 | D14: Obras Preliminares, Trazo y Movilización | E14: =IF(AND(A14>='01_PRESUPUESTO_CRONOGRAMA_BASE'!K2, A14<='01_PRESUPUESTO_CRONOGRAMA_BASE'!L2), '01_PRESUPUESTO_CRONOGRAMA_BASE'!M2, 0) + IF(AND(A14>='01_PRESUPUESTO_CRONOGRAMA_BASE'!K3, A14<='01_PRESUPUESTO_CRONOGRAMA_BASE'!L3), '01_PRESUPUESTO_CRONOGRAMA_BASE'!M3, 0) -> 1166.89 | F14: =SUMIFS(E$2:E14, C$2:C14, C14) -> 4667.56
A15: 4 | B15: 2026-08-04 | C15: WBS-200 | D15: Red de Alcantarillado, Zanjas y Buzones | E15: =IF(AND(A15>='01_PRESUPUESTO_CRONOGRAMA_BASE'!K4, A15<='01_PRESUPUESTO_CRONOGRAMA_BASE'!L4), '01_PRESUPUESTO_CRONOGRAMA_BASE'!M4, 0) + IF(AND(A15>='01_PRESUPUESTO_CRONOGRAMA_BASE'!K5, A15<='01_PRESUPUESTO_CRONOGRAMA_BASE'!L5), '01_PRESUPUESTO_CRONOGRAMA_BASE'!M5, 0) + IF(AND(A15>='01_PRESUPUESTO_CRONOGRAMA_BASE'!K6, A15<='01_PRESUPUESTO_CRONOGRAMA_BASE'!L6), '01_PRESUPUESTO_CRONOGRAMA_BASE'!M6, 0) + IF(AND(A15>='01_PRESUPUESTO_CRONOGRAMA_BASE'!K7, A15<='01_PRESUPUESTO_CRONOGRAMA_BASE'!L7), '01_PRESUPUESTO_CRONOGRAMA_BASE'!M7, 0) + IF(AND(A15>='01_PRESUPUESTO_CRONOGRAMA_BASE'!K8, A15<='01_PRESUPUESTO_CRONOGRAMA_BASE'!L8), '01_PRESUPUESTO_CRONOGRAMA_BASE'!M8, 0) + IF(AND(A15>='01_PRESUPUESTO_CRONOGRAMA_BASE'!K9, A15<='01_PRESUPUESTO_CRONOGRAMA_BASE'!L9), '01_PRESUPUESTO_CRONOGRAMA_BASE'!M9, 0) -> 0 | F15: =SUMIFS(E$2:E15, C$2:C15, C15) -> 0
A16: 4 | B16: 2026-08-04 | C16: WBS-300 | D16: Red de Agua Potable y Conexiones Domiciliarias | E16: =IF(AND(A16>='01_PRESUPUESTO_CRONOGRAMA_BASE'!K10, A16<='01_PRESUPUESTO_CRONOGRAMA_BASE'!L10), '01_PRESUPUESTO_CRONOGRAMA_BASE'!M10, 0) + IF(AND(A16>='01_PRESUPUESTO_CRONOGRAMA_BASE'!K11, A16<='01_PRESUPUESTO_CRONOGRAMA_BASE'!L11), '01_PRESUPUESTO_CRONOGRAMA_BASE'!M11, 0) -> 0 | F16: =SUMIFS(E$2:E16, C$2:C16, C16) -> 0
A17: 4 | B17: 2026-08-04 | C17: WBS-400 | D17: Pruebas Hidráulicas, Desinfección y Entrega | E17: =IF(AND(A17>='01_PRESUPUESTO_CRONOGRAMA_BASE'!K12, A17<='01_PRESUPUESTO_CRONOGRAMA_BASE'!L12), '01_PRESUPUESTO_CRONOGRAMA_BASE'!M12, 0) -> 0 | F17: =SUMIFS(E$2:E17, C$2:C17, C17) -> 0
A18: 5 | B18: 2026-08-05 | C18: WBS-100 | D18: Obras Preliminares, Trazo y Movilización | E18: =IF(AND(A18>='01_PRESUPUESTO_CRONOGRAMA_BASE'!K2, A18<='01_PRESUPUESTO_CRONOGRAMA_BASE'!L2), '01_PRESUPUESTO_CRONOGRAMA_BASE'!M2, 0) + IF(AND(A18>='01_PRESUPUESTO_CRONOGRAMA_BASE'!K3, A18<='01_PRESUPUESTO_CRONOGRAMA_BASE'!L3), '01_PRESUPUESTO_CRONOGRAMA_BASE'!M3, 0) -> 1166.89 | F18: =SUMIFS(E$2:E18, C$2:C18, C18) -> 5834.45
A19: 5 | B19: 2026-08-05 | C19: WBS-200 | D19: Red de Alcantarillado, Zanjas y Buzones | E19: =IF(AND(A19>='01_PRESUPUESTO_CRONOGRAMA_BASE'!K4, A19<='01_PRESUPUESTO_CRONOGRAMA_BASE'!L4), '01_PRESUPUESTO_CRONOGRAMA_BASE'!M4, 0) + IF(AND(A19>='01_PRESUPUESTO_CRONOGRAMA_BASE'!K5, A19<='01_PRESUPUESTO_CRONOGRAMA_BASE'!L5), '01_PRESUPUESTO_CRONOGRAMA_BASE'!M5, 0) + IF(AND(A19>='01_PRESUPUESTO_CRONOGRAMA_BASE'!K6, A19<='01_PRESUPUESTO_CRONOGRAMA_BASE'!L6), '01_PRESUPUESTO_CRONOGRAMA_BASE'!M6, 0) + IF(AND(A19>='01_PRESUPUESTO_CRONOGRAMA_BASE'!K7, A19<='01_PRESUPUESTO_CRONOGRAMA_BASE'!L7), '01_PRESUPUESTO_CRONOGRAMA_BASE'!M7, 0) + IF(AND(A19>='01_PRESUPUESTO_CRONOGRAMA_BASE'!K8, A19<='01_PRESUPUESTO_CRONOGRAMA_BASE'!L8), '01_PRESUPUESTO_CRONOGRAMA_BASE'!M8, 0) + IF(AND(A19>='01_PRESUPUESTO_CRONOGRAMA_BASE'!K9, A19<='01_PRESUPUESTO_CRONOGRAMA_BASE'!L9), '01_PRESUPUESTO_CRONOGRAMA_BASE'!M9, 0) -> 0 | F19: =SUMIFS(E$2:E19, C$2:C19, C19) -> 0
A20: 5 | B20: 2026-08-05 | C20: WBS-300 | D20: Red de Agua Potable y Conexiones Domiciliarias | E20: =IF(AND(A20>='01_PRESUPUESTO_CRONOGRAMA_BASE'!K10, A20<='01_PRESUPUESTO_CRONOGRAMA_BASE'!L10), '01_PRESUPUESTO_CRONOGRAMA_BASE'!M10, 0) + IF(AND(A20>='01_PRESUPUESTO_CRONOGRAMA_BASE'!K11, A20<='01_PRESUPUESTO_CRONOGRAMA_BASE'!L11), '01_PRESUPUESTO_CRONOGRAMA_BASE'!M11, 0) -> 0 | F20: =SUMIFS(E$2:E20, C$2:C20, C20) -> 0
A21: 5 | B21: 2026-08-05 | C21: WBS-400 | D21: Pruebas Hidráulicas, Desinfección y Entrega | E21: =IF(AND(A21>='01_PRESUPUESTO_CRONOGRAMA_BASE'!K12, A21<='01_PRESUPUESTO_CRONOGRAMA_BASE'!L12), '01_PRESUPUESTO_CRONOGRAMA_BASE'!M12, 0) -> 0 | F21: =SUMIFS(E$2:E21, C$2:C21, C21) -> 0
A22: 6 | B22: 2026-08-06 | C22: WBS-100 | D22: Obras Preliminares, Trazo y Movilización | E22: =IF(AND(A22>='01_PRESUPUESTO_CRONOGRAMA_BASE'!K2, A22<='01_PRESUPUESTO_CRONOGRAMA_BASE'!L2), '01_PRESUPUESTO_CRONOGRAMA_BASE'!M2, 0) + IF(AND(A22>='01_PRESUPUESTO_CRONOGRAMA_BASE'!K3, A22<='01_PRESUPUESTO_CRONOGRAMA_BASE'!L3), '01_PRESUPUESTO_CRONOGRAMA_BASE'!M3, 0) -> 1166.89 | F22: =SUMIFS(E$2:E22, C$2:C22, C22) -> 7001.34
A23: 6 | B23: 2026-08-06 | C23: WBS-200 | D23: Red de Alcantarillado, Zanjas y Buzones | E23: =IF(AND(A23>='01_PRESUPUESTO_CRONOGRAMA_BASE'!K4, A23<='01_PRESUPUESTO_CRONOGRAMA_BASE'!L4), '01_PRESUPUESTO_CRONOGRAMA_BASE'!M4, 0) + IF(AND(A23>='01_PRESUPUESTO_CRONOGRAMA_BASE'!K5, A23<='01_PRESUPUESTO_CRONOGRAMA_BASE'!L5), '01_PRESUPUESTO_CRONOGRAMA_BASE'!M5, 0) + IF(AND(A23>='01_PRESUPUESTO_CRONOGRAMA_BASE'!K6, A23<='01_PRESUPUESTO_CRONOGRAMA_BASE'!L6), '01_PRESUPUESTO_CRONOGRAMA_BASE'!M6, 0) + IF(AND(A23>='01_PRESUPUESTO_CRONOGRAMA_BASE'!K7, A23<='01_PRESUPUESTO_CRONOGRAMA_BASE'!L7), '01_PRESUPUESTO_CRONOGRAMA_BASE'!M7, 0) + IF(AND(A23>='01_PRESUPUESTO_CRONOGRAMA_BASE'!K8, A23<='01_PRESUPUESTO_CRONOGRAMA_BASE'!L8), '01_PRESUPUESTO_CRONOGRAMA_BASE'!M8, 0) + IF(AND(A23>='01_PRESUPUESTO_CRONOGRAMA_BASE'!K9, A23<='01_PRESUPUESTO_CRONOGRAMA_BASE'!L9), '01_PRESUPUESTO_CRONOGRAMA_BASE'!M9, 0) -> 0 | F23: =SUMIFS(E$2:E23, C$2:C23, C23) -> 0
A24: 6 | B24: 2026-08-06 | C24: WBS-300 | D24: Red de Agua Potable y Conexiones Domiciliarias | E24: =IF(AND(A24>='01_PRESUPUESTO_CRONOGRAMA_BASE'!K10, A24<='01_PRESUPUESTO_CRONOGRAMA_BASE'!L10), '01_PRESUPUESTO_CRONOGRAMA_BASE'!M10, 0) + IF(AND(A24>='01_PRESUPUESTO_CRONOGRAMA_BASE'!K11, A24<='01_PRESUPUESTO_CRONOGRAMA_BASE'!L11), '01_PRESUPUESTO_CRONOGRAMA_BASE'!M11, 0) -> 0 | F24: =SUMIFS(E$2:E24, C$2:C24, C24) -> 0
A25: 6 | B25: 2026-08-06 | C25: WBS-400 | D25: Pruebas Hidráulicas, Desinfección y Entrega | E25: =IF(AND(A25>='01_PRESUPUESTO_CRONOGRAMA_BASE'!K12, A25<='01_PRESUPUESTO_CRONOGRAMA_BASE'!L12), '01_PRESUPUESTO_CRONOGRAMA_BASE'!M12, 0) -> 0 | F25: =SUMIFS(E$2:E25, C$2:C25, C25) -> 0
A26: 7 | B26: 2026-08-07 | C26: WBS-100 | D26: Obras Preliminares, Trazo y Movilización | E26: =IF(AND(A26>='01_PRESUPUESTO_CRONOGRAMA_BASE'!K2, A26<='01_PRESUPUESTO_CRONOGRAMA_BASE'!L2), '01_PRESUPUESTO_CRONOGRAMA_BASE'!M2, 0) + IF(AND(A26>='01_PRESUPUESTO_CRONOGRAMA_BASE'!K3, A26<='01_PRESUPUESTO_CRONOGRAMA_BASE'!L3), '01_PRESUPUESTO_CRONOGRAMA_BASE'!M3, 0) -> 1166.89 | F26: =SUMIFS(E$2:E26, C$2:C26, C26) -> 8168.23
A27: 7 | B27: 2026-08-07 | C27: WBS-200 | D27: Red de Alcantarillado, Zanjas y Buzones | E27: =IF(AND(A27>='01_PRESUPUESTO_CRONOGRAMA_BASE'!K4, A27<='01_PRESUPUESTO_CRONOGRAMA_BASE'!L4), '01_PRESUPUESTO_CRONOGRAMA_BASE'!M4, 0) + IF(AND(A27>='01_PRESUPUESTO_CRONOGRAMA_BASE'!K5, A27<='01_PRESUPUESTO_CRONOGRAMA_BASE'!L5), '01_PRESUPUESTO_CRONOGRAMA_BASE'!M5, 0) + IF(AND(A27>='01_PRESUPUESTO_CRONOGRAMA_BASE'!K6, A27<='01_PRESUPUESTO_CRONOGRAMA_BASE'!L6), '01_PRESUPUESTO_CRONOGRAMA_BASE'!M6, 0) + IF(AND(A27>='01_PRESUPUESTO_CRONOGRAMA_BASE'!K7, A27<='01_PRESUPUESTO_CRONOGRAMA_BASE'!L7), '01_PRESUPUESTO_CRONOGRAMA_BASE'!M7, 0) + IF(AND(A27>='01_PRESUPUESTO_CRONOGRAMA_BASE'!K8, A27<='01_PRESUPUESTO_CRONOGRAMA_BASE'!L8), '01_PRESUPUESTO_CRONOGRAMA_BASE'!M8, 0) + IF(AND(A27>='01_PRESUPUESTO_CRONOGRAMA_BASE'!K9, A27<='01_PRESUPUESTO_CRONOGRAMA_BASE'!L9), '01_PRESUPUESTO_CRONOGRAMA_BASE'!M9, 0) -> 0 | F27: =SUMIFS(E$2:E27, C$2:C27, C27) -> 0
A28: 7 | B28: 2026-08-07 | C28: WBS-300 | D28: Red de Agua Potable y Conexiones Domiciliarias | E28: =IF(AND(A28>='01_PRESUPUESTO_CRONOGRAMA_BASE'!K10, A28<='01_PRESUPUESTO_CRONOGRAMA_BASE'!L10), '01_PRESUPUESTO_CRONOGRAMA_BASE'!M10, 0) + IF(AND(A28>='01_PRESUPUESTO_CRONOGRAMA_BASE'!K11, A28<='01_PRESUPUESTO_CRONOGRAMA_BASE'!L11), '01_PRESUPUESTO_CRONOGRAMA_BASE'!M11, 0) -> 0 | F28: =SUMIFS(E$2:E28, C$2:C28, C28) -> 0
A29: 7 | B29: 2026-08-07 | C29: WBS-400 | D29: Pruebas Hidráulicas, Desinfección y Entrega | E29: =IF(AND(A29>='01_PRESUPUESTO_CRONOGRAMA_BASE'!K12, A29<='01_PRESUPUESTO_CRONOGRAMA_BASE'!L12), '01_PRESUPUESTO_CRONOGRAMA_BASE'!M12, 0) -> 0 | F29: =SUMIFS(E$2:E29, C$2:C29, C29) -> 0
A30: 8 | B30: 2026-08-08 | C30: WBS-100 | D30: Obras Preliminares, Trazo y Movilización | E30: =IF(AND(A30>='01_PRESUPUESTO_CRONOGRAMA_BASE'!K2, A30<='01_PRESUPUESTO_CRONOGRAMA_BASE'!L2), '01_PRESUPUESTO_CRONOGRAMA_BASE'!M2, 0) + IF(AND(A30>='01_PRESUPUESTO_CRONOGRAMA_BASE'!K3, A30<='01_PRESUPUESTO_CRONOGRAMA_BASE'!L3), '01_PRESUPUESTO_CRONOGRAMA_BASE'!M3, 0) -> 1166.89 | F30: =SUMIFS(E$2:E30, C$2:C30, C30) -> 9335.12
A31: 8 | B31: 2026-08-08 | C31: WBS-200 | D31: Red de Alcantarillado, Zanjas y Buzones | E31: =IF(AND(A31>='01_PRESUPUESTO_CRONOGRAMA_BASE'!K4, A31<='01_PRESUPUESTO_CRONOGRAMA_BASE'!L4), '01_PRESUPUESTO_CRONOGRAMA_BASE'!M4, 0) + IF(AND(A31>='01_PRESUPUESTO_CRONOGRAMA_BASE'!K5, A31<='01_PRESUPUESTO_CRONOGRAMA_BASE'!L5), '01_PRESUPUESTO_CRONOGRAMA_BASE'!M5, 0) + IF(AND(A31>='01_PRESUPUESTO_CRONOGRAMA_BASE'!K6, A31<='01_PRESUPUESTO_CRONOGRAMA_BASE'!L6), '01_PRESUPUESTO_CRONOGRAMA_BASE'!M6, 0) + IF(AND(A31>='01_PRESUPUESTO_CRONOGRAMA_BASE'!K7, A31<='01_PRESUPUESTO_CRONOGRAMA_BASE'!L7), '01_PRESUPUESTO_CRONOGRAMA_BASE'!M7, 0) + IF(AND(A31>='01_PRESUPUESTO_CRONOGRAMA_BASE'!K8, A31<='01_PRESUPUESTO_CRONOGRAMA_BASE'!L8), '01_PRESUPUESTO_CRONOGRAMA_BASE'!M8, 0) + IF(AND(A31>='01_PRESUPUESTO_CRONOGRAMA_BASE'!K9, A31<='01_PRESUPUESTO_CRONOGRAMA_BASE'!L9), '01_PRESUPUESTO_CRONOGRAMA_BASE'!M9, 0) -> 0 | F31: =SUMIFS(E$2:E31, C$2:C31, C31) -> 0
A32: 8 | B32: 2026-08-08 | C32: WBS-300 | D32: Red de Agua Potable y Conexiones Domiciliarias | E32: =IF(AND(A32>='01_PRESUPUESTO_CRONOGRAMA_BASE'!K10, A32<='01_PRESUPUESTO_CRONOGRAMA_BASE'!L10), '01_PRESUPUESTO_CRONOGRAMA_BASE'!M10, 0) + IF(AND(A32>='01_PRESUPUESTO_CRONOGRAMA_BASE'!K11, A32<='01_PRESUPUESTO_CRONOGRAMA_BASE'!L11), '01_PRESUPUESTO_CRONOGRAMA_BASE'!M11, 0) -> 0 | F32: =SUMIFS(E$2:E32, C$2:C32, C32) -> 0
A33: 8 | B33: 2026-08-08 | C33: WBS-400 | D33: Pruebas Hidráulicas, Desinfección y Entrega | E33: =IF(AND(A33>='01_PRESUPUESTO_CRONOGRAMA_BASE'!K12, A33<='01_PRESUPUESTO_CRONOGRAMA_BASE'!L12), '01_PRESUPUESTO_CRONOGRAMA_BASE'!M12, 0) -> 0 | F33: =SUMIFS(E$2:E33, C$2:C33, C33) -> 0
A34: 9 | B34: 2026-08-09 | C34: WBS-100 | D34: Obras Preliminares, Trazo y Movilización | E34: =IF(AND(A34>='01_PRESUPUESTO_CRONOGRAMA_BASE'!K2, A34<='01_PRESUPUESTO_CRONOGRAMA_BASE'!L2), '01_PRESUPUESTO_CRONOGRAMA_BASE'!M2, 0) + IF(AND(A34>='01_PRESUPUESTO_CRONOGRAMA_BASE'!K3, A34<='01_PRESUPUESTO_CRONOGRAMA_BASE'!L3), '01_PRESUPUESTO_CRONOGRAMA_BASE'!M3, 0) -> 1166.89 | F34: =SUMIFS(E$2:E34, C$2:C34, C34) -> 10502.01
A35: 9 | B35: 2026-08-09 | C35: WBS-200 | D35: Red de Alcantarillado, Zanjas y Buzones | E35: =IF(AND(A35>='01_PRESUPUESTO_CRONOGRAMA_BASE'!K4, A35<='01_PRESUPUESTO_CRONOGRAMA_BASE'!L4), '01_PRESUPUESTO_CRONOGRAMA_BASE'!M4, 0) + IF(AND(A35>='01_PRESUPUESTO_CRONOGRAMA_BASE'!K5, A35<='01_PRESUPUESTO_CRONOGRAMA_BASE'!L5), '01_PRESUPUESTO_CRONOGRAMA_BASE'!M5, 0) + IF(AND(A35>='01_PRESUPUESTO_CRONOGRAMA_BASE'!K6, A35<='01_PRESUPUESTO_CRONOGRAMA_BASE'!L6), '01_PRESUPUESTO_CRONOGRAMA_BASE'!M6, 0) + IF(AND(A35>='01_PRESUPUESTO_CRONOGRAMA_BASE'!K7, A35<='01_PRESUPUESTO_CRONOGRAMA_BASE'!L7), '01_PRESUPUESTO_CRONOGRAMA_BASE'!M7, 0) + IF(AND(A35>='01_PRESUPUESTO_CRONOGRAMA_BASE'!K8, A35<='01_PRESUPUESTO_CRONOGRAMA_BASE'!L8), '01_PRESUPUESTO_CRONOGRAMA_BASE'!M8, 0) + IF(AND(A35>='01_PRESUPUESTO_CRONOGRAMA_BASE'!K9, A35<='01_PRESUPUESTO_CRONOGRAMA_BASE'!L9), '01_PRESUPUESTO_CRONOGRAMA_BASE'!M9, 0) -> 0 | F35: =SUMIFS(E$2:E35, C$2:C35, C35) -> 0
A36: 9 | B36: 2026-08-09 | C36: WBS-300 | D36: Red de Agua Potable y Conexiones Domiciliarias | E36: =IF(AND(A36>='01_PRESUPUESTO_CRONOGRAMA_BASE'!K10, A36<='01_PRESUPUESTO_CRONOGRAMA_BASE'!L10), '01_PRESUPUESTO_CRONOGRAMA_BASE'!M10, 0) + IF(AND(A36>='01_PRESUPUESTO_CRONOGRAMA_BASE'!K11, A36<='01_PRESUPUESTO_CRONOGRAMA_BASE'!L11), '01_PRESUPUESTO_CRONOGRAMA_BASE'!M11, 0) -> 0 | F36: =SUMIFS(E$2:E36, C$2:C36, C36) -> 0
A37: 9 | B37: 2026-08-09 | C37: WBS-400 | D37: Pruebas Hidráulicas, Desinfección y Entrega | E37: =IF(AND(A37>='01_PRESUPUESTO_CRONOGRAMA_BASE'!K12, A37<='01_PRESUPUESTO_CRONOGRAMA_BASE'!L12), '01_PRESUPUESTO_CRONOGRAMA_BASE'!M12, 0) -> 0 | F37: =SUMIFS(E$2:E37, C$2:C37, C37) -> 0
A38: 10 | B38: 2026-08-10 | C38: WBS-100 | D38: Obras Preliminares, Trazo y Movilización | E38: =IF(AND(A38>='01_PRESUPUESTO_CRONOGRAMA_BASE'!K2, A38<='01_PRESUPUESTO_CRONOGRAMA_BASE'!L2), '01_PRESUPUESTO_CRONOGRAMA_BASE'!M2, 0) + IF(AND(A38>='01_PRESUPUESTO_CRONOGRAMA_BASE'!K3, A38<='01_PRESUPUESTO_CRONOGRAMA_BASE'!L3), '01_PRESUPUESTO_CRONOGRAMA_BASE'!M3, 0) -> 1166.89 | F38: =SUMIFS(E$2:E38, C$2:C38, C38) -> 11668.9
A39: 10 | B39: 2026-08-10 | C39: WBS-200 | D39: Red de Alcantarillado, Zanjas y Buzones | E39: =IF(AND(A39>='01_PRESUPUESTO_CRONOGRAMA_BASE'!K4, A39<='01_PRESUPUESTO_CRONOGRAMA_BASE'!L4), '01_PRESUPUESTO_CRONOGRAMA_BASE'!M4, 0) + IF(AND(A39>='01_PRESUPUESTO_CRONOGRAMA_BASE'!K5, A39<='01_PRESUPUESTO_CRONOGRAMA_BASE'!L5), '01_PRESUPUESTO_CRONOGRAMA_BASE'!M5, 0) + IF(AND(A39>='01_PRESUPUESTO_CRONOGRAMA_BASE'!K6, A39<='01_PRESUPUESTO_CRONOGRAMA_BASE'!L6), '01_PRESUPUESTO_CRONOGRAMA_BASE'!M6, 0) + IF(AND(A39>='01_PRESUPUESTO_CRONOGRAMA_BASE'!K7, A39<='01_PRESUPUESTO_CRONOGRAMA_BASE'!L7), '01_PRESUPUESTO_CRONOGRAMA_BASE'!M7, 0) + IF(AND(A39>='01_PRESUPUESTO_CRONOGRAMA_BASE'!K8, A39<='01_PRESUPUESTO_CRONOGRAMA_BASE'!L8), '01_PRESUPUESTO_CRONOGRAMA_BASE'!M8, 0) + IF(AND(A39>='01_PRESUPUESTO_CRONOGRAMA_BASE'!K9, A39<='01_PRESUPUESTO_CRONOGRAMA_BASE'!L9), '01_PRESUPUESTO_CRONOGRAMA_BASE'!M9, 0) -> 2798.4 | F39: =SUMIFS(E$2:E39, C$2:C39, C39) -> 2798.4
A40: 10 | B40: 2026-08-10 | C40: WBS-300 | D40: Red de Agua Potable y Conexiones Domiciliarias | E40: =IF(AND(A40>='01_PRESUPUESTO_CRONOGRAMA_BASE'!K10, A40<='01_PRESUPUESTO_CRONOGRAMA_BASE'!L10), '01_PRESUPUESTO_CRONOGRAMA_BASE'!M10, 0) + IF(AND(A40>='01_PRESUPUESTO_CRONOGRAMA_BASE'!K11, A40<='01_PRESUPUESTO_CRONOGRAMA_BASE'!L11), '01_PRESUPUESTO_CRONOGRAMA_BASE'!M11, 0) -> 0 | F40: =SUMIFS(E$2:E40, C$2:C40, C40) -> 0
A41: 10 | B41: 2026-08-10 | C41: WBS-400 | D41: Pruebas Hidráulicas, Desinfección y Entrega | E41: =IF(AND(A41>='01_PRESUPUESTO_CRONOGRAMA_BASE'!K12, A41<='01_PRESUPUESTO_CRONOGRAMA_BASE'!L12), '01_PRESUPUESTO_CRONOGRAMA_BASE'!M12, 0) -> 0 | F41: =SUMIFS(E$2:E41, C$2:C41, C41) -> 0
A42: 11 | B42: 2026-08-11 | C42: WBS-100 | D42: Obras Preliminares, Trazo y Movilización | E42: =IF(AND(A42>='01_PRESUPUESTO_CRONOGRAMA_BASE'!K2, A42<='01_PRESUPUESTO_CRONOGRAMA_BASE'!L2), '01_PRESUPUESTO_CRONOGRAMA_BASE'!M2, 0) + IF(AND(A42>='01_PRESUPUESTO_CRONOGRAMA_BASE'!K3, A42<='01_PRESUPUESTO_CRONOGRAMA_BASE'!L3), '01_PRESUPUESTO_CRONOGRAMA_BASE'!M3, 0) -> 1166.89 | F42: =SUMIFS(E$2:E42, C$2:C42, C42) -> 12835.79
A43: 11 | B43: 2026-08-11 | C43: WBS-200 | D43: Red de Alcantarillado, Zanjas y Buzones | E43: =IF(AND(A43>='01_PRESUPUESTO_CRONOGRAMA_BASE'!K4, A43<='01_PRESUPUESTO_CRONOGRAMA_BASE'!L4), '01_PRESUPUESTO_CRONOGRAMA_BASE'!M4, 0) + IF(AND(A43>='01_PRESUPUESTO_CRONOGRAMA_BASE'!K5, A43<='01_PRESUPUESTO_CRONOGRAMA_BASE'!L5), '01_PRESUPUESTO_CRONOGRAMA_BASE'!M5, 0) + IF(AND(A43>='01_PRESUPUESTO_CRONOGRAMA_BASE'!K6, A43<='01_PRESUPUESTO_CRONOGRAMA_BASE'!L6), '01_PRESUPUESTO_CRONOGRAMA_BASE'!M6, 0) + IF(AND(A43>='01_PRESUPUESTO_CRONOGRAMA_BASE'!K7, A43<='01_PRESUPUESTO_CRONOGRAMA_BASE'!L7), '01_PRESUPUESTO_CRONOGRAMA_BASE'!M7, 0) + IF(AND(A43>='01_PRESUPUESTO_CRONOGRAMA_BASE'!K8, A43<='01_PRESUPUESTO_CRONOGRAMA_BASE'!L8), '01_PRESUPUESTO_CRONOGRAMA_BASE'!M8, 0) + IF(AND(A43>='01_PRESUPUESTO_CRONOGRAMA_BASE'!K9, A43<='01_PRESUPUESTO_CRONOGRAMA_BASE'!L9), '01_PRESUPUESTO_CRONOGRAMA_BASE'!M9, 0) -> 2798.4 | F43: =SUMIFS(E$2:E43, C$2:C43, C43) -> 5596.8
A44: 11 | B44: 2026-08-11 | C44: WBS-300 | D44: Red de Agua Potable y Conexiones Domiciliarias | E44: =IF(AND(A44>='01_PRESUPUESTO_CRONOGRAMA_BASE'!K10, A44<='01_PRESUPUESTO_CRONOGRAMA_BASE'!L10), '01_PRESUPUESTO_CRONOGRAMA_BASE'!M10, 0) + IF(AND(A44>='01_PRESUPUESTO_CRONOGRAMA_BASE'!K11, A44<='01_PRESUPUESTO_CRONOGRAMA_BASE'!L11), '01_PRESUPUESTO_CRONOGRAMA_BASE'!M11, 0) -> 0 | F44: =SUMIFS(E$2:E44, C$2:C44, C44) -> 0
A45: 11 | B45: 2026-08-11 | C45: WBS-400 | D45: Pruebas Hidráulicas, Desinfección y Entrega | E45: =IF(AND(A45>='01_PRESUPUESTO_CRONOGRAMA_BASE'!K12, A45<='01_PRESUPUESTO_CRONOGRAMA_BASE'!L12), '01_PRESUPUESTO_CRONOGRAMA_BASE'!M12, 0) -> 0 | F45: =SUMIFS(E$2:E45, C$2:C45, C45) -> 0
A46: 12 | B46: 2026-08-12 | C46: WBS-100 | D46: Obras Preliminares, Trazo y Movilización | E46: =IF(AND(A46>='01_PRESUPUESTO_CRONOGRAMA_BASE'!K2, A46<='01_PRESUPUESTO_CRONOGRAMA_BASE'!L2), '01_PRESUPUESTO_CRONOGRAMA_BASE'!M2, 0) + IF(AND(A46>='01_PRESUPUESTO_CRONOGRAMA_BASE'!K3, A46<='01_PRESUPUESTO_CRONOGRAMA_BASE'!L3), '01_PRESUPUESTO_CRONOGRAMA_BASE'!M3, 0) -> 1166.89 | F46: =SUMIFS(E$2:E46, C$2:C46, C46) -> 14002.68
A47: 12 | B47: 2026-08-12 | C47: WBS-200 | D47: Red de Alcantarillado, Zanjas y Buzones | E47: =IF(AND(A47>='01_PRESUPUESTO_CRONOGRAMA_BASE'!K4, A47<='01_PRESUPUESTO_CRONOGRAMA_BASE'!L4), '01_PRESUPUESTO_CRONOGRAMA_BASE'!M4, 0) + IF(AND(A47>='01_PRESUPUESTO_CRONOGRAMA_BASE'!K5, A47<='01_PRESUPUESTO_CRONOGRAMA_BASE'!L5), '01_PRESUPUESTO_CRONOGRAMA_BASE'!M5, 0) + IF(AND(A47>='01_PRESUPUESTO_CRONOGRAMA_BASE'!K6, A47<='01_PRESUPUESTO_CRONOGRAMA_BASE'!L6), '01_PRESUPUESTO_CRONOGRAMA_BASE'!M6, 0) + IF(AND(A47>='01_PRESUPUESTO_CRONOGRAMA_BASE'!K7, A47<='01_PRESUPUESTO_CRONOGRAMA_BASE'!L7), '01_PRESUPUESTO_CRONOGRAMA_BASE'!M7, 0) + IF(AND(A47>='01_PRESUPUESTO_CRONOGRAMA_BASE'!K8, A47<='01_PRESUPUESTO_CRONOGRAMA_BASE'!L8), '01_PRESUPUESTO_CRONOGRAMA_BASE'!M8, 0) + IF(AND(A47>='01_PRESUPUESTO_CRONOGRAMA_BASE'!K9, A47<='01_PRESUPUESTO_CRONOGRAMA_BASE'!L9), '01_PRESUPUESTO_CRONOGRAMA_BASE'!M9, 0) -> 4368.28 | F47: =SUMIFS(E$2:E47, C$2:C47, C47) -> 9965.08
A48: 12 | B48: 2026-08-12 | C48: WBS-300 | D48: Red de Agua Potable y Conexiones Domiciliarias | E48: =IF(AND(A48>='01_PRESUPUESTO_CRONOGRAMA_BASE'!K10, A48<='01_PRESUPUESTO_CRONOGRAMA_BASE'!L10), '01_PRESUPUESTO_CRONOGRAMA_BASE'!M10, 0) + IF(AND(A48>='01_PRESUPUESTO_CRONOGRAMA_BASE'!K11, A48<='01_PRESUPUESTO_CRONOGRAMA_BASE'!L11), '01_PRESUPUESTO_CRONOGRAMA_BASE'!M11, 0) -> 0 | F48: =SUMIFS(E$2:E48, C$2:C48, C48) -> 0
A49: 12 | B49: 2026-08-12 | C49: WBS-400 | D49: Pruebas Hidráulicas, Desinfección y Entrega | E49: =IF(AND(A49>='01_PRESUPUESTO_CRONOGRAMA_BASE'!K12, A49<='01_PRESUPUESTO_CRONOGRAMA_BASE'!L12), '01_PRESUPUESTO_CRONOGRAMA_BASE'!M12, 0) -> 0 | F49: =SUMIFS(E$2:E49, C$2:C49, C49) -> 0
A50: 13 | B50: 2026-08-13 | C50: WBS-100 | D50: Obras Preliminares, Trazo y Movilización | E50: =IF(AND(A50>='01_PRESUPUESTO_CRONOGRAMA_BASE'!K2, A50<='01_PRESUPUESTO_CRONOGRAMA_BASE'!L2), '01_PRESUPUESTO_CRONOGRAMA_BASE'!M2, 0) + IF(AND(A50>='01_PRESUPUESTO_CRONOGRAMA_BASE'!K3, A50<='01_PRESUPUESTO_CRONOGRAMA_BASE'!L3), '01_PRESUPUESTO_CRONOGRAMA_BASE'!M3, 0) -> 1166.89 | F50: =SUMIFS(E$2:E50, C$2:C50, C50) -> 15169.57
A51: 13 | B51: 2026-08-13 | C51: WBS-200 | D51: Red de Alcantarillado, Zanjas y Buzones | E51: =IF(AND(A51>='01_PRESUPUESTO_CRONOGRAMA_BASE'!K4, A51<='01_PRESUPUESTO_CRONOGRAMA_BASE'!L4), '01_PRESUPUESTO_CRONOGRAMA_BASE'!M4, 0) + IF(AND(A51>='01_PRESUPUESTO_CRONOGRAMA_BASE'!K5, A51<='01_PRESUPUESTO_CRONOGRAMA_BASE'!L5), '01_PRESUPUESTO_CRONOGRAMA_BASE'!M5, 0) + IF(AND(A51>='01_PRESUPUESTO_CRONOGRAMA_BASE'!K6, A51<='01_PRESUPUESTO_CRONOGRAMA_BASE'!L6), '01_PRESUPUESTO_CRONOGRAMA_BASE'!M6, 0) + IF(AND(A51>='01_PRESUPUESTO_CRONOGRAMA_BASE'!K7, A51<='01_PRESUPUESTO_CRONOGRAMA_BASE'!L7), '01_PRESUPUESTO_CRONOGRAMA_BASE'!M7, 0) + IF(AND(A51>='01_PRESUPUESTO_CRONOGRAMA_BASE'!K8, A51<='01_PRESUPUESTO_CRONOGRAMA_BASE'!L8), '01_PRESUPUESTO_CRONOGRAMA_BASE'!M8, 0) + IF(AND(A51>='01_PRESUPUESTO_CRONOGRAMA_BASE'!K9, A51<='01_PRESUPUESTO_CRONOGRAMA_BASE'!L9), '01_PRESUPUESTO_CRONOGRAMA_BASE'!M9, 0) -> 4368.28 | F51: =SUMIFS(E$2:E51, C$2:C51, C51) -> 14333.36
A52: 13 | B52: 2026-08-13 | C52: WBS-300 | D52: Red de Agua Potable y Conexiones Domiciliarias | E52: =IF(AND(A52>='01_PRESUPUESTO_CRONOGRAMA_BASE'!K10, A52<='01_PRESUPUESTO_CRONOGRAMA_BASE'!L10), '01_PRESUPUESTO_CRONOGRAMA_BASE'!M10, 0) + IF(AND(A52>='01_PRESUPUESTO_CRONOGRAMA_BASE'!K11, A52<='01_PRESUPUESTO_CRONOGRAMA_BASE'!L11), '01_PRESUPUESTO_CRONOGRAMA_BASE'!M11, 0) -> 0 | F52: =SUMIFS(E$2:E52, C$2:C52, C52) -> 0
A53: 13 | B53: 2026-08-13 | C53: WBS-400 | D53: Pruebas Hidráulicas, Desinfección y Entrega | E53: =IF(AND(A53>='01_PRESUPUESTO_CRONOGRAMA_BASE'!K12, A53<='01_PRESUPUESTO_CRONOGRAMA_BASE'!L12), '01_PRESUPUESTO_CRONOGRAMA_BASE'!M12, 0) -> 0 | F53: =SUMIFS(E$2:E53, C$2:C53, C53) -> 0
A54: 14 | B54: 2026-08-14 | C54: WBS-100 | D54: Obras Preliminares, Trazo y Movilización | E54: =IF(AND(A54>='01_PRESUPUESTO_CRONOGRAMA_BASE'!K2, A54<='01_PRESUPUESTO_CRONOGRAMA_BASE'!L2), '01_PRESUPUESTO_CRONOGRAMA_BASE'!M2, 0) + IF(AND(A54>='01_PRESUPUESTO_CRONOGRAMA_BASE'!K3, A54<='01_PRESUPUESTO_CRONOGRAMA_BASE'!L3), '01_PRESUPUESTO_CRONOGRAMA_BASE'!M3, 0) -> 1166.89 | F54: =SUMIFS(E$2:E54, C$2:C54, C54) -> 16336.46
A55: 14 | B55: 2026-08-14 | C55: WBS-200 | D55: Red de Alcantarillado, Zanjas y Buzones | E55: =IF(AND(A55>='01_PRESUPUESTO_CRONOGRAMA_BASE'!K4, A55<='01_PRESUPUESTO_CRONOGRAMA_BASE'!L4), '01_PRESUPUESTO_CRONOGRAMA_BASE'!M4, 0) + IF(AND(A55>='01_PRESUPUESTO_CRONOGRAMA_BASE'!K5, A55<='01_PRESUPUESTO_CRONOGRAMA_BASE'!L5), '01_PRESUPUESTO_CRONOGRAMA_BASE'!M5, 0) + IF(AND(A55>='01_PRESUPUESTO_CRONOGRAMA_BASE'!K6, A55<='01_PRESUPUESTO_CRONOGRAMA_BASE'!L6), '01_PRESUPUESTO_CRONOGRAMA_BASE'!M6, 0) + IF(AND(A55>='01_PRESUPUESTO_CRONOGRAMA_BASE'!K7, A55<='01_PRESUPUESTO_CRONOGRAMA_BASE'!L7), '01_PRESUPUESTO_CRONOGRAMA_BASE'!M7, 0) + IF(AND(A55>='01_PRESUPUESTO_CRONOGRAMA_BASE'!K8, A55<='01_PRESUPUESTO_CRONOGRAMA_BASE'!L8), '01_PRESUPUESTO_CRONOGRAMA_BASE'!M8, 0) + IF(AND(A55>='01_PRESUPUESTO_CRONOGRAMA_BASE'!K9, A55<='01_PRESUPUESTO_CRONOGRAMA_BASE'!L9), '01_PRESUPUESTO_CRONOGRAMA_BASE'!M9, 0) -> 4368.28 | F55: =SUMIFS(E$2:E55, C$2:C55, C55) -> 18701.64
A56: 14 | B56: 2026-08-14 | C56: WBS-300 | D56: Red de Agua Potable y Conexiones Domiciliarias | E56: =IF(AND(A56>='01_PRESUPUESTO_CRONOGRAMA_BASE'!K10, A56<='01_PRESUPUESTO_CRONOGRAMA_BASE'!L10), '01_PRESUPUESTO_CRONOGRAMA_BASE'!M10, 0) + IF(AND(A56>='01_PRESUPUESTO_CRONOGRAMA_BASE'!K11, A56<='01_PRESUPUESTO_CRONOGRAMA_BASE'!L11), '01_PRESUPUESTO_CRONOGRAMA_BASE'!M11, 0) -> 0 | F56: =SUMIFS(E$2:E56, C$2:C56, C56) -> 0
A57: 14 | B57: 2026-08-14 | C57: WBS-400 | D57: Pruebas Hidráulicas, Desinfección y Entrega | E57: =IF(AND(A57>='01_PRESUPUESTO_CRONOGRAMA_BASE'!K12, A57<='01_PRESUPUESTO_CRONOGRAMA_BASE'!L12), '01_PRESUPUESTO_CRONOGRAMA_BASE'!M12, 0) -> 0 | F57: =SUMIFS(E$2:E57, C$2:C57, C57) -> 0
A58: 15 | B58: 2026-08-15 | C58: WBS-100 | D58: Obras Preliminares, Trazo y Movilización | E58: =IF(AND(A58>='01_PRESUPUESTO_CRONOGRAMA_BASE'!K2, A58<='01_PRESUPUESTO_CRONOGRAMA_BASE'!L2), '01_PRESUPUESTO_CRONOGRAMA_BASE'!M2, 0) + IF(AND(A58>='01_PRESUPUESTO_CRONOGRAMA_BASE'!K3, A58<='01_PRESUPUESTO_CRONOGRAMA_BASE'!L3), '01_PRESUPUESTO_CRONOGRAMA_BASE'!M3, 0) -> 0 | F58: =SUMIFS(E$2:E58, C$2:C58, C58) -> 16336.46
A59: 15 | B59: 2026-08-15 | C59: WBS-200 | D59: Red de Alcantarillado, Zanjas y Buzones | E59: =IF(AND(A59>='01_PRESUPUESTO_CRONOGRAMA_BASE'!K4, A59<='01_PRESUPUESTO_CRONOGRAMA_BASE'!L4), '01_PRESUPUESTO_CRONOGRAMA_BASE'!M4, 0) + IF(AND(A59>='01_PRESUPUESTO_CRONOGRAMA_BASE'!K5, A59<='01_PRESUPUESTO_CRONOGRAMA_BASE'!L5), '01_PRESUPUESTO_CRONOGRAMA_BASE'!M5, 0) + IF(AND(A59>='01_PRESUPUESTO_CRONOGRAMA_BASE'!K6, A59<='01_PRESUPUESTO_CRONOGRAMA_BASE'!L6), '01_PRESUPUESTO_CRONOGRAMA_BASE'!M6, 0) + IF(AND(A59>='01_PRESUPUESTO_CRONOGRAMA_BASE'!K7, A59<='01_PRESUPUESTO_CRONOGRAMA_BASE'!L7), '01_PRESUPUESTO_CRONOGRAMA_BASE'!M7, 0) + IF(AND(A59>='01_PRESUPUESTO_CRONOGRAMA_BASE'!K8, A59<='01_PRESUPUESTO_CRONOGRAMA_BASE'!L8), '01_PRESUPUESTO_CRONOGRAMA_BASE'!M8, 0) + IF(AND(A59>='01_PRESUPUESTO_CRONOGRAMA_BASE'!K9, A59<='01_PRESUPUESTO_CRONOGRAMA_BASE'!L9), '01_PRESUPUESTO_CRONOGRAMA_BASE'!M9, 0) -> 8939.69 | F59: =SUMIFS(E$2:E59, C$2:C59, C59) -> 27641.33
A60: 15 | B60: 2026-08-15 | C60: WBS-300 | D60: Red de Agua Potable y Conexiones Domiciliarias | E60: =IF(AND(A60>='01_PRESUPUESTO_CRONOGRAMA_BASE'!K10, A60<='01_PRESUPUESTO_CRONOGRAMA_BASE'!L10), '01_PRESUPUESTO_CRONOGRAMA_BASE'!M10, 0) + IF(AND(A60>='01_PRESUPUESTO_CRONOGRAMA_BASE'!K11, A60<='01_PRESUPUESTO_CRONOGRAMA_BASE'!L11), '01_PRESUPUESTO_CRONOGRAMA_BASE'!M11, 0) -> 0 | F60: =SUMIFS(E$2:E60, C$2:C60, C60) -> 0
A61: 15 | B61: 2026-08-15 | C61: WBS-400 | D61: Pruebas Hidráulicas, Desinfección y Entrega | E61: =IF(AND(A61>='01_PRESUPUESTO_CRONOGRAMA_BASE'!K12, A61<='01_PRESUPUESTO_CRONOGRAMA_BASE'!L12), '01_PRESUPUESTO_CRONOGRAMA_BASE'!M12, 0) -> 0 | F61: =SUMIFS(E$2:E61, C$2:C61, C61) -> 0
A62: 16 | B62: 2026-08-16 | C62: WBS-100 | D62: Obras Preliminares, Trazo y Movilización | E62: =IF(AND(A62>='01_PRESUPUESTO_CRONOGRAMA_BASE'!K2, A62<='01_PRESUPUESTO_CRONOGRAMA_BASE'!L2), '01_PRESUPUESTO_CRONOGRAMA_BASE'!M2, 0) + IF(AND(A62>='01_PRESUPUESTO_CRONOGRAMA_BASE'!K3, A62<='01_PRESUPUESTO_CRONOGRAMA_BASE'!L3), '01_PRESUPUESTO_CRONOGRAMA_BASE'!M3, 0) -> 0 | F62: =SUMIFS(E$2:E62, C$2:C62, C62) -> 16336.46
A63: 16 | B63: 2026-08-16 | C63: WBS-200 | D63: Red de Alcantarillado, Zanjas y Buzones | E63: =IF(AND(A63>='01_PRESUPUESTO_CRONOGRAMA_BASE'!K4, A63<='01_PRESUPUESTO_CRONOGRAMA_BASE'!L4), '01_PRESUPUESTO_CRONOGRAMA_BASE'!M4, 0) + IF(AND(A63>='01_PRESUPUESTO_CRONOGRAMA_BASE'!K5, A63<='01_PRESUPUESTO_CRONOGRAMA_BASE'!L5), '01_PRESUPUESTO_CRONOGRAMA_BASE'!M5, 0) + IF(AND(A63>='01_PRESUPUESTO_CRONOGRAMA_BASE'!K6, A63<='01_PRESUPUESTO_CRONOGRAMA_BASE'!L6), '01_PRESUPUESTO_CRONOGRAMA_BASE'!M6, 0) + IF(AND(A63>='01_PRESUPUESTO_CRONOGRAMA_BASE'!K7, A63<='01_PRESUPUESTO_CRONOGRAMA_BASE'!L7), '01_PRESUPUESTO_CRONOGRAMA_BASE'!M7, 0) + IF(AND(A63>='01_PRESUPUESTO_CRONOGRAMA_BASE'!K8, A63<='01_PRESUPUESTO_CRONOGRAMA_BASE'!L8), '01_PRESUPUESTO_CRONOGRAMA_BASE'!M8, 0) + IF(AND(A63>='01_PRESUPUESTO_CRONOGRAMA_BASE'!K9, A63<='01_PRESUPUESTO_CRONOGRAMA_BASE'!L9), '01_PRESUPUESTO_CRONOGRAMA_BASE'!M9, 0) -> 8939.69 | F63: =SUMIFS(E$2:E63, C$2:C63, C63) -> 36581.02
A64: 16 | B64: 2026-08-16 | C64: WBS-300 | D64: Red de Agua Potable y Conexiones Domiciliarias | E64: =IF(AND(A64>='01_PRESUPUESTO_CRONOGRAMA_BASE'!K10, A64<='01_PRESUPUESTO_CRONOGRAMA_BASE'!L10), '01_PRESUPUESTO_CRONOGRAMA_BASE'!M10, 0) + IF(AND(A64>='01_PRESUPUESTO_CRONOGRAMA_BASE'!K11, A64<='01_PRESUPUESTO_CRONOGRAMA_BASE'!L11), '01_PRESUPUESTO_CRONOGRAMA_BASE'!M11, 0) -> 0 | F64: =SUMIFS(E$2:E64, C$2:C64, C64) -> 0
A65: 16 | B65: 2026-08-16 | C65: WBS-400 | D65: Pruebas Hidráulicas, Desinfección y Entrega | E65: =IF(AND(A65>='01_PRESUPUESTO_CRONOGRAMA_BASE'!K12, A65<='01_PRESUPUESTO_CRONOGRAMA_BASE'!L12), '01_PRESUPUESTO_CRONOGRAMA_BASE'!M12, 0) -> 0 | F65: =SUMIFS(E$2:E65, C$2:C65, C65) -> 0
A66: 17 | B66: 2026-08-17 | C66: WBS-100 | D66: Obras Preliminares, Trazo y Movilización | E66: =IF(AND(A66>='01_PRESUPUESTO_CRONOGRAMA_BASE'!K2, A66<='01_PRESUPUESTO_CRONOGRAMA_BASE'!L2), '01_PRESUPUESTO_CRONOGRAMA_BASE'!M2, 0) + IF(AND(A66>='01_PRESUPUESTO_CRONOGRAMA_BASE'!K3, A66<='01_PRESUPUESTO_CRONOGRAMA_BASE'!L3), '01_PRESUPUESTO_CRONOGRAMA_BASE'!M3, 0) -> 0 | F66: =SUMIFS(E$2:E66, C$2:C66, C66) -> 16336.46
A67: 17 | B67: 2026-08-17 | C67: WBS-200 | D67: Red de Alcantarillado, Zanjas y Buzones | E67: =IF(AND(A67>='01_PRESUPUESTO_CRONOGRAMA_BASE'!K4, A67<='01_PRESUPUESTO_CRONOGRAMA_BASE'!L4), '01_PRESUPUESTO_CRONOGRAMA_BASE'!M4, 0) + IF(AND(A67>='01_PRESUPUESTO_CRONOGRAMA_BASE'!K5, A67<='01_PRESUPUESTO_CRONOGRAMA_BASE'!L5), '01_PRESUPUESTO_CRONOGRAMA_BASE'!M5, 0) + IF(AND(A67>='01_PRESUPUESTO_CRONOGRAMA_BASE'!K6, A67<='01_PRESUPUESTO_CRONOGRAMA_BASE'!L6), '01_PRESUPUESTO_CRONOGRAMA_BASE'!M6, 0) + IF(AND(A67>='01_PRESUPUESTO_CRONOGRAMA_BASE'!K7, A67<='01_PRESUPUESTO_CRONOGRAMA_BASE'!L7), '01_PRESUPUESTO_CRONOGRAMA_BASE'!M7, 0) + IF(AND(A67>='01_PRESUPUESTO_CRONOGRAMA_BASE'!K8, A67<='01_PRESUPUESTO_CRONOGRAMA_BASE'!L8), '01_PRESUPUESTO_CRONOGRAMA_BASE'!M8, 0) + IF(AND(A67>='01_PRESUPUESTO_CRONOGRAMA_BASE'!K9, A67<='01_PRESUPUESTO_CRONOGRAMA_BASE'!L9), '01_PRESUPUESTO_CRONOGRAMA_BASE'!M9, 0) -> 8939.69 | F67: =SUMIFS(E$2:E67, C$2:C67, C67) -> 45520.71
A68: 17 | B68: 2026-08-17 | C68: WBS-300 | D68: Red de Agua Potable y Conexiones Domiciliarias | E68: =IF(AND(A68>='01_PRESUPUESTO_CRONOGRAMA_BASE'!K10, A68<='01_PRESUPUESTO_CRONOGRAMA_BASE'!L10), '01_PRESUPUESTO_CRONOGRAMA_BASE'!M10, 0) + IF(AND(A68>='01_PRESUPUESTO_CRONOGRAMA_BASE'!K11, A68<='01_PRESUPUESTO_CRONOGRAMA_BASE'!L11), '01_PRESUPUESTO_CRONOGRAMA_BASE'!M11, 0) -> 0 | F68: =SUMIFS(E$2:E68, C$2:C68, C68) -> 0
A69: 17 | B69: 2026-08-17 | C69: WBS-400 | D69: Pruebas Hidráulicas, Desinfección y Entrega | E69: =IF(AND(A69>='01_PRESUPUESTO_CRONOGRAMA_BASE'!K12, A69<='01_PRESUPUESTO_CRONOGRAMA_BASE'!L12), '01_PRESUPUESTO_CRONOGRAMA_BASE'!M12, 0) -> 0 | F69: =SUMIFS(E$2:E69, C$2:C69, C69) -> 0
A70: 18 | B70: 2026-08-18 | C70: WBS-100 | D70: Obras Preliminares, Trazo y Movilización | E70: =IF(AND(A70>='01_PRESUPUESTO_CRONOGRAMA_BASE'!K2, A70<='01_PRESUPUESTO_CRONOGRAMA_BASE'!L2), '01_PRESUPUESTO_CRONOGRAMA_BASE'!M2, 0) + IF(AND(A70>='01_PRESUPUESTO_CRONOGRAMA_BASE'!K3, A70<='01_PRESUPUESTO_CRONOGRAMA_BASE'!L3), '01_PRESUPUESTO_CRONOGRAMA_BASE'!M3, 0) -> 0 | F70: =SUMIFS(E$2:E70, C$2:C70, C70) -> 16336.46
A71: 18 | B71: 2026-08-18 | C71: WBS-200 | D71: Red de Alcantarillado, Zanjas y Buzones | E71: =IF(AND(A71>='01_PRESUPUESTO_CRONOGRAMA_BASE'!K4, A71<='01_PRESUPUESTO_CRONOGRAMA_BASE'!L4), '01_PRESUPUESTO_CRONOGRAMA_BASE'!M4, 0) + IF(AND(A71>='01_PRESUPUESTO_CRONOGRAMA_BASE'!K5, A71<='01_PRESUPUESTO_CRONOGRAMA_BASE'!L5), '01_PRESUPUESTO_CRONOGRAMA_BASE'!M5, 0) + IF(AND(A71>='01_PRESUPUESTO_CRONOGRAMA_BASE'!K6, A71<='01_PRESUPUESTO_CRONOGRAMA_BASE'!L6), '01_PRESUPUESTO_CRONOGRAMA_BASE'!M6, 0) + IF(AND(A71>='01_PRESUPUESTO_CRONOGRAMA_BASE'!K7, A71<='01_PRESUPUESTO_CRONOGRAMA_BASE'!L7), '01_PRESUPUESTO_CRONOGRAMA_BASE'!M7, 0) + IF(AND(A71>='01_PRESUPUESTO_CRONOGRAMA_BASE'!K8, A71<='01_PRESUPUESTO_CRONOGRAMA_BASE'!L8), '01_PRESUPUESTO_CRONOGRAMA_BASE'!M8, 0) + IF(AND(A71>='01_PRESUPUESTO_CRONOGRAMA_BASE'!K9, A71<='01_PRESUPUESTO_CRONOGRAMA_BASE'!L9), '01_PRESUPUESTO_CRONOGRAMA_BASE'!M9, 0) -> 13896.64 | F71: =SUMIFS(E$2:E71, C$2:C71, C71) -> 59417.35
A72: 18 | B72: 2026-08-18 | C72: WBS-300 | D72: Red de Agua Potable y Conexiones Domiciliarias | E72: =IF(AND(A72>='01_PRESUPUESTO_CRONOGRAMA_BASE'!K10, A72<='01_PRESUPUESTO_CRONOGRAMA_BASE'!L10), '01_PRESUPUESTO_CRONOGRAMA_BASE'!M10, 0) + IF(AND(A72>='01_PRESUPUESTO_CRONOGRAMA_BASE'!K11, A72<='01_PRESUPUESTO_CRONOGRAMA_BASE'!L11), '01_PRESUPUESTO_CRONOGRAMA_BASE'!M11, 0) -> 0 | F72: =SUMIFS(E$2:E72, C$2:C72, C72) -> 0
A73: 18 | B73: 2026-08-18 | C73: WBS-400 | D73: Pruebas Hidráulicas, Desinfección y Entrega | E73: =IF(AND(A73>='01_PRESUPUESTO_CRONOGRAMA_BASE'!K12, A73<='01_PRESUPUESTO_CRONOGRAMA_BASE'!L12), '01_PRESUPUESTO_CRONOGRAMA_BASE'!M12, 0) -> 0 | F73: =SUMIFS(E$2:E73, C$2:C73, C73) -> 0
A74: 19 | B74: 2026-08-19 | C74: WBS-100 | D74: Obras Preliminares, Trazo y Movilización | E74: =IF(AND(A74>='01_PRESUPUESTO_CRONOGRAMA_BASE'!K2, A74<='01_PRESUPUESTO_CRONOGRAMA_BASE'!L2), '01_PRESUPUESTO_CRONOGRAMA_BASE'!M2, 0) + IF(AND(A74>='01_PRESUPUESTO_CRONOGRAMA_BASE'!K3, A74<='01_PRESUPUESTO_CRONOGRAMA_BASE'!L3), '01_PRESUPUESTO_CRONOGRAMA_BASE'!M3, 0) -> 0 | F74: =SUMIFS(E$2:E74, C$2:C74, C74) -> 16336.46
A75: 19 | B75: 2026-08-19 | C75: WBS-200 | D75: Red de Alcantarillado, Zanjas y Buzones | E75: =IF(AND(A75>='01_PRESUPUESTO_CRONOGRAMA_BASE'!K4, A75<='01_PRESUPUESTO_CRONOGRAMA_BASE'!L4), '01_PRESUPUESTO_CRONOGRAMA_BASE'!M4, 0) + IF(AND(A75>='01_PRESUPUESTO_CRONOGRAMA_BASE'!K5, A75<='01_PRESUPUESTO_CRONOGRAMA_BASE'!L5), '01_PRESUPUESTO_CRONOGRAMA_BASE'!M5, 0) + IF(AND(A75>='01_PRESUPUESTO_CRONOGRAMA_BASE'!K6, A75<='01_PRESUPUESTO_CRONOGRAMA_BASE'!L6), '01_PRESUPUESTO_CRONOGRAMA_BASE'!M6, 0) + IF(AND(A75>='01_PRESUPUESTO_CRONOGRAMA_BASE'!K7, A75<='01_PRESUPUESTO_CRONOGRAMA_BASE'!L7), '01_PRESUPUESTO_CRONOGRAMA_BASE'!M7, 0) + IF(AND(A75>='01_PRESUPUESTO_CRONOGRAMA_BASE'!K8, A75<='01_PRESUPUESTO_CRONOGRAMA_BASE'!L8), '01_PRESUPUESTO_CRONOGRAMA_BASE'!M8, 0) + IF(AND(A75>='01_PRESUPUESTO_CRONOGRAMA_BASE'!K9, A75<='01_PRESUPUESTO_CRONOGRAMA_BASE'!L9), '01_PRESUPUESTO_CRONOGRAMA_BASE'!M9, 0) -> 13896.64 | F75: =SUMIFS(E$2:E75, C$2:C75, C75) -> 73313.99
A76: 19 | B76: 2026-08-19 | C76: WBS-300 | D76: Red de Agua Potable y Conexiones Domiciliarias | E76: =IF(AND(A76>='01_PRESUPUESTO_CRONOGRAMA_BASE'!K10, A76<='01_PRESUPUESTO_CRONOGRAMA_BASE'!L10), '01_PRESUPUESTO_CRONOGRAMA_BASE'!M10, 0) + IF(AND(A76>='01_PRESUPUESTO_CRONOGRAMA_BASE'!K11, A76<='01_PRESUPUESTO_CRONOGRAMA_BASE'!L11), '01_PRESUPUESTO_CRONOGRAMA_BASE'!M11, 0) -> 0 | F76: =SUMIFS(E$2:E76, C$2:C76, C76) -> 0
A77: 19 | B77: 2026-08-19 | C77: WBS-400 | D77: Pruebas Hidráulicas, Desinfección y Entrega | E77: =IF(AND(A77>='01_PRESUPUESTO_CRONOGRAMA_BASE'!K12, A77<='01_PRESUPUESTO_CRONOGRAMA_BASE'!L12), '01_PRESUPUESTO_CRONOGRAMA_BASE'!M12, 0) -> 0 | F77: =SUMIFS(E$2:E77, C$2:C77, C77) -> 0
A78: 20 | B78: 2026-08-20 | C78: WBS-100 | D78: Obras Preliminares, Trazo y Movilización | E78: =IF(AND(A78>='01_PRESUPUESTO_CRONOGRAMA_BASE'!K2, A78<='01_PRESUPUESTO_CRONOGRAMA_BASE'!L2), '01_PRESUPUESTO_CRONOGRAMA_BASE'!M2, 0) + IF(AND(A78>='01_PRESUPUESTO_CRONOGRAMA_BASE'!K3, A78<='01_PRESUPUESTO_CRONOGRAMA_BASE'!L3), '01_PRESUPUESTO_CRONOGRAMA_BASE'!M3, 0) -> 0 | F78: =SUMIFS(E$2:E78, C$2:C78, C78) -> 16336.46
A79: 20 | B79: 2026-08-20 | C79: WBS-200 | D79: Red de Alcantarillado, Zanjas y Buzones | E79: =IF(AND(A79>='01_PRESUPUESTO_CRONOGRAMA_BASE'!K4, A79<='01_PRESUPUESTO_CRONOGRAMA_BASE'!L4), '01_PRESUPUESTO_CRONOGRAMA_BASE'!M4, 0) + IF(AND(A79>='01_PRESUPUESTO_CRONOGRAMA_BASE'!K5, A79<='01_PRESUPUESTO_CRONOGRAMA_BASE'!L5), '01_PRESUPUESTO_CRONOGRAMA_BASE'!M5, 0) + IF(AND(A79>='01_PRESUPUESTO_CRONOGRAMA_BASE'!K6, A79<='01_PRESUPUESTO_CRONOGRAMA_BASE'!L6), '01_PRESUPUESTO_CRONOGRAMA_BASE'!M6, 0) + IF(AND(A79>='01_PRESUPUESTO_CRONOGRAMA_BASE'!K7, A79<='01_PRESUPUESTO_CRONOGRAMA_BASE'!L7), '01_PRESUPUESTO_CRONOGRAMA_BASE'!M7, 0) + IF(AND(A79>='01_PRESUPUESTO_CRONOGRAMA_BASE'!K8, A79<='01_PRESUPUESTO_CRONOGRAMA_BASE'!L8), '01_PRESUPUESTO_CRONOGRAMA_BASE'!M8, 0) + IF(AND(A79>='01_PRESUPUESTO_CRONOGRAMA_BASE'!K9, A79<='01_PRESUPUESTO_CRONOGRAMA_BASE'!L9), '01_PRESUPUESTO_CRONOGRAMA_BASE'!M9, 0) -> 13896.64 | F79: =SUMIFS(E$2:E79, C$2:C79, C79) -> 87210.63
A80: 20 | B80: 2026-08-20 | C80: WBS-300 | D80: Red de Agua Potable y Conexiones Domiciliarias | E80: =IF(AND(A80>='01_PRESUPUESTO_CRONOGRAMA_BASE'!K10, A80<='01_PRESUPUESTO_CRONOGRAMA_BASE'!L10), '01_PRESUPUESTO_CRONOGRAMA_BASE'!M10, 0) + IF(AND(A80>='01_PRESUPUESTO_CRONOGRAMA_BASE'!K11, A80<='01_PRESUPUESTO_CRONOGRAMA_BASE'!L11), '01_PRESUPUESTO_CRONOGRAMA_BASE'!M11, 0) -> 0 | F80: =SUMIFS(E$2:E80, C$2:C80, C80) -> 0
A81: 20 | B81: 2026-08-20 | C81: WBS-400 | D81: Pruebas Hidráulicas, Desinfección y Entrega | E81: =IF(AND(A81>='01_PRESUPUESTO_CRONOGRAMA_BASE'!K12, A81<='01_PRESUPUESTO_CRONOGRAMA_BASE'!L12), '01_PRESUPUESTO_CRONOGRAMA_BASE'!M12, 0) -> 0 | F81: =SUMIFS(E$2:E81, C$2:C81, C81) -> 0
A82: 21 | B82: 2026-08-21 | C82: WBS-100 | D82: Obras Preliminares, Trazo y Movilización | E82: =IF(AND(A82>='01_PRESUPUESTO_CRONOGRAMA_BASE'!K2, A82<='01_PRESUPUESTO_CRONOGRAMA_BASE'!L2), '01_PRESUPUESTO_CRONOGRAMA_BASE'!M2, 0) + IF(AND(A82>='01_PRESUPUESTO_CRONOGRAMA_BASE'!K3, A82<='01_PRESUPUESTO_CRONOGRAMA_BASE'!L3), '01_PRESUPUESTO_CRONOGRAMA_BASE'!M3, 0) -> 0 | F82: =SUMIFS(E$2:E82, C$2:C82, C82) -> 16336.46
A83: 21 | B83: 2026-08-21 | C83: WBS-200 | D83: Red de Alcantarillado, Zanjas y Buzones | E83: =IF(AND(A83>='01_PRESUPUESTO_CRONOGRAMA_BASE'!K4, A83<='01_PRESUPUESTO_CRONOGRAMA_BASE'!L4), '01_PRESUPUESTO_CRONOGRAMA_BASE'!M4, 0) + IF(AND(A83>='01_PRESUPUESTO_CRONOGRAMA_BASE'!K5, A83<='01_PRESUPUESTO_CRONOGRAMA_BASE'!L5), '01_PRESUPUESTO_CRONOGRAMA_BASE'!M5, 0) + IF(AND(A83>='01_PRESUPUESTO_CRONOGRAMA_BASE'!K6, A83<='01_PRESUPUESTO_CRONOGRAMA_BASE'!L6), '01_PRESUPUESTO_CRONOGRAMA_BASE'!M6, 0) + IF(AND(A83>='01_PRESUPUESTO_CRONOGRAMA_BASE'!K7, A83<='01_PRESUPUESTO_CRONOGRAMA_BASE'!L7), '01_PRESUPUESTO_CRONOGRAMA_BASE'!M7, 0) + IF(AND(A83>='01_PRESUPUESTO_CRONOGRAMA_BASE'!K8, A83<='01_PRESUPUESTO_CRONOGRAMA_BASE'!L8), '01_PRESUPUESTO_CRONOGRAMA_BASE'!M8, 0) + IF(AND(A83>='01_PRESUPUESTO_CRONOGRAMA_BASE'!K9, A83<='01_PRESUPUESTO_CRONOGRAMA_BASE'!L9), '01_PRESUPUESTO_CRONOGRAMA_BASE'!M9, 0) -> 13896.64 | F83: =SUMIFS(E$2:E83, C$2:C83, C83) -> 101107.27
A84: 21 | B84: 2026-08-21 | C84: WBS-300 | D84: Red de Agua Potable y Conexiones Domiciliarias | E84: =IF(AND(A84>='01_PRESUPUESTO_CRONOGRAMA_BASE'!K10, A84<='01_PRESUPUESTO_CRONOGRAMA_BASE'!L10), '01_PRESUPUESTO_CRONOGRAMA_BASE'!M10, 0) + IF(AND(A84>='01_PRESUPUESTO_CRONOGRAMA_BASE'!K11, A84<='01_PRESUPUESTO_CRONOGRAMA_BASE'!L11), '01_PRESUPUESTO_CRONOGRAMA_BASE'!M11, 0) -> 0 | F84: =SUMIFS(E$2:E84, C$2:C84, C84) -> 0
A85: 21 | B85: 2026-08-21 | C85: WBS-400 | D85: Pruebas Hidráulicas, Desinfección y Entrega | E85: =IF(AND(A85>='01_PRESUPUESTO_CRONOGRAMA_BASE'!K12, A85<='01_PRESUPUESTO_CRONOGRAMA_BASE'!L12), '01_PRESUPUESTO_CRONOGRAMA_BASE'!M12, 0) -> 0 | F85: =SUMIFS(E$2:E85, C$2:C85, C85) -> 0
A86: 22 | B86: 2026-08-22 | C86: WBS-100 | D86: Obras Preliminares, Trazo y Movilización | E86: =IF(AND(A86>='01_PRESUPUESTO_CRONOGRAMA_BASE'!K2, A86<='01_PRESUPUESTO_CRONOGRAMA_BASE'!L2), '01_PRESUPUESTO_CRONOGRAMA_BASE'!M2, 0) + IF(AND(A86>='01_PRESUPUESTO_CRONOGRAMA_BASE'!K3, A86<='01_PRESUPUESTO_CRONOGRAMA_BASE'!L3), '01_PRESUPUESTO_CRONOGRAMA_BASE'!M3, 0) -> 0 | F86: =SUMIFS(E$2:E86, C$2:C86, C86) -> 16336.46
A87: 22 | B87: 2026-08-22 | C87: WBS-200 | D87: Red de Alcantarillado, Zanjas y Buzones | E87: =IF(AND(A87>='01_PRESUPUESTO_CRONOGRAMA_BASE'!K4, A87<='01_PRESUPUESTO_CRONOGRAMA_BASE'!L4), '01_PRESUPUESTO_CRONOGRAMA_BASE'!M4, 0) + IF(AND(A87>='01_PRESUPUESTO_CRONOGRAMA_BASE'!K5, A87<='01_PRESUPUESTO_CRONOGRAMA_BASE'!L5), '01_PRESUPUESTO_CRONOGRAMA_BASE'!M5, 0) + IF(AND(A87>='01_PRESUPUESTO_CRONOGRAMA_BASE'!K6, A87<='01_PRESUPUESTO_CRONOGRAMA_BASE'!L6), '01_PRESUPUESTO_CRONOGRAMA_BASE'!M6, 0) + IF(AND(A87>='01_PRESUPUESTO_CRONOGRAMA_BASE'!K7, A87<='01_PRESUPUESTO_CRONOGRAMA_BASE'!L7), '01_PRESUPUESTO_CRONOGRAMA_BASE'!M7, 0) + IF(AND(A87>='01_PRESUPUESTO_CRONOGRAMA_BASE'!K8, A87<='01_PRESUPUESTO_CRONOGRAMA_BASE'!L8), '01_PRESUPUESTO_CRONOGRAMA_BASE'!M8, 0) + IF(AND(A87>='01_PRESUPUESTO_CRONOGRAMA_BASE'!K9, A87<='01_PRESUPUESTO_CRONOGRAMA_BASE'!L9), '01_PRESUPUESTO_CRONOGRAMA_BASE'!M9, 0) -> 17897.81 | F87: =SUMIFS(E$2:E87, C$2:C87, C87) -> 119005.08
A88: 22 | B88: 2026-08-22 | C88: WBS-300 | D88: Red de Agua Potable y Conexiones Domiciliarias | E88: =IF(AND(A88>='01_PRESUPUESTO_CRONOGRAMA_BASE'!K10, A88<='01_PRESUPUESTO_CRONOGRAMA_BASE'!L10), '01_PRESUPUESTO_CRONOGRAMA_BASE'!M10, 0) + IF(AND(A88>='01_PRESUPUESTO_CRONOGRAMA_BASE'!K11, A88<='01_PRESUPUESTO_CRONOGRAMA_BASE'!L11), '01_PRESUPUESTO_CRONOGRAMA_BASE'!M11, 0) -> 1761.82 | F88: =SUMIFS(E$2:E88, C$2:C88, C88) -> 1761.82
A89: 22 | B89: 2026-08-22 | C89: WBS-400 | D89: Pruebas Hidráulicas, Desinfección y Entrega | E89: =IF(AND(A89>='01_PRESUPUESTO_CRONOGRAMA_BASE'!K12, A89<='01_PRESUPUESTO_CRONOGRAMA_BASE'!L12), '01_PRESUPUESTO_CRONOGRAMA_BASE'!M12, 0) -> 0 | F89: =SUMIFS(E$2:E89, C$2:C89, C89) -> 0
A90: 23 | B90: 2026-08-23 | C90: WBS-100 | D90: Obras Preliminares, Trazo y Movilización | E90: =IF(AND(A90>='01_PRESUPUESTO_CRONOGRAMA_BASE'!K2, A90<='01_PRESUPUESTO_CRONOGRAMA_BASE'!L2), '01_PRESUPUESTO_CRONOGRAMA_BASE'!M2, 0) + IF(AND(A90>='01_PRESUPUESTO_CRONOGRAMA_BASE'!K3, A90<='01_PRESUPUESTO_CRONOGRAMA_BASE'!L3), '01_PRESUPUESTO_CRONOGRAMA_BASE'!M3, 0) -> 0 | F90: =SUMIFS(E$2:E90, C$2:C90, C90) -> 16336.46
A91: 23 | B91: 2026-08-23 | C91: WBS-200 | D91: Red de Alcantarillado, Zanjas y Buzones | E91: =IF(AND(A91>='01_PRESUPUESTO_CRONOGRAMA_BASE'!K4, A91<='01_PRESUPUESTO_CRONOGRAMA_BASE'!L4), '01_PRESUPUESTO_CRONOGRAMA_BASE'!M4, 0) + IF(AND(A91>='01_PRESUPUESTO_CRONOGRAMA_BASE'!K5, A91<='01_PRESUPUESTO_CRONOGRAMA_BASE'!L5), '01_PRESUPUESTO_CRONOGRAMA_BASE'!M5, 0) + IF(AND(A91>='01_PRESUPUESTO_CRONOGRAMA_BASE'!K6, A91<='01_PRESUPUESTO_CRONOGRAMA_BASE'!L6), '01_PRESUPUESTO_CRONOGRAMA_BASE'!M6, 0) + IF(AND(A91>='01_PRESUPUESTO_CRONOGRAMA_BASE'!K7, A91<='01_PRESUPUESTO_CRONOGRAMA_BASE'!L7), '01_PRESUPUESTO_CRONOGRAMA_BASE'!M7, 0) + IF(AND(A91>='01_PRESUPUESTO_CRONOGRAMA_BASE'!K8, A91<='01_PRESUPUESTO_CRONOGRAMA_BASE'!L8), '01_PRESUPUESTO_CRONOGRAMA_BASE'!M8, 0) + IF(AND(A91>='01_PRESUPUESTO_CRONOGRAMA_BASE'!K9, A91<='01_PRESUPUESTO_CRONOGRAMA_BASE'!L9), '01_PRESUPUESTO_CRONOGRAMA_BASE'!M9, 0) -> 17897.81 | F91: =SUMIFS(E$2:E91, C$2:C91, C91) -> 136902.89
A92: 23 | B92: 2026-08-23 | C92: WBS-300 | D92: Red de Agua Potable y Conexiones Domiciliarias | E92: =IF(AND(A92>='01_PRESUPUESTO_CRONOGRAMA_BASE'!K10, A92<='01_PRESUPUESTO_CRONOGRAMA_BASE'!L10), '01_PRESUPUESTO_CRONOGRAMA_BASE'!M10, 0) + IF(AND(A92>='01_PRESUPUESTO_CRONOGRAMA_BASE'!K11, A92<='01_PRESUPUESTO_CRONOGRAMA_BASE'!L11), '01_PRESUPUESTO_CRONOGRAMA_BASE'!M11, 0) -> 1761.82 | F92: =SUMIFS(E$2:E92, C$2:C92, C92) -> 3523.64
A93: 23 | B93: 2026-08-23 | C93: WBS-400 | D93: Pruebas Hidráulicas, Desinfección y Entrega | E93: =IF(AND(A93>='01_PRESUPUESTO_CRONOGRAMA_BASE'!K12, A93<='01_PRESUPUESTO_CRONOGRAMA_BASE'!L12), '01_PRESUPUESTO_CRONOGRAMA_BASE'!M12, 0) -> 0 | F93: =SUMIFS(E$2:E93, C$2:C93, C93) -> 0
A94: 24 | B94: 2026-08-24 | C94: WBS-100 | D94: Obras Preliminares, Trazo y Movilización | E94: =IF(AND(A94>='01_PRESUPUESTO_CRONOGRAMA_BASE'!K2, A94<='01_PRESUPUESTO_CRONOGRAMA_BASE'!L2), '01_PRESUPUESTO_CRONOGRAMA_BASE'!M2, 0) + IF(AND(A94>='01_PRESUPUESTO_CRONOGRAMA_BASE'!K3, A94<='01_PRESUPUESTO_CRONOGRAMA_BASE'!L3), '01_PRESUPUESTO_CRONOGRAMA_BASE'!M3, 0) -> 0 | F94: =SUMIFS(E$2:E94, C$2:C94, C94) -> 16336.46
A95: 24 | B95: 2026-08-24 | C95: WBS-200 | D95: Red de Alcantarillado, Zanjas y Buzones | E95: =IF(AND(A95>='01_PRESUPUESTO_CRONOGRAMA_BASE'!K4, A95<='01_PRESUPUESTO_CRONOGRAMA_BASE'!L4), '01_PRESUPUESTO_CRONOGRAMA_BASE'!M4, 0) + IF(AND(A95>='01_PRESUPUESTO_CRONOGRAMA_BASE'!K5, A95<='01_PRESUPUESTO_CRONOGRAMA_BASE'!L5), '01_PRESUPUESTO_CRONOGRAMA_BASE'!M5, 0) + IF(AND(A95>='01_PRESUPUESTO_CRONOGRAMA_BASE'!K6, A95<='01_PRESUPUESTO_CRONOGRAMA_BASE'!L6), '01_PRESUPUESTO_CRONOGRAMA_BASE'!M6, 0) + IF(AND(A95>='01_PRESUPUESTO_CRONOGRAMA_BASE'!K7, A95<='01_PRESUPUESTO_CRONOGRAMA_BASE'!L7), '01_PRESUPUESTO_CRONOGRAMA_BASE'!M7, 0) + IF(AND(A95>='01_PRESUPUESTO_CRONOGRAMA_BASE'!K8, A95<='01_PRESUPUESTO_CRONOGRAMA_BASE'!L8), '01_PRESUPUESTO_CRONOGRAMA_BASE'!M8, 0) + IF(AND(A95>='01_PRESUPUESTO_CRONOGRAMA_BASE'!K9, A95<='01_PRESUPUESTO_CRONOGRAMA_BASE'!L9), '01_PRESUPUESTO_CRONOGRAMA_BASE'!M9, 0) -> 17897.81 | F95: =SUMIFS(E$2:E95, C$2:C95, C95) -> 154800.7
A96: 24 | B96: 2026-08-24 | C96: WBS-300 | D96: Red de Agua Potable y Conexiones Domiciliarias | E96: =IF(AND(A96>='01_PRESUPUESTO_CRONOGRAMA_BASE'!K10, A96<='01_PRESUPUESTO_CRONOGRAMA_BASE'!L10), '01_PRESUPUESTO_CRONOGRAMA_BASE'!M10, 0) + IF(AND(A96>='01_PRESUPUESTO_CRONOGRAMA_BASE'!K11, A96<='01_PRESUPUESTO_CRONOGRAMA_BASE'!L11), '01_PRESUPUESTO_CRONOGRAMA_BASE'!M11, 0) -> 1761.82 | F96: =SUMIFS(E$2:E96, C$2:C96, C96) -> 5285.46
A97: 24 | B97: 2026-08-24 | C97: WBS-400 | D97: Pruebas Hidráulicas, Desinfección y Entrega | E97: =IF(AND(A97>='01_PRESUPUESTO_CRONOGRAMA_BASE'!K12, A97<='01_PRESUPUESTO_CRONOGRAMA_BASE'!L12), '01_PRESUPUESTO_CRONOGRAMA_BASE'!M12, 0) -> 0 | F97: =SUMIFS(E$2:E97, C$2:C97, C97) -> 0
A98: 25 | B98: 2026-08-25 | C98: WBS-100 | D98: Obras Preliminares, Trazo y Movilización | E98: =IF(AND(A98>='01_PRESUPUESTO_CRONOGRAMA_BASE'!K2, A98<='01_PRESUPUESTO_CRONOGRAMA_BASE'!L2), '01_PRESUPUESTO_CRONOGRAMA_BASE'!M2, 0) + IF(AND(A98>='01_PRESUPUESTO_CRONOGRAMA_BASE'!K3, A98<='01_PRESUPUESTO_CRONOGRAMA_BASE'!L3), '01_PRESUPUESTO_CRONOGRAMA_BASE'!M3, 0) -> 0 | F98: =SUMIFS(E$2:E98, C$2:C98, C98) -> 16336.46
A99: 25 | B99: 2026-08-25 | C99: WBS-200 | D99: Red de Alcantarillado, Zanjas y Buzones | E99: =IF(AND(A99>='01_PRESUPUESTO_CRONOGRAMA_BASE'!K4, A99<='01_PRESUPUESTO_CRONOGRAMA_BASE'!L4), '01_PRESUPUESTO_CRONOGRAMA_BASE'!M4, 0) + IF(AND(A99>='01_PRESUPUESTO_CRONOGRAMA_BASE'!K5, A99<='01_PRESUPUESTO_CRONOGRAMA_BASE'!L5), '01_PRESUPUESTO_CRONOGRAMA_BASE'!M5, 0) + IF(AND(A99>='01_PRESUPUESTO_CRONOGRAMA_BASE'!K6, A99<='01_PRESUPUESTO_CRONOGRAMA_BASE'!L6), '01_PRESUPUESTO_CRONOGRAMA_BASE'!M6, 0) + IF(AND(A99>='01_PRESUPUESTO_CRONOGRAMA_BASE'!K7, A99<='01_PRESUPUESTO_CRONOGRAMA_BASE'!L7), '01_PRESUPUESTO_CRONOGRAMA_BASE'!M7, 0) + IF(AND(A99>='01_PRESUPUESTO_CRONOGRAMA_BASE'!K8, A99<='01_PRESUPUESTO_CRONOGRAMA_BASE'!L8), '01_PRESUPUESTO_CRONOGRAMA_BASE'!M8, 0) + IF(AND(A99>='01_PRESUPUESTO_CRONOGRAMA_BASE'!K9, A99<='01_PRESUPUESTO_CRONOGRAMA_BASE'!L9), '01_PRESUPUESTO_CRONOGRAMA_BASE'!M9, 0) -> 17897.81 | F99: =SUMIFS(E$2:E99, C$2:C99, C99) -> 172698.51
A100: 25 | B100: 2026-08-25 | C100: WBS-300 | D100: Red de Agua Potable y Conexiones Domiciliarias | E100: =IF(AND(A100>='01_PRESUPUESTO_CRONOGRAMA_BASE'!K10, A100<='01_PRESUPUESTO_CRONOGRAMA_BASE'!L10), '01_PRESUPUESTO_CRONOGRAMA_BASE'!M10, 0) + IF(AND(A100>='01_PRESUPUESTO_CRONOGRAMA_BASE'!K11, A100<='01_PRESUPUESTO_CRONOGRAMA_BASE'!L11), '01_PRESUPUESTO_CRONOGRAMA_BASE'!M11, 0) -> 1761.82 | F100: =SUMIFS(E$2:E100, C$2:C100, C100) -> 7047.28
...

Sheet 03_CONSOLIDADO_DIARIO_EVM_WBS
A1: N° Día Obra | B1: Fecha Obra | C1: Código WBS | D1: Nombre Frente WBS | E1: Presupuesto BAC (S/) | F1: PV Programado Día (S/) | G1: PV Acumulado (S/) | H1: EV Ejecutado Día (S/) | I1: EV Acumulado (S/) | J1: AC Costo Real Día (S/) | K1: AC Acumulado (S/) | L1: Variación Costo CV (S/) | M1: Variación Plazo SV (S/) | N1: SPI Plazo (EV/PV) | O1: CPI Costo (EV/AC) | P1: Estado Alerta WBS
A2: 1 | B2: 2026-08-01 | C2: WBS-100 | D2: Obras Preliminares, Trazo y Movilización | E2: =SUM('01_PRESUPUESTO_CRONOGRAMA_BASE'!G2:G3) -> 16336.4 | F2: =SUMIFS('02_CRONOGRAMA_PV_DIARIO'!E:E, '02_CRONOGRAMA_PV_DIARIO'!A:A, A2, '02_CRONOGRAMA_PV_DIARIO'!C:C, C2) -> 1166.89 | G2: =SUMIFS(F$2:F2, C$2:C2, C2) -> 1166.89 | H2: =SUMIFS('04_LOG_FIELD_ENTRIES'!J:J, '04_LOG_FIELD_ENTRIES'!B:B, B2, '04_LOG_FIELD_ENTRIES'!D:D, C2, '04_LOG_FIELD_ENTRIES'!K:K, "EV_PRODUCCION") -> 5823.2 | I2: =SUMIFS(H$2:H2, C$2:C2, C2) -> 5823.2 | J2: =SUMIFS('04_LOG_FIELD_ENTRIES'!J:J, '04_LOG_FIELD_ENTRIES'!B:B, B2, '04_LOG_FIELD_ENTRIES'!D:D, C2, '04_LOG_FIELD_ENTRIES'!K:K, "AC_*") -> 6331 | K2: =SUMIFS(J$2:J2, C$2:C2, C2) -> 6331 | L2: =I2-K2 -> -507.8 | M2: =I2-G2 -> 4656.31 | N2: =IF(G2>0, I2/G2, 1) -> 4.990359 | O2: =IF(K2>0, I2/K2, 1) -> 0.9197915 | P2: =IF(AND(N2>=0.95, O2>=0.95), "SALUDABLE", IF(N2<0.9, "ALERTA RETRASO", "ALERTA SOBRECOSTO")) -> ALERTA SOBRECOSTO
A3: 1 | B3: 2026-08-01 | C3: WBS-200 | D3: Red de Alcantarillado, Zanjas y Buzones | E3: =SUM('01_PRESUPUESTO_CRONOGRAMA_BASE'!G4:G9) -> 372046.56 | F3: =SUMIFS('02_CRONOGRAMA_PV_DIARIO'!E:E, '02_CRONOGRAMA_PV_DIARIO'!A:A, A3, '02_CRONOGRAMA_PV_DIARIO'!C:C, C3) -> 0 | G3: =SUMIFS(F$2:F3, C$2:C3, C3) -> 0 | H3: =SUMIFS('04_LOG_FIELD_ENTRIES'!J:J, '04_LOG_FIELD_ENTRIES'!B:B, B3, '04_LOG_FIELD_ENTRIES'!D:D, C3, '04_LOG_FIELD_ENTRIES'!K:K, "EV_PRODUCCION") -> 0 | I3: =SUMIFS(H$2:H3, C$2:C3, C3) -> 0 | J3: =SUMIFS('04_LOG_FIELD_ENTRIES'!J:J, '04_LOG_FIELD_ENTRIES'!B:B, B3, '04_LOG_FIELD_ENTRIES'!D:D, C3, '04_LOG_FIELD_ENTRIES'!K:K, "AC_*") -> 0 | K3: =SUMIFS(J$2:J3, C$2:C3, C3) -> 0 | L3: =I3-K3 -> 0 | M3: =I3-G3 -> 0 | N3: =IF(G3>0, I3/G3, 1) -> 1 | O3: =IF(K3>0, I3/K3, 1) -> 1 | P3: =IF(AND(N3>=0.95, O3>=0.95), "SALUDABLE", IF(N3<0.9, "ALERTA RETRASO", "ALERTA SOBRECOSTO")) -> SALUDABLE
A4: 1 | B4: 2026-08-01 | C4: WBS-300 | D4: Red de Agua Potable y Conexiones Domiciliarias | E4: =SUM('01_PRESUPUESTO_CRONOGRAMA_BASE'!G10:G11) -> 57565.2 | F4: =SUMIFS('02_CRONOGRAMA_PV_DIARIO'!E:E, '02_CRONOGRAMA_PV_DIARIO'!A:A, A4, '02_CRONOGRAMA_PV_DIARIO'!C:C, C4) -> 0 | G4: =SUMIFS(F$2:F4, C$2:C4, C4) -> 0 | H4: =SUMIFS('04_LOG_FIELD_ENTRIES'!J:J, '04_LOG_FIELD_ENTRIES'!B:B, B4, '04_LOG_FIELD_ENTRIES'!D:D, C4, '04_LOG_FIELD_ENTRIES'!K:K, "EV_PRODUCCION") -> 0 | I4: =SUMIFS(H$2:H4, C$2:C4, C4) -> 0 | J4: =SUMIFS('04_LOG_FIELD_ENTRIES'!J:J, '04_LOG_FIELD_ENTRIES'!B:B, B4, '04_LOG_FIELD_ENTRIES'!D:D, C4, '04_LOG_FIELD_ENTRIES'!K:K, "AC_*") -> 0 | K4: =SUMIFS(J$2:J4, C$2:C4, C4) -> 0 | L4: =I4-K4 -> 0 | M4: =I4-G4 -> 0 | N4: =IF(G4>0, I4/G4, 1) -> 1 | O4: =IF(K4>0, I4/K4, 1) -> 1 | P4: =IF(AND(N4>=0.95, O4>=0.95), "SALUDABLE", IF(N4<0.9, "ALERTA RETRASO", "ALERTA SOBRECOSTO")) -> SALUDABLE
A5: 1 | B5: 2026-08-01 | C5: WBS-400 | D5: Pruebas Hidráulicas, Desinfección y Entrega | E5: =SUM('01_PRESUPUESTO_CRONOGRAMA_BASE'!G12:G12) -> 9348.06 | F5: =SUMIFS('02_CRONOGRAMA_PV_DIARIO'!E:E, '02_CRONOGRAMA_PV_DIARIO'!A:A, A5, '02_CRONOGRAMA_PV_DIARIO'!C:C, C5) -> 0 | G5: =SUMIFS(F$2:F5, C$2:C5, C5) -> 0 | H5: =SUMIFS('04_LOG_FIELD_ENTRIES'!J:J, '04_LOG_FIELD_ENTRIES'!B:B, B5, '04_LOG_FIELD_ENTRIES'!D:D, C5, '04_LOG_FIELD_ENTRIES'!K:K, "EV_PRODUCCION") -> 0 | I5: =SUMIFS(H$2:H5, C$2:C5, C5) -> 0 | J5: =SUMIFS('04_LOG_FIELD_ENTRIES'!J:J, '04_LOG_FIELD_ENTRIES'!B:B, B5, '04_LOG_FIELD_ENTRIES'!D:D, C5, '04_LOG_FIELD_ENTRIES'!K:K, "AC_*") -> 0 | K5: =SUMIFS(J$2:J5, C$2:C5, C5) -> 0 | L5: =I5-K5 -> 0 | M5: =I5-G5 -> 0 | N5: =IF(G5>0, I5/G5, 1) -> 1 | O5: =IF(K5>0, I5/K5, 1) -> 1 | P5: =IF(AND(N5>=0.95, O5>=0.95), "SALUDABLE", IF(N5<0.9, "ALERTA RETRASO", "ALERTA SOBRECOSTO")) -> SALUDABLE
A6: 2 | B6: 2026-08-02 | C6: WBS-100 | D6: Obras Preliminares, Trazo y Movilización | E6: =SUM('01_PRESUPUESTO_CRONOGRAMA_BASE'!G2:G3) -> 16336.4 | F6: =SUMIFS('02_CRONOGRAMA_PV_DIARIO'!E:E, '02_CRONOGRAMA_PV_DIARIO'!A:A, A6, '02_CRONOGRAMA_PV_DIARIO'!C:C, C6) -> 1166.89 | G6: =SUMIFS(F$2:F6, C$2:C6, C6) -> 2333.78 | H6: =SUMIFS('04_LOG_FIELD_ENTRIES'!J:J, '04_LOG_FIELD_ENTRIES'!B:B, B6, '04_LOG_FIELD_ENTRIES'!D:D, C6, '04_LOG_FIELD_ENTRIES'!K:K, "EV_PRODUCCION") -> 0 | I6: =SUMIFS(H$2:H6, C$2:C6, C6) -> 5823.2 | J6: =SUMIFS('04_LOG_FIELD_ENTRIES'!J:J, '04_LOG_FIELD_ENTRIES'!B:B, B6, '04_LOG_FIELD_ENTRIES'!D:D, C6, '04_LOG_FIELD_ENTRIES'!K:K, "AC_*") -> 0 | K6: =SUMIFS(J$2:J6, C$2:C6, C6) -> 6331 | L6: =I6-K6 -> -507.8 | M6: =I6-G6 -> 3489.42 | N6: =IF(G6>0, I6/G6, 1) -> 2.4951795 | O6: =IF(K6>0, I6/K6, 1) -> 0.9197915 | P6: =IF(AND(N6>=0.95, O6>=0.95), "SALUDABLE", IF(N6<0.9, "ALERTA RETRASO", "ALERTA SOBRECOSTO")) -> ALERTA SOBRECOSTO
A7: 2 | B7: 2026-08-02 | C7: WBS-200 | D7: Red de Alcantarillado, Zanjas y Buzones | E7: =SUM('01_PRESUPUESTO_CRONOGRAMA_BASE'!G4:G9) -> 372046.56 | F7: =SUMIFS('02_CRONOGRAMA_PV_DIARIO'!E:E, '02_CRONOGRAMA_PV_DIARIO'!A:A, A7, '02_CRONOGRAMA_PV_DIARIO'!C:C, C7) -> 0 | G7: =SUMIFS(F$2:F7, C$2:C7, C7) -> 0 | H7: =SUMIFS('04_LOG_FIELD_ENTRIES'!J:J, '04_LOG_FIELD_ENTRIES'!B:B, B7, '04_LOG_FIELD_ENTRIES'!D:D, C7, '04_LOG_FIELD_ENTRIES'!K:K, "EV_PRODUCCION") -> 8583 | I7: =SUMIFS(H$2:H7, C$2:C7, C7) -> 8583 | J7: =SUMIFS('04_LOG_FIELD_ENTRIES'!J:J, '04_LOG_FIELD_ENTRIES'!B:B, B7, '04_LOG_FIELD_ENTRIES'!D:D, C7, '04_LOG_FIELD_ENTRIES'!K:K, "AC_*") -> 4923 | K7: =SUMIFS(J$2:J7, C$2:C7, C7) -> 4923 | L7: =I7-K7 -> 3660 | M7: =I7-G7 -> 8583 | N7: =IF(G7>0, I7/G7, 1) -> 1 | O7: =IF(K7>0, I7/K7, 1) -> 1.7434491 | P7: =IF(AND(N7>=0.95, O7>=0.95), "SALUDABLE", IF(N7<0.9, "ALERTA RETRASO", "ALERTA SOBRECOSTO")) -> SALUDABLE
A8: 2 | B8: 2026-08-02 | C8: WBS-300 | D8: Red de Agua Potable y Conexiones Domiciliarias | E8: =SUM('01_PRESUPUESTO_CRONOGRAMA_BASE'!G10:G11) -> 57565.2 | F8: =SUMIFS('02_CRONOGRAMA_PV_DIARIO'!E:E, '02_CRONOGRAMA_PV_DIARIO'!A:A, A8, '02_CRONOGRAMA_PV_DIARIO'!C:C, C8) -> 0 | G8: =SUMIFS(F$2:F8, C$2:C8, C8) -> 0 | H8: =SUMIFS('04_LOG_FIELD_ENTRIES'!J:J, '04_LOG_FIELD_ENTRIES'!B:B, B8, '04_LOG_FIELD_ENTRIES'!D:D, C8, '04_LOG_FIELD_ENTRIES'!K:K, "EV_PRODUCCION") -> 0 | I8: =SUMIFS(H$2:H8, C$2:C8, C8) -> 0 | J8: =SUMIFS('04_LOG_FIELD_ENTRIES'!J:J, '04_LOG_FIELD_ENTRIES'!B:B, B8, '04_LOG_FIELD_ENTRIES'!D:D, C8, '04_LOG_FIELD_ENTRIES'!K:K, "AC_*") -> 0 | K8: =SUMIFS(J$2:J8, C$2:C8, C8) -> 0 | L8: =I8-K8 -> 0 | M8: =I8-G8 -> 0 | N8: =IF(G8>0, I8/G8, 1) -> 1 | O8: =IF(K8>0, I8/K8, 1) -> 1 | P8: =IF(AND(N8>=0.95, O8>=0.95), "SALUDABLE", IF(N8<0.9, "ALERTA RETRASO", "ALERTA SOBRECOSTO")) -> SALUDABLE
A9: 2 | B9: 2026-08-02 | C9: WBS-400 | D9: Pruebas Hidráulicas, Desinfección y Entrega | E9: =SUM('01_PRESUPUESTO_CRONOGRAMA_BASE'!G12:G12) -> 9348.06 | F9: =SUMIFS('02_CRONOGRAMA_PV_DIARIO'!E:E, '02_CRONOGRAMA_PV_DIARIO'!A:A, A9, '02_CRONOGRAMA_PV_DIARIO'!C:C, C9) -> 0 | G9: =SUMIFS(F$2:F9, C$2:C9, C9) -> 0 | H9: =SUMIFS('04_LOG_FIELD_ENTRIES'!J:J, '04_LOG_FIELD_ENTRIES'!B:B, B9, '04_LOG_FIELD_ENTRIES'!D:D, C9, '04_LOG_FIELD_ENTRIES'!K:K, "EV_PRODUCCION") -> 0 | I9: =SUMIFS(H$2:H9, C$2:C9, C9) -> 0 | J9: =SUMIFS('04_LOG_FIELD_ENTRIES'!J:J, '04_LOG_FIELD_ENTRIES'!B:B, B9, '04_LOG_FIELD_ENTRIES'!D:D, C9, '04_LOG_FIELD_ENTRIES'!K:K, "AC_*") -> 0 | K9: =SUMIFS(J$2:J9, C$2:C9, C9) -> 0 | L9: =I9-K9 -> 0 | M9: =I9-G9 -> 0 | N9: =IF(G9>0, I9/G9, 1) -> 1 | O9: =IF(K9>0, I9/K9, 1) -> 1 | P9: =IF(AND(N9>=0.95, O9>=0.95), "SALUDABLE", IF(N9<0.9, "ALERTA RETRASO", "ALERTA SOBRECOSTO")) -> SALUDABLE
A10: 3 | B10: 2026-08-03 | C10: WBS-100 | D10: Obras Preliminares, Trazo y Movilización | E10: =SUM('01_PRESUPUESTO_CRONOGRAMA_BASE'!G2:G3) -> 16336.4 | F10: =SUMIFS('02_CRONOGRAMA_PV_DIARIO'!E:E, '02_CRONOGRAMA_PV_DIARIO'!A:A, A10, '02_CRONOGRAMA_PV_DIARIO'!C:C, C10) -> 1166.89 | G10: =SUMIFS(F$2:F10, C$2:C10, C10) -> 3500.67 | H10: =SUMIFS('04_LOG_FIELD_ENTRIES'!J:J, '04_LOG_FIELD_ENTRIES'!B:B, B10, '04_LOG_FIELD_ENTRIES'!D:D, C10, '04_LOG_FIELD_ENTRIES'!K:K, "EV_PRODUCCION") -> 0 | I10: =SUMIFS(H$2:H10, C$2:C10, C10) -> 5823.2 | J10: =SUMIFS('04_LOG_FIELD_ENTRIES'!J:J, '04_LOG_FIELD_ENTRIES'!B:B, B10, '04_LOG_FIELD_ENTRIES'!D:D, C10, '04_LOG_FIELD_ENTRIES'!K:K, "AC_*") -> 0 | K10: =SUMIFS(J$2:J10, C$2:C10, C10) -> 6331 | L10: =I10-K10 -> -507.8 | M10: =I10-G10 -> 2322.53 | N10: =IF(G10>0, I10/G10, 1) -> 1.663453 | O10: =IF(K10>0, I10/K10, 1) -> 0.9197915 | P10: =IF(AND(N10>=0.95, O10>=0.95), "SALUDABLE", IF(N10<0.9, "ALERTA RETRASO", "ALERTA SOBRECOSTO")) -> ALERTA SOBRECOSTO
A11: 3 | B11: 2026-08-03 | C11: WBS-200 | D11: Red de Alcantarillado, Zanjas y Buzones | E11: =SUM('01_PRESUPUESTO_CRONOGRAMA_BASE'!G4:G9) -> 372046.56 | F11: =SUMIFS('02_CRONOGRAMA_PV_DIARIO'!E:E, '02_CRONOGRAMA_PV_DIARIO'!A:A, A11, '02_CRONOGRAMA_PV_DIARIO'!C:C, C11) -> 0 | G11: =SUMIFS(F$2:F11, C$2:C11, C11) -> 0 | H11: =SUMIFS('04_LOG_FIELD_ENTRIES'!J:J, '04_LOG_FIELD_ENTRIES'!B:B, B11, '04_LOG_FIELD_ENTRIES'!D:D, C11, '04_LOG_FIELD_ENTRIES'!K:K, "EV_PRODUCCION") -> 19585.5 | I11: =SUMIFS(H$2:H11, C$2:C11, C11) -> 28168.5 | J11: =SUMIFS('04_LOG_FIELD_ENTRIES'!J:J, '04_LOG_FIELD_ENTRIES'!B:B, B11, '04_LOG_FIELD_ENTRIES'!D:D, C11, '04_LOG_FIELD_ENTRIES'!K:K, "AC_*") -> 17373.6 | K11: =SUMIFS(J$2:J11, C$2:C11, C11) -> 22296.6 | L11: =I11-K11 -> 5871.9 | M11: =I11-G11 -> 28168.5 | N11: =IF(G11>0, I11/G11, 1) -> 1 | O11: =IF(K11>0, I11/K11, 1) -> 1.2633541 | P11: =IF(AND(N11>=0.95, O11>=0.95), "SALUDABLE", IF(N11<0.9, "ALERTA RETRASO", "ALERTA SOBRECOSTO")) -> SALUDABLE
A12: 3 | B12: 2026-08-03 | C12: WBS-300 | D12: Red de Agua Potable y Conexiones Domiciliarias | E12: =SUM('01_PRESUPUESTO_CRONOGRAMA_BASE'!G10:G11) -> 57565.2 | F12: =SUMIFS('02_CRONOGRAMA_PV_DIARIO'!E:E, '02_CRONOGRAMA_PV_DIARIO'!A:A, A12, '02_CRONOGRAMA_PV_DIARIO'!C:C, C12) -> 0 | G12: =SUMIFS(F$2:F12, C$2:C12, C12) -> 0 | H12: =SUMIFS('04_LOG_FIELD_ENTRIES'!J:J, '04_LOG_FIELD_ENTRIES'!B:B, B12, '04_LOG_FIELD_ENTRIES'!D:D, C12, '04_LOG_FIELD_ENTRIES'!K:K, "EV_PRODUCCION") -> 0 | I12: =SUMIFS(H$2:H12, C$2:C12, C12) -> 0 | J12: =SUMIFS('04_LOG_FIELD_ENTRIES'!J:J, '04_LOG_FIELD_ENTRIES'!B:B, B12, '04_LOG_FIELD_ENTRIES'!D:D, C12, '04_LOG_FIELD_ENTRIES'!K:K, "AC_*") -> 0 | K12: =SUMIFS(J$2:J12, C$2:C12, C12) -> 0 | L12: =I12-K12 -> 0 | M12: =I12-G12 -> 0 | N12: =IF(G12>0, I12/G12, 1) -> 1 | O12: =IF(K12>0, I12/K12, 1) -> 1 | P12: =IF(AND(N12>=0.95, O12>=0.95), "SALUDABLE", IF(N12<0.9, "ALERTA RETRASO", "ALERTA SOBRECOSTO")) -> SALUDABLE
A13: 3 | B13: 2026-08-03 | C13: WBS-400 | D13: Pruebas Hidráulicas, Desinfección y Entrega | E13: =SUM('01_PRESUPUESTO_CRONOGRAMA_BASE'!G12:G12) -> 9348.06 | F13: =SUMIFS('02_CRONOGRAMA_PV_DIARIO'!E:E, '02_CRONOGRAMA_PV_DIARIO'!A:A, A13, '02_CRONOGRAMA_PV_DIARIO'!C:C, C13) -> 0 | G13: =SUMIFS(F$2:F13, C$2:C13, C13) -> 0 | H13: =SUMIFS('04_LOG_FIELD_ENTRIES'!J:J, '04_LOG_FIELD_ENTRIES'!B:B, B13, '04_LOG_FIELD_ENTRIES'!D:D, C13, '04_LOG_FIELD_ENTRIES'!K:K, "EV_PRODUCCION") -> 0 | I13: =SUMIFS(H$2:H13, C$2:C13, C13) -> 0 | J13: =SUMIFS('04_LOG_FIELD_ENTRIES'!J:J, '04_LOG_FIELD_ENTRIES'!B:B, B13, '04_LOG_FIELD_ENTRIES'!D:D, C13, '04_LOG_FIELD_ENTRIES'!K:K, "AC_*") -> 0 | K13: =SUMIFS(J$2:J13, C$2:C13, C13) -> 0 | L13: =I13-K13 -> 0 | M13: =I13-G13 -> 0 | N13: =IF(G13>0, I13/G13, 1) -> 1 | O13: =IF(K13>0, I13/K13, 1) -> 1 | P13: =IF(AND(N13>=0.95, O13>=0.95), "SALUDABLE", IF(N13<0.9, "ALERTA RETRASO", "ALERTA SOBRECOSTO")) -> SALUDABLE
A14: 4 | B14: 2026-08-04 | C14: WBS-100 | D14: Obras Preliminares, Trazo y Movilización | E14: =SUM('01_PRESUPUESTO_CRONOGRAMA_BASE'!G2:G3) -> 16336.4 | F14: =SUMIFS('02_CRONOGRAMA_PV_DIARIO'!E:E, '02_CRONOGRAMA_PV_DIARIO'!A:A, A14, '02_CRONOGRAMA_PV_DIARIO'!C:C, C14) -> 1166.89 | G14: =SUMIFS(F$2:F14, C$2:C14, C14) -> 4667.56 | H14: =SUMIFS('04_LOG_FIELD_ENTRIES'!J:J, '04_LOG_FIELD_ENTRIES'!B:B, B14, '04_LOG_FIELD_ENTRIES'!D:D, C14, '04_LOG_FIELD_ENTRIES'!K:K, "EV_PRODUCCION") -> 0 | I14: =SUMIFS(H$2:H14, C$2:C14, C14) -> 5823.2 | J14: =SUMIFS('04_LOG_FIELD_ENTRIES'!J:J, '04_LOG_FIELD_ENTRIES'!B:B, B14, '04_LOG_FIELD_ENTRIES'!D:D, C14, '04_LOG_FIELD_ENTRIES'!K:K, "AC_*") -> 0 | K14: =SUMIFS(J$2:J14, C$2:C14, C14) -> 6331 | L14: =I14-K14 -> -507.8 | M14: =I14-G14 -> 1155.64 | N14: =IF(G14>0, I14/G14, 1) -> 1.2475897 | O14: =IF(K14>0, I14/K14, 1) -> 0.9197915 | P14: =IF(AND(N14>=0.95, O14>=0.95), "SALUDABLE", IF(N14<0.9, "ALERTA RETRASO", "ALERTA SOBRECOSTO")) -> ALERTA SOBRECOSTO
A15: 4 | B15: 2026-08-04 | C15: WBS-200 | D15: Red de Alcantarillado, Zanjas y Buzones | E15: =SUM('01_PRESUPUESTO_CRONOGRAMA_BASE'!G4:G9) -> 372046.56 | F15: =SUMIFS('02_CRONOGRAMA_PV_DIARIO'!E:E, '02_CRONOGRAMA_PV_DIARIO'!A:A, A15, '02_CRONOGRAMA_PV_DIARIO'!C:C, C15) -> 0 | G15: =SUMIFS(F$2:F15, C$2:C15, C15) -> 0 | H15: =SUMIFS('04_LOG_FIELD_ENTRIES'!J:J, '04_LOG_FIELD_ENTRIES'!B:B, B15, '04_LOG_FIELD_ENTRIES'!D:D, C15, '04_LOG_FIELD_ENTRIES'!K:K, "EV_PRODUCCION") -> 10002.92 | I15: =SUMIFS(H$2:H15, C$2:C15, C15) -> 38171.42 | J15: =SUMIFS('04_LOG_FIELD_ENTRIES'!J:J, '04_LOG_FIELD_ENTRIES'!B:B, B15, '04_LOG_FIELD_ENTRIES'!D:D, C15, '04_LOG_FIELD_ENTRIES'!K:K, "AC_*") -> 6588.8 | K15: =SUMIFS(J$2:J15, C$2:C15, C15) -> 28885.4 | L15: =I15-K15 -> 9286.02 | M15: =I15-G15 -> 38171.42 | N15: =IF(G15>0, I15/G15, 1) -> 1 | O15: =IF(K15>0, I15/K15, 1) -> 1.321478 | P15: =IF(AND(N15>=0.95, O15>=0.95), "SALUDABLE", IF(N15<0.9, "ALERTA RETRASO", "ALERTA SOBRECOSTO")) -> SALUDABLE
A16: 4 | B16: 2026-08-04 | C16: WBS-300 | D16: Red de Agua Potable y Conexiones Domiciliarias | E16: =SUM('01_PRESUPUESTO_CRONOGRAMA_BASE'!G10:G11) -> 57565.2 | F16: =SUMIFS('02_CRONOGRAMA_PV_DIARIO'!E:E, '02_CRONOGRAMA_PV_DIARIO'!A:A, A16, '02_CRONOGRAMA_PV_DIARIO'!C:C, C16) -> 0 | G16: =SUMIFS(F$2:F16, C$2:C16, C16) -> 0 | H16: =SUMIFS('04_LOG_FIELD_ENTRIES'!J:J, '04_LOG_FIELD_ENTRIES'!B:B, B16, '04_LOG_FIELD_ENTRIES'!D:D, C16, '04_LOG_FIELD_ENTRIES'!K:K, "EV_PRODUCCION") -> 6976.8 | I16: =SUMIFS(H$2:H16, C$2:C16, C16) -> 6976.8 | J16: =SUMIFS('04_LOG_FIELD_ENTRIES'!J:J, '04_LOG_FIELD_ENTRIES'!B:B, B16, '04_LOG_FIELD_ENTRIES'!D:D, C16, '04_LOG_FIELD_ENTRIES'!K:K, "AC_*") -> 6372 | K16: =SUMIFS(J$2:J16, C$2:C16, C16) -> 6372 | L16: =I16-K16 -> 604.8 | M16: =I16-G16 -> 6976.8 | N16: =IF(G16>0, I16/G16, 1) -> 1 | O16: =IF(K16>0, I16/K16, 1) -> 1.0949153 | P16: =IF(AND(N16>=0.95, O16>=0.95), "SALUDABLE", IF(N16<0.9, "ALERTA RETRASO", "ALERTA SOBRECOSTO")) -> SALUDABLE
A17: 4 | B17: 2026-08-04 | C17: WBS-400 | D17: Pruebas Hidráulicas, Desinfección y Entrega | E17: =SUM('01_PRESUPUESTO_CRONOGRAMA_BASE'!G12:G12) -> 9348.06 | F17: =SUMIFS('02_CRONOGRAMA_PV_DIARIO'!E:E, '02_CRONOGRAMA_PV_DIARIO'!A:A, A17, '02_CRONOGRAMA_PV_DIARIO'!C:C, C17) -> 0 | G17: =SUMIFS(F$2:F17, C$2:C17, C17) -> 0 | H17: =SUMIFS('04_LOG_FIELD_ENTRIES'!J:J, '04_LOG_FIELD_ENTRIES'!B:B, B17, '04_LOG_FIELD_ENTRIES'!D:D, C17, '04_LOG_FIELD_ENTRIES'!K:K, "EV_PRODUCCION") -> 0 | I17: =SUMIFS(H$2:H17, C$2:C17, C17) -> 0 | J17: =SUMIFS('04_LOG_FIELD_ENTRIES'!J:J, '04_LOG_FIELD_ENTRIES'!B:B, B17, '04_LOG_FIELD_ENTRIES'!D:D, C17, '04_LOG_FIELD_ENTRIES'!K:K, "AC_*") -> 0 | K17: =SUMIFS(J$2:J17, C$2:C17, C17) -> 0 | L17: =I17-K17 -> 0 | M17: =I17-G17 -> 0 | N17: =IF(G17>0, I17/G17, 1) -> 1 | O17: =IF(K17>0, I17/K17, 1) -> 1 | P17: =IF(AND(N17>=0.95, O17>=0.95), "SALUDABLE", IF(N17<0.9, "ALERTA RETRASO", "ALERTA SOBRECOSTO")) -> SALUDABLE
A18: 5 | B18: 2026-08-05 | C18: WBS-100 | D18: Obras Preliminares, Trazo y Movilización | E18: =SUM('01_PRESUPUESTO_CRONOGRAMA_BASE'!G2:G3) -> 16336.4 | F18: =SUMIFS('02_CRONOGRAMA_PV_DIARIO'!E:E, '02_CRONOGRAMA_PV_DIARIO'!A:A, A18, '02_CRONOGRAMA_PV_DIARIO'!C:C, C18) -> 1166.89 | G18: =SUMIFS(F$2:F18, C$2:C18, C18) -> 5834.45 | H18: =SUMIFS('04_LOG_FIELD_ENTRIES'!J:J, '04_LOG_FIELD_ENTRIES'!B:B, B18, '04_LOG_FIELD_ENTRIES'!D:D, C18, '04_LOG_FIELD_ENTRIES'!K:K, "EV_PRODUCCION") -> 0 | I18: =SUMIFS(H$2:H18, C$2:C18, C18) -> 5823.2 | J18: =SUMIFS('04_LOG_FIELD_ENTRIES'!J:J, '04_LOG_FIELD_ENTRIES'!B:B, B18, '04_LOG_FIELD_ENTRIES'!D:D, C18, '04_LOG_FIELD_ENTRIES'!K:K, "AC_*") -> 0 | K18: =SUMIFS(J$2:J18, C$2:C18, C18) -> 6331 | L18: =I18-K18 -> -507.8 | M18: =I18-G18 -> -11.25 | N18: =IF(G18>0, I18/G18, 1) -> 0.9980718 | O18: =IF(K18>0, I18/K18, 1) -> 0.9197915 | P18: =IF(AND(N18>=0.95, O18>=0.95), "SALUDABLE", IF(N18<0.9, "ALERTA RETRASO", "ALERTA SOBRECOSTO")) -> ALERTA SOBRECOSTO
A19: 5 | B19: 2026-08-05 | C19: WBS-200 | D19: Red de Alcantarillado, Zanjas y Buzones | E19: =SUM('01_PRESUPUESTO_CRONOGRAMA_BASE'!G4:G9) -> 372046.56 | F19: =SUMIFS('02_CRONOGRAMA_PV_DIARIO'!E:E, '02_CRONOGRAMA_PV_DIARIO'!A:A, A19, '02_CRONOGRAMA_PV_DIARIO'!C:C, C19) -> 0 | G19: =SUMIFS(F$2:F19, C$2:C19, C19) -> 0 | H19: =SUMIFS('04_LOG_FIELD_ENTRIES'!J:J, '04_LOG_FIELD_ENTRIES'!B:B, B19, '04_LOG_FIELD_ENTRIES'!D:D, C19, '04_LOG_FIELD_ENTRIES'!K:K, "EV_PRODUCCION") -> 6083.1 | I19: =SUMIFS(H$2:H19, C$2:C19, C19) -> 44254.52 | J19: =SUMIFS('04_LOG_FIELD_ENTRIES'!J:J, '04_LOG_FIELD_ENTRIES'!B:B, B19, '04_LOG_FIELD_ENTRIES'!D:D, C19, '04_LOG_FIELD_ENTRIES'!K:K, "AC_*") -> 5383.8 | K19: =SUMIFS(J$2:J19, C$2:C19, C19) -> 34269.2 | L19: =I19-K19 -> 9985.32 | M19: =I19-G19 -> 44254.52 | N19: =IF(G19>0, I19/G19, 1) -> 1 | O19: =IF(K19>0, I19/K19, 1) -> 1.2913788 | P19: =IF(AND(N19>=0.95, O19>=0.95), "SALUDABLE", IF(N19<0.9, "ALERTA RETRASO", "ALERTA SOBRECOSTO")) -> SALUDABLE
A20: 5 | B20: 2026-08-05 | C20: WBS-300 | D20: Red de Agua Potable y Conexiones Domiciliarias | E20: =SUM('01_PRESUPUESTO_CRONOGRAMA_BASE'!G10:G11) -> 57565.2 | F20: =SUMIFS('02_CRONOGRAMA_PV_DIARIO'!E:E, '02_CRONOGRAMA_PV_DIARIO'!A:A, A20, '02_CRONOGRAMA_PV_DIARIO'!C:C, C20) -> 0 | G20: =SUMIFS(F$2:F20, C$2:C20, C20) -> 0 | H20: =SUMIFS('04_LOG_FIELD_ENTRIES'!J:J, '04_LOG_FIELD_ENTRIES'!B:B, B20, '04_LOG_FIELD_ENTRIES'!D:D, C20, '04_LOG_FIELD_ENTRIES'!K:K, "EV_PRODUCCION") -> 2350.65 | I20: =SUMIFS(H$2:H20, C$2:C20, C20) -> 9327.45 | J20: =SUMIFS('04_LOG_FIELD_ENTRIES'!J:J, '04_LOG_FIELD_ENTRIES'!B:B, B20, '04_LOG_FIELD_ENTRIES'!D:D, C20, '04_LOG_FIELD_ENTRIES'!K:K, "AC_*") -> 1358.8 | K20: =SUMIFS(J$2:J20, C$2:C20, C20) -> 7730.8 | L20: =I20-K20 -> 1596.65 | M20: =I20-G20 -> 9327.45 | N20: =IF(G20>0, I20/G20, 1) -> 1 | O20: =IF(K20>0, I20/K20, 1) -> 1.206531 | P20: =IF(AND(N20>=0.95, O20>=0.95), "SALUDABLE", IF(N20<0.9, "ALERTA RETRASO", "ALERTA SOBRECOSTO")) -> SALUDABLE
A21: 5 | B21: 2026-08-05 | C21: WBS-400 | D21: Pruebas Hidráulicas, Desinfección y Entrega | E21: =SUM('01_PRESUPUESTO_CRONOGRAMA_BASE'!G12:G12) -> 9348.06 | F21: =SUMIFS('02_CRONOGRAMA_PV_DIARIO'!E:E, '02_CRONOGRAMA_PV_DIARIO'!A:A, A21, '02_CRONOGRAMA_PV_DIARIO'!C:C, C21) -> 0 | G21: =SUMIFS(F$2:F21, C$2:C21, C21) -> 0 | H21: =SUMIFS('04_LOG_FIELD_ENTRIES'!J:J, '04_LOG_FIELD_ENTRIES'!B:B, B21, '04_LOG_FIELD_ENTRIES'!D:D, C21, '04_LOG_FIELD_ENTRIES'!K:K, "EV_PRODUCCION") -> 2337.02 | I21: =SUMIFS(H$2:H21, C$2:C21, C21) -> 2337.02 | J21: =SUMIFS('04_LOG_FIELD_ENTRIES'!J:J, '04_LOG_FIELD_ENTRIES'!B:B, B21, '04_LOG_FIELD_ENTRIES'!D:D, C21, '04_LOG_FIELD_ENTRIES'!K:K, "AC_*") -> 1299.2 | K21: =SUMIFS(J$2:J21, C$2:C21, C21) -> 1299.2 | L21: =I21-K21 -> 1037.82 | M21: =I21-G21 -> 2337.02 | N21: =IF(G21>0, I21/G21, 1) -> 1 | O21: =IF(K21>0, I21/K21, 1) -> 1.7988147 | P21: =IF(AND(N21>=0.95, O21>=0.95), "SALUDABLE", IF(N21<0.9, "ALERTA RETRASO", "ALERTA SOBRECOSTO")) -> SALUDABLE
A22: 6 | B22: 2026-08-06 | C22: WBS-100 | D22: Obras Preliminares, Trazo y Movilización | E22: =SUM('01_PRESUPUESTO_CRONOGRAMA_BASE'!G2:G3) -> 16336.4 | F22: =SUMIFS('02_CRONOGRAMA_PV_DIARIO'!E:E, '02_CRONOGRAMA_PV_DIARIO'!A:A, A22, '02_CRONOGRAMA_PV_DIARIO'!C:C, C22) -> 1166.89 | G22: =SUMIFS(F$2:F22, C$2:C22, C22) -> 7001.34 | H22: =SUMIFS('04_LOG_FIELD_ENTRIES'!J:J, '04_LOG_FIELD_ENTRIES'!B:B, B22, '04_LOG_FIELD_ENTRIES'!D:D, C22, '04_LOG_FIELD_ENTRIES'!K:K, "EV_PRODUCCION") -> 0 | I22: =SUMIFS(H$2:H22, C$2:C22, C22) -> 5823.2 | J22: =SUMIFS('04_LOG_FIELD_ENTRIES'!J:J, '04_LOG_FIELD_ENTRIES'!B:B, B22, '04_LOG_FIELD_ENTRIES'!D:D, C22, '04_LOG_FIELD_ENTRIES'!K:K, "AC_*") -> 0 | K22: =SUMIFS(J$2:J22, C$2:C22, C22) -> 6331 | L22: =I22-K22 -> -507.8 | M22: =I22-G22 -> -1178.14 | N22: =IF(G22>0, I22/G22, 1) -> 0.8317265 | O22: =IF(K22>0, I22/K22, 1) -> 0.9197915 | P22: =IF(AND(N22>=0.95, O22>=0.95), "SALUDABLE", IF(N22<0.9, "ALERTA RETRASO", "ALERTA SOBRECOSTO")) -> ALERTA RETRASO
A23: 6 | B23: 2026-08-06 | C23: WBS-200 | D23: Red de Alcantarillado, Zanjas y Buzones | E23: =SUM('01_PRESUPUESTO_CRONOGRAMA_BASE'!G4:G9) -> 372046.56 | F23: =SUMIFS('02_CRONOGRAMA_PV_DIARIO'!E:E, '02_CRONOGRAMA_PV_DIARIO'!A:A, A23, '02_CRONOGRAMA_PV_DIARIO'!C:C, C23) -> 0 | G23: =SUMIFS(F$2:F23, C$2:C23, C23) -> 0 | H23: =SUMIFS('04_LOG_FIELD_ENTRIES'!J:J, '04_LOG_FIELD_ENTRIES'!B:B, B23, '04_LOG_FIELD_ENTRIES'!D:D, C23, '04_LOG_FIELD_ENTRIES'!K:K, "EV_PRODUCCION") -> 0 | I23: =SUMIFS(H$2:H23, C$2:C23, C23) -> 44254.52 | J23: =SUMIFS('04_LOG_FIELD_ENTRIES'!J:J, '04_LOG_FIELD_ENTRIES'!B:B, B23, '04_LOG_FIELD_ENTRIES'!D:D, C23, '04_LOG_FIELD_ENTRIES'!K:K, "AC_*") -> 0 | K23: =SUMIFS(J$2:J23, C$2:C23, C23) -> 34269.2 | L23: =I23-K23 -> 9985.32 | M23: =I23-G23 -> 44254.52 | N23: =IF(G23>0, I23/G23, 1) -> 1 | O23: =IF(K23>0, I23/K23, 1) -> 1.2913788 | P23: =IF(AND(N23>=0.95, O23>=0.95), "SALUDABLE", IF(N23<0.9, "ALERTA RETRASO", "ALERTA SOBRECOSTO")) -> SALUDABLE
A24: 6 | B24: 2026-08-06 | C24: WBS-300 | D24: Red de Agua Potable y Conexiones Domiciliarias | E24: =SUM('01_PRESUPUESTO_CRONOGRAMA_BASE'!G10:G11) -> 57565.2 | F24: =SUMIFS('02_CRONOGRAMA_PV_DIARIO'!E:E, '02_CRONOGRAMA_PV_DIARIO'!A:A, A24, '02_CRONOGRAMA_PV_DIARIO'!C:C, C24) -> 0 | G24: =SUMIFS(F$2:F24, C$2:C24, C24) -> 0 | H24: =SUMIFS('04_LOG_FIELD_ENTRIES'!J:J, '04_LOG_FIELD_ENTRIES'!B:B, B24, '04_LOG_FIELD_ENTRIES'!D:D, C24, '04_LOG_FIELD_ENTRIES'!K:K, "EV_PRODUCCION") -> 0 | I24: =SUMIFS(H$2:H24, C$2:C24, C24) -> 9327.45 | J24: =SUMIFS('04_LOG_FIELD_ENTRIES'!J:J, '04_LOG_FIELD_ENTRIES'!B:B, B24, '04_LOG_FIELD_ENTRIES'!D:D, C24, '04_LOG_FIELD_ENTRIES'!K:K, "AC_*") -> 0 | K24: =SUMIFS(J$2:J24, C$2:C24, C24) -> 7730.8 | L24: =I24-K24 -> 1596.65 | M24: =I24-G24 -> 9327.45 | N24: =IF(G24>0, I24/G24, 1) -> 1 | O24: =IF(K24>0, I24/K24, 1) -> 1.206531 | P24: =IF(AND(N24>=0.95, O24>=0.95), "SALUDABLE", IF(N24<0.9, "ALERTA RETRASO", "ALERTA SOBRECOSTO")) -> SALUDABLE
A25: 6 | B25: 2026-08-06 | C25: WBS-400 | D25: Pruebas Hidráulicas, Desinfección y Entrega | E25: =SUM('01_PRESUPUESTO_CRONOGRAMA_BASE'!G12:G12) -> 9348.06 | F25: =SUMIFS('02_CRONOGRAMA_PV_DIARIO'!E:E, '02_CRONOGRAMA_PV_DIARIO'!A:A, A25, '02_CRONOGRAMA_PV_DIARIO'!C:C, C25) -> 0 | G25: =SUMIFS(F$2:F25, C$2:C25, C25) -> 0 | H25: =SUMIFS('04_LOG_FIELD_ENTRIES'!J:J, '04_LOG_FIELD_ENTRIES'!B:B, B25, '04_LOG_FIELD_ENTRIES'!D:D, C25, '04_LOG_FIELD_ENTRIES'!K:K, "EV_PRODUCCION") -> 0 | I25: =SUMIFS(H$2:H25, C$2:C25, C25) -> 2337.02 | J25: =SUMIFS('04_LOG_FIELD_ENTRIES'!J:J, '04_LOG_FIELD_ENTRIES'!B:B, B25, '04_LOG_FIELD_ENTRIES'!D:D, C25, '04_LOG_FIELD_ENTRIES'!K:K, "AC_*") -> 0 | K25: =SUMIFS(J$2:J25, C$2:C25, C25) -> 1299.2 | L25: =I25-K25 -> 1037.82 | M25: =I25-G25 -> 2337.02 | N25: =IF(G25>0, I25/G25, 1) -> 1 | O25: =IF(K25>0, I25/K25, 1) -> 1.7988147 | P25: =IF(AND(N25>=0.95, O25>=0.95), "SALUDABLE", IF(N25<0.9, "ALERTA RETRASO", "ALERTA SOBRECOSTO")) -> SALUDABLE
A26: 7 | B26: 2026-08-07 | C26: WBS-100 | D26: Obras Preliminares, Trazo y Movilización | E26: =SUM('01_PRESUPUESTO_CRONOGRAMA_BASE'!G2:G3) -> 16336.4 | F26: =SUMIFS('02_CRONOGRAMA_PV_DIARIO'!E:E, '02_CRONOGRAMA_PV_DIARIO'!A:A, A26, '02_CRONOGRAMA_PV_DIARIO'!C:C, C26) -> 1166.89 | G26: =SUMIFS(F$2:F26, C$2:C26, C26) -> 8168.23 | H26: =SUMIFS('04_LOG_FIELD_ENTRIES'!J:J, '04_LOG_FIELD_ENTRIES'!B:B, B26, '04_LOG_FIELD_ENTRIES'!D:D, C26, '04_LOG_FIELD_ENTRIES'!K:K, "EV_PRODUCCION") -> 0 | I26: =SUMIFS(H$2:H26, C$2:C26, C26) -> 5823.2 | J26: =SUMIFS('04_LOG_FIELD_ENTRIES'!J:J, '04_LOG_FIELD_ENTRIES'!B:B, B26, '04_LOG_FIELD_ENTRIES'!D:D, C26, '04_LOG_FIELD_ENTRIES'!K:K, "AC_*") -> 0 | K26: =SUMIFS(J$2:J26, C$2:C26, C26) -> 6331 | L26: =I26-K26 -> -507.8 | M26: =I26-G26 -> -2345.03 | N26: =IF(G26>0, I26/G26, 1) -> 0.71290843 | O26: =IF(K26>0, I26/K26, 1) -> 0.9197915 | P26: =IF(AND(N26>=0.95, O26>=0.95), "SALUDABLE", IF(N26<0.9, "ALERTA RETRASO", "ALERTA SOBRECOSTO")) -> ALERTA RETRASO
A27: 7 | B27: 2026-08-07 | C27: WBS-200 | D27: Red de Alcantarillado, Zanjas y Buzones | E27: =SUM('01_PRESUPUESTO_CRONOGRAMA_BASE'!G4:G9) -> 372046.56 | F27: =SUMIFS('02_CRONOGRAMA_PV_DIARIO'!E:E, '02_CRONOGRAMA_PV_DIARIO'!A:A, A27, '02_CRONOGRAMA_PV_DIARIO'!C:C, C27) -> 0 | G27: =SUMIFS(F$2:F27, C$2:C27, C27) -> 0 | H27: =SUMIFS('04_LOG_FIELD_ENTRIES'!J:J, '04_LOG_FIELD_ENTRIES'!B:B, B27, '04_LOG_FIELD_ENTRIES'!D:D, C27, '04_LOG_FIELD_ENTRIES'!K:K, "EV_PRODUCCION") -> 0 | I27: =SUMIFS(H$2:H27, C$2:C27, C27) -> 44254.52 | J27: =SUMIFS('04_LOG_FIELD_ENTRIES'!J:J, '04_LOG_FIELD_ENTRIES'!B:B, B27, '04_LOG_FIELD_ENTRIES'!D:D, C27, '04_LOG_FIELD_ENTRIES'!K:K, "AC_*") -> 0 | K27: =SUMIFS(J$2:J27, C$2:C27, C27) -> 34269.2 | L27: =I27-K27 -> 9985.32 | M27: =I27-G27 -> 44254.52 | N27: =IF(G27>0, I27/G27, 1) -> 1 | O27: =IF(K27>0, I27/K27, 1) -> 1.2913788 | P27: =IF(AND(N27>=0.95, O27>=0.95), "SALUDABLE", IF(N27<0.9, "ALERTA RETRASO", "ALERTA SOBRECOSTO")) -> SALUDABLE
A28: 7 | B28: 2026-08-07 | C28: WBS-300 | D28: Red de Agua Potable y Conexiones Domiciliarias | E28: =SUM('01_PRESUPUESTO_CRONOGRAMA_BASE'!G10:G11) -> 57565.2 | F28: =SUMIFS('02_CRONOGRAMA_PV_DIARIO'!E:E, '02_CRONOGRAMA_PV_DIARIO'!A:A, A28, '02_CRONOGRAMA_PV_DIARIO'!C:C, C28) -> 0 | G28: =SUMIFS(F$2:F28, C$2:C28, C28) -> 0 | H28: =SUMIFS('04_LOG_FIELD_ENTRIES'!J:J, '04_LOG_FIELD_ENTRIES'!B:B, B28, '04_LOG_FIELD_ENTRIES'!D:D, C28, '04_LOG_FIELD_ENTRIES'!K:K, "EV_PRODUCCION") -> 0 | I28: =SUMIFS(H$2:H28, C$2:C28, C28) -> 9327.45 | J28: =SUMIFS('04_LOG_FIELD_ENTRIES'!J:J, '04_LOG_FIELD_ENTRIES'!B:B, B28, '04_LOG_FIELD_ENTRIES'!D:D, C28, '04_LOG_FIELD_ENTRIES'!K:K, "AC_*") -> 0 | K28: =SUMIFS(J$2:J28, C$2:C28, C28) -> 7730.8 | L28: =I28-K28 -> 1596.65 | M28: =I28-G28 -> 9327.45 | N28: =IF(G28>0, I28/G28, 1) -> 1 | O28: =IF(K28>0, I28/K28, 1) -> 1.206531 | P28: =IF(AND(N28>=0.95, O28>=0.95), "SALUDABLE", IF(N28<0.9, "ALERTA RETRASO", "ALERTA SOBRECOSTO")) -> SALUDABLE
A29: 7 | B29: 2026-08-07 | C29: WBS-400 | D29: Pruebas Hidráulicas, Desinfección y Entrega | E29: =SUM('01_PRESUPUESTO_CRONOGRAMA_BASE'!G12:G12) -> 9348.06 | F29: =SUMIFS('02_CRONOGRAMA_PV_DIARIO'!E:E, '02_CRONOGRAMA_PV_DIARIO'!A:A, A29, '02_CRONOGRAMA_PV_DIARIO'!C:C, C29) -> 0 | G29: =SUMIFS(F$2:F29, C$2:C29, C29) -> 0 | H29: =SUMIFS('04_LOG_FIELD_ENTRIES'!J:J, '04_LOG_FIELD_ENTRIES'!B:B, B29, '04_LOG_FIELD_ENTRIES'!D:D, C29, '04_LOG_FIELD_ENTRIES'!K:K, "EV_PRODUCCION") -> 0 | I29: =SUMIFS(H$2:H29, C$2:C29, C29) -> 2337.02 | J29: =SUMIFS('04_LOG_FIELD_ENTRIES'!J:J, '04_LOG_FIELD_ENTRIES'!B:B, B29, '04_LOG_FIELD_ENTRIES'!D:D, C29, '04_LOG_FIELD_ENTRIES'!K:K, "AC_*") -> 0 | K29: =SUMIFS(J$2:J29, C$2:C29, C29) -> 1299.2 | L29: =I29-K29 -> 1037.82 | M29: =I29-G29 -> 2337.02 | N29: =IF(G29>0, I29/G29, 1) -> 1 | O29: =IF(K29>0, I29/K29, 1) -> 1.7988147 | P29: =IF(AND(N29>=0.95, O29>=0.95), "SALUDABLE", IF(N29<0.9, "ALERTA RETRASO", "ALERTA SOBRECOSTO")) -> SALUDABLE
A30: 8 | B30: 2026-08-08 | C30: WBS-100 | D30: Obras Preliminares, Trazo y Movilización | E30: =SUM('01_PRESUPUESTO_CRONOGRAMA_BASE'!G2:G3) -> 16336.4 | F30: =SUMIFS('02_CRONOGRAMA_PV_DIARIO'!E:E, '02_CRONOGRAMA_PV_DIARIO'!A:A, A30, '02_CRONOGRAMA_PV_DIARIO'!C:C, C30) -> 1166.89 | G30: =SUMIFS(F$2:F30, C$2:C30, C30) -> 9335.12 | H30: =SUMIFS('04_LOG_FIELD_ENTRIES'!J:J, '04_LOG_FIELD_ENTRIES'!B:B, B30, '04_LOG_FIELD_ENTRIES'!D:D, C30, '04_LOG_FIELD_ENTRIES'!K:K, "EV_PRODUCCION") -> 0 | I30: =SUMIFS(H$2:H30, C$2:C30, C30) -> 5823.2 | J30: =SUMIFS('04_LOG_FIELD_ENTRIES'!J:J, '04_LOG_FIELD_ENTRIES'!B:B, B30, '04_LOG_FIELD_ENTRIES'!D:D, C30, '04_LOG_FIELD_ENTRIES'!K:K, "AC_*") -> 0 | K30: =SUMIFS(J$2:J30, C$2:C30, C30) -> 6331 | L30: =I30-K30 -> -507.8 | M30: =I30-G30 -> -3511.92 | N30: =IF(G30>0, I30/G30, 1) -> 0.62379487 | O30: =IF(K30>0, I30/K30, 1) -> 0.9197915 | P30: =IF(AND(N30>=0.95, O30>=0.95), "SALUDABLE", IF(N30<0.9, "ALERTA RETRASO", "ALERTA SOBRECOSTO")) -> ALERTA RETRASO
A31: 8 | B31: 2026-08-08 | C31: WBS-200 | D31: Red de Alcantarillado, Zanjas y Buzones | E31: =SUM('01_PRESUPUESTO_CRONOGRAMA_BASE'!G4:G9) -> 372046.56 | F31: =SUMIFS('02_CRONOGRAMA_PV_DIARIO'!E:E, '02_CRONOGRAMA_PV_DIARIO'!A:A, A31, '02_CRONOGRAMA_PV_DIARIO'!C:C, C31) -> 0 | G31: =SUMIFS(F$2:F31, C$2:C31, C31) -> 0 | H31: =SUMIFS('04_LOG_FIELD_ENTRIES'!J:J, '04_LOG_FIELD_ENTRIES'!B:B, B31, '04_LOG_FIELD_ENTRIES'!D:D, C31, '04_LOG_FIELD_ENTRIES'!K:K, "EV_PRODUCCION") -> 0 | I31: =SUMIFS(H$2:H31, C$2:C31, C31) -> 44254.52 | J31: =SUMIFS('04_LOG_FIELD_ENTRIES'!J:J, '04_LOG_FIELD_ENTRIES'!B:B, B31, '04_LOG_FIELD_ENTRIES'!D:D, C31, '04_LOG_FIELD_ENTRIES'!K:K, "AC_*") -> 0 | K31: =SUMIFS(J$2:J31, C$2:C31, C31) -> 34269.2 | L31: =I31-K31 -> 9985.32 | M31: =I31-G31 -> 44254.52 | N31: =IF(G31>0, I31/G31, 1) -> 1 | O31: =IF(K31>0, I31/K31, 1) -> 1.2913788 | P31: =IF(AND(N31>=0.95, O31>=0.95), "SALUDABLE", IF(N31<0.9, "ALERTA RETRASO", "ALERTA SOBRECOSTO")) -> SALUDABLE
A32: 8 | B32: 2026-08-08 | C32: WBS-300 | D32: Red de Agua Potable y Conexiones Domiciliarias | E32: =SUM('01_PRESUPUESTO_CRONOGRAMA_BASE'!G10:G11) -> 57565.2 | F32: =SUMIFS('02_CRONOGRAMA_PV_DIARIO'!E:E, '02_CRONOGRAMA_PV_DIARIO'!A:A, A32, '02_CRONOGRAMA_PV_DIARIO'!C:C, C32) -> 0 | G32: =SUMIFS(F$2:F32, C$2:C32, C32) -> 0 | H32: =SUMIFS('04_LOG_FIELD_ENTRIES'!J:J, '04_LOG_FIELD_ENTRIES'!B:B, B32, '04_LOG_FIELD_ENTRIES'!D:D, C32, '04_LOG_FIELD_ENTRIES'!K:K, "EV_PRODUCCION") -> 0 | I32: =SUMIFS(H$2:H32, C$2:C32, C32) -> 9327.45 | J32: =SUMIFS('04_LOG_FIELD_ENTRIES'!J:J, '04_LOG_FIELD_ENTRIES'!B:B, B32, '04_LOG_FIELD_ENTRIES'!D:D, C32, '04_LOG_FIELD_ENTRIES'!K:K, "AC_*") -> 0 | K32: =SUMIFS(J$2:J32, C$2:C32, C32) -> 7730.8 | L32: =I32-K32 -> 1596.65 | M32: =I32-G32 -> 9327.45 | N32: =IF(G32>0, I32/G32, 1) -> 1 | O32: =IF(K32>0, I32/K32, 1) -> 1.206531 | P32: =IF(AND(N32>=0.95, O32>=0.95), "SALUDABLE", IF(N32<0.9, "ALERTA RETRASO", "ALERTA SOBRECOSTO")) -> SALUDABLE
A33: 8 | B33: 2026-08-08 | C33: WBS-400 | D33: Pruebas Hidráulicas, Desinfección y Entrega | E33: =SUM('01_PRESUPUESTO_CRONOGRAMA_BASE'!G12:G12) -> 9348.06 | F33: =SUMIFS('02_CRONOGRAMA_PV_DIARIO'!E:E, '02_CRONOGRAMA_PV_DIARIO'!A:A, A33, '02_CRONOGRAMA_PV_DIARIO'!C:C, C33) -> 0 | G33: =SUMIFS(F$2:F33, C$2:C33, C33) -> 0 | H33: =SUMIFS('04_LOG_FIELD_ENTRIES'!J:J, '04_LOG_FIELD_ENTRIES'!B:B, B33, '04_LOG_FIELD_ENTRIES'!D:D, C33, '04_LOG_FIELD_ENTRIES'!K:K, "EV_PRODUCCION") -> 0 | I33: =SUMIFS(H$2:H33, C$2:C33, C33) -> 2337.02 | J33: =SUMIFS('04_LOG_FIELD_ENTRIES'!J:J, '04_LOG_FIELD_ENTRIES'!B:B, B33, '04_LOG_FIELD_ENTRIES'!D:D, C33, '04_LOG_FIELD_ENTRIES'!K:K, "AC_*") -> 0 | K33: =SUMIFS(J$2:J33, C$2:C33, C33) -> 1299.2 | L33: =I33-K33 -> 1037.82 | M33: =I33-G33 -> 2337.02 | N33: =IF(G33>0, I33/G33, 1) -> 1 | O33: =IF(K33>0, I33/K33, 1) -> 1.7988147 | P33: =IF(AND(N33>=0.95, O33>=0.95), "SALUDABLE", IF(N33<0.9, "ALERTA RETRASO", "ALERTA SOBRECOSTO")) -> SALUDABLE
A34: 9 | B34: 2026-08-09 | C34: WBS-100 | D34: Obras Preliminares, Trazo y Movilización | E34: =SUM('01_PRESUPUESTO_CRONOGRAMA_BASE'!G2:G3) -> 16336.4 | F34: =SUMIFS('02_CRONOGRAMA_PV_DIARIO'!E:E, '02_CRONOGRAMA_PV_DIARIO'!A:A, A34, '02_CRONOGRAMA_PV_DIARIO'!C:C, C34) -> 1166.89 | G34: =SUMIFS(F$2:F34, C$2:C34, C34) -> 10502.01 | H34: =SUMIFS('04_LOG_FIELD_ENTRIES'!J:J, '04_LOG_FIELD_ENTRIES'!B:B, B34, '04_LOG_FIELD_ENTRIES'!D:D, C34, '04_LOG_FIELD_ENTRIES'!K:K, "EV_PRODUCCION") -> 0 | I34: =SUMIFS(H$2:H34, C$2:C34, C34) -> 5823.2 | J34: =SUMIFS('04_LOG_FIELD_ENTRIES'!J:J, '04_LOG_FIELD_ENTRIES'!B:B, B34, '04_LOG_FIELD_ENTRIES'!D:D, C34, '04_LOG_FIELD_ENTRIES'!K:K, "AC_*") -> 0 | K34: =SUMIFS(J$2:J34, C$2:C34, C34) -> 6331 | L34: =I34-K34 -> -507.8 | M34: =I34-G34 -> -4678.81 | N34: =IF(G34>0, I34/G34, 1) -> 0.55448433 | O34: =IF(K34>0, I34/K34, 1) -> 0.9197915 | P34: =IF(AND(N34>=0.95, O34>=0.95), "SALUDABLE", IF(N34<0.9, "ALERTA RETRASO", "ALERTA SOBRECOSTO")) -> ALERTA RETRASO
A35: 9 | B35: 2026-08-09 | C35: WBS-200 | D35: Red de Alcantarillado, Zanjas y Buzones | E35: =SUM('01_PRESUPUESTO_CRONOGRAMA_BASE'!G4:G9) -> 372046.56 | F35: =SUMIFS('02_CRONOGRAMA_PV_DIARIO'!E:E, '02_CRONOGRAMA_PV_DIARIO'!A:A, A35, '02_CRONOGRAMA_PV_DIARIO'!C:C, C35) -> 0 | G35: =SUMIFS(F$2:F35, C$2:C35, C35) -> 0 | H35: =SUMIFS('04_LOG_FIELD_ENTRIES'!J:J, '04_LOG_FIELD_ENTRIES'!B:B, B35, '04_LOG_FIELD_ENTRIES'!D:D, C35, '04_LOG_FIELD_ENTRIES'!K:K, "EV_PRODUCCION") -> 0 | I35: =SUMIFS(H$2:H35, C$2:C35, C35) -> 44254.52 | J35: =SUMIFS('04_LOG_FIELD_ENTRIES'!J:J, '04_LOG_FIELD_ENTRIES'!B:B, B35, '04_LOG_FIELD_ENTRIES'!D:D, C35, '04_LOG_FIELD_ENTRIES'!K:K, "AC_*") -> 0 | K35: =SUMIFS(J$2:J35, C$2:C35, C35) -> 34269.2 | L35: =I35-K35 -> 9985.32 | M35: =I35-G35 -> 44254.52 | N35: =IF(G35>0, I35/G35, 1) -> 1 | O35: =IF(K35>0, I35/K35, 1) -> 1.2913788 | P35: =IF(AND(N35>=0.95, O35>=0.95), "SALUDABLE", IF(N35<0.9, "ALERTA RETRASO", "ALERTA SOBRECOSTO")) -> SALUDABLE
A36: 9 | B36: 2026-08-09 | C36: WBS-300 | D36: Red de Agua Potable y Conexiones Domiciliarias | E36: =SUM('01_PRESUPUESTO_CRONOGRAMA_BASE'!G10:G11) -> 57565.2 | F36: =SUMIFS('02_CRONOGRAMA_PV_DIARIO'!E:E, '02_CRONOGRAMA_PV_DIARIO'!A:A, A36, '02_CRONOGRAMA_PV_DIARIO'!C:C, C36) -> 0 | G36: =SUMIFS(F$2:F36, C$2:C36, C36) -> 0 | H36: =SUMIFS('04_LOG_FIELD_ENTRIES'!J:J, '04_LOG_FIELD_ENTRIES'!B:B, B36, '04_LOG_FIELD_ENTRIES'!D:D, C36, '04_LOG_FIELD_ENTRIES'!K:K, "EV_PRODUCCION") -> 0 | I36: =SUMIFS(H$2:H36, C$2:C36, C36) -> 9327.45 | J36: =SUMIFS('04_LOG_FIELD_ENTRIES'!J:J, '04_LOG_FIELD_ENTRIES'!B:B, B36, '04_LOG_FIELD_ENTRIES'!D:D, C36, '04_LOG_FIELD_ENTRIES'!K:K, "AC_*") -> 0 | K36: =SUMIFS(J$2:J36, C$2:C36, C36) -> 7730.8 | L36: =I36-K36 -> 1596.65 | M36: =I36-G36 -> 9327.45 | N36: =IF(G36>0, I36/G36, 1) -> 1 | O36: =IF(K36>0, I36/K36, 1) -> 1.206531 | P36: =IF(AND(N36>=0.95, O36>=0.95), "SALUDABLE", IF(N36<0.9, "ALERTA RETRASO", "ALERTA SOBRECOSTO")) -> SALUDABLE
A37: 9 | B37: 2026-08-09 | C37: WBS-400 | D37: Pruebas Hidráulicas, Desinfección y Entrega | E37: =SUM('01_PRESUPUESTO_CRONOGRAMA_BASE'!G12:G12) -> 9348.06 | F37: =SUMIFS('02_CRONOGRAMA_PV_DIARIO'!E:E, '02_CRONOGRAMA_PV_DIARIO'!A:A, A37, '02_CRONOGRAMA_PV_DIARIO'!C:C, C37) -> 0 | G37: =SUMIFS(F$2:F37, C$2:C37, C37) -> 0 | H37: =SUMIFS('04_LOG_FIELD_ENTRIES'!J:J, '04_LOG_FIELD_ENTRIES'!B:B, B37, '04_LOG_FIELD_ENTRIES'!D:D, C37, '04_LOG_FIELD_ENTRIES'!K:K, "EV_PRODUCCION") -> 0 | I37: =SUMIFS(H$2:H37, C$2:C37, C37) -> 2337.02 | J37: =SUMIFS('04_LOG_FIELD_ENTRIES'!J:J, '04_LOG_FIELD_ENTRIES'!B:B, B37, '04_LOG_FIELD_ENTRIES'!D:D, C37, '04_LOG_FIELD_ENTRIES'!K:K, "AC_*") -> 0 | K37: =SUMIFS(J$2:J37, C$2:C37, C37) -> 1299.2 | L37: =I37-K37 -> 1037.82 | M37: =I37-G37 -> 2337.02 | N37: =IF(G37>0, I37/G37, 1) -> 1 | O37: =IF(K37>0, I37/K37, 1) -> 1.7988147 | P37: =IF(AND(N37>=0.95, O37>=0.95), "SALUDABLE", IF(N37<0.9, "ALERTA RETRASO", "ALERTA SOBRECOSTO")) -> SALUDABLE
A38: 10 | B38: 2026-08-10 | C38: WBS-100 | D38: Obras Preliminares, Trazo y Movilización | E38: =SUM('01_PRESUPUESTO_CRONOGRAMA_BASE'!G2:G3) -> 16336.4 | F38: =SUMIFS('02_CRONOGRAMA_PV_DIARIO'!E:E, '02_CRONOGRAMA_PV_DIARIO'!A:A, A38, '02_CRONOGRAMA_PV_DIARIO'!C:C, C38) -> 1166.89 | G38: =SUMIFS(F$2:F38, C$2:C38, C38) -> 11668.9 | H38: =SUMIFS('04_LOG_FIELD_ENTRIES'!J:J, '04_LOG_FIELD_ENTRIES'!B:B, B38, '04_LOG_FIELD_ENTRIES'!D:D, C38, '04_LOG_FIELD_ENTRIES'!K:K, "EV_PRODUCCION") -> 0 | I38: =SUMIFS(H$2:H38, C$2:C38, C38) -> 5823.2 | J38: =SUMIFS('04_LOG_FIELD_ENTRIES'!J:J, '04_LOG_FIELD_ENTRIES'!B:B, B38, '04_LOG_FIELD_ENTRIES'!D:D, C38, '04_LOG_FIELD_ENTRIES'!K:K, "AC_*") -> 0 | K38: =SUMIFS(J$2:J38, C$2:C38, C38) -> 6331 | L38: =I38-K38 -> -507.8 | M38: =I38-G38 -> -5845.7 | N38: =IF(G38>0, I38/G38, 1) -> 0.4990359 | O38: =IF(K38>0, I38/K38, 1) -> 0.9197915 | P38: =IF(AND(N38>=0.95, O38>=0.95), "SALUDABLE", IF(N38<0.9, "ALERTA RETRASO", "ALERTA SOBRECOSTO")) -> ALERTA RETRASO
A39: 10 | B39: 2026-08-10 | C39: WBS-200 | D39: Red de Alcantarillado, Zanjas y Buzones | E39: =SUM('01_PRESUPUESTO_CRONOGRAMA_BASE'!G4:G9) -> 372046.56 | F39: =SUMIFS('02_CRONOGRAMA_PV_DIARIO'!E:E, '02_CRONOGRAMA_PV_DIARIO'!A:A, A39, '02_CRONOGRAMA_PV_DIARIO'!C:C, C39) -> 2798.4 | G39: =SUMIFS(F$2:F39, C$2:C39, C39) -> 2798.4 | H39: =SUMIFS('04_LOG_FIELD_ENTRIES'!J:J, '04_LOG_FIELD_ENTRIES'!B:B, B39, '04_LOG_FIELD_ENTRIES'!D:D, C39, '04_LOG_FIELD_ENTRIES'!K:K, "EV_PRODUCCION") -> 0 | I39: =SUMIFS(H$2:H39, C$2:C39, C39) -> 44254.52 | J39: =SUMIFS('04_LOG_FIELD_ENTRIES'!J:J, '04_LOG_FIELD_ENTRIES'!B:B, B39, '04_LOG_FIELD_ENTRIES'!D:D, C39, '04_LOG_FIELD_ENTRIES'!K:K, "AC_*") -> 0 | K39: =SUMIFS(J$2:J39, C$2:C39, C39) -> 34269.2 | L39: =I39-K39 -> 9985.32 | M39: =I39-G39 -> 41456.12 | N39: =IF(G39>0, I39/G39, 1) -> 15.814222 | O39: =IF(K39>0, I39/K39, 1) -> 1.2913788 | P39: =IF(AND(N39>=0.95, O39>=0.95), "SALUDABLE", IF(N39<0.9, "ALERTA RETRASO", "ALERTA SOBRECOSTO")) -> SALUDABLE
A40: 10 | B40: 2026-08-10 | C40: WBS-300 | D40: Red de Agua Potable y Conexiones Domiciliarias | E40: =SUM('01_PRESUPUESTO_CRONOGRAMA_BASE'!G10:G11) -> 57565.2 | F40: =SUMIFS('02_CRONOGRAMA_PV_DIARIO'!E:E, '02_CRONOGRAMA_PV_DIARIO'!A:A, A40, '02_CRONOGRAMA_PV_DIARIO'!C:C, C40) -> 0 | G40: =SUMIFS(F$2:F40, C$2:C40, C40) -> 0 | H40: =SUMIFS('04_LOG_FIELD_ENTRIES'!J:J, '04_LOG_FIELD_ENTRIES'!B:B, B40, '04_LOG_FIELD_ENTRIES'!D:D, C40, '04_LOG_FIELD_ENTRIES'!K:K, "EV_PRODUCCION") -> 0 | I40: =SUMIFS(H$2:H40, C$2:C40, C40) -> 9327.45 | J40: =SUMIFS('04_LOG_FIELD_ENTRIES'!J:J, '04_LOG_FIELD_ENTRIES'!B:B, B40, '04_LOG_FIELD_ENTRIES'!D:D, C40, '04_LOG_FIELD_ENTRIES'!K:K, "AC_*") -> 0 | K40: =SUMIFS(J$2:J40, C$2:C40, C40) -> 7730.8 | L40: =I40-K40 -> 1596.65 | M40: =I40-G40 -> 9327.45 | N40: =IF(G40>0, I40/G40, 1) -> 1 | O40: =IF(K40>0, I40/K40, 1) -> 1.206531 | P40: =IF(AND(N40>=0.95, O40>=0.95), "SALUDABLE", IF(N40<0.9, "ALERTA RETRASO", "ALERTA SOBRECOSTO")) -> SALUDABLE
A41: 10 | B41: 2026-08-10 | C41: WBS-400 | D41: Pruebas Hidráulicas, Desinfección y Entrega | E41: =SUM('01_PRESUPUESTO_CRONOGRAMA_BASE'!G12:G12) -> 9348.06 | F41: =SUMIFS('02_CRONOGRAMA_PV_DIARIO'!E:E, '02_CRONOGRAMA_PV_DIARIO'!A:A, A41, '02_CRONOGRAMA_PV_DIARIO'!C:C, C41) -> 0 | G41: =SUMIFS(F$2:F41, C$2:C41, C41) -> 0 | H41: =SUMIFS('04_LOG_FIELD_ENTRIES'!J:J, '04_LOG_FIELD_ENTRIES'!B:B, B41, '04_LOG_FIELD_ENTRIES'!D:D, C41, '04_LOG_FIELD_ENTRIES'!K:K, "EV_PRODUCCION") -> 0 | I41: =SUMIFS(H$2:H41, C$2:C41, C41) -> 2337.02 | J41: =SUMIFS('04_LOG_FIELD_ENTRIES'!J:J, '04_LOG_FIELD_ENTRIES'!B:B, B41, '04_LOG_FIELD_ENTRIES'!D:D, C41, '04_LOG_FIELD_ENTRIES'!K:K, "AC_*") -> 0 | K41: =SUMIFS(J$2:J41, C$2:C41, C41) -> 1299.2 | L41: =I41-K41 -> 1037.82 | M41: =I41-G41 -> 2337.02 | N41: =IF(G41>0, I41/G41, 1) -> 1 | O41: =IF(K41>0, I41/K41, 1) -> 1.7988147 | P41: =IF(AND(N41>=0.95, O41>=0.95), "SALUDABLE", IF(N41<0.9, "ALERTA RETRASO", "ALERTA SOBRECOSTO")) -> SALUDABLE
A42: 11 | B42: 2026-08-11 | C42: WBS-100 | D42: Obras Preliminares, Trazo y Movilización | E42: =SUM('01_PRESUPUESTO_CRONOGRAMA_BASE'!G2:G3) -> 16336.4 | F42: =SUMIFS('02_CRONOGRAMA_PV_DIARIO'!E:E, '02_CRONOGRAMA_PV_DIARIO'!A:A, A42, '02_CRONOGRAMA_PV_DIARIO'!C:C, C42) -> 1166.89 | G42: =SUMIFS(F$2:F42, C$2:C42, C42) -> 12835.79 | H42: =SUMIFS('04_LOG_FIELD_ENTRIES'!J:J, '04_LOG_FIELD_ENTRIES'!B:B, B42, '04_LOG_FIELD_ENTRIES'!D:D, C42, '04_LOG_FIELD_ENTRIES'!K:K, "EV_PRODUCCION") -> 0 | I42: =SUMIFS(H$2:H42, C$2:C42, C42) -> 5823.2 | J42: =SUMIFS('04_LOG_FIELD_ENTRIES'!J:J, '04_LOG_FIELD_ENTRIES'!B:B, B42, '04_LOG_FIELD_ENTRIES'!D:D, C42, '04_LOG_FIELD_ENTRIES'!K:K, "AC_*") -> 0 | K42: =SUMIFS(J$2:J42, C$2:C42, C42) -> 6331 | L42: =I42-K42 -> -507.8 | M42: =I42-G42 -> -7012.59 | N42: =IF(G42>0, I42/G42, 1) -> 0.453669 | O42: =IF(K42>0, I42/K42, 1) -> 0.9197915 | P42: =IF(AND(N42>=0.95, O42>=0.95), "SALUDABLE", IF(N42<0.9, "ALERTA RETRASO", "ALERTA SOBRECOSTO")) -> ALERTA RETRASO
A43: 11 | B43: 2026-08-11 | C43: WBS-200 | D43: Red de Alcantarillado, Zanjas y Buzones | E43: =SUM('01_PRESUPUESTO_CRONOGRAMA_BASE'!G4:G9) -> 372046.56 | F43: =SUMIFS('02_CRONOGRAMA_PV_DIARIO'!E:E, '02_CRONOGRAMA_PV_DIARIO'!A:A, A43, '02_CRONOGRAMA_PV_DIARIO'!C:C, C43) -> 2798.4 | G43: =SUMIFS(F$2:F43, C$2:C43, C43) -> 5596.8 | H43: =SUMIFS('04_LOG_FIELD_ENTRIES'!J:J, '04_LOG_FIELD_ENTRIES'!B:B, B43, '04_LOG_FIELD_ENTRIES'!D:D, C43, '04_LOG_FIELD_ENTRIES'!K:K, "EV_PRODUCCION") -> 0 | I43: =SUMIFS(H$2:H43, C$2:C43, C43) -> 44254.52 | J43: =SUMIFS('04_LOG_FIELD_ENTRIES'!J:J, '04_LOG_FIELD_ENTRIES'!B:B, B43, '04_LOG_FIELD_ENTRIES'!D:D, C43, '04_LOG_FIELD_ENTRIES'!K:K, "AC_*") -> 0 | K43: =SUMIFS(J$2:J43, C$2:C43, C43) -> 34269.2 | L43: =I43-K43 -> 9985.32 | M43: =I43-G43 -> 38657.72 | N43: =IF(G43>0, I43/G43, 1) -> 7.9071112 | O43: =IF(K43>0, I43/K43, 1) -> 1.2913788 | P43: =IF(AND(N43>=0.95, O43>=0.95), "SALUDABLE", IF(N43<0.9, "ALERTA RETRASO", "ALERTA SOBRECOSTO")) -> SALUDABLE
A44: 11 | B44: 2026-08-11 | C44: WBS-300 | D44: Red de Agua Potable y Conexiones Domiciliarias | E44: =SUM('01_PRESUPUESTO_CRONOGRAMA_BASE'!G10:G11) -> 57565.2 | F44: =SUMIFS('02_CRONOGRAMA_PV_DIARIO'!E:E, '02_CRONOGRAMA_PV_DIARIO'!A:A, A44, '02_CRONOGRAMA_PV_DIARIO'!C:C, C44) -> 0 | G44: =SUMIFS(F$2:F44, C$2:C44, C44) -> 0 | H44: =SUMIFS('04_LOG_FIELD_ENTRIES'!J:J, '04_LOG_FIELD_ENTRIES'!B:B, B44, '04_LOG_FIELD_ENTRIES'!D:D, C44, '04_LOG_FIELD_ENTRIES'!K:K, "EV_PRODUCCION") -> 0 | I44: =SUMIFS(H$2:H44, C$2:C44, C44) -> 9327.45 | J44: =SUMIFS('04_LOG_FIELD_ENTRIES'!J:J, '04_LOG_FIELD_ENTRIES'!B:B, B44, '04_LOG_FIELD_ENTRIES'!D:D, C44, '04_LOG_FIELD_ENTRIES'!K:K, "AC_*") -> 0 | K44: =SUMIFS(J$2:J44, C$2:C44, C44) -> 7730.8 | L44: =I44-K44 -> 1596.65 | M44: =I44-G44 -> 9327.45 | N44: =IF(G44>0, I44/G44, 1) -> 1 | O44: =IF(K44>0, I44/K44, 1) -> 1.206531 | P44: =IF(AND(N44>=0.95, O44>=0.95), "SALUDABLE", IF(N44<0.9, "ALERTA RETRASO", "ALERTA SOBRECOSTO")) -> SALUDABLE
A45: 11 | B45: 2026-08-11 | C45: WBS-400 | D45: Pruebas Hidráulicas, Desinfección y Entrega | E45: =SUM('01_PRESUPUESTO_CRONOGRAMA_BASE'!G12:G12) -> 9348.06 | F45: =SUMIFS('02_CRONOGRAMA_PV_DIARIO'!E:E, '02_CRONOGRAMA_PV_DIARIO'!A:A, A45, '02_CRONOGRAMA_PV_DIARIO'!C:C, C45) -> 0 | G45: =SUMIFS(F$2:F45, C$2:C45, C45) -> 0 | H45: =SUMIFS('04_LOG_FIELD_ENTRIES'!J:J, '04_LOG_FIELD_ENTRIES'!B:B, B45, '04_LOG_FIELD_ENTRIES'!D:D, C45, '04_LOG_FIELD_ENTRIES'!K:K, "EV_PRODUCCION") -> 0 | I45: =SUMIFS(H$2:H45, C$2:C45, C45) -> 2337.02 | J45: =SUMIFS('04_LOG_FIELD_ENTRIES'!J:J, '04_LOG_FIELD_ENTRIES'!B:B, B45, '04_LOG_FIELD_ENTRIES'!D:D, C45, '04_LOG_FIELD_ENTRIES'!K:K, "AC_*") -> 0 | K45: =SUMIFS(J$2:J45, C$2:C45, C45) -> 1299.2 | L45: =I45-K45 -> 1037.82 | M45: =I45-G45 -> 2337.02 | N45: =IF(G45>0, I45/G45, 1) -> 1 | O45: =IF(K45>0, I45/K45, 1) -> 1.7988147 | P45: =IF(AND(N45>=0.95, O45>=0.95), "SALUDABLE", IF(N45<0.9, "ALERTA RETRASO", "ALERTA SOBRECOSTO")) -> SALUDABLE
A46: 12 | B46: 2026-08-12 | C46: WBS-100 | D46: Obras Preliminares, Trazo y Movilización | E46: =SUM('01_PRESUPUESTO_CRONOGRAMA_BASE'!G2:G3) -> 16336.4 | F46: =SUMIFS('02_CRONOGRAMA_PV_DIARIO'!E:E, '02_CRONOGRAMA_PV_DIARIO'!A:A, A46, '02_CRONOGRAMA_PV_DIARIO'!C:C, C46) -> 1166.89 | G46: =SUMIFS(F$2:F46, C$2:C46, C46) -> 14002.68 | H46: =SUMIFS('04_LOG_FIELD_ENTRIES'!J:J, '04_LOG_FIELD_ENTRIES'!B:B, B46, '04_LOG_FIELD_ENTRIES'!D:D, C46, '04_LOG_FIELD_ENTRIES'!K:K, "EV_PRODUCCION") -> 0 | I46: =SUMIFS(H$2:H46, C$2:C46, C46) -> 5823.2 | J46: =SUMIFS('04_LOG_FIELD_ENTRIES'!J:J, '04_LOG_FIELD_ENTRIES'!B:B, B46, '04_LOG_FIELD_ENTRIES'!D:D, C46, '04_LOG_FIELD_ENTRIES'!K:K, "AC_*") -> 0 | K46: =SUMIFS(J$2:J46, C$2:C46, C46) -> 6331 | L46: =I46-K46 -> -507.8 | M46: =I46-G46 -> -8179.48 | N46: =IF(G46>0, I46/G46, 1) -> 0.41586325 | O46: =IF(K46>0, I46/K46, 1) -> 0.9197915 | P46: =IF(AND(N46>=0.95, O46>=0.95), "SALUDABLE", IF(N46<0.9, "ALERTA RETRASO", "ALERTA SOBRECOSTO")) -> ALERTA RETRASO
A47: 12 | B47: 2026-08-12 | C47: WBS-200 | D47: Red de Alcantarillado, Zanjas y Buzones | E47: =SUM('01_PRESUPUESTO_CRONOGRAMA_BASE'!G4:G9) -> 372046.56 | F47: =SUMIFS('02_CRONOGRAMA_PV_DIARIO'!E:E, '02_CRONOGRAMA_PV_DIARIO'!A:A, A47, '02_CRONOGRAMA_PV_DIARIO'!C:C, C47) -> 4368.28 | G47: =SUMIFS(F$2:F47, C$2:C47, C47) -> 9965.08 | H47: =SUMIFS('04_LOG_FIELD_ENTRIES'!J:J, '04_LOG_FIELD_ENTRIES'!B:B, B47, '04_LOG_FIELD_ENTRIES'!D:D, C47, '04_LOG_FIELD_ENTRIES'!K:K, "EV_PRODUCCION") -> 0 | I47: =SUMIFS(H$2:H47, C$2:C47, C47) -> 44254.52 | J47: =SUMIFS('04_LOG_FIELD_ENTRIES'!J:J, '04_LOG_FIELD_ENTRIES'!B:B, B47, '04_LOG_FIELD_ENTRIES'!D:D, C47, '04_LOG_FIELD_ENTRIES'!K:K, "AC_*") -> 0 | K47: =SUMIFS(J$2:J47, C$2:C47, C47) -> 34269.2 | L47: =I47-K47 -> 9985.32 | M47: =I47-G47 -> 34289.44 | N47: =IF(G47>0, I47/G47, 1) -> 4.4409598 | O47: =IF(K47>0, I47/K47, 1) -> 1.2913788 | P47: =IF(AND(N47>=0.95, O47>=0.95), "SALUDABLE", IF(N47<0.9, "ALERTA RETRASO", "ALERTA SOBRECOSTO")) -> SALUDABLE
A48: 12 | B48: 2026-08-12 | C48: WBS-300 | D48: Red de Agua Potable y Conexiones Domiciliarias | E48: =SUM('01_PRESUPUESTO_CRONOGRAMA_BASE'!G10:G11) -> 57565.2 | F48: =SUMIFS('02_CRONOGRAMA_PV_DIARIO'!E:E, '02_CRONOGRAMA_PV_DIARIO'!A:A, A48, '02_CRONOGRAMA_PV_DIARIO'!C:C, C48) -> 0 | G48: =SUMIFS(F$2:F48, C$2:C48, C48) -> 0 | H48: =SUMIFS('04_LOG_FIELD_ENTRIES'!J:J, '04_LOG_FIELD_ENTRIES'!B:B, B48, '04_LOG_FIELD_ENTRIES'!D:D, C48, '04_LOG_FIELD_ENTRIES'!K:K, "EV_PRODUCCION") -> 0 | I48: =SUMIFS(H$2:H48, C$2:C48, C48) -> 9327.45 | J48: =SUMIFS('04_LOG_FIELD_ENTRIES'!J:J, '04_LOG_FIELD_ENTRIES'!B:B, B48, '04_LOG_FIELD_ENTRIES'!D:D, C48, '04_LOG_FIELD_ENTRIES'!K:K, "AC_*") -> 0 | K48: =SUMIFS(J$2:J48, C$2:C48, C48) -> 7730.8 | L48: =I48-K48 -> 1596.65 | M48: =I48-G48 -> 9327.45 | N48: =IF(G48>0, I48/G48, 1) -> 1 | O48: =IF(K48>0, I48/K48, 1) -> 1.206531 | P48: =IF(AND(N48>=0.95, O48>=0.95), "SALUDABLE", IF(N48<0.9, "ALERTA RETRASO", "ALERTA SOBRECOSTO")) -> SALUDABLE
A49: 12 | B49: 2026-08-12 | C49: WBS-400 | D49: Pruebas Hidráulicas, Desinfección y Entrega | E49: =SUM('01_PRESUPUESTO_CRONOGRAMA_BASE'!G12:G12) -> 9348.06 | F49: =SUMIFS('02_CRONOGRAMA_PV_DIARIO'!E:E, '02_CRONOGRAMA_PV_DIARIO'!A:A, A49, '02_CRONOGRAMA_PV_DIARIO'!C:C, C49) -> 0 | G49: =SUMIFS(F$2:F49, C$2:C49, C49) -> 0 | H49: =SUMIFS('04_LOG_FIELD_ENTRIES'!J:J, '04_LOG_FIELD_ENTRIES'!B:B, B49, '04_LOG_FIELD_ENTRIES'!D:D, C49, '04_LOG_FIELD_ENTRIES'!K:K, "EV_PRODUCCION") -> 0 | I49: =SUMIFS(H$2:H49, C$2:C49, C49) -> 2337.02 | J49: =SUMIFS('04_LOG_FIELD_ENTRIES'!J:J, '04_LOG_FIELD_ENTRIES'!B:B, B49, '04_LOG_FIELD_ENTRIES'!D:D, C49, '04_LOG_FIELD_ENTRIES'!K:K, "AC_*") -> 0 | K49: =SUMIFS(J$2:J49, C$2:C49, C49) -> 1299.2 | L49: =I49-K49 -> 1037.82 | M49: =I49-G49 -> 2337.02 | N49: =IF(G49>0, I49/G49, 1) -> 1 | O49: =IF(K49>0, I49/K49, 1) -> 1.7988147 | P49: =IF(AND(N49>=0.95, O49>=0.95), "SALUDABLE", IF(N49<0.9, "ALERTA RETRASO", "ALERTA SOBRECOSTO")) -> SALUDABLE
A50: 13 | B50: 2026-08-13 | C50: WBS-100 | D50: Obras Preliminares, Trazo y Movilización | E50: =SUM('01_PRESUPUESTO_CRONOGRAMA_BASE'!G2:G3) -> 16336.4 | F50: =SUMIFS('02_CRONOGRAMA_PV_DIARIO'!E:E, '02_CRONOGRAMA_PV_DIARIO'!A:A, A50, '02_CRONOGRAMA_PV_DIARIO'!C:C, C50) -> 1166.89 | G50: =SUMIFS(F$2:F50, C$2:C50, C50) -> 15169.57 | H50: =SUMIFS('04_LOG_FIELD_ENTRIES'!J:J, '04_LOG_FIELD_ENTRIES'!B:B, B50, '04_LOG_FIELD_ENTRIES'!D:D, C50, '04_LOG_FIELD_ENTRIES'!K:K, "EV_PRODUCCION") -> 0 | I50: =SUMIFS(H$2:H50, C$2:C50, C50) -> 5823.2 | J50: =SUMIFS('04_LOG_FIELD_ENTRIES'!J:J, '04_LOG_FIELD_ENTRIES'!B:B, B50, '04_LOG_FIELD_ENTRIES'!D:D, C50, '04_LOG_FIELD_ENTRIES'!K:K, "AC_*") -> 0 | K50: =SUMIFS(J$2:J50, C$2:C50, C50) -> 6331 | L50: =I50-K50 -> -507.8 | M50: =I50-G50 -> -9346.37 | N50: =IF(G50>0, I50/G50, 1) -> 0.38387377 | O50: =IF(K50>0, I50/K50, 1) -> 0.9197915 | P50: =IF(AND(N50>=0.95, O50>=0.95), "SALUDABLE", IF(N50<0.9, "ALERTA RETRASO", "ALERTA SOBRECOSTO")) -> ALERTA RETRASO
A51: 13 | B51: 2026-08-13 | C51: WBS-200 | D51: Red de Alcantarillado, Zanjas y Buzones | E51: =SUM('01_PRESUPUESTO_CRONOGRAMA_BASE'!G4:G9) -> 372046.56 | F51: =SUMIFS('02_CRONOGRAMA_PV_DIARIO'!E:E, '02_CRONOGRAMA_PV_DIARIO'!A:A, A51, '02_CRONOGRAMA_PV_DIARIO'!C:C, C51) -> 4368.28 | G51: =SUMIFS(F$2:F51, C$2:C51, C51) -> 14333.36 | H51: =SUMIFS('04_LOG_FIELD_ENTRIES'!J:J, '04_LOG_FIELD_ENTRIES'!B:B, B51, '04_LOG_FIELD_ENTRIES'!D:D, C51, '04_LOG_FIELD_ENTRIES'!K:K, "EV_PRODUCCION") -> 0 | I51: =SUMIFS(H$2:H51, C$2:C51, C51) -> 44254.52 | J51: =SUMIFS('04_LOG_FIELD_ENTRIES'!J:J, '04_LOG_FIELD_ENTRIES'!B:B, B51, '04_LOG_FIELD_ENTRIES'!D:D, C51, '04_LOG_FIELD_ENTRIES'!K:K, "AC_*") -> 0 | K51: =SUMIFS(J$2:J51, C$2:C51, C51) -> 34269.2 | L51: =I51-K51 -> 9985.32 | M51: =I51-G51 -> 29921.16 | N51: =IF(G51>0, I51/G51, 1) -> 3.0875189 | O51: =IF(K51>0, I51/K51, 1) -> 1.2913788 | P51: =IF(AND(N51>=0.95, O51>=0.95), "SALUDABLE", IF(N51<0.9, "ALERTA RETRASO", "ALERTA SOBRECOSTO")) -> SALUDABLE
A52: 13 | B52: 2026-08-13 | C52: WBS-300 | D52: Red de Agua Potable y Conexiones Domiciliarias | E52: =SUM('01_PRESUPUESTO_CRONOGRAMA_BASE'!G10:G11) -> 57565.2 | F52: =SUMIFS('02_CRONOGRAMA_PV_DIARIO'!E:E, '02_CRONOGRAMA_PV_DIARIO'!A:A, A52, '02_CRONOGRAMA_PV_DIARIO'!C:C, C52) -> 0 | G52: =SUMIFS(F$2:F52, C$2:C52, C52) -> 0 | H52: =SUMIFS('04_LOG_FIELD_ENTRIES'!J:J, '04_LOG_FIELD_ENTRIES'!B:B, B52, '04_LOG_FIELD_ENTRIES'!D:D, C52, '04_LOG_FIELD_ENTRIES'!K:K, "EV_PRODUCCION") -> 0 | I52: =SUMIFS(H$2:H52, C$2:C52, C52) -> 9327.45 | J52: =SUMIFS('04_LOG_FIELD_ENTRIES'!J:J, '04_LOG_FIELD_ENTRIES'!B:B, B52, '04_LOG_FIELD_ENTRIES'!D:D, C52, '04_LOG_FIELD_ENTRIES'!K:K, "AC_*") -> 0 | K52: =SUMIFS(J$2:J52, C$2:C52, C52) -> 7730.8 | L52: =I52-K52 -> 1596.65 | M52: =I52-G52 -> 9327.45 | N52: =IF(G52>0, I52/G52, 1) -> 1 | O52: =IF(K52>0, I52/K52, 1) -> 1.206531 | P52: =IF(AND(N52>=0.95, O52>=0.95), "SALUDABLE", IF(N52<0.9, "ALERTA RETRASO", "ALERTA SOBRECOSTO")) -> SALUDABLE
A53: 13 | B53: 2026-08-13 | C53: WBS-400 | D53: Pruebas Hidráulicas, Desinfección y Entrega | E53: =SUM('01_PRESUPUESTO_CRONOGRAMA_BASE'!G12:G12) -> 9348.06 | F53: =SUMIFS('02_CRONOGRAMA_PV_DIARIO'!E:E, '02_CRONOGRAMA_PV_DIARIO'!A:A, A53, '02_CRONOGRAMA_PV_DIARIO'!C:C, C53) -> 0 | G53: =SUMIFS(F$2:F53, C$2:C53, C53) -> 0 | H53: =SUMIFS('04_LOG_FIELD_ENTRIES'!J:J, '04_LOG_FIELD_ENTRIES'!B:B, B53, '04_LOG_FIELD_ENTRIES'!D:D, C53, '04_LOG_FIELD_ENTRIES'!K:K, "EV_PRODUCCION") -> 0 | I53: =SUMIFS(H$2:H53, C$2:C53, C53) -> 2337.02 | J53: =SUMIFS('04_LOG_FIELD_ENTRIES'!J:J, '04_LOG_FIELD_ENTRIES'!B:B, B53, '04_LOG_FIELD_ENTRIES'!D:D, C53, '04_LOG_FIELD_ENTRIES'!K:K, "AC_*") -> 0 | K53: =SUMIFS(J$2:J53, C$2:C53, C53) -> 1299.2 | L53: =I53-K53 -> 1037.82 | M53: =I53-G53 -> 2337.02 | N53: =IF(G53>0, I53/G53, 1) -> 1 | O53: =IF(K53>0, I53/K53, 1) -> 1.7988147 | P53: =IF(AND(N53>=0.95, O53>=0.95), "SALUDABLE", IF(N53<0.9, "ALERTA RETRASO", "ALERTA SOBRECOSTO")) -> SALUDABLE
A54: 14 | B54: 2026-08-14 | C54: WBS-100 | D54: Obras Preliminares, Trazo y Movilización | E54: =SUM('01_PRESUPUESTO_CRONOGRAMA_BASE'!G2:G3) -> 16336.4 | F54: =SUMIFS('02_CRONOGRAMA_PV_DIARIO'!E:E, '02_CRONOGRAMA_PV_DIARIO'!A:A, A54, '02_CRONOGRAMA_PV_DIARIO'!C:C, C54) -> 1166.89 | G54: =SUMIFS(F$2:F54, C$2:C54, C54) -> 16336.46 | H54: =SUMIFS('04_LOG_FIELD_ENTRIES'!J:J, '04_LOG_FIELD_ENTRIES'!B:B, B54, '04_LOG_FIELD_ENTRIES'!D:D, C54, '04_LOG_FIELD_ENTRIES'!K:K, "EV_PRODUCCION") -> 0 | I54: =SUMIFS(H$2:H54, C$2:C54, C54) -> 5823.2 | J54: =SUMIFS('04_LOG_FIELD_ENTRIES'!J:J, '04_LOG_FIELD_ENTRIES'!B:B, B54, '04_LOG_FIELD_ENTRIES'!D:D, C54, '04_LOG_FIELD_ENTRIES'!K:K, "AC_*") -> 0 | K54: =SUMIFS(J$2:J54, C$2:C54, C54) -> 6331 | L54: =I54-K54 -> -507.8 | M54: =I54-G54 -> -10513.26 | N54: =IF(G54>0, I54/G54, 1) -> 0.35645421 | O54: =IF(K54>0, I54/K54, 1) -> 0.9197915 | P54: =IF(AND(N54>=0.95, O54>=0.95), "SALUDABLE", IF(N54<0.9, "ALERTA RETRASO", "ALERTA SOBRECOSTO")) -> ALERTA RETRASO
A55: 14 | B55: 2026-08-14 | C55: WBS-200 | D55: Red de Alcantarillado, Zanjas y Buzones | E55: =SUM('01_PRESUPUESTO_CRONOGRAMA_BASE'!G4:G9) -> 372046.56 | F55: =SUMIFS('02_CRONOGRAMA_PV_DIARIO'!E:E, '02_CRONOGRAMA_PV_DIARIO'!A:A, A55, '02_CRONOGRAMA_PV_DIARIO'!C:C, C55) -> 4368.28 | G55: =SUMIFS(F$2:F55, C$2:C55, C55) -> 18701.64 | H55: =SUMIFS('04_LOG_FIELD_ENTRIES'!J:J, '04_LOG_FIELD_ENTRIES'!B:B, B55, '04_LOG_FIELD_ENTRIES'!D:D, C55, '04_LOG_FIELD_ENTRIES'!K:K, "EV_PRODUCCION") -> 0 | I55: =SUMIFS(H$2:H55, C$2:C55, C55) -> 44254.52 | J55: =SUMIFS('04_LOG_FIELD_ENTRIES'!J:J, '04_LOG_FIELD_ENTRIES'!B:B, B55, '04_LOG_FIELD_ENTRIES'!D:D, C55, '04_LOG_FIELD_ENTRIES'!K:K, "AC_*") -> 0 | K55: =SUMIFS(J$2:J55, C$2:C55, C55) -> 34269.2 | L55: =I55-K55 -> 9985.32 | M55: =I55-G55 -> 25552.88 | N55: =IF(G55>0, I55/G55, 1) -> 2.3663443 | O55: =IF(K55>0, I55/K55, 1) -> 1.2913788 | P55: =IF(AND(N55>=0.95, O55>=0.95), "SALUDABLE", IF(N55<0.9, "ALERTA RETRASO", "ALERTA SOBRECOSTO")) -> SALUDABLE
A56: 14 | B56: 2026-08-14 | C56: WBS-300 | D56: Red de Agua Potable y Conexiones Domiciliarias | E56: =SUM('01_PRESUPUESTO_CRONOGRAMA_BASE'!G10:G11) -> 57565.2 | F56: =SUMIFS('02_CRONOGRAMA_PV_DIARIO'!E:E, '02_CRONOGRAMA_PV_DIARIO'!A:A, A56, '02_CRONOGRAMA_PV_DIARIO'!C:C, C56) -> 0 | G56: =SUMIFS(F$2:F56, C$2:C56, C56) -> 0 | H56: =SUMIFS('04_LOG_FIELD_ENTRIES'!J:J, '04_LOG_FIELD_ENTRIES'!B:B, B56, '04_LOG_FIELD_ENTRIES'!D:D, C56, '04_LOG_FIELD_ENTRIES'!K:K, "EV_PRODUCCION") -> 0 | I56: =SUMIFS(H$2:H56, C$2:C56, C56) -> 9327.45 | J56: =SUMIFS('04_LOG_FIELD_ENTRIES'!J:J, '04_LOG_FIELD_ENTRIES'!B:B, B56, '04_LOG_FIELD_ENTRIES'!D:D, C56, '04_LOG_FIELD_ENTRIES'!K:K, "AC_*") -> 0 | K56: =SUMIFS(J$2:J56, C$2:C56, C56) -> 7730.8 | L56: =I56-K56 -> 1596.65 | M56: =I56-G56 -> 9327.45 | N56: =IF(G56>0, I56/G56, 1) -> 1 | O56: =IF(K56>0, I56/K56, 1) -> 1.206531 | P56: =IF(AND(N56>=0.95, O56>=0.95), "SALUDABLE", IF(N56<0.9, "ALERTA RETRASO", "ALERTA SOBRECOSTO")) -> SALUDABLE
A57: 14 | B57: 2026-08-14 | C57: WBS-400 | D57: Pruebas Hidráulicas, Desinfección y Entrega | E57: =SUM('01_PRESUPUESTO_CRONOGRAMA_BASE'!G12:G12) -> 9348.06 | F57: =SUMIFS('02_CRONOGRAMA_PV_DIARIO'!E:E, '02_CRONOGRAMA_PV_DIARIO'!A:A, A57, '02_CRONOGRAMA_PV_DIARIO'!C:C, C57) -> 0 | G57: =SUMIFS(F$2:F57, C$2:C57, C57) -> 0 | H57: =SUMIFS('04_LOG_FIELD_ENTRIES'!J:J, '04_LOG_FIELD_ENTRIES'!B:B, B57, '04_LOG_FIELD_ENTRIES'!D:D, C57, '04_LOG_FIELD_ENTRIES'!K:K, "EV_PRODUCCION") -> 0 | I57: =SUMIFS(H$2:H57, C$2:C57, C57) -> 2337.02 | J57: =SUMIFS('04_LOG_FIELD_ENTRIES'!J:J, '04_LOG_FIELD_ENTRIES'!B:B, B57, '04_LOG_FIELD_ENTRIES'!D:D, C57, '04_LOG_FIELD_ENTRIES'!K:K, "AC_*") -> 0 | K57: =SUMIFS(J$2:J57, C$2:C57, C57) -> 1299.2 | L57: =I57-K57 -> 1037.82 | M57: =I57-G57 -> 2337.02 | N57: =IF(G57>0, I57/G57, 1) -> 1 | O57: =IF(K57>0, I57/K57, 1) -> 1.7988147 | P57: =IF(AND(N57>=0.95, O57>=0.95), "SALUDABLE", IF(N57<0.9, "ALERTA RETRASO", "ALERTA SOBRECOSTO")) -> SALUDABLE
A58: 15 | B58: 2026-08-15 | C58: WBS-100 | D58: Obras Preliminares, Trazo y Movilización | E58: =SUM('01_PRESUPUESTO_CRONOGRAMA_BASE'!G2:G3) -> 16336.4 | F58: =SUMIFS('02_CRONOGRAMA_PV_DIARIO'!E:E, '02_CRONOGRAMA_PV_DIARIO'!A:A, A58, '02_CRONOGRAMA_PV_DIARIO'!C:C, C58) -> 0 | G58: =SUMIFS(F$2:F58, C$2:C58, C58) -> 16336.46 | H58: =SUMIFS('04_LOG_FIELD_ENTRIES'!J:J, '04_LOG_FIELD_ENTRIES'!B:B, B58, '04_LOG_FIELD_ENTRIES'!D:D, C58, '04_LOG_FIELD_ENTRIES'!K:K, "EV_PRODUCCION") -> 0 | I58: =SUMIFS(H$2:H58, C$2:C58, C58) -> 5823.2 | J58: =SUMIFS('04_LOG_FIELD_ENTRIES'!J:J, '04_LOG_FIELD_ENTRIES'!B:B, B58, '04_LOG_FIELD_ENTRIES'!D:D, C58, '04_LOG_FIELD_ENTRIES'!K:K, "AC_*") -> 0 | K58: =SUMIFS(J$2:J58, C$2:C58, C58) -> 6331 | L58: =I58-K58 -> -507.8 | M58: =I58-G58 -> -10513.26 | N58: =IF(G58>0, I58/G58, 1) -> 0.35645421 | O58: =IF(K58>0, I58/K58, 1) -> 0.9197915 | P58: =IF(AND(N58>=0.95, O58>=0.95), "SALUDABLE", IF(N58<0.9, "ALERTA RETRASO", "ALERTA SOBRECOSTO")) -> ALERTA RETRASO
A59: 15 | B59: 2026-08-15 | C59: WBS-200 | D59: Red de Alcantarillado, Zanjas y Buzones | E59: =SUM('01_PRESUPUESTO_CRONOGRAMA_BASE'!G4:G9) -> 372046.56 | F59: =SUMIFS('02_CRONOGRAMA_PV_DIARIO'!E:E, '02_CRONOGRAMA_PV_DIARIO'!A:A, A59, '02_CRONOGRAMA_PV_DIARIO'!C:C, C59) -> 8939.69 | G59: =SUMIFS(F$2:F59, C$2:C59, C59) -> 27641.33 | H59: =SUMIFS('04_LOG_FIELD_ENTRIES'!J:J, '04_LOG_FIELD_ENTRIES'!B:B, B59, '04_LOG_FIELD_ENTRIES'!D:D, C59, '04_LOG_FIELD_ENTRIES'!K:K, "EV_PRODUCCION") -> 0 | I59: =SUMIFS(H$2:H59, C$2:C59, C59) -> 44254.52 | J59: =SUMIFS('04_LOG_FIELD_ENTRIES'!J:J, '04_LOG_FIELD_ENTRIES'!B:B, B59, '04_LOG_FIELD_ENTRIES'!D:D, C59, '04_LOG_FIELD_ENTRIES'!K:K, "AC_*") -> 0 | K59: =SUMIFS(J$2:J59, C$2:C59, C59) -> 34269.2 | L59: =I59-K59 -> 9985.32 | M59: =I59-G59 -> 16613.19 | N59: =IF(G59>0, I59/G59, 1) -> 1.6010272 | O59: =IF(K59>0, I59/K59, 1) -> 1.2913788 | P59: =IF(AND(N59>=0.95, O59>=0.95), "SALUDABLE", IF(N59<0.9, "ALERTA RETRASO", "ALERTA SOBRECOSTO")) -> SALUDABLE
A60: 15 | B60: 2026-08-15 | C60: WBS-300 | D60: Red de Agua Potable y Conexiones Domiciliarias | E60: =SUM('01_PRESUPUESTO_CRONOGRAMA_BASE'!G10:G11) -> 57565.2 | F60: =SUMIFS('02_CRONOGRAMA_PV_DIARIO'!E:E, '02_CRONOGRAMA_PV_DIARIO'!A:A, A60, '02_CRONOGRAMA_PV_DIARIO'!C:C, C60) -> 0 | G60: =SUMIFS(F$2:F60, C$2:C60, C60) -> 0 | H60: =SUMIFS('04_LOG_FIELD_ENTRIES'!J:J, '04_LOG_FIELD_ENTRIES'!B:B, B60, '04_LOG_FIELD_ENTRIES'!D:D, C60, '04_LOG_FIELD_ENTRIES'!K:K, "EV_PRODUCCION") -> 0 | I60: =SUMIFS(H$2:H60, C$2:C60, C60) -> 9327.45 | J60: =SUMIFS('04_LOG_FIELD_ENTRIES'!J:J, '04_LOG_FIELD_ENTRIES'!B:B, B60, '04_LOG_FIELD_ENTRIES'!D:D, C60, '04_LOG_FIELD_ENTRIES'!K:K, "AC_*") -> 0 | K60: =SUMIFS(J$2:J60, C$2:C60, C60) -> 7730.8 | L60: =I60-K60 -> 1596.65 | M60: =I60-G60 -> 9327.45 | N60: =IF(G60>0, I60/G60, 1) -> 1 | O60: =IF(K60>0, I60/K60, 1) -> 1.206531 | P60: =IF(AND(N60>=0.95, O60>=0.95), "SALUDABLE", IF(N60<0.9, "ALERTA RETRASO", "ALERTA SOBRECOSTO")) -> SALUDABLE
A61: 15 | B61: 2026-08-15 | C61: WBS-400 | D61: Pruebas Hidráulicas, Desinfección y Entrega | E61: =SUM('01_PRESUPUESTO_CRONOGRAMA_BASE'!G12:G12) -> 9348.06 | F61: =SUMIFS('02_CRONOGRAMA_PV_DIARIO'!E:E, '02_CRONOGRAMA_PV_DIARIO'!A:A, A61, '02_CRONOGRAMA_PV_DIARIO'!C:C, C61) -> 0 | G61: =SUMIFS(F$2:F61, C$2:C61, C61) -> 0 | H61: =SUMIFS('04_LOG_FIELD_ENTRIES'!J:J, '04_LOG_FIELD_ENTRIES'!B:B, B61, '04_LOG_FIELD_ENTRIES'!D:D, C61, '04_LOG_FIELD_ENTRIES'!K:K, "EV_PRODUCCION") -> 0 | I61: =SUMIFS(H$2:H61, C$2:C61, C61) -> 2337.02 | J61: =SUMIFS('04_LOG_FIELD_ENTRIES'!J:J, '04_LOG_FIELD_ENTRIES'!B:B, B61, '04_LOG_FIELD_ENTRIES'!D:D, C61, '04_LOG_FIELD_ENTRIES'!K:K, "AC_*") -> 0 | K61: =SUMIFS(J$2:J61, C$2:C61, C61) -> 1299.2 | L61: =I61-K61 -> 1037.82 | M61: =I61-G61 -> 2337.02 | N61: =IF(G61>0, I61/G61, 1) -> 1 | O61: =IF(K61>0, I61/K61, 1) -> 1.7988147 | P61: =IF(AND(N61>=0.95, O61>=0.95), "SALUDABLE", IF(N61<0.9, "ALERTA RETRASO", "ALERTA SOBRECOSTO")) -> SALUDABLE
A62: 16 | B62: 2026-08-16 | C62: WBS-100 | D62: Obras Preliminares, Trazo y Movilización | E62: =SUM('01_PRESUPUESTO_CRONOGRAMA_BASE'!G2:G3) -> 16336.4 | F62: =SUMIFS('02_CRONOGRAMA_PV_DIARIO'!E:E, '02_CRONOGRAMA_PV_DIARIO'!A:A, A62, '02_CRONOGRAMA_PV_DIARIO'!C:C, C62) -> 0 | G62: =SUMIFS(F$2:F62, C$2:C62, C62) -> 16336.46 | H62: =SUMIFS('04_LOG_FIELD_ENTRIES'!J:J, '04_LOG_FIELD_ENTRIES'!B:B, B62, '04_LOG_FIELD_ENTRIES'!D:D, C62, '04_LOG_FIELD_ENTRIES'!K:K, "EV_PRODUCCION") -> 0 | I62: =SUMIFS(H$2:H62, C$2:C62, C62) -> 5823.2 | J62: =SUMIFS('04_LOG_FIELD_ENTRIES'!J:J, '04_LOG_FIELD_ENTRIES'!B:B, B62, '04_LOG_FIELD_ENTRIES'!D:D, C62, '04_LOG_FIELD_ENTRIES'!K:K, "AC_*") -> 0 | K62: =SUMIFS(J$2:J62, C$2:C62, C62) -> 6331 | L62: =I62-K62 -> -507.8 | M62: =I62-G62 -> -10513.26 | N62: =IF(G62>0, I62/G62, 1) -> 0.35645421 | O62: =IF(K62>0, I62/K62, 1) -> 0.9197915 | P62: =IF(AND(N62>=0.95, O62>=0.95), "SALUDABLE", IF(N62<0.9, "ALERTA RETRASO", "ALERTA SOBRECOSTO")) -> ALERTA RETRASO
A63: 16 | B63: 2026-08-16 | C63: WBS-200 | D63: Red de Alcantarillado, Zanjas y Buzones | E63: =SUM('01_PRESUPUESTO_CRONOGRAMA_BASE'!G4:G9) -> 372046.56 | F63: =SUMIFS('02_CRONOGRAMA_PV_DIARIO'!E:E, '02_CRONOGRAMA_PV_DIARIO'!A:A, A63, '02_CRONOGRAMA_PV_DIARIO'!C:C, C63) -> 8939.69 | G63: =SUMIFS(F$2:F63, C$2:C63, C63) -> 36581.02 | H63: =SUMIFS('04_LOG_FIELD_ENTRIES'!J:J, '04_LOG_FIELD_ENTRIES'!B:B, B63, '04_LOG_FIELD_ENTRIES'!D:D, C63, '04_LOG_FIELD_ENTRIES'!K:K, "EV_PRODUCCION") -> 0 | I63: =SUMIFS(H$2:H63, C$2:C63, C63) -> 44254.52 | J63: =SUMIFS('04_LOG_FIELD_ENTRIES'!J:J, '04_LOG_FIELD_ENTRIES'!B:B, B63, '04_LOG_FIELD_ENTRIES'!D:D, C63, '04_LOG_FIELD_ENTRIES'!K:K, "AC_*") -> 0 | K63: =SUMIFS(J$2:J63, C$2:C63, C63) -> 34269.2 | L63: =I63-K63 -> 9985.32 | M63: =I63-G63 -> 7673.5 | N63: =IF(G63>0, I63/G63, 1) -> 1.2097673 | O63: =IF(K63>0, I63/K63, 1) -> 1.2913788 | P63: =IF(AND(N63>=0.95, O63>=0.95), "SALUDABLE", IF(N63<0.9, "ALERTA RETRASO", "ALERTA SOBRECOSTO")) -> SALUDABLE
A64: 16 | B64: 2026-08-16 | C64: WBS-300 | D64: Red de Agua Potable y Conexiones Domiciliarias | E64: =SUM('01_PRESUPUESTO_CRONOGRAMA_BASE'!G10:G11) -> 57565.2 | F64: =SUMIFS('02_CRONOGRAMA_PV_DIARIO'!E:E, '02_CRONOGRAMA_PV_DIARIO'!A:A, A64, '02_CRONOGRAMA_PV_DIARIO'!C:C, C64) -> 0 | G64: =SUMIFS(F$2:F64, C$2:C64, C64) -> 0 | H64: =SUMIFS('04_LOG_FIELD_ENTRIES'!J:J, '04_LOG_FIELD_ENTRIES'!B:B, B64, '04_LOG_FIELD_ENTRIES'!D:D, C64, '04_LOG_FIELD_ENTRIES'!K:K, "EV_PRODUCCION") -> 0 | I64: =SUMIFS(H$2:H64, C$2:C64, C64) -> 9327.45 | J64: =SUMIFS('04_LOG_FIELD_ENTRIES'!J:J, '04_LOG_FIELD_ENTRIES'!B:B, B64, '04_LOG_FIELD_ENTRIES'!D:D, C64, '04_LOG_FIELD_ENTRIES'!K:K, "AC_*") -> 0 | K64: =SUMIFS(J$2:J64, C$2:C64, C64) -> 7730.8 | L64: =I64-K64 -> 1596.65 | M64: =I64-G64 -> 9327.45 | N64: =IF(G64>0, I64/G64, 1) -> 1 | O64: =IF(K64>0, I64/K64, 1) -> 1.206531 | P64: =IF(AND(N64>=0.95, O64>=0.95), "SALUDABLE", IF(N64<0.9, "ALERTA RETRASO", "ALERTA SOBRECOSTO")) -> SALUDABLE
A65: 16 | B65: 2026-08-16 | C65: WBS-400 | D65: Pruebas Hidráulicas, Desinfección y Entrega | E65: =SUM('01_PRESUPUESTO_CRONOGRAMA_BASE'!G12:G12) -> 9348.06 | F65: =SUMIFS('02_CRONOGRAMA_PV_DIARIO'!E:E, '02_CRONOGRAMA_PV_DIARIO'!A:A, A65, '02_CRONOGRAMA_PV_DIARIO'!C:C, C65) -> 0 | G65: =SUMIFS(F$2:F65, C$2:C65, C65) -> 0 | H65: =SUMIFS('04_LOG_FIELD_ENTRIES'!J:J, '04_LOG_FIELD_ENTRIES'!B:B, B65, '04_LOG_FIELD_ENTRIES'!D:D, C65, '04_LOG_FIELD_ENTRIES'!K:K, "EV_PRODUCCION") -> 0 | I65: =SUMIFS(H$2:H65, C$2:C65, C65) -> 2337.02 | J65: =SUMIFS('04_LOG_FIELD_ENTRIES'!J:J, '04_LOG_FIELD_ENTRIES'!B:B, B65, '04_LOG_FIELD_ENTRIES'!D:D, C65, '04_LOG_FIELD_ENTRIES'!K:K, "AC_*") -> 0 | K65: =SUMIFS(J$2:J65, C$2:C65, C65) -> 1299.2 | L65: =I65-K65 -> 1037.82 | M65: =I65-G65 -> 2337.02 | N65: =IF(G65>0, I65/G65, 1) -> 1 | O65: =IF(K65>0, I65/K65, 1) -> 1.7988147 | P65: =IF(AND(N65>=0.95, O65>=0.95), "SALUDABLE", IF(N65<0.9, "ALERTA RETRASO", "ALERTA SOBRECOSTO")) -> SALUDABLE
A66: 17 | B66: 2026-08-17 | C66: WBS-100 | D66: Obras Preliminares, Trazo y Movilización | E66: =SUM('01_PRESUPUESTO_CRONOGRAMA_BASE'!G2:G3) -> 16336.4 | F66: =SUMIFS('02_CRONOGRAMA_PV_DIARIO'!E:E, '02_CRONOGRAMA_PV_DIARIO'!A:A, A66, '02_CRONOGRAMA_PV_DIARIO'!C:C, C66) -> 0 | G66: =SUMIFS(F$2:F66, C$2:C66, C66) -> 16336.46 | H66: =SUMIFS('04_LOG_FIELD_ENTRIES'!J:J, '04_LOG_FIELD_ENTRIES'!B:B, B66, '04_LOG_FIELD_ENTRIES'!D:D, C66, '04_LOG_FIELD_ENTRIES'!K:K, "EV_PRODUCCION") -> 0 | I66: =SUMIFS(H$2:H66, C$2:C66, C66) -> 5823.2 | J66: =SUMIFS('04_LOG_FIELD_ENTRIES'!J:J, '04_LOG_FIELD_ENTRIES'!B:B, B66, '04_LOG_FIELD_ENTRIES'!D:D, C66, '04_LOG_FIELD_ENTRIES'!K:K, "AC_*") -> 0 | K66: =SUMIFS(J$2:J66, C$2:C66, C66) -> 6331 | L66: =I66-K66 -> -507.8 | M66: =I66-G66 -> -10513.26 | N66: =IF(G66>0, I66/G66, 1) -> 0.35645421 | O66: =IF(K66>0, I66/K66, 1) -> 0.9197915 | P66: =IF(AND(N66>=0.95, O66>=0.95), "SALUDABLE", IF(N66<0.9, "ALERTA RETRASO", "ALERTA SOBRECOSTO")) -> ALERTA RETRASO
A67: 17 | B67: 2026-08-17 | C67: WBS-200 | D67: Red de Alcantarillado, Zanjas y Buzones | E67: =SUM('01_PRESUPUESTO_CRONOGRAMA_BASE'!G4:G9) -> 372046.56 | F67: =SUMIFS('02_CRONOGRAMA_PV_DIARIO'!E:E, '02_CRONOGRAMA_PV_DIARIO'!A:A, A67, '02_CRONOGRAMA_PV_DIARIO'!C:C, C67) -> 8939.69 | G67: =SUMIFS(F$2:F67, C$2:C67, C67) -> 45520.71 | H67: =SUMIFS('04_LOG_FIELD_ENTRIES'!J:J, '04_LOG_FIELD_ENTRIES'!B:B, B67, '04_LOG_FIELD_ENTRIES'!D:D, C67, '04_LOG_FIELD_ENTRIES'!K:K, "EV_PRODUCCION") -> 0 | I67: =SUMIFS(H$2:H67, C$2:C67, C67) -> 44254.52 | J67: =SUMIFS('04_LOG_FIELD_ENTRIES'!J:J, '04_LOG_FIELD_ENTRIES'!B:B, B67, '04_LOG_FIELD_ENTRIES'!D:D, C67, '04_LOG_FIELD_ENTRIES'!K:K, "AC_*") -> 0 | K67: =SUMIFS(J$2:J67, C$2:C67, C67) -> 34269.2 | L67: =I67-K67 -> 9985.32 | M67: =I67-G67 -> -1266.19 | N67: =IF(G67>0, I67/G67, 1) -> 0.97218431 | O67: =IF(K67>0, I67/K67, 1) -> 1.2913788 | P67: =IF(AND(N67>=0.95, O67>=0.95), "SALUDABLE", IF(N67<0.9, "ALERTA RETRASO", "ALERTA SOBRECOSTO")) -> SALUDABLE
A68: 17 | B68: 2026-08-17 | C68: WBS-300 | D68: Red de Agua Potable y Conexiones Domiciliarias | E68: =SUM('01_PRESUPUESTO_CRONOGRAMA_BASE'!G10:G11) -> 57565.2 | F68: =SUMIFS('02_CRONOGRAMA_PV_DIARIO'!E:E, '02_CRONOGRAMA_PV_DIARIO'!A:A, A68, '02_CRONOGRAMA_PV_DIARIO'!C:C, C68) -> 0 | G68: =SUMIFS(F$2:F68, C$2:C68, C68) -> 0 | H68: =SUMIFS('04_LOG_FIELD_ENTRIES'!J:J, '04_LOG_FIELD_ENTRIES'!B:B, B68, '04_LOG_FIELD_ENTRIES'!D:D, C68, '04_LOG_FIELD_ENTRIES'!K:K, "EV_PRODUCCION") -> 0 | I68: =SUMIFS(H$2:H68, C$2:C68, C68) -> 9327.45 | J68: =SUMIFS('04_LOG_FIELD_ENTRIES'!J:J, '04_LOG_FIELD_ENTRIES'!B:B, B68, '04_LOG_FIELD_ENTRIES'!D:D, C68, '04_LOG_FIELD_ENTRIES'!K:K, "AC_*") -> 0 | K68: =SUMIFS(J$2:J68, C$2:C68, C68) -> 7730.8 | L68: =I68-K68 -> 1596.65 | M68: =I68-G68 -> 9327.45 | N68: =IF(G68>0, I68/G68, 1) -> 1 | O68: =IF(K68>0, I68/K68, 1) -> 1.206531 | P68: =IF(AND(N68>=0.95, O68>=0.95), "SALUDABLE", IF(N68<0.9, "ALERTA RETRASO", "ALERTA SOBRECOSTO")) -> SALUDABLE
A69: 17 | B69: 2026-08-17 | C69: WBS-400 | D69: Pruebas Hidráulicas, Desinfección y Entrega | E69: =SUM('01_PRESUPUESTO_CRONOGRAMA_BASE'!G12:G12) -> 9348.06 | F69: =SUMIFS('02_CRONOGRAMA_PV_DIARIO'!E:E, '02_CRONOGRAMA_PV_DIARIO'!A:A, A69, '02_CRONOGRAMA_PV_DIARIO'!C:C, C69) -> 0 | G69: =SUMIFS(F$2:F69, C$2:C69, C69) -> 0 | H69: =SUMIFS('04_LOG_FIELD_ENTRIES'!J:J, '04_LOG_FIELD_ENTRIES'!B:B, B69, '04_LOG_FIELD_ENTRIES'!D:D, C69, '04_LOG_FIELD_ENTRIES'!K:K, "EV_PRODUCCION") -> 0 | I69: =SUMIFS(H$2:H69, C$2:C69, C69) -> 2337.02 | J69: =SUMIFS('04_LOG_FIELD_ENTRIES'!J:J, '04_LOG_FIELD_ENTRIES'!B:B, B69, '04_LOG_FIELD_ENTRIES'!D:D, C69, '04_LOG_FIELD_ENTRIES'!K:K, "AC_*") -> 0 | K69: =SUMIFS(J$2:J69, C$2:C69, C69) -> 1299.2 | L69: =I69-K69 -> 1037.82 | M69: =I69-G69 -> 2337.02 | N69: =IF(G69>0, I69/G69, 1) -> 1 | O69: =IF(K69>0, I69/K69, 1) -> 1.7988147 | P69: =IF(AND(N69>=0.95, O69>=0.95), "SALUDABLE", IF(N69<0.9, "ALERTA RETRASO", "ALERTA SOBRECOSTO")) -> SALUDABLE
A70: 18 | B70: 2026-08-18 | C70: WBS-100 | D70: Obras Preliminares, Trazo y Movilización | E70: =SUM('01_PRESUPUESTO_CRONOGRAMA_BASE'!G2:G3) -> 16336.4 | F70: =SUMIFS('02_CRONOGRAMA_PV_DIARIO'!E:E, '02_CRONOGRAMA_PV_DIARIO'!A:A, A70, '02_CRONOGRAMA_PV_DIARIO'!C:C, C70) -> 0 | G70: =SUMIFS(F$2:F70, C$2:C70, C70) -> 16336.46 | H70: =SUMIFS('04_LOG_FIELD_ENTRIES'!J:J, '04_LOG_FIELD_ENTRIES'!B:B, B70, '04_LOG_FIELD_ENTRIES'!D:D, C70, '04_LOG_FIELD_ENTRIES'!K:K, "EV_PRODUCCION") -> 0 | I70: =SUMIFS(H$2:H70, C$2:C70, C70) -> 5823.2 | J70: =SUMIFS('04_LOG_FIELD_ENTRIES'!J:J, '04_LOG_FIELD_ENTRIES'!B:B, B70, '04_LOG_FIELD_ENTRIES'!D:D, C70, '04_LOG_FIELD_ENTRIES'!K:K, "AC_*") -> 0 | K70: =SUMIFS(J$2:J70, C$2:C70, C70) -> 6331 | L70: =I70-K70 -> -507.8 | M70: =I70-G70 -> -10513.26 | N70: =IF(G70>0, I70/G70, 1) -> 0.35645421 | O70: =IF(K70>0, I70/K70, 1) -> 0.9197915 | P70: =IF(AND(N70>=0.95, O70>=0.95), "SALUDABLE", IF(N70<0.9, "ALERTA RETRASO", "ALERTA SOBRECOSTO")) -> ALERTA RETRASO
A71: 18 | B71: 2026-08-18 | C71: WBS-200 | D71: Red de Alcantarillado, Zanjas y Buzones | E71: =SUM('01_PRESUPUESTO_CRONOGRAMA_BASE'!G4:G9) -> 372046.56 | F71: =SUMIFS('02_CRONOGRAMA_PV_DIARIO'!E:E, '02_CRONOGRAMA_PV_DIARIO'!A:A, A71, '02_CRONOGRAMA_PV_DIARIO'!C:C, C71) -> 13896.64 | G71: =SUMIFS(F$2:F71, C$2:C71, C71) -> 59417.35 | H71: =SUMIFS('04_LOG_FIELD_ENTRIES'!J:J, '04_LOG_FIELD_ENTRIES'!B:B, B71, '04_LOG_FIELD_ENTRIES'!D:D, C71, '04_LOG_FIELD_ENTRIES'!K:K, "EV_PRODUCCION") -> 0 | I71: =SUMIFS(H$2:H71, C$2:C71, C71) -> 44254.52 | J71: =SUMIFS('04_LOG_FIELD_ENTRIES'!J:J, '04_LOG_FIELD_ENTRIES'!B:B, B71, '04_LOG_FIELD_ENTRIES'!D:D, C71, '04_LOG_FIELD_ENTRIES'!K:K, "AC_*") -> 0 | K71: =SUMIFS(J$2:J71, C$2:C71, C71) -> 34269.2 | L71: =I71-K71 -> 9985.32 | M71: =I71-G71 -> -15162.83 | N71: =IF(G71>0, I71/G71, 1) -> 0.74480804 | O71: =IF(K71>0, I71/K71, 1) -> 1.2913788 | P71: =IF(AND(N71>=0.95, O71>=0.95), "SALUDABLE", IF(N71<0.9, "ALERTA RETRASO", "ALERTA SOBRECOSTO")) -> ALERTA RETRASO
A72: 18 | B72: 2026-08-18 | C72: WBS-300 | D72: Red de Agua Potable y Conexiones Domiciliarias | E72: =SUM('01_PRESUPUESTO_CRONOGRAMA_BASE'!G10:G11) -> 57565.2 | F72: =SUMIFS('02_CRONOGRAMA_PV_DIARIO'!E:E, '02_CRONOGRAMA_PV_DIARIO'!A:A, A72, '02_CRONOGRAMA_PV_DIARIO'!C:C, C72) -> 0 | G72: =SUMIFS(F$2:F72, C$2:C72, C72) -> 0 | H72: =SUMIFS('04_LOG_FIELD_ENTRIES'!J:J, '04_LOG_FIELD_ENTRIES'!B:B, B72, '04_LOG_FIELD_ENTRIES'!D:D, C72, '04_LOG_FIELD_ENTRIES'!K:K, "EV_PRODUCCION") -> 0 | I72: =SUMIFS(H$2:H72, C$2:C72, C72) -> 9327.45 | J72: =SUMIFS('04_LOG_FIELD_ENTRIES'!J:J, '04_LOG_FIELD_ENTRIES'!B:B, B72, '04_LOG_FIELD_ENTRIES'!D:D, C72, '04_LOG_FIELD_ENTRIES'!K:K, "AC_*") -> 0 | K72: =SUMIFS(J$2:J72, C$2:C72, C72) -> 7730.8 | L72: =I72-K72 -> 1596.65 | M72: =I72-G72 -> 9327.45 | N72: =IF(G72>0, I72/G72, 1) -> 1 | O72: =IF(K72>0, I72/K72, 1) -> 1.206531 | P72: =IF(AND(N72>=0.95, O72>=0.95), "SALUDABLE", IF(N72<0.9, "ALERTA RETRASO", "ALERTA SOBRECOSTO")) -> SALUDABLE
A73: 18 | B73: 2026-08-18 | C73: WBS-400 | D73: Pruebas Hidráulicas, Desinfección y Entrega | E73: =SUM('01_PRESUPUESTO_CRONOGRAMA_BASE'!G12:G12) -> 9348.06 | F73: =SUMIFS('02_CRONOGRAMA_PV_DIARIO'!E:E, '02_CRONOGRAMA_PV_DIARIO'!A:A, A73, '02_CRONOGRAMA_PV_DIARIO'!C:C, C73) -> 0 | G73: =SUMIFS(F$2:F73, C$2:C73, C73) -> 0 | H73: =SUMIFS('04_LOG_FIELD_ENTRIES'!J:J, '04_LOG_FIELD_ENTRIES'!B:B, B73, '04_LOG_FIELD_ENTRIES'!D:D, C73, '04_LOG_FIELD_ENTRIES'!K:K, "EV_PRODUCCION") -> 0 | I73: =SUMIFS(H$2:H73, C$2:C73, C73) -> 2337.02 | J73: =SUMIFS('04_LOG_FIELD_ENTRIES'!J:J, '04_LOG_FIELD_ENTRIES'!B:B, B73, '04_LOG_FIELD_ENTRIES'!D:D, C73, '04_LOG_FIELD_ENTRIES'!K:K, "AC_*") -> 0 | K73: =SUMIFS(J$2:J73, C$2:C73, C73) -> 1299.2 | L73: =I73-K73 -> 1037.82 | M73: =I73-G73 -> 2337.02 | N73: =IF(G73>0, I73/G73, 1) -> 1 | O73: =IF(K73>0, I73/K73, 1) -> 1.7988147 | P73: =IF(AND(N73>=0.95, O73>=0.95), "SALUDABLE", IF(N73<0.9, "ALERTA RETRASO", "ALERTA SOBRECOSTO")) -> SALUDABLE
A74: 19 | B74: 2026-08-19 | C74: WBS-100 | D74: Obras Preliminares, Trazo y Movilización | E74: =SUM('01_PRESUPUESTO_CRONOGRAMA_BASE'!G2:G3) -> 16336.4 | F74: =SUMIFS('02_CRONOGRAMA_PV_DIARIO'!E:E, '02_CRONOGRAMA_PV_DIARIO'!A:A, A74, '02_CRONOGRAMA_PV_DIARIO'!C:C, C74) -> 0 | G74: =SUMIFS(F$2:F74, C$2:C74, C74) -> 16336.46 | H74: =SUMIFS('04_LOG_FIELD_ENTRIES'!J:J, '04_LOG_FIELD_ENTRIES'!B:B, B74, '04_LOG_FIELD_ENTRIES'!D:D, C74, '04_LOG_FIELD_ENTRIES'!K:K, "EV_PRODUCCION") -> 0 | I74: =SUMIFS(H$2:H74, C$2:C74, C74) -> 5823.2 | J74: =SUMIFS('04_LOG_FIELD_ENTRIES'!J:J, '04_LOG_FIELD_ENTRIES'!B:B, B74, '04_LOG_FIELD_ENTRIES'!D:D, C74, '04_LOG_FIELD_ENTRIES'!K:K, "AC_*") -> 0 | K74: =SUMIFS(J$2:J74, C$2:C74, C74) -> 6331 | L74: =I74-K74 -> -507.8 | M74: =I74-G74 -> -10513.26 | N74: =IF(G74>0, I74/G74, 1) -> 0.35645421 | O74: =IF(K74>0, I74/K74, 1) -> 0.9197915 | P74: =IF(AND(N74>=0.95, O74>=0.95), "SALUDABLE", IF(N74<0.9, "ALERTA RETRASO", "ALERTA SOBRECOSTO")) -> ALERTA RETRASO
A75: 19 | B75: 2026-08-19 | C75: WBS-200 | D75: Red de Alcantarillado, Zanjas y Buzones | E75: =SUM('01_PRESUPUESTO_CRONOGRAMA_BASE'!G4:G9) -> 372046.56 | F75: =SUMIFS('02_CRONOGRAMA_PV_DIARIO'!E:E, '02_CRONOGRAMA_PV_DIARIO'!A:A, A75, '02_CRONOGRAMA_PV_DIARIO'!C:C, C75) -> 13896.64 | G75: =SUMIFS(F$2:F75, C$2:C75, C75) -> 73313.99 | H75: =SUMIFS('04_LOG_FIELD_ENTRIES'!J:J, '04_LOG_FIELD_ENTRIES'!B:B, B75, '04_LOG_FIELD_ENTRIES'!D:D, C75, '04_LOG_FIELD_ENTRIES'!K:K, "EV_PRODUCCION") -> 0 | I75: =SUMIFS(H$2:H75, C$2:C75, C75) -> 44254.52 | J75: =SUMIFS('04_LOG_FIELD_ENTRIES'!J:J, '04_LOG_FIELD_ENTRIES'!B:B, B75, '04_LOG_FIELD_ENTRIES'!D:D, C75, '04_LOG_FIELD_ENTRIES'!K:K, "AC_*") -> 0 | K75: =SUMIFS(J$2:J75, C$2:C75, C75) -> 34269.2 | L75: =I75-K75 -> 9985.32 | M75: =I75-G75 -> -29059.47 | N75: =IF(G75>0, I75/G75, 1) -> 0.60362995 | O75: =IF(K75>0, I75/K75, 1) -> 1.2913788 | P75: =IF(AND(N75>=0.95, O75>=0.95), "SALUDABLE", IF(N75<0.9, "ALERTA RETRASO", "ALERTA SOBRECOSTO")) -> ALERTA RETRASO
A76: 19 | B76: 2026-08-19 | C76: WBS-300 | D76: Red de Agua Potable y Conexiones Domiciliarias | E76: =SUM('01_PRESUPUESTO_CRONOGRAMA_BASE'!G10:G11) -> 57565.2 | F76: =SUMIFS('02_CRONOGRAMA_PV_DIARIO'!E:E, '02_CRONOGRAMA_PV_DIARIO'!A:A, A76, '02_CRONOGRAMA_PV_DIARIO'!C:C, C76) -> 0 | G76: =SUMIFS(F$2:F76, C$2:C76, C76) -> 0 | H76: =SUMIFS('04_LOG_FIELD_ENTRIES'!J:J, '04_LOG_FIELD_ENTRIES'!B:B, B76, '04_LOG_FIELD_ENTRIES'!D:D, C76, '04_LOG_FIELD_ENTRIES'!K:K, "EV_PRODUCCION") -> 0 | I76: =SUMIFS(H$2:H76, C$2:C76, C76) -> 9327.45 | J76: =SUMIFS('04_LOG_FIELD_ENTRIES'!J:J, '04_LOG_FIELD_ENTRIES'!B:B, B76, '04_LOG_FIELD_ENTRIES'!D:D, C76, '04_LOG_FIELD_ENTRIES'!K:K, "AC_*") -> 0 | K76: =SUMIFS(J$2:J76, C$2:C76, C76) -> 7730.8 | L76: =I76-K76 -> 1596.65 | M76: =I76-G76 -> 9327.45 | N76: =IF(G76>0, I76/G76, 1) -> 1 | O76: =IF(K76>0, I76/K76, 1) -> 1.206531 | P76: =IF(AND(N76>=0.95, O76>=0.95), "SALUDABLE", IF(N76<0.9, "ALERTA RETRASO", "ALERTA SOBRECOSTO")) -> SALUDABLE
A77: 19 | B77: 2026-08-19 | C77: WBS-400 | D77: Pruebas Hidráulicas, Desinfección y Entrega | E77: =SUM('01_PRESUPUESTO_CRONOGRAMA_BASE'!G12:G12) -> 9348.06 | F77: =SUMIFS('02_CRONOGRAMA_PV_DIARIO'!E:E, '02_CRONOGRAMA_PV_DIARIO'!A:A, A77, '02_CRONOGRAMA_PV_DIARIO'!C:C, C77) -> 0 | G77: =SUMIFS(F$2:F77, C$2:C77, C77) -> 0 | H77: =SUMIFS('04_LOG_FIELD_ENTRIES'!J:J, '04_LOG_FIELD_ENTRIES'!B:B, B77, '04_LOG_FIELD_ENTRIES'!D:D, C77, '04_LOG_FIELD_ENTRIES'!K:K, "EV_PRODUCCION") -> 0 | I77: =SUMIFS(H$2:H77, C$2:C77, C77) -> 2337.02 | J77: =SUMIFS('04_LOG_FIELD_ENTRIES'!J:J, '04_LOG_FIELD_ENTRIES'!B:B, B77, '04_LOG_FIELD_ENTRIES'!D:D, C77, '04_LOG_FIELD_ENTRIES'!K:K, "AC_*") -> 0 | K77: =SUMIFS(J$2:J77, C$2:C77, C77) -> 1299.2 | L77: =I77-K77 -> 1037.82 | M77: =I77-G77 -> 2337.02 | N77: =IF(G77>0, I77/G77, 1) -> 1 | O77: =IF(K77>0, I77/K77, 1) -> 1.7988147 | P77: =IF(AND(N77>=0.95, O77>=0.95), "SALUDABLE", IF(N77<0.9, "ALERTA RETRASO", "ALERTA SOBRECOSTO")) -> SALUDABLE
A78: 20 | B78: 2026-08-20 | C78: WBS-100 | D78: Obras Preliminares, Trazo y Movilización | E78: =SUM('01_PRESUPUESTO_CRONOGRAMA_BASE'!G2:G3) -> 16336.4 | F78: =SUMIFS('02_CRONOGRAMA_PV_DIARIO'!E:E, '02_CRONOGRAMA_PV_DIARIO'!A:A, A78, '02_CRONOGRAMA_PV_DIARIO'!C:C, C78) -> 0 | G78: =SUMIFS(F$2:F78, C$2:C78, C78) -> 16336.46 | H78: =SUMIFS('04_LOG_FIELD_ENTRIES'!J:J, '04_LOG_FIELD_ENTRIES'!B:B, B78, '04_LOG_FIELD_ENTRIES'!D:D, C78, '04_LOG_FIELD_ENTRIES'!K:K, "EV_PRODUCCION") -> 0 | I78: =SUMIFS(H$2:H78, C$2:C78, C78) -> 5823.2 | J78: =SUMIFS('04_LOG_FIELD_ENTRIES'!J:J, '04_LOG_FIELD_ENTRIES'!B:B, B78, '04_LOG_FIELD_ENTRIES'!D:D, C78, '04_LOG_FIELD_ENTRIES'!K:K, "AC_*") -> 0 | K78: =SUMIFS(J$2:J78, C$2:C78, C78) -> 6331 | L78: =I78-K78 -> -507.8 | M78: =I78-G78 -> -10513.26 | N78: =IF(G78>0, I78/G78, 1) -> 0.35645421 | O78: =IF(K78>0, I78/K78, 1) -> 0.9197915 | P78: =IF(AND(N78>=0.95, O78>=0.95), "SALUDABLE", IF(N78<0.9, "ALERTA RETRASO", "ALERTA SOBRECOSTO")) -> ALERTA RETRASO
A79: 20 | B79: 2026-08-20 | C79: WBS-200 | D79: Red de Alcantarillado, Zanjas y Buzones | E79: =SUM('01_PRESUPUESTO_CRONOGRAMA_BASE'!G4:G9) -> 372046.56 | F79: =SUMIFS('02_CRONOGRAMA_PV_DIARIO'!E:E, '02_CRONOGRAMA_PV_DIARIO'!A:A, A79, '02_CRONOGRAMA_PV_DIARIO'!C:C, C79) -> 13896.64 | G79: =SUMIFS(F$2:F79, C$2:C79, C79) -> 87210.63 | H79: =SUMIFS('04_LOG_FIELD_ENTRIES'!J:J, '04_LOG_FIELD_ENTRIES'!B:B, B79, '04_LOG_FIELD_ENTRIES'!D:D, C79, '04_LOG_FIELD_ENTRIES'!K:K, "EV_PRODUCCION") -> 0 | I79: =SUMIFS(H$2:H79, C$2:C79, C79) -> 44254.52 | J79: =SUMIFS('04_LOG_FIELD_ENTRIES'!J:J, '04_LOG_FIELD_ENTRIES'!B:B, B79, '04_LOG_FIELD_ENTRIES'!D:D, C79, '04_LOG_FIELD_ENTRIES'!K:K, "AC_*") -> 0 | K79: =SUMIFS(J$2:J79, C$2:C79, C79) -> 34269.2 | L79: =I79-K79 -> 9985.32 | M79: =I79-G79 -> -42956.11 | N79: =IF(G79>0, I79/G79, 1) -> 0.5074441 | O79: =IF(K79>0, I79/K79, 1) -> 1.2913788 | P79: =IF(AND(N79>=0.95, O79>=0.95), "SALUDABLE", IF(N79<0.9, "ALERTA RETRASO", "ALERTA SOBRECOSTO")) -> ALERTA RETRASO
A80: 20 | B80: 2026-08-20 | C80: WBS-300 | D80: Red de Agua Potable y Conexiones Domiciliarias | E80: =SUM('01_PRESUPUESTO_CRONOGRAMA_BASE'!G10:G11) -> 57565.2 | F80: =SUMIFS('02_CRONOGRAMA_PV_DIARIO'!E:E, '02_CRONOGRAMA_PV_DIARIO'!A:A, A80, '02_CRONOGRAMA_PV_DIARIO'!C:C, C80) -> 0 | G80: =SUMIFS(F$2:F80, C$2:C80, C80) -> 0 | H80: =SUMIFS('04_LOG_FIELD_ENTRIES'!J:J, '04_LOG_FIELD_ENTRIES'!B:B, B80, '04_LOG_FIELD_ENTRIES'!D:D, C80, '04_LOG_FIELD_ENTRIES'!K:K, "EV_PRODUCCION") -> 0 | I80: =SUMIFS(H$2:H80, C$2:C80, C80) -> 9327.45 | J80: =SUMIFS('04_LOG_FIELD_ENTRIES'!J:J, '04_LOG_FIELD_ENTRIES'!B:B, B80, '04_LOG_FIELD_ENTRIES'!D:D, C80, '04_LOG_FIELD_ENTRIES'!K:K, "AC_*") -> 0 | K80: =SUMIFS(J$2:J80, C$2:C80, C80) -> 7730.8 | L80: =I80-K80 -> 1596.65 | M80: =I80-G80 -> 9327.45 | N80: =IF(G80>0, I80/G80, 1) -> 1 | O80: =IF(K80>0, I80/K80, 1) -> 1.206531 | P80: =IF(AND(N80>=0.95, O80>=0.95), "SALUDABLE", IF(N80<0.9, "ALERTA RETRASO", "ALERTA SOBRECOSTO")) -> SALUDABLE
A81: 20 | B81: 2026-08-20 | C81: WBS-400 | D81: Pruebas Hidráulicas, Desinfección y Entrega | E81: =SUM('01_PRESUPUESTO_CRONOGRAMA_BASE'!G12:G12) -> 9348.06 | F81: =SUMIFS('02_CRONOGRAMA_PV_DIARIO'!E:E, '02_CRONOGRAMA_PV_DIARIO'!A:A, A81, '02_CRONOGRAMA_PV_DIARIO'!C:C, C81) -> 0 | G81: =SUMIFS(F$2:F81, C$2:C81, C81) -> 0 | H81: =SUMIFS('04_LOG_FIELD_ENTRIES'!J:J, '04_LOG_FIELD_ENTRIES'!B:B, B81, '04_LOG_FIELD_ENTRIES'!D:D, C81, '04_LOG_FIELD_ENTRIES'!K:K, "EV_PRODUCCION") -> 0 | I81: =SUMIFS(H$2:H81, C$2:C81, C81) -> 2337.02 | J81: =SUMIFS('04_LOG_FIELD_ENTRIES'!J:J, '04_LOG_FIELD_ENTRIES'!B:B, B81, '04_LOG_FIELD_ENTRIES'!D:D, C81, '04_LOG_FIELD_ENTRIES'!K:K, "AC_*") -> 0 | K81: =SUMIFS(J$2:J81, C$2:C81, C81) -> 1299.2 | L81: =I81-K81 -> 1037.82 | M81: =I81-G81 -> 2337.02 | N81: =IF(G81>0, I81/G81, 1) -> 1 | O81: =IF(K81>0, I81/K81, 1) -> 1.7988147 | P81: =IF(AND(N81>=0.95, O81>=0.95), "SALUDABLE", IF(N81<0.9, "ALERTA RETRASO", "ALERTA SOBRECOSTO")) -> SALUDABLE
A82: 21 | B82: 2026-08-21 | C82: WBS-100 | D82: Obras Preliminares, Trazo y Movilización | E82: =SUM('01_PRESUPUESTO_CRONOGRAMA_BASE'!G2:G3) -> 16336.4 | F82: =SUMIFS('02_CRONOGRAMA_PV_DIARIO'!E:E, '02_CRONOGRAMA_PV_DIARIO'!A:A, A82, '02_CRONOGRAMA_PV_DIARIO'!C:C, C82) -> 0 | G82: =SUMIFS(F$2:F82, C$2:C82, C82) -> 16336.46 | H82: =SUMIFS('04_LOG_FIELD_ENTRIES'!J:J, '04_LOG_FIELD_ENTRIES'!B:B, B82, '04_LOG_FIELD_ENTRIES'!D:D, C82, '04_LOG_FIELD_ENTRIES'!K:K, "EV_PRODUCCION") -> 0 | I82: =SUMIFS(H$2:H82, C$2:C82, C82) -> 5823.2 | J82: =SUMIFS('04_LOG_FIELD_ENTRIES'!J:J, '04_LOG_FIELD_ENTRIES'!B:B, B82, '04_LOG_FIELD_ENTRIES'!D:D, C82, '04_LOG_FIELD_ENTRIES'!K:K, "AC_*") -> 0 | K82: =SUMIFS(J$2:J82, C$2:C82, C82) -> 6331 | L82: =I82-K82 -> -507.8 | M82: =I82-G82 -> -10513.26 | N82: =IF(G82>0, I82/G82, 1) -> 0.35645421 | O82: =IF(K82>0, I82/K82, 1) -> 0.9197915 | P82: =IF(AND(N82>=0.95, O82>=0.95), "SALUDABLE", IF(N82<0.9, "ALERTA RETRASO", "ALERTA SOBRECOSTO")) -> ALERTA RETRASO
A83: 21 | B83: 2026-08-21 | C83: WBS-200 | D83: Red de Alcantarillado, Zanjas y Buzones | E83: =SUM('01_PRESUPUESTO_CRONOGRAMA_BASE'!G4:G9) -> 372046.56 | F83: =SUMIFS('02_CRONOGRAMA_PV_DIARIO'!E:E, '02_CRONOGRAMA_PV_DIARIO'!A:A, A83, '02_CRONOGRAMA_PV_DIARIO'!C:C, C83) -> 13896.64 | G83: =SUMIFS(F$2:F83, C$2:C83, C83) -> 101107.27 | H83: =SUMIFS('04_LOG_FIELD_ENTRIES'!J:J, '04_LOG_FIELD_ENTRIES'!B:B, B83, '04_LOG_FIELD_ENTRIES'!D:D, C83, '04_LOG_FIELD_ENTRIES'!K:K, "EV_PRODUCCION") -> 0 | I83: =SUMIFS(H$2:H83, C$2:C83, C83) -> 44254.52 | J83: =SUMIFS('04_LOG_FIELD_ENTRIES'!J:J, '04_LOG_FIELD_ENTRIES'!B:B, B83, '04_LOG_FIELD_ENTRIES'!D:D, C83, '04_LOG_FIELD_ENTRIES'!K:K, "AC_*") -> 0 | K83: =SUMIFS(J$2:J83, C$2:C83, C83) -> 34269.2 | L83: =I83-K83 -> 9985.32 | M83: =I83-G83 -> -56852.75 | N83: =IF(G83>0, I83/G83, 1) -> 0.43769869 | O83: =IF(K83>0, I83/K83, 1) -> 1.2913788 | P83: =IF(AND(N83>=0.95, O83>=0.95), "SALUDABLE", IF(N83<0.9, "ALERTA RETRASO", "ALERTA SOBRECOSTO")) -> ALERTA RETRASO
A84: 21 | B84: 2026-08-21 | C84: WBS-300 | D84: Red de Agua Potable y Conexiones Domiciliarias | E84: =SUM('01_PRESUPUESTO_CRONOGRAMA_BASE'!G10:G11) -> 57565.2 | F84: =SUMIFS('02_CRONOGRAMA_PV_DIARIO'!E:E, '02_CRONOGRAMA_PV_DIARIO'!A:A, A84, '02_CRONOGRAMA_PV_DIARIO'!C:C, C84) -> 0 | G84: =SUMIFS(F$2:F84, C$2:C84, C84) -> 0 | H84: =SUMIFS('04_LOG_FIELD_ENTRIES'!J:J, '04_LOG_FIELD_ENTRIES'!B:B, B84, '04_LOG_FIELD_ENTRIES'!D:D, C84, '04_LOG_FIELD_ENTRIES'!K:K, "EV_PRODUCCION") -> 0 | I84: =SUMIFS(H$2:H84, C$2:C84, C84) -> 9327.45 | J84: =SUMIFS('04_LOG_FIELD_ENTRIES'!J:J, '04_LOG_FIELD_ENTRIES'!B:B, B84, '04_LOG_FIELD_ENTRIES'!D:D, C84, '04_LOG_FIELD_ENTRIES'!K:K, "AC_*") -> 0 | K84: =SUMIFS(J$2:J84, C$2:C84, C84) -> 7730.8 | L84: =I84-K84 -> 1596.65 | M84: =I84-G84 -> 9327.45 | N84: =IF(G84>0, I84/G84, 1) -> 1 | O84: =IF(K84>0, I84/K84, 1) -> 1.206531 | P84: =IF(AND(N84>=0.95, O84>=0.95), "SALUDABLE", IF(N84<0.9, "ALERTA RETRASO", "ALERTA SOBRECOSTO")) -> SALUDABLE
A85: 21 | B85: 2026-08-21 | C85: WBS-400 | D85: Pruebas Hidráulicas, Desinfección y Entrega | E85: =SUM('01_PRESUPUESTO_CRONOGRAMA_BASE'!G12:G12) -> 9348.06 | F85: =SUMIFS('02_CRONOGRAMA_PV_DIARIO'!E:E, '02_CRONOGRAMA_PV_DIARIO'!A:A, A85, '02_CRONOGRAMA_PV_DIARIO'!C:C, C85) -> 0 | G85: =SUMIFS(F$2:F85, C$2:C85, C85) -> 0 | H85: =SUMIFS('04_LOG_FIELD_ENTRIES'!J:J, '04_LOG_FIELD_ENTRIES'!B:B, B85, '04_LOG_FIELD_ENTRIES'!D:D, C85, '04_LOG_FIELD_ENTRIES'!K:K, "EV_PRODUCCION") -> 0 | I85: =SUMIFS(H$2:H85, C$2:C85, C85) -> 2337.02 | J85: =SUMIFS('04_LOG_FIELD_ENTRIES'!J:J, '04_LOG_FIELD_ENTRIES'!B:B, B85, '04_LOG_FIELD_ENTRIES'!D:D, C85, '04_LOG_FIELD_ENTRIES'!K:K, "AC_*") -> 0 | K85: =SUMIFS(J$2:J85, C$2:C85, C85) -> 1299.2 | L85: =I85-K85 -> 1037.82 | M85: =I85-G85 -> 2337.02 | N85: =IF(G85>0, I85/G85, 1) -> 1 | O85: =IF(K85>0, I85/K85, 1) -> 1.7988147 | P85: =IF(AND(N85>=0.95, O85>=0.95), "SALUDABLE", IF(N85<0.9, "ALERTA RETRASO", "ALERTA SOBRECOSTO")) -> SALUDABLE
A86: 22 | B86: 2026-08-22 | C86: WBS-100 | D86: Obras Preliminares, Trazo y Movilización | E86: =SUM('01_PRESUPUESTO_CRONOGRAMA_BASE'!G2:G3) -> 16336.4 | F86: =SUMIFS('02_CRONOGRAMA_PV_DIARIO'!E:E, '02_CRONOGRAMA_PV_DIARIO'!A:A, A86, '02_CRONOGRAMA_PV_DIARIO'!C:C, C86) -> 0 | G86: =SUMIFS(F$2:F86, C$2:C86, C86) -> 16336.46 | H86: =SUMIFS('04_LOG_FIELD_ENTRIES'!J:J, '04_LOG_FIELD_ENTRIES'!B:B, B86, '04_LOG_FIELD_ENTRIES'!D:D, C86, '04_LOG_FIELD_ENTRIES'!K:K, "EV_PRODUCCION") -> 0 | I86: =SUMIFS(H$2:H86, C$2:C86, C86) -> 5823.2 | J86: =SUMIFS('04_LOG_FIELD_ENTRIES'!J:J, '04_LOG_FIELD_ENTRIES'!B:B, B86, '04_LOG_FIELD_ENTRIES'!D:D, C86, '04_LOG_FIELD_ENTRIES'!K:K, "AC_*") -> 0 | K86: =SUMIFS(J$2:J86, C$2:C86, C86) -> 6331 | L86: =I86-K86 -> -507.8 | M86: =I86-G86 -> -10513.26 | N86: =IF(G86>0, I86/G86, 1) -> 0.35645421 | O86: =IF(K86>0, I86/K86, 1) -> 0.9197915 | P86: =IF(AND(N86>=0.95, O86>=0.95), "SALUDABLE", IF(N86<0.9, "ALERTA RETRASO", "ALERTA SOBRECOSTO")) -> ALERTA RETRASO
A87: 22 | B87: 2026-08-22 | C87: WBS-200 | D87: Red de Alcantarillado, Zanjas y Buzones | E87: =SUM('01_PRESUPUESTO_CRONOGRAMA_BASE'!G4:G9) -> 372046.56 | F87: =SUMIFS('02_CRONOGRAMA_PV_DIARIO'!E:E, '02_CRONOGRAMA_PV_DIARIO'!A:A, A87, '02_CRONOGRAMA_PV_DIARIO'!C:C, C87) -> 17897.81 | G87: =SUMIFS(F$2:F87, C$2:C87, C87) -> 119005.08 | H87: =SUMIFS('04_LOG_FIELD_ENTRIES'!J:J, '04_LOG_FIELD_ENTRIES'!B:B, B87, '04_LOG_FIELD_ENTRIES'!D:D, C87, '04_LOG_FIELD_ENTRIES'!K:K, "EV_PRODUCCION") -> 0 | I87: =SUMIFS(H$2:H87, C$2:C87, C87) -> 44254.52 | J87: =SUMIFS('04_LOG_FIELD_ENTRIES'!J:J, '04_LOG_FIELD_ENTRIES'!B:B, B87, '04_LOG_FIELD_ENTRIES'!D:D, C87, '04_LOG_FIELD_ENTRIES'!K:K, "AC_*") -> 0 | K87: =SUMIFS(J$2:J87, C$2:C87, C87) -> 34269.2 | L87: =I87-K87 -> 9985.32 | M87: =I87-G87 -> -74750.56 | N87: =IF(G87>0, I87/G87, 1) -> 0.37187085 | O87: =IF(K87>0, I87/K87, 1) -> 1.2913788 | P87: =IF(AND(N87>=0.95, O87>=0.95), "SALUDABLE", IF(N87<0.9, "ALERTA RETRASO", "ALERTA SOBRECOSTO")) -> ALERTA RETRASO
A88: 22 | B88: 2026-08-22 | C88: WBS-300 | D88: Red de Agua Potable y Conexiones Domiciliarias | E88: =SUM('01_PRESUPUESTO_CRONOGRAMA_BASE'!G10:G11) -> 57565.2 | F88: =SUMIFS('02_CRONOGRAMA_PV_DIARIO'!E:E, '02_CRONOGRAMA_PV_DIARIO'!A:A, A88, '02_CRONOGRAMA_PV_DIARIO'!C:C, C88) -> 1761.82 | G88: =SUMIFS(F$2:F88, C$2:C88, C88) -> 1761.82 | H88: =SUMIFS('04_LOG_FIELD_ENTRIES'!J:J, '04_LOG_FIELD_ENTRIES'!B:B, B88, '04_LOG_FIELD_ENTRIES'!D:D, C88, '04_LOG_FIELD_ENTRIES'!K:K, "EV_PRODUCCION") -> 0 | I88: =SUMIFS(H$2:H88, C$2:C88, C88) -> 9327.45 | J88: =SUMIFS('04_LOG_FIELD_ENTRIES'!J:J, '04_LOG_FIELD_ENTRIES'!B:B, B88, '04_LOG_FIELD_ENTRIES'!D:D, C88, '04_LOG_FIELD_ENTRIES'!K:K, "AC_*") -> 0 | K88: =SUMIFS(J$2:J88, C$2:C88, C88) -> 7730.8 | L88: =I88-K88 -> 1596.65 | M88: =I88-G88 -> 7565.63 | N88: =IF(G88>0, I88/G88, 1) -> 5.2942128 | O88: =IF(K88>0, I88/K88, 1) -> 1.206531 | P88: =IF(AND(N88>=0.95, O88>=0.95), "SALUDABLE", IF(N88<0.9, "ALERTA RETRASO", "ALERTA SOBRECOSTO")) -> SALUDABLE
A89: 22 | B89: 2026-08-22 | C89: WBS-400 | D89: Pruebas Hidráulicas, Desinfección y Entrega | E89: =SUM('01_PRESUPUESTO_CRONOGRAMA_BASE'!G12:G12) -> 9348.06 | F89: =SUMIFS('02_CRONOGRAMA_PV_DIARIO'!E:E, '02_CRONOGRAMA_PV_DIARIO'!A:A, A89, '02_CRONOGRAMA_PV_DIARIO'!C:C, C89) -> 0 | G89: =SUMIFS(F$2:F89, C$2:C89, C89) -> 0 | H89: =SUMIFS('04_LOG_FIELD_ENTRIES'!J:J, '04_LOG_FIELD_ENTRIES'!B:B, B89, '04_LOG_FIELD_ENTRIES'!D:D, C89, '04_LOG_FIELD_ENTRIES'!K:K, "EV_PRODUCCION") -> 0 | I89: =SUMIFS(H$2:H89, C$2:C89, C89) -> 2337.02 | J89: =SUMIFS('04_LOG_FIELD_ENTRIES'!J:J, '04_LOG_FIELD_ENTRIES'!B:B, B89, '04_LOG_FIELD_ENTRIES'!D:D, C89, '04_LOG_FIELD_ENTRIES'!K:K, "AC_*") -> 0 | K89: =SUMIFS(J$2:J89, C$2:C89, C89) -> 1299.2 | L89: =I89-K89 -> 1037.82 | M89: =I89-G89 -> 2337.02 | N89: =IF(G89>0, I89/G89, 1) -> 1 | O89: =IF(K89>0, I89/K89, 1) -> 1.7988147 | P89: =IF(AND(N89>=0.95, O89>=0.95), "SALUDABLE", IF(N89<0.9, "ALERTA RETRASO", "ALERTA SOBRECOSTO")) -> SALUDABLE
A90: 23 | B90: 2026-08-23 | C90: WBS-100 | D90: Obras Preliminares, Trazo y Movilización | E90: =SUM('01_PRESUPUESTO_CRONOGRAMA_BASE'!G2:G3) -> 16336.4 | F90: =SUMIFS('02_CRONOGRAMA_PV_DIARIO'!E:E, '02_CRONOGRAMA_PV_DIARIO'!A:A, A90, '02_CRONOGRAMA_PV_DIARIO'!C:C, C90) -> 0 | G90: =SUMIFS(F$2:F90, C$2:C90, C90) -> 16336.46 | H90: =SUMIFS('04_LOG_FIELD_ENTRIES'!J:J, '04_LOG_FIELD_ENTRIES'!B:B, B90, '04_LOG_FIELD_ENTRIES'!D:D, C90, '04_LOG_FIELD_ENTRIES'!K:K, "EV_PRODUCCION") -> 0 | I90: =SUMIFS(H$2:H90, C$2:C90, C90) -> 5823.2 | J90: =SUMIFS('04_LOG_FIELD_ENTRIES'!J:J, '04_LOG_FIELD_ENTRIES'!B:B, B90, '04_LOG_FIELD_ENTRIES'!D:D, C90, '04_LOG_FIELD_ENTRIES'!K:K, "AC_*") -> 0 | K90: =SUMIFS(J$2:J90, C$2:C90, C90) -> 6331 | L90: =I90-K90 -> -507.8 | M90: =I90-G90 -> -10513.26 | N90: =IF(G90>0, I90/G90, 1) -> 0.35645421 | O90: =IF(K90>0, I90/K90, 1) -> 0.9197915 | P90: =IF(AND(N90>=0.95, O90>=0.95), "SALUDABLE", IF(N90<0.9, "ALERTA RETRASO", "ALERTA SOBRECOSTO")) -> ALERTA RETRASO
A91: 23 | B91: 2026-08-23 | C91: WBS-200 | D91: Red de Alcantarillado, Zanjas y Buzones | E91: =SUM('01_PRESUPUESTO_CRONOGRAMA_BASE'!G4:G9) -> 372046.56 | F91: =SUMIFS('02_CRONOGRAMA_PV_DIARIO'!E:E, '02_CRONOGRAMA_PV_DIARIO'!A:A, A91, '02_CRONOGRAMA_PV_DIARIO'!C:C, C91) -> 17897.81 | G91: =SUMIFS(F$2:F91, C$2:C91, C91) -> 136902.89 | H91: =SUMIFS('04_LOG_FIELD_ENTRIES'!J:J, '04_LOG_FIELD_ENTRIES'!B:B, B91, '04_LOG_FIELD_ENTRIES'!D:D, C91, '04_LOG_FIELD_ENTRIES'!K:K, "EV_PRODUCCION") -> 0 | I91: =SUMIFS(H$2:H91, C$2:C91, C91) -> 44254.52 | J91: =SUMIFS('04_LOG_FIELD_ENTRIES'!J:J, '04_LOG_FIELD_ENTRIES'!B:B, B91, '04_LOG_FIELD_ENTRIES'!D:D, C91, '04_LOG_FIELD_ENTRIES'!K:K, "AC_*") -> 0 | K91: =SUMIFS(J$2:J91, C$2:C91, C91) -> 34269.2 | L91: =I91-K91 -> 9985.32 | M91: =I91-G91 -> -92648.37 | N91: =IF(G91>0, I91/G91, 1) -> 0.32325483 | O91: =IF(K91>0, I91/K91, 1) -> 1.2913788 | P91: =IF(AND(N91>=0.95, O91>=0.95), "SALUDABLE", IF(N91<0.9, "ALERTA RETRASO", "ALERTA SOBRECOSTO")) -> ALERTA RETRASO
A92: 23 | B92: 2026-08-23 | C92: WBS-300 | D92: Red de Agua Potable y Conexiones Domiciliarias | E92: =SUM('01_PRESUPUESTO_CRONOGRAMA_BASE'!G10:G11) -> 57565.2 | F92: =SUMIFS('02_CRONOGRAMA_PV_DIARIO'!E:E, '02_CRONOGRAMA_PV_DIARIO'!A:A, A92, '02_CRONOGRAMA_PV_DIARIO'!C:C, C92) -> 1761.82 | G92: =SUMIFS(F$2:F92, C$2:C92, C92) -> 3523.64 | H92: =SUMIFS('04_LOG_FIELD_ENTRIES'!J:J, '04_LOG_FIELD_ENTRIES'!B:B, B92, '04_LOG_FIELD_ENTRIES'!D:D, C92, '04_LOG_FIELD_ENTRIES'!K:K, "EV_PRODUCCION") -> 0 | I92: =SUMIFS(H$2:H92, C$2:C92, C92) -> 9327.45 | J92: =SUMIFS('04_LOG_FIELD_ENTRIES'!J:J, '04_LOG_FIELD_ENTRIES'!B:B, B92, '04_LOG_FIELD_ENTRIES'!D:D, C92, '04_LOG_FIELD_ENTRIES'!K:K, "AC_*") -> 0 | K92: =SUMIFS(J$2:J92, C$2:C92, C92) -> 7730.8 | L92: =I92-K92 -> 1596.65 | M92: =I92-G92 -> 5803.81 | N92: =IF(G92>0, I92/G92, 1) -> 2.6471064 | O92: =IF(K92>0, I92/K92, 1) -> 1.206531 | P92: =IF(AND(N92>=0.95, O92>=0.95), "SALUDABLE", IF(N92<0.9, "ALERTA RETRASO", "ALERTA SOBRECOSTO")) -> SALUDABLE
A93: 23 | B93: 2026-08-23 | C93: WBS-400 | D93: Pruebas Hidráulicas, Desinfección y Entrega | E93: =SUM('01_PRESUPUESTO_CRONOGRAMA_BASE'!G12:G12) -> 9348.06 | F93: =SUMIFS('02_CRONOGRAMA_PV_DIARIO'!E:E, '02_CRONOGRAMA_PV_DIARIO'!A:A, A93, '02_CRONOGRAMA_PV_DIARIO'!C:C, C93) -> 0 | G93: =SUMIFS(F$2:F93, C$2:C93, C93) -> 0 | H93: =SUMIFS('04_LOG_FIELD_ENTRIES'!J:J, '04_LOG_FIELD_ENTRIES'!B:B, B93, '04_LOG_FIELD_ENTRIES'!D:D, C93, '04_LOG_FIELD_ENTRIES'!K:K, "EV_PRODUCCION") -> 0 | I93: =SUMIFS(H$2:H93, C$2:C93, C93) -> 2337.02 | J93: =SUMIFS('04_LOG_FIELD_ENTRIES'!J:J, '04_LOG_FIELD_ENTRIES'!B:B, B93, '04_LOG_FIELD_ENTRIES'!D:D, C93, '04_LOG_FIELD_ENTRIES'!K:K, "AC_*") -> 0 | K93: =SUMIFS(J$2:J93, C$2:C93, C93) -> 1299.2 | L93: =I93-K93 -> 1037.82 | M93: =I93-G93 -> 2337.02 | N93: =IF(G93>0, I93/G93, 1) -> 1 | O93: =IF(K93>0, I93/K93, 1) -> 1.7988147 | P93: =IF(AND(N93>=0.95, O93>=0.95), "SALUDABLE", IF(N93<0.9, "ALERTA RETRASO", "ALERTA SOBRECOSTO")) -> SALUDABLE
A94: 24 | B94: 2026-08-24 | C94: WBS-100 | D94: Obras Preliminares, Trazo y Movilización | E94: =SUM('01_PRESUPUESTO_CRONOGRAMA_BASE'!G2:G3) -> 16336.4 | F94: =SUMIFS('02_CRONOGRAMA_PV_DIARIO'!E:E, '02_CRONOGRAMA_PV_DIARIO'!A:A, A94, '02_CRONOGRAMA_PV_DIARIO'!C:C, C94) -> 0 | G94: =SUMIFS(F$2:F94, C$2:C94, C94) -> 16336.46 | H94: =SUMIFS('04_LOG_FIELD_ENTRIES'!J:J, '04_LOG_FIELD_ENTRIES'!B:B, B94, '04_LOG_FIELD_ENTRIES'!D:D, C94, '04_LOG_FIELD_ENTRIES'!K:K, "EV_PRODUCCION") -> 0 | I94: =SUMIFS(H$2:H94, C$2:C94, C94) -> 5823.2 | J94: =SUMIFS('04_LOG_FIELD_ENTRIES'!J:J, '04_LOG_FIELD_ENTRIES'!B:B, B94, '04_LOG_FIELD_ENTRIES'!D:D, C94, '04_LOG_FIELD_ENTRIES'!K:K, "AC_*") -> 0 | K94: =SUMIFS(J$2:J94, C$2:C94, C94) -> 6331 | L94: =I94-K94 -> -507.8 | M94: =I94-G94 -> -10513.26 | N94: =IF(G94>0, I94/G94, 1) -> 0.35645421 | O94: =IF(K94>0, I94/K94, 1) -> 0.9197915 | P94: =IF(AND(N94>=0.95, O94>=0.95), "SALUDABLE", IF(N94<0.9, "ALERTA RETRASO", "ALERTA SOBRECOSTO")) -> ALERTA RETRASO
A95: 24 | B95: 2026-08-24 | C95: WBS-200 | D95: Red de Alcantarillado, Zanjas y Buzones | E95: =SUM('01_PRESUPUESTO_CRONOGRAMA_BASE'!G4:G9) -> 372046.56 | F95: =SUMIFS('02_CRONOGRAMA_PV_DIARIO'!E:E, '02_CRONOGRAMA_PV_DIARIO'!A:A, A95, '02_CRONOGRAMA_PV_DIARIO'!C:C, C95) -> 17897.81 | G95: =SUMIFS(F$2:F95, C$2:C95, C95) -> 154800.7 | H95: =SUMIFS('04_LOG_FIELD_ENTRIES'!J:J, '04_LOG_FIELD_ENTRIES'!B:B, B95, '04_LOG_FIELD_ENTRIES'!D:D, C95, '04_LOG_FIELD_ENTRIES'!K:K, "EV_PRODUCCION") -> 0 | I95: =SUMIFS(H$2:H95, C$2:C95, C95) -> 44254.52 | J95: =SUMIFS('04_LOG_FIELD_ENTRIES'!J:J, '04_LOG_FIELD_ENTRIES'!B:B, B95, '04_LOG_FIELD_ENTRIES'!D:D, C95, '04_LOG_FIELD_ENTRIES'!K:K, "AC_*") -> 0 | K95: =SUMIFS(J$2:J95, C$2:C95, C95) -> 34269.2 | L95: =I95-K95 -> 9985.32 | M95: =I95-G95 -> -110546.18 | N95: =IF(G95>0, I95/G95, 1) -> 0.28588062 | O95: =IF(K95>0, I95/K95, 1) -> 1.2913788 | P95: =IF(AND(N95>=0.95, O95>=0.95), "SALUDABLE", IF(N95<0.9, "ALERTA RETRASO", "ALERTA SOBRECOSTO")) -> ALERTA RETRASO
A96: 24 | B96: 2026-08-24 | C96: WBS-300 | D96: Red de Agua Potable y Conexiones Domiciliarias | E96: =SUM('01_PRESUPUESTO_CRONOGRAMA_BASE'!G10:G11) -> 57565.2 | F96: =SUMIFS('02_CRONOGRAMA_PV_DIARIO'!E:E, '02_CRONOGRAMA_PV_DIARIO'!A:A, A96, '02_CRONOGRAMA_PV_DIARIO'!C:C, C96) -> 1761.82 | G96: =SUMIFS(F$2:F96, C$2:C96, C96) -> 5285.46 | H96: =SUMIFS('04_LOG_FIELD_ENTRIES'!J:J, '04_LOG_FIELD_ENTRIES'!B:B, B96, '04_LOG_FIELD_ENTRIES'!D:D, C96, '04_LOG_FIELD_ENTRIES'!K:K, "EV_PRODUCCION") -> 0 | I96: =SUMIFS(H$2:H96, C$2:C96, C96) -> 9327.45 | J96: =SUMIFS('04_LOG_FIELD_ENTRIES'!J:J, '04_LOG_FIELD_ENTRIES'!B:B, B96, '04_LOG_FIELD_ENTRIES'!D:D, C96, '04_LOG_FIELD_ENTRIES'!K:K, "AC_*") -> 0 | K96: =SUMIFS(J$2:J96, C$2:C96, C96) -> 7730.8 | L96: =I96-K96 -> 1596.65 | M96: =I96-G96 -> 4041.99 | N96: =IF(G96>0, I96/G96, 1) -> 1.7647376 | O96: =IF(K96>0, I96/K96, 1) -> 1.206531 | P96: =IF(AND(N96>=0.95, O96>=0.95), "SALUDABLE", IF(N96<0.9, "ALERTA RETRASO", "ALERTA SOBRECOSTO")) -> SALUDABLE
A97: 24 | B97: 2026-08-24 | C97: WBS-400 | D97: Pruebas Hidráulicas, Desinfección y Entrega | E97: =SUM('01_PRESUPUESTO_CRONOGRAMA_BASE'!G12:G12) -> 9348.06 | F97: =SUMIFS('02_CRONOGRAMA_PV_DIARIO'!E:E, '02_CRONOGRAMA_PV_DIARIO'!A:A, A97, '02_CRONOGRAMA_PV_DIARIO'!C:C, C97) -> 0 | G97: =SUMIFS(F$2:F97, C$2:C97, C97) -> 0 | H97: =SUMIFS('04_LOG_FIELD_ENTRIES'!J:J, '04_LOG_FIELD_ENTRIES'!B:B, B97, '04_LOG_FIELD_ENTRIES'!D:D, C97, '04_LOG_FIELD_ENTRIES'!K:K, "EV_PRODUCCION") -> 0 | I97: =SUMIFS(H$2:H97, C$2:C97, C97) -> 2337.02 | J97: =SUMIFS('04_LOG_FIELD_ENTRIES'!J:J, '04_LOG_FIELD_ENTRIES'!B:B, B97, '04_LOG_FIELD_ENTRIES'!D:D, C97, '04_LOG_FIELD_ENTRIES'!K:K, "AC_*") -> 0 | K97: =SUMIFS(J$2:J97, C$2:C97, C97) -> 1299.2 | L97: =I97-K97 -> 1037.82 | M97: =I97-G97 -> 2337.02 | N97: =IF(G97>0, I97/G97, 1) -> 1 | O97: =IF(K97>0, I97/K97, 1) -> 1.7988147 | P97: =IF(AND(N97>=0.95, O97>=0.95), "SALUDABLE", IF(N97<0.9, "ALERTA RETRASO", "ALERTA SOBRECOSTO")) -> SALUDABLE
A98: 25 | B98: 2026-08-25 | C98: WBS-100 | D98: Obras Preliminares, Trazo y Movilización | E98: =SUM('01_PRESUPUESTO_CRONOGRAMA_BASE'!G2:G3) -> 16336.4 | F98: =SUMIFS('02_CRONOGRAMA_PV_DIARIO'!E:E, '02_CRONOGRAMA_PV_DIARIO'!A:A, A98, '02_CRONOGRAMA_PV_DIARIO'!C:C, C98) -> 0 | G98: =SUMIFS(F$2:F98, C$2:C98, C98) -> 16336.46 | H98: =SUMIFS('04_LOG_FIELD_ENTRIES'!J:J, '04_LOG_FIELD_ENTRIES'!B:B, B98, '04_LOG_FIELD_ENTRIES'!D:D, C98, '04_LOG_FIELD_ENTRIES'!K:K, "EV_PRODUCCION") -> 0 | I98: =SUMIFS(H$2:H98, C$2:C98, C98) -> 5823.2 | J98: =SUMIFS('04_LOG_FIELD_ENTRIES'!J:J, '04_LOG_FIELD_ENTRIES'!B:B, B98, '04_LOG_FIELD_ENTRIES'!D:D, C98, '04_LOG_FIELD_ENTRIES'!K:K, "AC_*") -> 0 | K98: =SUMIFS(J$2:J98, C$2:C98, C98) -> 6331 | L98: =I98-K98 -> -507.8 | M98: =I98-G98 -> -10513.26 | N98: =IF(G98>0, I98/G98, 1) -> 0.35645421 | O98: =IF(K98>0, I98/K98, 1) -> 0.9197915 | P98: =IF(AND(N98>=0.95, O98>=0.95), "SALUDABLE", IF(N98<0.9, "ALERTA RETRASO", "ALERTA SOBRECOSTO")) -> ALERTA RETRASO
A99: 25 | B99: 2026-08-25 | C99: WBS-200 | D99: Red de Alcantarillado, Zanjas y Buzones | E99: =SUM('01_PRESUPUESTO_CRONOGRAMA_BASE'!G4:G9) -> 372046.56 | F99: =SUMIFS('02_CRONOGRAMA_PV_DIARIO'!E:E, '02_CRONOGRAMA_PV_DIARIO'!A:A, A99, '02_CRONOGRAMA_PV_DIARIO'!C:C, C99) -> 17897.81 | G99: =SUMIFS(F$2:F99, C$2:C99, C99) -> 172698.51 | H99: =SUMIFS('04_LOG_FIELD_ENTRIES'!J:J, '04_LOG_FIELD_ENTRIES'!B:B, B99, '04_LOG_FIELD_ENTRIES'!D:D, C99, '04_LOG_FIELD_ENTRIES'!K:K, "EV_PRODUCCION") -> 0 | I99: =SUMIFS(H$2:H99, C$2:C99, C99) -> 44254.52 | J99: =SUMIFS('04_LOG_FIELD_ENTRIES'!J:J, '04_LOG_FIELD_ENTRIES'!B:B, B99, '04_LOG_FIELD_ENTRIES'!D:D, C99, '04_LOG_FIELD_ENTRIES'!K:K, "AC_*") -> 0 | K99: =SUMIFS(J$2:J99, C$2:C99, C99) -> 34269.2 | L99: =I99-K99 -> 9985.32 | M99: =I99-G99 -> -128443.99 | N99: =IF(G99>0, I99/G99, 1) -> 0.25625305 | O99: =IF(K99>0, I99/K99, 1) -> 1.2913788 | P99: =IF(AND(N99>=0.95, O99>=0.95), "SALUDABLE", IF(N99<0.9, "ALERTA RETRASO", "ALERTA SOBRECOSTO")) -> ALERTA RETRASO
A100: 25 | B100: 2026-08-25 | C100: WBS-300 | D100: Red de Agua Potable y Conexiones Domiciliarias | E100: =SUM('01_PRESUPUESTO_CRONOGRAMA_BASE'!G10:G11) -> 57565.2 | F100: =SUMIFS('02_CRONOGRAMA_PV_DIARIO'!E:E, '02_CRONOGRAMA_PV_DIARIO'!A:A, A100, '02_CRONOGRAMA_PV_DIARIO'!C:C, C100) -> 1761.82 | G100: =SUMIFS(F$2:F100, C$2:C100, C100) -> 7047.28 | H100: =SUMIFS('04_LOG_FIELD_ENTRIES'!J:J, '04_LOG_FIELD_ENTRIES'!B:B, B100, '04_LOG_FIELD_ENTRIES'!D:D, C100, '04_LOG_FIELD_ENTRIES'!K:K, "EV_PRODUCCION") -> 0 | I100: =SUMIFS(H$2:H100, C$2:C100, C100) -> 9327.45 | J100: =SUMIFS('04_LOG_FIELD_ENTRIES'!J:J, '04_LOG_FIELD_ENTRIES'!B:B, B100, '04_LOG_FIELD_ENTRIES'!D:D, C100, '04_LOG_FIELD_ENTRIES'!K:K, "AC_*") -> 0 | K100: =SUMIFS(J$2:J100, C$2:C100, C100) -> 7730.8 | L100: =I100-K100 -> 1596.65 | M100: =I100-G100 -> 2280.17 | N100: =IF(G100>0, I100/G100, 1) -> 1.3235532 | O100: =IF(K100>0, I100/K100, 1) -> 1.206531 | P100: =IF(AND(N100>=0.95, O100>=0.95), "SALUDABLE", IF(N100<0.9, "ALERTA RETRASO", "ALERTA SOBRECOSTO")) -> SALUDABLE
...

Sheet 04_LOG_FIELD_ENTRIES
A1: ID Registro | B1: Fecha | C1: Rol Responsable | D1: Código WBS | E1: Código Recurso/Partida | F1: Descripción / Detalle | G1: Cantidad Campo | H1: Unidad | I1: P.U. (Busca en Maestro) | J1: Subtotal Monto (S/) | K1: Categoría EVM | L1: Origen HTML
A2: LOG-20260801-001 | B2: 2026-08-01 | C2: Tareador (Bildin) | D2: WBS-100 | E2: MO_CAPATAZ | F2: CAPATAZ (1 pers. x 8h) | G2: 8 | H2: hh | I2: =IFERROR(VLOOKUP(E2, '05_MAESTRO_RECURSOS'!A:D, 4, FALSE), IFERROR(VLOOKUP(E2, '06_MAESTRO_PARTIDAS_EV'!B:F, 5, FALSE), 0)) -> 32.5 | J2: =ROUND(G2 * I2, 2) -> 260 | K2: AC_MO | L2: tareador.html
A3: LOG-20260801-002 | B3: 2026-08-01 | C3: Tareador (Bildin) | D3: WBS-100 | E3: MO_OPERARIO | F3: OPERARIO (2 pers. x 8h) | G3: 16 | H3: hh | I3: =IFERROR(VLOOKUP(E3, '05_MAESTRO_RECURSOS'!A:D, 4, FALSE), IFERROR(VLOOKUP(E3, '06_MAESTRO_PARTIDAS_EV'!B:F, 5, FALSE), 0)) -> 26.8 | J3: =ROUND(G3 * I3, 2) -> 428.8 | K3: AC_MO | L3: tareador.html
A4: LOG-20260801-003 | B4: 2026-08-01 | C4: Tareador (Bildin) | D4: WBS-100 | E4: MO_PEON | F4: PEON (4 pers. x 8h) | G4: 32 | H4: hh | I4: =IFERROR(VLOOKUP(E4, '05_MAESTRO_RECURSOS'!A:D, 4, FALSE), IFERROR(VLOOKUP(E4, '06_MAESTRO_PARTIDAS_EV'!B:F, 5, FALSE), 0)) -> 20.1 | J4: =ROUND(G4 * I4, 2) -> 643.2 | K4: AC_MO | L4: tareador.html
A5: LOG-20260801-004 | B5: 2026-08-01 | C5: Almacenero | D5: WBS-100 | E5: MAT_ESTACA | F5: ESTACAS Y MADERA PARA TRAZO | G5: 150 | H5: pza | I5: =IFERROR(VLOOKUP(E5, '05_MAESTRO_RECURSOS'!A:D, 4, FALSE), IFERROR(VLOOKUP(E5, '06_MAESTRO_PARTIDAS_EV'!B:F, 5, FALSE), 0)) -> 4.5 | J5: =ROUND(G5 * I5, 2) -> 675 | K5: AC_MAT | L5: almacenero.html
A6: LOG-20260801-005 | B6: 2026-08-01 | C6: Almacenero | D6: WBS-100 | E6: MAT_PINTURA | F6: PINTURA SPRAY MARCADOR ZANJA | G6: 10 | H6: gla | I6: =IFERROR(VLOOKUP(E6, '05_MAESTRO_RECURSOS'!A:D, 4, FALSE), IFERROR(VLOOKUP(E6, '06_MAESTRO_PARTIDAS_EV'!B:F, 5, FALSE), 0)) -> 18 | J6: =ROUND(G6 * I6, 2) -> 180 | K6: AC_MAT | L6: almacenero.html
A7: LOG-20260801-006 | B7: 2026-08-01 | C7: Administradora | D7: WBS-100 | E7: SUB_MOVILIZACION | F7: MOVILIZACION DE MAQUINARIA | G7: 1 | H7: glb | I7: =IFERROR(VLOOKUP(E7, '05_MAESTRO_RECURSOS'!A:D, 4, FALSE), IFERROR(VLOOKUP(E7, '06_MAESTRO_PARTIDAS_EV'!B:F, 5, FALSE), 0)) -> 4000 | J7: =ROUND(G7 * I7, 2) -> 4000 | K7: AC_SUB | L7: administradora.html
A8: LOG-20260801-007 | B8: 2026-08-01 | C8: Administradora | D8: WBS-100 | E8: EQ_ESTACION_TOTAL | F8: ESTACION TOTAL TOPOGRAFICA | G8: 8 | H8: hm | I8: =IFERROR(VLOOKUP(E8, '05_MAESTRO_RECURSOS'!A:D, 4, FALSE), IFERROR(VLOOKUP(E8, '06_MAESTRO_PARTIDAS_EV'!B:F, 5, FALSE), 0)) -> 18 | J8: =ROUND(G8 * I8, 2) -> 144 | K8: AC_EQP | L8: administradora.html
A9: LOG-20260801-008 | B9: 2026-08-01 | C9: Ing. de Campo | D9: WBS-100 | E9: 01.01 | F9: OBRAS PRELIMINARES Y PROVISIONALES (50%) | G9: 0.5 | H9: GLB | I9: =IFERROR(VLOOKUP(E9, '05_MAESTRO_RECURSOS'!A:D, 4, FALSE), IFERROR(VLOOKUP(E9, '06_MAESTRO_PARTIDAS_EV'!B:F, 5, FALSE), 0)) -> 8296.4 | J9: =ROUND(G9 * I9, 2) -> 4148.2 | K9: EV_PRODUCCION | L9: ing_campo.html
A10: LOG-20260801-009 | B10: 2026-08-01 | C10: Ing. de Campo | D10: WBS-100 | E10: 01.02.01 | F10: TRAZO Y REPLANTEO INICIAL TRAMO T-1 | G10: 500 | H10: M | I10: =IFERROR(VLOOKUP(E10, '05_MAESTRO_RECURSOS'!A:D, 4, FALSE), IFERROR(VLOOKUP(E10, '06_MAESTRO_PARTIDAS_EV'!B:F, 5, FALSE), 0)) -> 3.35 | J10: =ROUND(G10 * I10, 2) -> 1675 | K10: EV_PRODUCCION | L10: ing_campo.html
A11: LOG-20260802-010 | B11: 2026-08-02 | C11: Tareador (Bildin) | D11: WBS-200 | E11: MO_CAPATAZ | F11: CAPATAZ CONTROL ZANJA | G11: 8 | H11: hh | I11: =IFERROR(VLOOKUP(E11, '05_MAESTRO_RECURSOS'!A:D, 4, FALSE), IFERROR(VLOOKUP(E11, '06_MAESTRO_PARTIDAS_EV'!B:F, 5, FALSE), 0)) -> 32.5 | J11: =ROUND(G11 * I11, 2) -> 260 | K11: AC_MO | L11: tareador.html
A12: LOG-20260802-011 | B12: 2026-08-02 | C12: Tareador (Bildin) | D12: WBS-200 | E12: MO_OPERARIO | F12: OPERARIO ENTIBADO Y CAMA | G12: 24 | H12: hh | I12: =IFERROR(VLOOKUP(E12, '05_MAESTRO_RECURSOS'!A:D, 4, FALSE), IFERROR(VLOOKUP(E12, '06_MAESTRO_PARTIDAS_EV'!B:F, 5, FALSE), 0)) -> 26.8 | J12: =ROUND(G12 * I12, 2) -> 643.2 | K12: AC_MO | L12: tareador.html
A13: LOG-20260802-012 | B13: 2026-08-02 | C13: Tareador (Bildin) | D13: WBS-200 | E13: MO_PEON | F13: PEON REPELE Y CAMA | G13: 48 | H13: hh | I13: =IFERROR(VLOOKUP(E13, '05_MAESTRO_RECURSOS'!A:D, 4, FALSE), IFERROR(VLOOKUP(E13, '06_MAESTRO_PARTIDAS_EV'!B:F, 5, FALSE), 0)) -> 20.1 | J13: =ROUND(G13 * I13, 2) -> 964.8 | K13: AC_MO | L13: tareador.html
... A47: LOG-20260805-046 | B47: 2026-08-05 | C47: Ing. de Campo | D47: WBS-400 | E47: 01.04.01 | F47: PRUEBA HIDRAULICA TRAMO 1 REDES (25%) | G47: 0.25 | H47: GLB | I47: =IFERROR(VLOOKUP(E47, '05_MAESTRO_RECURSOS'!A:D, 4, FALSE), IFERROR(VLOOKUP(E47, '06_MAESTRO_PARTIDAS_EV'!B:F, 5, FALSE), 0)) -> 9348.06 | J47: =ROUND(G47 * I47, 2) -> 2337.02 | K47: EV_PRODUCCION | L47: ing_campo.html

Sheet 05_MAESTRO_RECURSOS
A1: Código Recurso | B1: Descripción del Recurso / Insumo | C1: Unidad | D1: P.U. Meta Oficial (S/) | E1: Categoría EVM
A2: MO_CAPATAZ | B2: CAPATAZ | C2: hh | D2: 32.5 | E2: AC_MO
A3: MO_OPERARIO | B3: OPERARIO | C3: hh | D3: 26.8 | E3: AC_MO
A4: MO_OFICIAL | B4: OFICIAL | C4: hh | D4: 22.4 | E4: AC_MO
A5: MO_PEON | B5: PEON | C5: hh | D5: 20.1 | E5: AC_MO
A6: MAT_ESTACA | B6: ESTACAS Y MADERA PARA TRAZO | C6: pza | D6: 4.5 | E6: AC_MAT
A7: MAT_PINTURA | B7: PINTURA SPRAY MARCADOR DE ZANJA | C7: gla | D7: 18 | E7: AC_MAT
A8: MAT_CORDEL | B8: CORDEL / NYLON | C8: m | D8: 0.8 | E8: AC_MAT
A9: MAT_ARENA_CAMAS | B9: ARENA FINA SELECCIONADA PARA CAMA E=0.10M | C9: m3 | D9: 45 | E9: AC_MAT
A10: MAT_TUB_PVC_200 | B10: TUBERIA PVC UF DN 200MM SERIE S-20 ALCANTARILLADO | C10: m | D10: 42 | E10: AC_MAT
A11: MAT_LUBRICANTE | B11: LUBRICANTE PARA TUBERIA CON ESPIGA Y CAMPANA | C11: kg | D11: 24 | E11: AC_MAT
A12: MAT_MATERIAL_PR | B12: MATERIAL DE PRÉSTAMO AFIRMADO PARA RELLENO COMPACTADO | C12: m3 | D12: 38 | E12: AC_MAT
A13: MAT_AGUA | B13: AGUA PARA COMPACTACIÓN Y PRUEBAS | C13: m3 | D13: 12 | E13: AC_MAT
... A33: SUB_MONTAJE_BUZON | B33: SUBCONTRATO SERVICIO ASENTADO Y ANCLAJE BUZONES PREFABRICADOS | C33: und | D33: 250 | E33: AC_SUB

Sheet 06_MAESTRO_PARTIDAS_EV
A1: Item Partida | B1: Código Partida | C1: Descripción de la Partida Presupuestal | D1: Unidad | E1: Metrado Presupuesto Meta | F1: P.U. Directo Meta (S/) | G1: Presupuesto Parcial Meta (S/) | H1: Metrado Ejecutado Acumulado (Formulado del Campo) | I1: % Avance Físico Partida | J1: Valor Ganado EV Acumulado (S/) | K1: Saldo Metrado por Ejecutar | L1: Saldo Valor por Ejecutar (S/)
A2: 01.01 | B2: 01.01 | C2: Obras Preliminares y Trabajos Provisionales | D2: GLB | E2: 1 | F2: 8296.4 | G2: =ROUND(E2*F2, 2) -> 8296.4 | H2: =SUMIFS('04_LOG_FIELD_ENTRIES'!G:G, '04_LOG_FIELD_ENTRIES'!E:E, B2, '04_LOG_FIELD_ENTRIES'!K:K, "EV_PRODUCCION") -> 0.5 | I2: =IF(E2>0, H2/E2, 0) -> 0.5 | J2: =ROUND(H2*F2, 2) -> 4148.2 | K2: =E2-H2 -> 0.5 | L2: =G2-J2 -> 4148.2
A3: 01.02.01 | B3: 01.02.01 | C3: Trazo, Nivelación y Replanteo de Zanjas | D3: M | E3: 2400 | F3: 3.35 | G3: =ROUND(E3*F3, 2) -> 8040 | H3: =SUMIFS('04_LOG_FIELD_ENTRIES'!G:G, '04_LOG_FIELD_ENTRIES'!E:E, B3, '04_LOG_FIELD_ENTRIES'!K:K, "EV_PRODUCCION") -> 500 | I3: =IF(E3>0, H3/E3, 0) -> 0.20833333 | J3: =ROUND(H3*F3, 2) -> 1675 | K3: =E3-H3 -> 1900 | L3: =G3-J3 -> 6365
A4: 01.02.02 | B4: 01.02.02 | C4: Excavación de Zanja H=1.50m - 2.20m a Máquina (Terreno Normal) | D4: M3 | E4: 3840 | F4: 11.66 | G4: =ROUND(E4*F4, 2) -> 44774.4 | H4: =SUMIFS('04_LOG_FIELD_ENTRIES'!G:G, '04_LOG_FIELD_ENTRIES'!E:E, B4, '04_LOG_FIELD_ENTRIES'!K:K, "EV_PRODUCCION") -> 450 | I4: =IF(E4>0, H4/E4, 0) -> 0.1171875 | J4: =ROUND(H4*F4, 2) -> 5247 | K4: =E4-H4 -> 3390 | L4: =G4-J4 -> 39527.4
A5: 01.02.03 | B5: 01.02.03 | C5: Preparación y Colocación de Cama de Arena e=0.10m | D5: M | E5: 2400 | F5: 11.12 | G5: =ROUND(E5*F5, 2) -> 26688 | H5: =SUMIFS('04_LOG_FIELD_ENTRIES'!G:G, '04_LOG_FIELD_ENTRIES'!E:E, B5, '04_LOG_FIELD_ENTRIES'!K:K, "EV_PRODUCCION") -> 300 | I5: =IF(E5>0, H5/E5, 0) -> 0.125 | J5: =ROUND(H5*F5, 2) -> 3336 | K5: =E5-H5 -> 2100 | L5: =G5-J5 -> 23352
A6: 01.02.04 | B6: 01.02.04 | C6: Suministro e Instalación de Tubería PVC UF DN 200mm Serie S-20 para Alcantarillado | D6: M | E6: 1400 | F6: 55.51 | G6: =ROUND(E6*F6, 2) -> 77714 | H6: =SUMIFS('04_LOG_FIELD_ENTRIES'!G:G, '04_LOG_FIELD_ENTRIES'!E:E, B6, '04_LOG_FIELD_ENTRIES'!K:K, "EV_PRODUCCION") -> 250 | I6: =IF(E6>0, H6/E6, 0) -> 0.17857143 | J6: =ROUND(H6*F6, 2) -> 13877.5 | K6: =E6-H6 -> 1150 | L6: =G6-J6 -> 63836.5
A7: 01.02.05 | B7: 01.02.05 | C7: Relleno Compactado de Zanja en Capas de 0.20m con Maquinaria/Plancha | D7: M3 | E7: 3300 | F7: 28.54 | G7: =ROUND(E7*F7, 2) -> 94182 | H7: =SUMIFS('04_LOG_FIELD_ENTRIES'!G:G, '04_LOG_FIELD_ENTRIES'!E:E, B7, '04_LOG_FIELD_ENTRIES'!K:K, "EV_PRODUCCION") -> 200 | I7: =IF(E7>0, H7/E7, 0) -> 0.060606061 | J7: =ROUND(H7*F7, 2) -> 5708 | K7: =E7-H7 -> 3100 | L7: =G7-J7 -> 88474
A8: 01.02.06 | B8: 01.02.06 | C8: Construcción de Buzones Prefabricados de Concreto h=1.50m - 2.50m (Inc. Marco y Tapa) | D8: UND | E8: 32 | F8: 2500.73 | G8: =ROUND(E8*F8, 2) -> 80023.36 | H8: =SUMIFS('04_LOG_FIELD_ENTRIES'!G:G, '04_LOG_FIELD_ENTRIES'!E:E, B8, '04_LOG_FIELD_ENTRIES'!K:K, "EV_PRODUCCION") -> 4 | I8: =IF(E8>0, H8/E8, 0) -> 0.125 | J8: =ROUND(H8*F8, 2) -> 10002.92 | K8: =E8-H8 -> 28 | L8: =G8-J8 -> 70020.44
A9: 01.02.07 | B9: 01.02.07 | C9: Conexiones Domiciliarias de Alcantarillado (Caja de Registro + Acometida) | D9: UND | E9: 120 | F9: 405.54 | G9: =ROUND(E9*F9, 2) -> 48664.8 | H9: =SUMIFS('04_LOG_FIELD_ENTRIES'!G:G, '04_LOG_FIELD_ENTRIES'!E:E, B9, '04_LOG_FIELD_ENTRIES'!K:K, "EV_PRODUCCION") -> 15 | I9: =IF(E9>0, H9/E9, 0) -> 0.125 | J9: =ROUND(H9*F9, 2) -> 6083.1 | K9: =E9-H9 -> 105 | L9: =G9-J9 -> 42581.7
A10: 01.03.01 | B10: 01.03.01 | C10: Suministro e Instalación de Tubería PVC C-10 DN 110mm para Agua Potable | D10: M | E10: 1000 | F10: 38.76 | G10: =ROUND(E10*F10, 2) -> 38760 | H10: =SUMIFS('04_LOG_FIELD_ENTRIES'!G:G, '04_LOG_FIELD_ENTRIES'!E:E, B10, '04_LOG_FIELD_ENTRIES'!K:K, "EV_PRODUCCION") -> 180 | I10: =IF(E10>0, H10/E10, 0) -> 0.18 | J10: =ROUND(H10*F10, 2) -> 6976.8 | K10: =E10-H10 -> 820 | L10: =G10-J10 -> 31783.2
A11: 01.03.02 | B11: 01.03.02 | C11: Conexiones Domiciliarias de Agua Potable (Caja de Agua + Abrazadera + Acometida) | D11: UND | E11: 120 | F11: 156.71 | G11: =ROUND(E11*F11, 2) -> 18805.2 | H11: =SUMIFS('04_LOG_FIELD_ENTRIES'!G:G, '04_LOG_FIELD_ENTRIES'!E:E, B11, '04_LOG_FIELD_ENTRIES'!K:K, "EV_PRODUCCION") -> 15 | I11: =IF(E11>0, H11/E11, 0) -> 0.125 | J11: =ROUND(H11*F11, 2) -> 2350.65 | K11: =E11-H11 -> 105 | L11: =G11-J11 -> 16454.55
A12: 01.04.01 | B12: 01.04.01 | C12: Pruebas Hidráulicas de Redes de Agua y Alcantarillado + Desinfección | D12: GLB | E12: 1 | F12: 9348.06 | G12: =ROUND(E12*F12, 2) -> 9348.06 | H12: =SUMIFS('04_LOG_FIELD_ENTRIES'!G:G, '04_LOG_FIELD_ENTRIES'!E:E, B12, '04_LOG_FIELD_ENTRIES'!K:K, "EV_PRODUCCION") -> 0.25 | I12: =IF(E12>0, H12/E12, 0) -> 0.25 | J12: =ROUND(H12*F12, 2) -> 2337.02 | K12: =E12-H12 -> 0.75 | L12: =G12-J12 -> 7011.04
A13: TOTAL OBRA | C13: Consolidado Partidas | G13: =SUM(G2:G12) -> 455296.22 | I13: =IF(G13>0, J13/G13, 0) -> 0.13560884 | J13: =SUM(J2:J12) -> 61742.19 | L13: =SUM(L2:L12) -> 393554.03
