Workbook

Sheet 01_DASHBOARD_KPI
A1: PANEL CENTRAL DE CONTROL DE RESULTADO OPERATIVO (RO) Y EVM - 5 DÍAS DE OBRA
A3: Habilitación Urbana Los Cedros | Redes Sanitarias | Base de Datos Viva Google Sheets / Excel
A5: Presupuesto Meta (BAC) | B5: Planificado a la Fecha (PV) | C5: Valor Ganado Exec (EV) | D5: Costo Real Incurrido (AC) | E5: Variación Costo (CV = EV-AC) | F5: Índice Costo (CPI) | G5: Índice Plazo (SPI) | H5: Proyección Cierre (EAC) | I5: Desvío Meta (EAC - BAC)
A6: =SUM('04_CATALOGO_WBS'!C4:C7) | B6: =SUM('04_CATALOGO_WBS'!D4:D7) | C6: =SUMIFS('02_REGISTROS_DIARIOS'!J:J, '02_REGISTROS_DIARIOS'!K:K, "EV_PRODUCCION") | D6: =SUMIFS('02_REGISTROS_DIARIOS'!J:J, '02_REGISTROS_DIARIOS'!K:K, "AC_*") | E6: =C6-D6 | F6: =IF(D6>0, C6/D6, 1) | G6: =IF(B6>0, C6/B6, 1) | H6: =IF(F6>0, A6/F6, A6) | I6: =H6-A6
A10: DESGLOSE DE COSTO REAL INCURRIDO ($AC$) POR COMPONENTE Y ROL DE CAMPO
A11: Componente Costo | B11: Rol Responsables | C11: Tipo EVM | D11: Fórmula Sumatoria Viva | E11: Monto Incurrido (PEN) | F11: % Incidencia AC
A12: Mano de Obra ($HH$) | B12: Tareador (Bildin) | C12: AC_MO | D12: =SUMIFS('02_REGISTROS_DIARIOS'!J:J, '02_REGISTROS_DIARIOS'!K:K, "AC_MO") | E12: =D12 | F12: =E12/E$16
A13: Materiales de Almacén | B13: Almacenero | C13: AC_MAT | D13: =SUMIFS('02_REGISTROS_DIARIOS'!J:J, '02_REGISTROS_DIARIOS'!K:K, "AC_MAT") | E13: =D13 | F13: =E13/E$16
A14: Equipos y Horas Máquina | B14: Administradora | C14: AC_EQP | D14: =SUMIFS('02_REGISTROS_DIARIOS'!J:J, '02_REGISTROS_DIARIOS'!K:K, "AC_EQP") | E14: =D14 | F14: =E14/E$16
A15: Subcontratos y Ensayos | B15: Administradora | C15: AC_SUB | D15: =SUMIFS('02_REGISTROS_DIARIOS'!J:J, '02_REGISTROS_DIARIOS'!K:K, "AC_SUB") | E15: =D15 | F15: =E15/E$16
A16: TOTAL COSTO REAL INCURRIDO (AC) | E16: =SUM(E12:E15) | F16: =SUM(F12:F15)
A18: HISTÓRICO Y EVOLUCIÓN DIARIA DE AVANCE (DÍA 1 AL DÍA 5)
A19: Fecha | B19: Costo MO (S/) | C19: Costo Mat (S/) | D19: Costo Eqp/Sub (S/) | E19: Total Costo Real ($AC$) | F19: Valor Ganado ($EV$) | G19: Diferencia Diaria ($EV-AC$) | H19: CPI Diario
A20: 2026-08-01 | B20: =SUMIFS('02_REGISTROS_DIARIOS'!J:J, '02_REGISTROS_DIARIOS'!B:B, A20, '02_REGISTROS_DIARIOS'!K:K, "AC_MO") | C20: =SUMIFS('02_REGISTROS_DIARIOS'!J:J, '02_REGISTROS_DIARIOS'!B:B, A20, '02_REGISTROS_DIARIOS'!K:K, "AC_MAT") | D20: =SUMIFS('02_REGISTROS_DIARIOS'!J:J, '02_REGISTROS_DIARIOS'!B:B, A20, '02_REGISTROS_DIARIOS'!K:K, "AC_EQP") + SUMIFS('02_REGISTROS_DIARIOS'!J:J, '02_REGISTROS_DIARIOS'!B:B, A20, '02_REGISTROS_DIARIOS'!K:K, "AC_SUB") | E20: =SUM(B20:D20) | F20: =SUMIFS('02_REGISTROS_DIARIOS'!J:J, '02_REGISTROS_DIARIOS'!B:B, A20, '02_REGISTROS_DIARIOS'!K:K, "EV_PRODUCCION") | G20: =F20-E20 | H20: =IF(E20>0, F20/E20, 1)
A21: 2026-08-02 | B21: =SUMIFS('02_REGISTROS_DIARIOS'!J:J, '02_REGISTROS_DIARIOS'!B:B, A21, '02_REGISTROS_DIARIOS'!K:K, "AC_MO") | C21: =SUMIFS('02_REGISTROS_DIARIOS'!J:J, '02_REGISTROS_DIARIOS'!B:B, A21, '02_REGISTROS_DIARIOS'!K:K, "AC_MAT") | D21: =SUMIFS('02_REGISTROS_DIARIOS'!J:J, '02_REGISTROS_DIARIOS'!B:B, A21, '02_REGISTROS_DIARIOS'!K:K, "AC_EQP") + SUMIFS('02_REGISTROS_DIARIOS'!J:J, '02_REGISTROS_DIARIOS'!B:B, A21, '02_REGISTROS_DIARIOS'!K:K, "AC_SUB") | E21: =SUM(B21:D21) | F21: =SUMIFS('02_REGISTROS_DIARIOS'!J:J, '02_REGISTROS_DIARIOS'!B:B, A21, '02_REGISTROS_DIARIOS'!K:K, "EV_PRODUCCION") | G21: =F21-E21 | H21: =IF(E21>0, F21/E21, 1)
A22: 2026-08-03 | B22: =SUMIFS('02_REGISTROS_DIARIOS'!J:J, '02_REGISTROS_DIARIOS'!B:B, A22, '02_REGISTROS_DIARIOS'!K:K, "AC_MO") | C22: =SUMIFS('02_REGISTROS_DIARIOS'!J:J, '02_REGISTROS_DIARIOS'!B:B, A22, '02_REGISTROS_DIARIOS'!K:K, "AC_MAT") | D22: =SUMIFS('02_REGISTROS_DIARIOS'!J:J, '02_REGISTROS_DIARIOS'!B:B, A22, '02_REGISTROS_DIARIOS'!K:K, "AC_EQP") + SUMIFS('02_REGISTROS_DIARIOS'!J:J, '02_REGISTROS_DIARIOS'!B:B, A22, '02_REGISTROS_DIARIOS'!K:K, "AC_SUB") | E22: =SUM(B22:D22) | F22: =SUMIFS('02_REGISTROS_DIARIOS'!J:J, '02_REGISTROS_DIARIOS'!B:B, A22, '02_REGISTROS_DIARIOS'!K:K, "EV_PRODUCCION") | G22: =F22-E22 | H22: =IF(E22>0, F22/E22, 1)
A23: 2026-08-04 | B23: =SUMIFS('02_REGISTROS_DIARIOS'!J:J, '02_REGISTROS_DIARIOS'!B:B, A23, '02_REGISTROS_DIARIOS'!K:K, "AC_MO") | C23: =SUMIFS('02_REGISTROS_DIARIOS'!J:J, '02_REGISTROS_DIARIOS'!B:B, A23, '02_REGISTROS_DIARIOS'!K:K, "AC_MAT") | D23: =SUMIFS('02_REGISTROS_DIARIOS'!J:J, '02_REGISTROS_DIARIOS'!B:B, A23, '02_REGISTROS_DIARIOS'!K:K, "AC_EQP") + SUMIFS('02_REGISTROS_DIARIOS'!J:J, '02_REGISTROS_DIARIOS'!B:B, A23, '02_REGISTROS_DIARIOS'!K:K, "AC_SUB") | E23: =SUM(B23:D23) | F23: =SUMIFS('02_REGISTROS_DIARIOS'!J:J, '02_REGISTROS_DIARIOS'!B:B, A23, '02_REGISTROS_DIARIOS'!K:K, "EV_PRODUCCION") | G23: =F23-E23 | H23: =IF(E23>0, F23/E23, 1)
A24: 2026-08-05 | B24: =SUMIFS('02_REGISTROS_DIARIOS'!J:J, '02_REGISTROS_DIARIOS'!B:B, A24, '02_REGISTROS_DIARIOS'!K:K, "AC_MO") | C24: =SUMIFS('02_REGISTROS_DIARIOS'!J:J, '02_REGISTROS_DIARIOS'!B:B, A24, '02_REGISTROS_DIARIOS'!K:K, "AC_MAT") | D24: =SUMIFS('02_REGISTROS_DIARIOS'!J:J, '02_REGISTROS_DIARIOS'!B:B, A24, '02_REGISTROS_DIARIOS'!K:K, "AC_EQP") + SUMIFS('02_REGISTROS_DIARIOS'!J:J, '02_REGISTROS_DIARIOS'!B:B, A24, '02_REGISTROS_DIARIOS'!K:K, "AC_SUB") | E24: =SUM(B24:D24) | F24: =SUMIFS('02_REGISTROS_DIARIOS'!J:J, '02_REGISTROS_DIARIOS'!B:B, A24, '02_REGISTROS_DIARIOS'!K:K, "EV_PRODUCCION") | G24: =F24-E24 | H24: =IF(E24>0, F24/E24, 1)
A25: TOTAL ACUMULADO OBRA | B25: =SUM(B20:B24) | C25: =SUM(C20:C24) | D25: =SUM(D20:D24) | E25: =SUM(E20:E24) | F25: =SUM(F20:F24) | G25: =SUM(G20:G24) | H25: =IF(E25>0, F25/E25, 1)

Sheet 02_REGISTROS_DIARIOS
A1: ID Registro | B1: Fecha | C1: Rol Responsable | D1: Código WBS | E1: Código Recurso/Partida | F1: Descripción / Detalle | G1: Cantidad | H1: Unidad | I1: P.U. Meta (S/) | J1: Costo Total (S/) | K1: Categoría EVM | L1: Origen HTML | M1: Estado Validado
A2: LOG-20260801-001 | B2: 2026-08-01 | C2: Tareador (Bildin) | D2: WBS-100 | E2: MO_CAPATAZ | F2: CAPATAZ (1 pers. x 8h) | G2: 8 | H2: hh | I2: 32.5 | J2: =ROUND(G2*I2, 2) | K2: AC_MO | L2: tareador.html | M2: VALIDO
A3: LOG-20260801-002 | B3: 2026-08-01 | C3: Tareador (Bildin) | D3: WBS-100 | E3: MO_OPERARIO | F3: OPERARIO (2 pers. x 8h) | G3: 16 | H3: hh | I3: 26.8 | J3: =ROUND(G3*I3, 2) | K3: AC_MO | L3: tareador.html | M3: VALIDO
A4: LOG-20260801-003 | B4: 2026-08-01 | C4: Tareador (Bildin) | D4: WBS-100 | E4: MO_PEON | F4: PEON (4 pers. x 8h) | G4: 32 | H4: hh | I4: 20.1 | J4: =ROUND(G4*I4, 2) | K4: AC_MO | L4: tareador.html | M4: VALIDO
A5: LOG-20260801-004 | B5: 2026-08-01 | C5: Almacenero | D5: WBS-100 | E5: MAT_ESTACA | F5: ESTACAS Y MADERA PARA TRAZO EN AV. LOS CEDROS | G5: 150 | H5: pza | I5: 4.5 | J5: =ROUND(G5*I5, 2) | K5: AC_MAT | L5: almacenero.html | M5: VALIDO
A6: LOG-20260801-005 | B6: 2026-08-01 | C6: Almacenero | D6: WBS-100 | E6: MAT_PINTURA | F6: PINTURA SPRAY MARCADOR ZANJA | G6: 10 | H6: gla | I6: 18 | J6: =ROUND(G6*I6, 2) | K6: AC_MAT | L6: almacenero.html | M6: VALIDO
A7: LOG-20260801-006 | B7: 2026-08-01 | C7: Administradora | D7: WBS-100 | E7: SUB_MOVILIZACION | F7: MOVILIZACION DE MAQUINARIA A OBRA | G7: 1 | H7: glb | I7: 4000 | J7: =ROUND(G7*I7, 2) | K7: AC_SUB | L7: administradora.html | M7: VALIDO
A8: LOG-20260801-007 | B8: 2026-08-01 | C8: Administradora | D8: WBS-100 | E8: EQ_ESTACION_TOTAL | F8: ESTACION TOTAL TOPOGRAFICA | G8: 8 | H8: hm | I8: 18 | J8: =ROUND(G8*I8, 2) | K8: AC_EQP | L8: administradora.html | M8: VALIDO
A9: LOG-20260801-008 | B9: 2026-08-01 | C9: Ing. de Campo | D9: WBS-100 | E9: 01.01 | F9: OBRAS PRELIMINARES Y TRABAJOS PROVISIONALES (50%) | G9: 0.5 | H9: GLB | I9: 8296.4 | J9: =ROUND(G9*I9, 2) | K9: EV_PRODUCCION | L9: ing_campo.html | M9: VALIDO
A10: LOG-20260801-009 | B10: 2026-08-01 | C10: Ing. de Campo | D10: WBS-100 | E10: 01.02.01 | F10: TRAZO Y REPLANTEO INICIAL TRAMO T-1 | G10: 500 | H10: M | I10: 3.35 | J10: =ROUND(G10*I10, 2) | K10: EV_PRODUCCION | L10: ing_campo.html | M10: VALIDO
A11: LOG-20260802-010 | B11: 2026-08-02 | C11: Tareador (Bildin) | D11: WBS-200 | E11: MO_CAPATAZ | F11: CAPATAZ CONTROL ZANJA | G11: 8 | H11: hh | I11: 32.5 | J11: =ROUND(G11*I11, 2) | K11: AC_MO | L11: tareador.html | M11: VALIDO
A12: LOG-20260802-011 | B12: 2026-08-02 | C12: Tareador (Bildin) | D12: WBS-200 | E12: MO_OPERARIO | F12: OPERARIO ENTIBADO Y CAMA | G12: 24 | H12: hh | I12: 26.8 | J12: =ROUND(G12*I12, 2) | K12: AC_MO | L12: tareador.html | M12: VALIDO
A13: LOG-20260802-012 | B13: 2026-08-02 | C13: Tareador (Bildin) | D13: WBS-200 | E13: MO_PEON | F13: PEON REPELE Y CAMA (6 pers. x 8h) | G13: 48 | H13: hh | I13: 20.1 | J13: =ROUND(G13*I13, 2) | K13: AC_MO | L13: tareador.html | M13: VALIDO
... A47: LOG-20260805-046 | B47: 2026-08-05 | C47: Ing. de Campo | D47: WBS-400 | E47: 01.04.01 | F47: PRUEBA HIDRAULICA TRAMO 1 ALCANTARILLADO Y AGUA (25%) | G47: 0.25 | H47: GLB | I47: 9348.06 | J47: =ROUND(G47*I47, 2) | K47: EV_PRODUCCION | L47: ing_campo.html | M47: VALIDO

Sheet 03_EVM_POR_WBS
A1: Código WBS | B1: Descripción Frente WBS | C1: Presupuesto BAC Meta (S/) | D1: Planificado PV (S/) | E1: Costo MO (S/) | F1: Costo Mat (S/) | G1: Costo Eqp/Sub (S/) | H1: Total Costo Real AC (S/) | I1: Valor Ganado EV (S/) | J1: Diferencia (EV - AC) | K1: CPI (Costo) | L1: SPI (Plazo) | M1: EAC Proyectado (S/)
A2: WBS-100 | B2: Obras Preliminares, Trazo y Movilización | C2: ='04_CATALOGO_WBS'!C4 | D2: ='04_CATALOGO_WBS'!D4 | E2: =SUMIFS('02_REGISTROS_DIARIOS'!J:J, '02_REGISTROS_DIARIOS'!D:D, A2, '02_REGISTROS_DIARIOS'!K:K, "AC_MO") | F2: =SUMIFS('02_REGISTROS_DIARIOS'!J:J, '02_REGISTROS_DIARIOS'!D:D, A2, '02_REGISTROS_DIARIOS'!K:K, "AC_MAT") | G2: =SUMIFS('02_REGISTROS_DIARIOS'!J:J, '02_REGISTROS_DIARIOS'!D:D, A2, '02_REGISTROS_DIARIOS'!K:K, "AC_EQP") + SUMIFS('02_REGISTROS_DIARIOS'!J:J, '02_REGISTROS_DIARIOS'!D:D, A2, '02_REGISTROS_DIARIOS'!K:K, "AC_SUB") | H2: =SUM(E2:G2) | I2: =SUMIFS('02_REGISTROS_DIARIOS'!J:J, '02_REGISTROS_DIARIOS'!D:D, A2, '02_REGISTROS_DIARIOS'!K:K, "EV_PRODUCCION") | J2: =I2-H2 | K2: =IF(H2>0, I2/H2, 1) | L2: =IF(D2>0, I2/D2, 1) | M2: =IF(K2>0, C2/K2, C2)
A3: WBS-200 | B3: Red de Alcantarillado, Zanjas y Buzones | C3: ='04_CATALOGO_WBS'!C5 | D3: ='04_CATALOGO_WBS'!D5 | E3: =SUMIFS('02_REGISTROS_DIARIOS'!J:J, '02_REGISTROS_DIARIOS'!D:D, A3, '02_REGISTROS_DIARIOS'!K:K, "AC_MO") | F3: =SUMIFS('02_REGISTROS_DIARIOS'!J:J, '02_REGISTROS_DIARIOS'!D:D, A3, '02_REGISTROS_DIARIOS'!K:K, "AC_MAT") | G3: =SUMIFS('02_REGISTROS_DIARIOS'!J:J, '02_REGISTROS_DIARIOS'!D:D, A3, '02_REGISTROS_DIARIOS'!K:K, "AC_EQP") + SUMIFS('02_REGISTROS_DIARIOS'!J:J, '02_REGISTROS_DIARIOS'!D:D, A3, '02_REGISTROS_DIARIOS'!K:K, "AC_SUB") | H3: =SUM(E3:G3) | I3: =SUMIFS('02_REGISTROS_DIARIOS'!J:J, '02_REGISTROS_DIARIOS'!D:D, A3, '02_REGISTROS_DIARIOS'!K:K, "EV_PRODUCCION") | J3: =I3-H3 | K3: =IF(H3>0, I3/H3, 1) | L3: =IF(D3>0, I3/D3, 1) | M3: =IF(K3>0, C3/K3, C3)
A4: WBS-300 | B4: Red de Agua Potable y Conexiones Domiciliarias | C4: ='04_CATALOGO_WBS'!C6 | D4: ='04_CATALOGO_WBS'!D6 | E4: =SUMIFS('02_REGISTROS_DIARIOS'!J:J, '02_REGISTROS_DIARIOS'!D:D, A4, '02_REGISTROS_DIARIOS'!K:K, "AC_MO") | F4: =SUMIFS('02_REGISTROS_DIARIOS'!J:J, '02_REGISTROS_DIARIOS'!D:D, A4, '02_REGISTROS_DIARIOS'!K:K, "AC_MAT") | G4: =SUMIFS('02_REGISTROS_DIARIOS'!J:J, '02_REGISTROS_DIARIOS'!D:D, A4, '02_REGISTROS_DIARIOS'!K:K, "AC_EQP") + SUMIFS('02_REGISTROS_DIARIOS'!J:J, '02_REGISTROS_DIARIOS'!D:D, A4, '02_REGISTROS_DIARIOS'!K:K, "AC_SUB") | H4: =SUM(E4:G4) | I4: =SUMIFS('02_REGISTROS_DIARIOS'!J:J, '02_REGISTROS_DIARIOS'!D:D, A4, '02_REGISTROS_DIARIOS'!K:K, "EV_PRODUCCION") | J4: =I4-H4 | K4: =IF(H4>0, I4/H4, 1) | L4: =IF(D4>0, I4/D4, 1) | M4: =IF(K4>0, C4/K4, C4)
A5: WBS-400 | B5: Pruebas Hidráulicas, Desinfección y Entrega | C5: ='04_CATALOGO_WBS'!C7 | D5: ='04_CATALOGO_WBS'!D7 | E5: =SUMIFS('02_REGISTROS_DIARIOS'!J:J, '02_REGISTROS_DIARIOS'!D:D, A5, '02_REGISTROS_DIARIOS'!K:K, "AC_MO") | F5: =SUMIFS('02_REGISTROS_DIARIOS'!J:J, '02_REGISTROS_DIARIOS'!D:D, A5, '02_REGISTROS_DIARIOS'!K:K, "AC_MAT") | G5: =SUMIFS('02_REGISTROS_DIARIOS'!J:J, '02_REGISTROS_DIARIOS'!D:D, A5, '02_REGISTROS_DIARIOS'!K:K, "AC_EQP") + SUMIFS('02_REGISTROS_DIARIOS'!J:J, '02_REGISTROS_DIARIOS'!D:D, A5, '02_REGISTROS_DIARIOS'!K:K, "AC_SUB") | H5: =SUM(E5:G5) | I5: =SUMIFS('02_REGISTROS_DIARIOS'!J:J, '02_REGISTROS_DIARIOS'!D:D, A5, '02_REGISTROS_DIARIOS'!K:K, "EV_PRODUCCION") | J5: =I5-H5 | K5: =IF(H5>0, I5/H5, 1) | L5: =IF(D5>0, I5/D5, 1) | M5: =IF(K5>0, C5/K5, C5)
A6: TOTAL OBRA WBS | B6: Consolidado de Redes Sanitarias | C6: =SUM(C2:C5) | D6: =SUM(D2:D5) | E6: =SUM(E2:E5) | F6: =SUM(F2:F5) | G6: =SUM(G2:G5) | H6: =SUM(H2:H5) | I6: =SUM(I2:I5) | J6: =SUM(J2:J5) | K6: =IF(H6>0, I6/H6, 1) | L6: =IF(D6>0, I6/D6, 1) | M6: =IF(K6>0, C6/K6, C6)

Sheet 04_CATALOGO_WBS
A1: CÓDIGO WBS | B1: NOMBRE DEL FRENTE / WBS | C1: PRESUPUESTO META (BAC S/) | D1: PLANIFICADO ACUMULADO (PV S/)
A2: WBS-100 | B2: Obras Preliminares, Trazo y Movilización | C2: 8296.4 | D2: 8296.4
A3: WBS-200 | B3: Red de Alcantarillado, Zanjas y Buzones | C3: 380086.56 | D3: 45000
A4: WBS-300 | B4: Red de Agua Potable y Conexiones Domiciliarias | C4: 57565.2 | D4: 12000
A5: WBS-400 | B5: Pruebas Hidráulicas, Desinfección y Entrega | C5: 9348.06 | D5: 2500

Sheet 05_CATALOGO_RECURSOS
A1: Código Recurso | B1: Descripción Recurso / Insumo | C1: Unidad | D1: P.U. Meta (S/) | E1: Categoría EVM
A2: MO_CAPATAZ | B2: CAPATAZ | C2: hh | D2: 32.5 | E2: AC_MO
A3: MO_OPERARIO | B3: OPERARIO | C3: hh | D3: 26.8 | E3: AC_MO
A4: MO_OFICIAL | B4: OFICIAL | C4: hh | D4: 22.4 | E4: AC_MO
A5: MO_PEON | B5: PEON | C5: hh | D5: 20.1 | E5: AC_MO
A6: MAT_ESTACA | B6: ESTACAS Y MADERA PARA TRAZO | C6: pza | D6: 4.5 | E6: AC_MAT
A7: MAT_PINTURA | B7: PINTURA SPRAY MARCADOR DE ZANJA | C7: gla | D7: 18 | E7: AC_MAT
A8: MAT_CORDEL | B8: CORDEL / NYLON | C8: m | D8: 0.8 | E8: AC_MAT
A9: MAT_ARENA_CAMAS | B9: ARENA FINA SELECCIONADA PARA CAMA E=0.10M | C9: m3 | D9: 45 | E9: AC_MAT
A10: MAT_TUB_PVC_200 | B10: TUBERIA PVC UF DN 200MM SERIE S-20 ALCANTARILLADO | C10: m | D10: 42 | E10: AC_MAT
A11: MAT_LUBRICANTE | B11: LUBRICANTE PARA TUBERIA CON ESPIGA Y CAMPANA | C11: kg | D11: 24 | E11: AC_MAT
A12: MAT_MATERIAL_PR | B12: MATERIAL DE PRÉSTAMO AFIRMADO PARA RELLENO COMPACTADO | C12: m3 | D12: 38 | E12: AC_MAT
A13: MAT_AGUA | B13: AGUA PARA COMPACTACIÓN Y PRUEBAS | C13: m3 | D13: 12 | E13: AC_MAT
... A28: SUB_MONTAJE_BUZON | B28: SUBCONTRATO SERVICIO ASENTADO Y ANCLAJE BUZONES PREFABRICADOS | C28: und | D28: 250 | E28: AC_SUB
