Workbook

Sheet MAESTRO_RECURSOS_Y_APU
A1: CATÁLOGO MAESTRO COMPLETO DE RECURSOS Y APU META (DICCIONARIO UNIFICADO)
A3: Categoría Tipo | B3: Código Recurso/Partida | C3: Descripción Detallada del Recurso / APU | D3: Unidad | E3: Precio Unitario Meta (S/)
A4: Mano de Obra | B4: MO_CAPATAZ | C4: CAPATAZ | D4: hh | E4: 32.5
A5: Mano de Obra | B5: MO_OPERARIO | C5: OPERARIO | D5: hh | E5: 26.8
A6: Mano de Obra | B6: MO_OFICIAL | C6: OFICIAL | D6: hh | E6: 22.4
A7: Mano de Obra | B7: MO_PEON | C7: PEON | D7: hh | E7: 20.1
A8: Materiales | B8: MAT_ESTACA | C8: ESTACAS Y MADERA PARA TRAZO | D8: pza | E8: 4.5
A9: Materiales | B9: MAT_PINTURA | C9: PINTURA SPRAY MARCADOR DE ZANJA | D9: gla | E9: 18
A10: Materiales | B10: MAT_CORDEL | C10: CORDEL / NYLON | D10: m | E10: 0.8
A11: Materiales | B11: MAT_ARENA_CAMAS | C11: ARENA FINA SELECCIONADA PARA CAMA E=0.10M | D11: m3 | E11: 45
A12: Materiales | B12: MAT_TUB_PVC_200 | C12: TUBERIA PVC UF DN 200MM SERIE S-20 ALCANTARILLADO | D12: m | E12: 42
A13: Materiales | B13: MAT_LUBRICANTE | C13: LUBRICANTE PARA TUBERIA CON ESPIGA Y CAMPANA | D13: kg | E13: 24
A14: Materiales | B14: MAT_MATERIAL_PR | C14: MATERIAL DE PRÉSTAMO AFIRMADO PARA RELLENO COMPACTADO | D14: m3 | E14: 38
A15: Materiales | B15: MAT_AGUA | C15: AGUA PARA COMPACTACIÓN Y PRUEBAS | D15: m3 | E15: 12
... A49: Partida APU (EV) | B49: 01.04.01 | C49: Partida 01.04.01 - Pruebas Hidráulicas de Redes de Agua y Alcantarillado + Desinfección | D49: GLB | E49: 9348.06

Sheet DB_REGISTROS_DIARIOS
A1: BASE DE DATOS REGISTROS DIARIOS CON TRAZABILIDAD Y BUSQUEDA DE TARIFAS META
A3: ID Registro | B3: Fecha | C3: Emisor / Rol | D3: Código WBS | E3: Código Recurso/Partida | F3: Descripción Detallada | G3: Cantidad | H3: Unidad | I3: Costo Unitario Formula (S/) | J3: Costo Total Formula (S/) | K3: Categoría EVM
A4: LOG-20260726-92000 | B4: 2026-07-26 | C4: Tareador (Bildin) | D4: WBS-200 | E4: MO_OPERARIO | F4: OPERARIO (2 pers. x 8h) | G4: 16 | H4: hh | I4: =VLOOKUP(E4, MAESTRO_RECURSOS_Y_APU!$B$4:$E$49, 4, FALSE) | J4: =G4*I4 | K4: AC_MO
A5: LOG-20260726-92000 | B5: 2026-07-26 | C5: Tareador (Bildin) | D5: WBS-200 | E5: MO_OPERARIO | F5: OPERARIO (2 pers. x 8h) | G5: 16 | H5: hh | I5: =VLOOKUP(E5, MAESTRO_RECURSOS_Y_APU!$B$4:$E$49, 4, FALSE) | J5: =G5*I5 | K5: AC_MO
A6: LOG-20260726-92000 | B6: 2026-07-26 | C6: Tareador (Bildin) | D6: WBS-200 | E6: MO_OPERARIO | F6: OPERARIO (2 pers. x 8h) | G6: 16 | H6: hh | I6: =VLOOKUP(E6, MAESTRO_RECURSOS_Y_APU!$B$4:$E$49, 4, FALSE) | J6: =G6*I6 | K6: AC_MO
A7: LOG-4 | B7: 2026-07-26 | C7: Tareador (Bildin) | D7: WBS-200 | E7: MO_OPERARIO | F7: OPERARIO (2 pers. x 8h) | G7: 16 | H7: hh | I7: =VLOOKUP(E7, MAESTRO_RECURSOS_Y_APU!$B$4:$E$49, 4, FALSE) | J7: =G7*I7 | K7: AC_MO

Sheet DASHBOARD_EVM_WBS
A1: DASHBOARD Y CONTROL DE RESULTADO OPERATIVO (CUANTIFICACIÓN DINÁMICA CON FORMULAS SUMIFS)
A3: Código WBS | B3: Descripción del Frente WBS | C3: Presupuesto BAC (S/) | D3: Planificado PV (S/) | E3: Valor Ganado EV (S/) | F3: Costo Real AC (S/) | G3: Variación Costo CV (S/) | H3: CPI (Costo) | I3: SPI (Plazo) | J3: EAC Proyectado (S/)
A4: WBS-100 | B4: Obras Preliminares, Trazo y Movilización | C4: 22900 | D4: 22900 | E4: =SUMIFS(DB_REGISTROS_DIARIOS!J:J, DB_REGISTROS_DIARIOS!D:D, A4, DB_REGISTROS_DIARIOS!K:K, "EV_PRODUCCION") | F4: =SUMIFS(DB_REGISTROS_DIARIOS!J:J, DB_REGISTROS_DIARIOS!D:D, A4, DB_REGISTROS_DIARIOS!K:K, "AC_*") | G4: =E4-F4 | H4: =IF(F4>0, E4/F4, 1.0) | I4: =IF(D4>0, E4/D4, 1.0) | J4: =IF(H4>0, F4+(C4-E4)/H4, C4)
A5: WBS-200 | B5: Red de Alcantarillado, Zanjas y Buzones | C5: 298000 | D5: 31170 | E5: =SUMIFS(DB_REGISTROS_DIARIOS!J:J, DB_REGISTROS_DIARIOS!D:D, A5, DB_REGISTROS_DIARIOS!K:K, "EV_PRODUCCION") | F5: =SUMIFS(DB_REGISTROS_DIARIOS!J:J, DB_REGISTROS_DIARIOS!D:D, A5, DB_REGISTROS_DIARIOS!K:K, "AC_*") | G5: =E5-F5 | H5: =IF(F5>0, E5/F5, 1.0) | I5: =IF(D5>0, E5/D5, 1.0) | J5: =IF(H5>0, F5+(C5-E5)/H5, C5)
A6: WBS-300 | B6: Red de Agua Potable y Conexiones Domiciliarias | C6: 55250 | D6: 0 | E6: =SUMIFS(DB_REGISTROS_DIARIOS!J:J, DB_REGISTROS_DIARIOS!D:D, A6, DB_REGISTROS_DIARIOS!K:K, "EV_PRODUCCION") | F6: =SUMIFS(DB_REGISTROS_DIARIOS!J:J, DB_REGISTROS_DIARIOS!D:D, A6, DB_REGISTROS_DIARIOS!K:K, "AC_*") | G6: =E6-F6 | H6: =IF(F6>0, E6/F6, 1.0) | I6: =IF(D6>0, E6/D6, 1.0) | J6: =IF(H6>0, F6+(C6-E6)/H6, C6)
A7: WBS-400 | B7: Pruebas Hidráulicas, Desinfección y Entrega | C7: 10450 | D7: 0 | E7: =SUMIFS(DB_REGISTROS_DIARIOS!J:J, DB_REGISTROS_DIARIOS!D:D, A7, DB_REGISTROS_DIARIOS!K:K, "EV_PRODUCCION") | F7: =SUMIFS(DB_REGISTROS_DIARIOS!J:J, DB_REGISTROS_DIARIOS!D:D, A7, DB_REGISTROS_DIARIOS!K:K, "AC_*") | G7: =E7-F7 | H7: =IF(F7>0, E7/F7, 1.0) | I7: =IF(D7>0, E7/D7, 1.0) | J7: =IF(H7>0, F7+(C7-E7)/H7, C7)
A8: TOTAL PROYECTO | C8: =SUM(C4:C7) | D8: =SUM(D4:D7) | E8: =SUM(E4:E7) | F8: =SUM(F4:F7) | G8: =E8-F8 | H8: =IF(F8>0, E8/F8, 1.0) | I8: =IF(D8>0, E8/D8, 1.0) | J8: =SUM(J4:J7)
